Workbook
Name Ability_to_perceive_handling: 'Parameters, general'!#REF!
Name AF_beef: 'Parameters, general'!$B$39
Name AF_beef_DE: 'Parameters, country spec'!$D$98
Name AF_beef_DK: 'Parameters, country spec'!$B$98
Name AF_beef_ES: 'Parameters, country spec'!$K$98
Name AF_beef_FR: 'Parameters, country spec'!$C$98
Name AF_beef_GR: 'Parameters, country spec'!$E$98
Name AF_beef_HU: 'Parameters, country spec'!$F$98
Name AF_beef_IE: 'Parameters, country spec'!$G$98
Name AF_beef_IT: 'Parameters, country spec'!$H$98
Name AF_beef_NL: 'Parameters, country spec'!$I$98
Name AF_beef_PL: 'Parameters, country spec'!$J$98
Name AF_beef_SE: 'Parameters, country spec'!$L$98
Name AF_calves: 'Parameters, general'!$B$40
Name AF_calves_DE: 'Parameters, country spec'!$D$97
Name AF_calves_DK: 'Parameters, country spec'!$B$97
Name AF_calves_ES: 'Parameters, country spec'!$K$97
Name AF_calves_FR: 'Parameters, country spec'!$C$97
Name AF_calves_GR: 'Parameters, country spec'!$E$97
Name AF_calves_HU: 'Parameters, country spec'!$F$97
Name AF_calves_IE: 'Parameters, country spec'!$G$97
Name AF_calves_IT: 'Parameters, country spec'!$H$97
Name AF_calves_NL: 'Parameters, country spec'!$I$97
Name AF_calves_PL: 'Parameters, country spec'!$J$97
Name AF_calves_SE: 'Parameters, country spec'!$L$97
Name AF_milk: 'Parameters, general'!$B$38
Name AF_milk_DE: 'Parameters, country spec'!$D$95
Name AF_milk_DK: 'Parameters, country spec'!$B$95
Name AF_milk_ES: 'Parameters, country spec'!$K$95
Name AF_milk_FR: 'Parameters, country spec'!$C$95
Name AF_milk_GR: 'Parameters, country spec'!$E$95
Name AF_milk_HU: 'Parameters, country spec'!$F$95
Name AF_milk_IE: 'Parameters, country spec'!$G$95
Name AF_milk_IT: 'Parameters, country spec'!$H$95
Name AF_milk_NL: 'Parameters, country spec'!$I$95
Name AF_milk_PL: 'Parameters, country spec'!$J$95
Name AF_milk_SE: 'Parameters, country spec'!$L$95
Name AF_offal: 'Parameters, general'!$B$41
Name AF_offal_DE: 'Parameters, country spec'!$D$99
Name AF_offal_DK: 'Parameters, country spec'!$B$99
Name AF_offal_ES: 'Parameters, country spec'!$K$99
Name AF_offal_FR: 'Parameters, country spec'!$C$99
Name AF_offal_GR: 'Parameters, country spec'!$E$99
Name AF_offal_HU: 'Parameters, country spec'!$F$99
Name AF_offal_IE: 'Parameters, country spec'!$G$99
Name AF_offal_IT: 'Parameters, country spec'!$H$99
Name AF_offal_NL: 'Parameters, country spec'!$I$99
Name AF_offal_PL: 'Parameters, country spec'!$J$99
Name AF_offal_SE: 'Parameters, country spec'!$L$99
Name AF_tallow: 'Parameters, general'!$B$42
Name AF_tallow_DE: 'Parameters, country spec'!$D$100
Name AF_tallow_DK: 'Parameters, country spec'!$B$100
Name AF_tallow_ES: 'Parameters, country spec'!$K$100
Name AF_tallow_FR: 'Parameters, country spec'!$C$100
Name AF_tallow_GR: 'Parameters, country spec'!$E$100
Name AF_tallow_HU: 'Parameters, country spec'!$F$100
Name AF_tallow_IE: 'Parameters, country spec'!$G$100
Name AF_tallow_IT: 'Parameters, country spec'!$H$100
Name AF_tallow_NL: 'Parameters, country spec'!$I$100
Name AF_tallow_PL: 'Parameters, country spec'!$J$100

Sheet README
A2: Read me
A4: This is a file that contains…
A17: Color codes:
B19: Results
B20: Sheets for input
B21: Intermediate calculations
A26: Att göra:
A27: Landsspecifika mortality rates ska gå att få ut från nationella databaser, i varjefall för vissa länder skriver de om här: https://www.sciencedirect.com/science/article/pii/S003452881830359X
A28: Se om det går att få ut en foderstat för denna från Frankrike https://productions-animales.org/article/view/5396

Sheet Figures
A2: Figures
A4: Greenhouse gas emission for milk across countries, to farmgate, no waste
B6: Production of mineral fertilizer | C6: Production of capital goods | D6: Emissions from soil | E6: Energy use cropping | F6: Energy use for feed processing | G6: Land use change emissions | H6: Feed transports | I6: Enteric fermentation | J6: Manure management | K6: Energy use in stables | L6: Energy use for slaughter | M6: Tot
A7: Poland | B7: ='GHG det, per kg milk'!H51 -> 0.069906025 | C7: ='GHG det, per kg milk'!I51 -> 0.027634303 | D7: ='GHG det, per kg milk'!J51+'GHG det, per kg milk'!K51 -> 0.11683022 | E7: ='GHG det, per kg milk'!L51+'GHG det, per kg milk'!N51 -> 0.031273195 | F7: ='GHG det, per kg milk'!O51+'GHG det, per kg milk'!Q51 -> 0.10873971 | G7: ='GHG det, per kg milk'!P51 -> 0.025194435 | H7: ='GHG det, per kg milk'!R51 -> 0.085313302 | I7: ='GHG det, per kg milk'!S51 -> 0.50693602 | J7: ='GHG det, per kg milk'!T51 -> 0.12913323 | K7: ='GHG det, per kg milk'!W51 -> 0.24446143 | L7: ='GHG det, per kg milk'!X51 -> 0.0024083566 | M7: =SUM(B7:L7) -> 1.3478302
A8: Hungary | B8: ='GHG det, per kg milk'!H31 -> 0.037362351 | C8: ='GHG det, per kg milk'!I31 -> 0.024658947 | D8: ='GHG det, per kg milk'!J31+'GHG det, per kg milk'!K31 -> 0.11929175 | E8: ='GHG det, per kg milk'!L31+'GHG det, per kg milk'!N31 -> 0.026515746 | F8: ='GHG det, per kg milk'!O31+'GHG det, per kg milk'!Q31 -> 0.13831284 | G8: ='GHG det, per kg milk'!P31 -> 0.035692686 | H8: ='GHG det, per kg milk'!R31 -> 0.12179168 | I8: ='GHG det, per kg milk'!S31 -> 0.49842953 | J8: ='GHG det, per kg milk'!T31 -> 0.18214136 | K8: ='GHG det, per kg milk'!W31 -> 0.094434922 | L8: ='GHG det, per kg milk'!X31 -> 0.0012586525 | M8: =SUM(B8:L8) -> 1.2798905
A9: Greece | B9: ='GHG det, per kg milk'!H26 -> 0.059535004 | C9: ='GHG det, per kg milk'!I26 -> 0.026974893 | D9: ='GHG det, per kg milk'!J26+'GHG det, per kg milk'!K26 -> 0.14402825 | E9: ='GHG det, per kg milk'!L26+'GHG det, per kg milk'!N26 -> 0.036975427 | F9: ='GHG det, per kg milk'!O26+'GHG det, per kg milk'!Q26 -> 0.089626125 | G9: ='GHG det, per kg milk'!P26 -> 0.025821298 | H9: ='GHG det, per kg milk'!R26 -> 0.069336164 | I9: ='GHG det, per kg milk'!S26 -> 0.48100638 | J9: ='GHG det, per kg milk'!T26 -> 0.13093999 | K9: ='GHG det, per kg milk'!W26 -> 0.17249535 | L9: ='GHG det, per kg milk'!X26 -> 0.0016097656 | M9: =SUM(B9:L9) -> 1.2383486
A10: Italy | B10: ='GHG det, per kg milk'!H41 -> 0.021040006 | C10: ='GHG det, per kg milk'!I41 -> 0.02403901 | D10: ='GHG det, per kg milk'!J41+'GHG det, per kg milk'!K41 -> 0.076927334 | E10: ='GHG det, per kg milk'!L41+'GHG det, per kg milk'!N41 -> 0.014615583 | F10: ='GHG det, per kg milk'!O41+'GHG det, per kg milk'!Q41 -> 0.10412706 | G10: ='GHG det, per kg milk'!P41 -> 0.035542667 | H10: ='GHG det, per kg milk'!R41 -> 0.09875542 | I10: ='GHG det, per kg milk'!S41 -> 0.5390151 | J10: ='GHG det, per kg milk'!T41 -> 0.20950377 | K10: ='GHG det, per kg milk'!W41 -> 0.10725069 | L10: ='GHG det, per kg milk'!X41 -> 0.0011827381 | M10: =SUM(B10:L10) -> 1.2319994
A11: Netherlands | B11: ='GHG det, per kg milk'!H46 -> 0.062917336 | C11: ='GHG det, per kg milk'!I46 -> 0.024986364 | D11: ='GHG det, per kg milk'!J46+'GHG det, per kg milk'!K46 -> 0.15287739 | E11: ='GHG det, per kg milk'!L46+'GHG det, per kg milk'!N46 -> 0.020029052 | F11: ='GHG det, per kg milk'!O46+'GHG det, per kg milk'!Q46 -> 0.051076114 | G11: ='GHG det, per kg milk'!P46 -> 0.032935739 | H11: ='GHG det, per kg milk'!R46 -> 0.040598987 | I11: ='GHG det, per kg milk'!S46 -> 0.46360695 | J11: ='GHG det, per kg milk'!T46 -> 0.15024441 | K11: ='GHG det, per kg milk'!W46 -> 0.13851426 | L11: ='GHG det, per kg milk'!X46 -> 0.001092463 | M11: =SUM(B11:L11) -> 1.1388791
A12: Germany | B12: ='GHG det, per kg milk'!H21 -> 0.029641136 | C12: ='GHG det, per kg milk'!I21 -> 0.026414324 | D12: ='GHG det, per kg milk'!J21+'GHG det, per kg milk'!K21 -> 0.078516242 | E12: ='GHG det, per kg milk'!L21+'GHG det, per kg milk'!N21 -> 0.015267153 | F12: ='GHG det, per kg milk'!O21+'GHG det, per kg milk'!Q21 -> 0.069433961 | G12: ='GHG det, per kg milk'!P21 -> 0.019267566 | H12: ='GHG det, per kg milk'!R21 -> 0.064759272 | I12: ='GHG det, per kg milk'!S21 -> 0.49188537 | J12: ='GHG det, per kg milk'!T21 -> 0.1496272 | K12: ='GHG det, per kg milk'!W21 -> 0.10134181 | L12: ='GHG det, per kg milk'!X21 -> 0.001109468 | M12: =SUM(B12:L12) -> 1.0472635
A13: Spain | B13: ='GHG det, per kg milk'!H56 -> 0.043062056 | C13: ='GHG det, per kg milk'!I56 -> 0.025099257 | D13: ='GHG det, per kg milk'!J56+'GHG det, per kg milk'!K56 -> 0.11916955 | E13: ='GHG det, per kg milk'!L56+'GHG det, per kg milk'!N56 -> 0.032934437 | F13: ='GHG det, per kg milk'!O56+'GHG det, per kg milk'!Q56 -> 0.061858141 | G13: ='GHG det, per kg milk'!P56 -> 0.030633719 | H13: ='GHG det, per kg milk'!R56 -> 0.044707834 | I13: ='GHG det, per kg milk'!S56 -> 0.45374833 | J13: ='GHG det, per kg milk'!T56 -> 0.14199359 | K13: ='GHG det, per kg milk'!W56 -> 0.076050804 | L13: ='GHG det, per kg milk'!X56 -> 0.00078114666 | M13: =SUM(B13:L13) -> 1.0300389
A14: Denmark | B14: ='GHG det, per kg milk'!H11 -> 0.048384711 | C14: ='GHG det, per kg milk'!I11 -> 0.021363862 | D14: ='GHG det, per kg milk'!J11+'GHG det, per kg milk'!K11 -> 0.10830012 | E14: ='GHG det, per kg milk'!L11+'GHG det, per kg milk'!N11 -> 0.01518799 | F14: ='GHG det, per kg milk'!O11+'GHG det, per kg milk'!Q11 -> 0.056312459 | G14: ='GHG det, per kg milk'!P11 -> 0.013241399 | H14: ='GHG det, per kg milk'!R11 -> 0.046081858 | I14: ='GHG det, per kg milk'!S11 -> 0.47343335 | J14: ='GHG det, per kg milk'!T11 -> 0.22039861 | K14: ='GHG det, per kg milk'!W11 -> 0.0013171699 | L14: ='GHG det, per kg milk'!X11 -> 0.00090100914 | M14: =SUM(B14:L14) -> 1.0049225
A15: France | B15: ='GHG det, per kg milk'!H16 -> 0.036925368 | C15: ='GHG det, per kg milk'!I16 -> 0.027274827 | D15: ='GHG det, per kg milk'!J16+'GHG det, per kg milk'!K16 -> 0.11143153 | E15: ='GHG det, per kg milk'!L16+'GHG det, per kg milk'!N16 -> 0.018533852 | F15: ='GHG det, per kg milk'!O16+'GHG det, per kg milk'!Q16 -> 0.068647118 | G15: ='GHG det, per kg milk'!P16 -> 0.015469464 | H15: ='GHG det, per kg milk'!R16 -> 0.058586097 | I15: ='GHG det, per kg milk'!S16 -> 0.52754027 | J15: ='GHG det, per kg milk'!T16 -> 0.11656127 | K15: ='GHG det, per kg milk'!W16 -> 0.01922052 | L15: ='GHG det, per kg milk'!X16 -> 0.00050121823 | M15: =SUM(B15:L15) -> 1.0006915
A16: Sweden | B16: ='GHG det, per kg milk'!H61 -> 0.037642578 | C16: ='GHG det, per kg milk'!I61 -> 0.027315517 | D16: ='GHG det, per kg milk'!J61+'GHG det, per kg milk'!K61 -> 0.11183223 | E16: ='GHG det, per kg milk'!L61+'GHG det, per kg milk'!N61 -> 0.024549872 | F16: ='GHG det, per kg milk'!O61+'GHG det, per kg milk'!Q61 -> 0.074151556 | G16: ='GHG det, per kg milk'!P61 -> 0.022203399 | H16: ='GHG det, per kg milk'!R61 -> 0.065425242 | I16: ='GHG det, per kg milk'!S61 -> 0.49785567 | J16: ='GHG det, per kg milk'!T61 -> 0.077274085 | K16: ='GHG det, per kg milk'!W61 -> 0.012571318 | L16: ='GHG det, per kg milk'!X61 -> 0.00039628936 | M16: =SUM(B16:L16) -> 0.95121776
A17: Ireland | B17: ='GHG det, per kg milk'!H36 -> 0.025856819 | C17: ='GHG det, per kg milk'!I36 -> 0.031647246 | D17: ='GHG det, per kg milk'!J36+'GHG det, per kg milk'!K36 -> 0.11129543 | E17: ='GHG det, per kg milk'!L36+'GHG det, per kg milk'!N36 -> 0.017248603 | F17: ='GHG det, per kg milk'!O36+'GHG det, per kg milk'!Q36 -> 0.013414023 | G17: ='GHG det, per kg milk'!P36 -> 0.0026265212 | H17: ='GHG det, per kg milk'!R36 -> 0.007732808 | I17: ='GHG det, per kg milk'!S36 -> 0.55921983 | J17: ='GHG det, per kg milk'!T36 -> 0.11943507 | K17: ='GHG det, per kg milk'!W36 -> 0.049755033 | L17: ='GHG det, per kg milk'!X36 -> 0.0011919296 | M17: =SUM(B17:L17) -> 0.93942331
C19: Andel | D19: Arla
A20: Våmjäsning | B20: =I17 -> 0.55921983 | C20: =B20/SUM($B$20:$B$23) -> 0.59527992 | D20: =1.15*0.41 -> 0.4715 | E20: =41/91 -> 0.45054945
A21: Foder | B21: =SUM(B17:H17) -> 0.20982145 | C21: =B21/SUM($B$20:$B$23) -> 0.22335133 | D21: =1.15*0.33 -> 0.3795 | E21: =33/91 -> 0.36263736
A22: Gödsel | B22: =J17 -> 0.11943507 | C22: =B22/SUM($B$20:$B$23) -> 0.12713658 | D22: =1.15*0.1 -> 0.115 | E22: =10/91 -> 0.10989011 | I22: Från Elmquist et al 2015
A23: Energi | B23: =K17+L17 -> 0.050946963 | C23: =B23/SUM($B$20:$B$23) -> 0.054232168 | D23: =1.15*0.05 -> 0.0575 | E23: =7/91 -> 0.076923077 | F23: För Arla även diesel | I23: 0.17 kWh/kg mjölk -> | K23: =0.17*0.092 -> 0.01564 | L23: kg CO2e/kg mjölk
B24: =SUM(B20:B23) -> 0.93942331 | D24: =SUM(D20:D23) -> 1.0235
A26: Comparison with Moberg et al. Sweden
A27: - Lower values for feed due to lower emissions from grains (no SOC changes acccounted for here), ley approx the same
A28: - Moberg has slightly higher EF for methane for dairy cows and heifers, but that makes a small difference
A29: - Slight difference in milk yield does not explain difference in methane emissions
A30: - Here we do not account for any emissions from by-products!! Should be added
A34: https://www.arla.se/4a9c19/globalassets/om-arla/hallbarhet/klimatberakningar/climate-check-report-2022.pdf | Z34: Ranking here: | AB34: Ranking Lesshen:
Z36: Germany | AB36: Poland
Z37: Spain | AB37: Ireland
Z38: Netherlands | AB38: Hungary
Z39: Greece | AB39: Greece
Z40: Italy | AB40: Netherlands
Z41: Poland | AB41: Italy
Z42: Ireland | AB42: Spain
Z43: Denmark | AB43: Germany
Z44: Hungary | AB44: France
Z45: France | AB45: Sweden
Z46: Sweden | AB46: Denmakr
B76: Manure
B77: Comp
B78: Emissions from manure (tot) from Emmas data, Swedish milk | H78: 0.11 kg C02e / kg past. Milk. Near exclusively direct emissions
B79: Arla: 10% of total emissons (10% of 1.1)
B80: 0.1 kg CO2e / kg milk, Swedish milk | F80: https://www.sciencedirect.com/science/article/pii/S1751731114001293
B81: 10% of 1.23 kg CO2e / milk
B83: Factors causing variations between countries
B84: For both methane and nitrogen emissions, dairy cows influence emissions more than heifers as they produce more manure / nitrogen and as the population is larger (0.6 heifers per dairy cow)
B85: Additionally, milk yield also influences results per kg milk greatly
B87: Methane
B88: Methane emissions from manure are vary with three independent factors:
B89: 1. Difference in total manure production
B90: 2. National MCF values for the different systems
B91: 3. Share of manure in these systems
B93: High emission countries are characterized by having a large share of the manure deposited in systems with a high national MCF factor.
B95: Highest emissions per kg milk
B96: Denmark | C96: By far highest manure production (also high milk yields, which balances it out some). 92% in liquid and deep bedding for dairy cows, 70% for heifers - with MCF of 14.4% for both
B97: Italy | C97: 54% and 47%, respectively, in liquid systems with MCF of 16.6%. Furthermore, relatively low milk yields giving high CH4 emissions per kg milk
B99: Sweden has an exceptionally low MCF-factor
B101: Nitrogen
B102: Nitrogen emissions mostly vary with 1 factor:
B103: The share deposited in pasture-systems. Emission factors for pasture are much lower than the other 3 systems, while the other 3 systems have similar emissions to eachother
B104: However, liquid systems have a lower emission factor (48%) than solid / deep bedding (54%)
B105: Therefore, high N emissions are seen for countries with low percentage of grazing animals
C106: No dairy cows in pasture, 65% of heifers. Dairy cows affect the results much more than heifers. Also, Spain has the lowest milk yield leading to high emissions per kg of milk
B107: Highest emissions per kg milk | C107: 8% dairy cows in pasture, 33% of heifers. No cows in liquid systems, with relatively low milk yields
B108: Spain
B109: Greece

Sheet Footprints, per kg milk
A2: Footprints (per kg of milk)
A5: Animal products | F5: Climate | L5: Land | M5: Nitrogen | N5: Phosphorus | O5: Water | P5: Pesticides | Q5: Biodiversity | R5: Ammonia | S5: Labour | T5: Animal welfare | U5: Use of antibiotics
A6: Code | B6: Name | C6: Category | D6: Country | E6: Country code | F6: Carbon footprint, kg CO2e/kg | G6: Carbon dioxide, kg CO2/kg | H6: Methane, fossil, kg CH4/kg | I6: Methane, biogenic, kg CH4/kg | J6: Nitrous oxide, kg N2O/kg | K6: HFCs, kg HFCs/kg | L6: Cropland use, m2/kg | M6: New N input, kg N/kg | N6: New P input, kg P/kg | O6: Blue freshwater use, m3/kg | P6: Pesticide use, g a.i./kg | Q6: Extinction rate, E/MSY/kg | R6: Ammonia emission, kg NH3/kg | S6: Labour requirements, h/kg | T6: Animal welfare index per kg of milk | U6: Antibiotics use indicator/kg
A7: 02211 | B7: Raw milk of cattle | C7: Dairy | D7: Denmark | E7: DK | F7: ='GHG det, per kg milk'!G11 -> 1.0049225 | G7: ='GHG det, per kg milk'!G7 -> 0.14515622 | H7: ='GHG det, per kg milk'!G8 -> 0.00084506497 | I7: ='GHG det, per kg milk'!G9 -> 0.023283056 | J7: ='GHG det, per kg milk'!G10 -> 0.00075436221 | L7: ='Footprints, absolute'!L7/Production!$B$9*AF_milk_DK -> 0.94139375 | M7: ='Footprints, absolute'!M7/Production!$B$9*AF_milk_DK -> 0.012509012 | N7: ='Footprints, absolute'!N7/Production!$B$9*AF_milk_DK -> 0.001026969 | O7: ='Footprints, absolute'!O7/Production!$B$9*AF_milk_DK -> 0.0075354671 | P7: ='Footprints, absolute'!P7/Production!$B$9*AF_milk_DK -> 0.065874837 | Q7: ='Footprints, absolute'!Q7/Production!$B$9*AF_milk_DK -> 1.022527e-11 | R7: ='Footprints, absolute'!R7/Production!$B$9*AF_milk_DK -> 0.00047317567 | T7: ='Footprints, absolute'!T7*AF_milk_DK -> 0.0075099482 | U7: ='Footprints, absolute'!U7*AF_milk_DK -> 0.73472176
A8: 02211 | B8: Raw milk of cattle | C8: Dairy | D8: France | E8: FR | F8: ='GHG det, per kg milk'!G16 -> 1.0006915 | G8: ='GHG det, per kg milk'!G12 -> 0.18854038 | H8: ='GHG det, per kg milk'!G13 -> 0.00096964335 | I8: ='GHG det, per kg milk'!G14 -> 0.021746613 | J8: ='GHG det, per kg milk'!G15 -> 0.00071830489 | L8: ='Footprints, absolute'!L8/Production!$C$9*AF_milk_FR -> 1.0060224 | M8: ='Footprints, absolute'!M8/Production!$C$9*AF_milk_FR -> 0.014351879 | N8: ='Footprints, absolute'!N8/Production!$C$9*AF_milk_FR -> 0.0011800522 | O8: ='Footprints, absolute'!O8/Production!$C$9*AF_milk_FR -> 0.010768766 | P8: ='Footprints, absolute'!P8/Production!$C$9*AF_milk_FR -> 0.098987497 | Q8: ='Footprints, absolute'!Q8/Production!$C$9*AF_milk_FR -> 2.12412e-11 | R8: ='Footprints, absolute'!R8/Production!$C$9*AF_milk_FR -> 0.00062855267 | T8: ='Footprints, absolute'!T8*AF_milk_FR -> 0.0070291999 | U8: ='Footprints, absolute'!U8*AF_milk_FR -> 1.0217196
A9: 02211 | B9: Raw milk of cattle | C9: Dairy | D9: Germany | E9: DE | F9: ='GHG det, per kg milk'!G21 -> 1.0472635 | G9: ='GHG det, per kg milk'!G17 -> 0.26771039 | H9: ='GHG det, per kg milk'!G18 -> 0.0010654407 | I9: ='GHG det, per kg milk'!G19 -> 0.021556166 | J9: ='GHG det, per kg milk'!G20 -> 0.00060727654 | L9: ='Footprints, absolute'!L9/Production!$D$9*AF_milk_DE -> 0.60463234 | M9: ='Footprints, absolute'!M9/Production!$D$9*AF_milk_DE -> 0.010876001 | N9: ='Footprints, absolute'!N9/Production!$D$9*AF_milk_DE -> 0.00055324016 | O9: ='Footprints, absolute'!O9/Production!$D$9*AF_milk_DE -> 0.005354824 | P9: ='Footprints, absolute'!P9/Production!$D$9*AF_milk_DE -> 0.038100835 | Q9: ='Footprints, absolute'!Q9/Production!$D$9*AF_milk_DE -> 1.6922016e-11 | R9: ='Footprints, absolute'!R9/Production!$D$9*AF_milk_DE -> 0.00031554148 | T9: ='Footprints, absolute'!T9*AF_milk_DE -> 0.0085212815 | U9: ='Footprints, absolute'!U9*AF_milk_DE -> 1.7736434
A10: 02211 | B10: Raw milk of cattle | C10: Dairy | D10: Greece | E10: GR | F10: ='GHG det, per kg milk'!G26 -> 1.2383486 | G10: ='GHG det, per kg milk'!G22 -> 0.43306998 | H10: ='GHG det, per kg milk'!G23 -> 0.0010722308 | I10: ='GHG det, per kg milk'!G24 -> 0.019491261 | J10: ='GHG det, per kg milk'!G25 -> 0.00090498954 | L10: ='Footprints, absolute'!L10/Production!$E$9*AF_milk_GR -> 1.6393959 | M10: ='Footprints, absolute'!M10/Production!$E$9*AF_milk_GR -> 0.023233588 | N10: ='Footprints, absolute'!N10/Production!$E$9*AF_milk_GR -> 0.0023470076 | O10: ='Footprints, absolute'!O10/Production!$E$9*AF_milk_GR -> 0.062020177 | P10: ='Footprints, absolute'!P10/Production!$E$9*AF_milk_GR -> 0.078647889 | Q10: ='Footprints, absolute'!Q10/Production!$E$9*AF_milk_GR -> 1.007069e-10 | R10: ='Footprints, absolute'!R10/Production!$E$9*AF_milk_GR -> 0.0017051508 | T10: ='Footprints, absolute'!T10*AF_milk_GR -> 0.010888635 | U10: ='Footprints, absolute'!U10*AF_milk_GR -> 3.3993396
A11: 02211 | B11: Raw milk of cattle | C11: Dairy | D11: Hungary | E11: HU | F11: ='GHG det, per kg milk'!G31 -> 1.2798905 | G11: ='GHG det, per kg milk'!G27 -> 0.4204242 | H11: ='GHG det, per kg milk'!G28 -> 0.0012766862 | I11: ='GHG det, per kg milk'!G29 -> 0.021642644 | J11: ='GHG det, per kg milk'!G30 -> 0.00086838692 | L11: ='Footprints, absolute'!L11/Production!$F$9*AF_milk_HU -> 1.5375074 | M11: ='Footprints, absolute'!M11/Production!$F$9*AF_milk_HU -> 0.020866725 | N11: ='Footprints, absolute'!N11/Production!$F$9*AF_milk_HU -> 0.0022268577 | O11: ='Footprints, absolute'!O11/Production!$F$9*AF_milk_HU -> 0.01240925 | P11: ='Footprints, absolute'!P11/Production!$F$9*AF_milk_HU -> 0.10909139 | Q11: ='Footprints, absolute'!Q11/Production!$F$9*AF_milk_HU -> 3.2731815e-11 | R11: ='Footprints, absolute'!R11/Production!$F$9*AF_milk_HU -> 0.00075959581 | T11: ='Footprints, absolute'!T11*AF_milk_HU -> 0.011034239 | U11: ='Footprints, absolute'!U11*AF_milk_HU -> 2.626647
A12: 02211 | B12: Raw milk of cattle | C12: Dairy | D12: Ireland | E12: IE | F12: ='GHG det, per kg milk'!G36 -> 0.93942331 | G12: ='GHG det, per kg milk'!G32 -> 0.13988284 | H12: ='GHG det, per kg milk'!G33 -> 0.0001907991 | I12: ='GHG det, per kg milk'!G34 -> 0.023271936 | J12: ='GHG det, per kg milk'!G35 -> 0.00060627249 | L12: ='Footprints, absolute'!L12/Production!$G$9*AF_milk_IE -> 0.2185803 | M12: ='Footprints, absolute'!M12/Production!$G$9*AF_milk_IE -> 0.015554624 | N12: ='Footprints, absolute'!N12/Production!$G$9*AF_milk_IE -> 0.00050827234 | O12: ='Footprints, absolute'!O12/Production!$G$9*AF_milk_IE -> 0.0079779436 | P12: ='Footprints, absolute'!P12/Production!$G$9*AF_milk_IE -> 0.072418607 | Q12: ='Footprints, absolute'!Q12/Production!$G$9*AF_milk_IE -> 5.4689502e-12 | R12: ='Footprints, absolute'!R12/Production!$G$9*AF_milk_IE -> 0.000493313 | T12: ='Footprints, absolute'!T12*AF_milk_IE -> 0.0067615109 | U12: ='Footprints, absolute'!U12*AF_milk_IE -> 1.1141639
A13: 02211 | B13: Raw milk of cattle | C13: Dairy | D13: Italy | E13: IT | F13: ='GHG det, per kg milk'!G41 -> 1.2319994 | G13: ='GHG det, per kg milk'!G37 -> 0.34128923 | H13: ='GHG det, per kg milk'!G38 -> 0.0015417531 | I13: ='GHG det, per kg milk'!G39 -> 0.02471509 | J13: ='GHG det, per kg milk'!G40 -> 0.00065003108 | L13: ='Footprints, absolute'!L13/Production!$H$9*AF_milk_IT -> 1.0329893 | M13: ='Footprints, absolute'!M13/Production!$H$9*AF_milk_IT -> 0.01796752 | N13: ='Footprints, absolute'!N13/Production!$H$9*AF_milk_IT -> 0.0011284835 | O13: ='Footprints, absolute'!O13/Production!$H$9*AF_milk_IT -> 0.009957532 | P13: ='Footprints, absolute'!P13/Production!$H$9*AF_milk_IT -> 0.060147558 | Q13: ='Footprints, absolute'!Q13/Production!$H$9*AF_milk_IT -> 7.7871028e-11 | R13: ='Footprints, absolute'!R13/Production!$H$9*AF_milk_IT -> 0.00082493602 | T13: ='Footprints, absolute'!T13*AF_milk_IT -> 0.0093574918 | U13: ='Footprints, absolute'!U13*AF_milk_IT -> 4.2239832
A14: 02211 | B14: Raw milk of cattle | C14: Dairy | D14: Netherlands | E14: NL | F14: ='GHG det, per kg milk'!G46 -> 1.1388791 | G14: ='GHG det, per kg milk'!G42 -> 0.3221955 | H14: ='GHG det, per kg milk'!G43 -> 0.00083083679 | I14: ='GHG det, per kg milk'!G44 -> 0.020716865 | J14: ='GHG det, per kg milk'!G45 -> 0.00085190216 | L14: ='Footprints, absolute'!L14/Production!$I$9*AF_milk_NL -> 0.7664139 | M14: ='Footprints, absolute'!M14/Production!$I$9*AF_milk_NL -> 0.022073534 | N14: ='Footprints, absolute'!N14/Production!$I$9*AF_milk_NL -> 0.0008474029 | O14: ='Footprints, absolute'!O14/Production!$I$9*AF_milk_NL -> 0.0057908868 | P14: ='Footprints, absolute'!P14/Production!$I$9*AF_milk_NL -> 0.070270298 | Q14: ='Footprints, absolute'!Q14/Production!$I$9*AF_milk_NL -> 2.3868869e-11 | R14: ='Footprints, absolute'!R14/Production!$I$9*AF_milk_NL -> 0.00085129052 | T14: ='Footprints, absolute'!T14*AF_milk_NL -> 0.0075988152 | U14: ='Footprints, absolute'!U14*AF_milk_NL -> 0.90415105
A15: 02211 | B15: Raw milk of cattle | C15: Dairy | D15: Poland | E15: PL | F15: ='GHG det, per kg milk'!G51 -> 1.3478302 | G15: ='GHG det, per kg milk'!G47 -> 0.5419399 | H15: ='GHG det, per kg milk'!G48 -> 0.0011759614 | I15: ='GHG det, per kg milk'!G49 -> 0.020093092 | J15: ='GHG det, per kg milk'!G50 -> 0.00083638531 | L15: ='Footprints, absolute'!L15/Production!$J$9*AF_milk_PL -> 1.0326888 | M15: ='Footprints, absolute'!M15/Production!$J$9*AF_milk_PL -> 0.017150686 | N15: ='Footprints, absolute'!N15/Production!$J$9*AF_milk_PL -> 0.0016314221 | O15: ='Footprints, absolute'!O15/Production!$J$9*AF_milk_PL -> 0.0061497727 | P15: ='Footprints, absolute'!P15/Production!$J$9*AF_milk_PL -> 0.079431334 | Q15: ='Footprints, absolute'!Q15/Production!$J$9*AF_milk_PL -> 1.6328412e-11 | R15: ='Footprints, absolute'!R15/Production!$J$9*AF_milk_PL -> 0.00070469438 | T15: ='Footprints, absolute'!T15*AF_milk_PL -> 0.0088334873 | U15: ='Footprints, absolute'!U15*AF_milk_PL -> 5.4535717
A16: 02211 | B16: Raw milk of cattle | C16: Dairy | D16: Spain | E16: ES | F16: ='GHG det, per kg milk'!G56 -> 1.0300389 | G16: ='GHG det, per kg milk'!G52 -> 0.27884907 | H16: ='GHG det, per kg milk'!G53 -> 0.00077041442 | I16: ='GHG det, per kg milk'!G54 -> 0.01975947 | J16: ='GHG det, per kg milk'!G55 -> 0.00071328116 | L16: ='Footprints, absolute'!L16/Production!$K$9*AF_milk_ES -> 1.1170397 | M16: ='Footprints, absolute'!M16/Production!$K$9*AF_milk_ES -> 0.021005385 | N16: ='Footprints, absolute'!N16/Production!$K$9*AF_milk_ES -> 0.0018869003 | O16: ='Footprints, absolute'!O16/Production!$K$9*AF_milk_ES -> 0.050929775 | P16: ='Footprints, absolute'!P16/Production!$K$9*AF_milk_ES -> 0.085598272 | Q16: ='Footprints, absolute'!Q16/Production!$K$9*AF_milk_ES -> 3.2378153e-11 | R16: ='Footprints, absolute'!R16/Production!$K$9*AF_milk_ES -> 0.00065346232 | T16: ='Footprints, absolute'!T16*AF_milk_ES -> 0.01068814 | U16: ='Footprints, absolute'!U16*AF_milk_ES -> 2.9001293
A17: 02211 | B17: Raw milk of cattle | C17: Dairy | D17: Sweden | E17: SE | F17: ='GHG det, per kg milk'!G61 -> 0.95121776 | G17: ='GHG det, per kg milk'!G57 -> 0.19760179 | H17: ='GHG det, per kg milk'!G58 -> 0.0011064216 | I17: ='GHG det, per kg milk'!G59 -> 0.019524873 | J17: ='GHG det, per kg milk'!G60 -> 0.00070869247 | L17: ='Footprints, absolute'!L17/Production!$L$9*AF_milk_SE -> 1.7743078 | M17: ='Footprints, absolute'!M17/Production!$L$9*AF_milk_SE -> 0.017658262 | N17: ='Footprints, absolute'!N17/Production!$L$9*AF_milk_SE -> 0.00088651879 | O17: ='Footprints, absolute'!O17/Production!$L$9*AF_milk_SE -> 0.005574545 | P17: ='Footprints, absolute'!P17/Production!$L$9*AF_milk_SE -> 0.043670453 | Q17: ='Footprints, absolute'!Q17/Production!$L$9*AF_milk_SE -> 1.111115e-11 | R17: ='Footprints, absolute'!R17/Production!$L$9*AF_milk_SE -> 0.00051682885 | T17: ='Footprints, absolute'!T17*AF_milk_SE -> 0.0070430532 | U17: ='Footprints, absolute'!U17*AF_milk_SE -> 0.35178939

Sheet GHG det, per kg milk
K1: * Calculated as percentage of direct emissions due to assumption due to data limitations regarding nitrogen leaching and volatilization from soils in different regions.
A2: GHG emissions (per kg of milk)
S4: Animals | W4: Stables | X4: Slaughter | Z4: Control
A5: Animal products | G5: Sum | H5: Inputs | J5: Soil emissions | L5: Energy use | P5: Land use change | Q5: Feed processing | R5: Transports | AA5: Dairy cows
A6: Code | B6: Name | C6: Category | D6: Country | E6: Country code | F6: Gas | G6: GHG | H6: Production of mineral fertilizer | I6: Production of capital goods | J6: Direct emissions | K6: Indirect emissions* | L6: Diesel use field mach | M6: Energy use in greenhouses | N6: Energy use for irrigation | O6: Energy use for post-harvest proc | P6: LUC emissions | Q6: Feed processing | R6: Feed transports | S6: Enteric fermentation* | T6: Manure management - tot | U6: Manure management - direct | V6: Manure management - indirect | W6: Energy use in stables | X6: Energy use for slaughter | Z6: Total feed, excl LUC | AA6: Feed mix emissions, kg CO2E per kg feed, excl. adjustement manure
A7: 02211 | B7: Raw milk of cattle | C7: Dairy | D7: Denmark | E7: DK | F7: CO2 | G7: =SUM(H7:X7) -> 0.14515622 | H7: ='GHG detailed, absolute'!H7/Production!$B$9*AF_milk_DK -> 0.033773285 | I7: ='GHG detailed, absolute'!I7/Production!$B$9*AF_milk_DK -> 0.01914369 | L7: ='GHG detailed, absolute'!L7/Production!$B$9*AF_milk_DK -> 0.014849058 | N7: ='GHG detailed, absolute'!N7/Production!$B$9*AF_milk_DK -> 3.0598311e-05 | O7: ='GHG detailed, absolute'!O7/Production!$B$9*AF_milk_DK -> 0.0099528167 | P7: ='GHG detailed, absolute'!P7/Production!$B$9*AF_milk_DK -> 0.013241399 | Q7: ='GHG detailed, absolute'!Q7/Production!$B$9*AF_milk_DK -> 0.026663839 | R7: ='GHG detailed, absolute'!R7/Production!$B$9*AF_milk_DK -> 0.026663839 | W7: ='GHG detailed, absolute'!W7/Production!$B$9*AF_milk_DK -> 0 | X7: ='GHG detailed, absolute'!X7/Production!$B$9*AF_milk_DK -> 0.00083770114
A8: 02211 | B8: Raw milk of cattle | C8: Dairy | D8: Denmark | E8: DK | F8: CH4, fossil | G8: =SUM(H8:X8) -> 0.00084506497 | H8: ='GHG detailed, absolute'!H8/Production!$B$9*AF_milk_DK -> 3.7254045e-05 | I8: ='GHG detailed, absolute'!I8/Production!$B$9*AF_milk_DK -> 6.7357429e-05 | L8: ='GHG detailed, absolute'!L8/Production!$B$9*AF_milk_DK -> 6.5776319e-06 | N8: ='GHG detailed, absolute'!N8/Production!$B$9*AF_milk_DK -> 1.023349e-07 | O8: ='GHG detailed, absolute'!O8/Production!$B$9*AF_milk_DK -> 5.9888558e-06 | P8: ='GHG detailed, absolute'!P8/Production!$B$9*AF_milk_DK -> 0 | Q8: ='GHG detailed, absolute'!Q8/Production!$B$9*AF_milk_DK -> 0.00034653896 | R8: ='GHG detailed, absolute'!R8/Production!$B$9*AF_milk_DK -> 0.00034653896 | W8: ='GHG detailed, absolute'!W8/Production!$B$9*AF_milk_DK -> 3.2943073e-05 | X8: ='GHG detailed, absolute'!X8/Production!$B$9*AF_milk_DK -> 1.7636849e-06
A9: 02211 | B9: Raw milk of cattle | C9: Dairy | D9: Denmark | E9: DK | F9: CH4, biogenic | G9: =SUM(H9:T9) -> 0.023283056 | S9: ='GHG detailed, absolute'!S9/Production!$B$9*AF_milk_DK -> 0.017534569 | T9: ='GHG detailed, absolute'!T9/Production!$B$9*AF_milk_DK -> 0.0057484871 | U9: ='GHG detailed, absolute'!U9/Production!$B$9*AF_milk_DK -> 0.0057484871
A10: 02211 | B10: Raw milk of cattle | C10: Dairy | D10: Denmark | E10: DK | F10: N2O | G10: =SUM(H10:T10)+W10+X10 -> 0.00075436221 | H10: ='GHG detailed, absolute'!H10/Production!$B$9*AF_milk_DK -> 4.9455149e-05 | I10: ='GHG detailed, absolute'!I10/Production!$B$9*AF_milk_DK -> 7.7992812e-07 | J10: ='GHG detailed, absolute'!J10/Production!$B$9*AF_milk_DK -> 0.00036063977 | K10: ='GHG detailed, absolute'!K10/Production!$B$9*AF_milk_DK -> 3.6063977e-05 | L10: ='GHG detailed, absolute'!L10/Production!$B$9*AF_milk_DK -> 3.9899997e-07 | N10: ='GHG detailed, absolute'!N10/Production!$B$9*AF_milk_DK -> 1.2594242e-09 | O10: ='GHG detailed, absolute'!O10/Production!$B$9*AF_milk_DK -> 3.6379476e-07 | P10: ='GHG detailed, absolute'!P10/Production!$B$9*AF_milk_DK -> 0 | Q10: ='GHG detailed, absolute'!Q10/Production!$B$9*AF_milk_DK -> 3.3300947e-05 | R10: ='GHG detailed, absolute'!R10/Production!$B$9*AF_milk_DK -> 3.3300947e-05 | T10: ='GHG detailed, absolute'!T10/Production!$B$9*AF_milk_DK -> 0.00023878924 | U10: ='GHG detailed, absolute'!U10/Production!$B$9*AF_milk_DK -> 0.00014070314 | V10: ='GHG detailed, absolute'!V10/Production!$B$9*AF_milk_DK -> 9.8086102e-05 | W10: ='GHG detailed, absolute'!W10/Production!$B$9*AF_milk_DK -> 1.2288145e-06 | X10: ='GHG detailed, absolute'!X10/Production!$B$9*AF_milk_DK -> 3.9377963e-08
A11: 02211 | B11: Raw milk of cattle | C11: Dairy | D11: Denmark | E11: DK | F11: CO2e | G11: =SUM(H11:X11) -> 1.0049225 | H11: =SUMPRODUCT(H7:H10,'Parameters, general'!$B$24:$B$27) -> 0.048384711 | I11: =SUMPRODUCT(I7:I10,'Parameters, general'!$B$24:$B$27) -> 0.021363862 | J11: =SUMPRODUCT(J7:J10,'Parameters, general'!$B$24:$B$27) -> 0.098454657 | K11: =SUMPRODUCT(K7:K10,'Parameters, general'!$B$24:$B$27) -> 0.0098454657 | L11: =SUMPRODUCT(L7:L10,'Parameters, general'!$B$24:$B$27) -> 0.015153998 | M11: =SUMPRODUCT(M7:M10,'Parameters, general'!$B$24:$B$27) -> 0 | N11: =SUMPRODUCT(N7:N10,'Parameters, general'!$B$24:$B$27) -> 3.3991714e-05 | O11: =SUMPRODUCT(O7:O10,'Parameters, general'!$B$24:$B$27) -> 0.010230601 | ... T11: =SUMPRODUCT(T7:T10,'Parameters, general'!$B$24:$B$27) -> 0.22039861 | W11: =SUMPRODUCT(W7:W10,'Parameters, general'!$B$24:$B$27) -> 0.0013171699 | X11: =SUMPRODUCT(X7:X10,'Parameters, general'!$B$24:$B$27) -> 0.00090100914 | Z11: =SUM(H11:R11) -> 0.3088724 | AA11: ='CO2 per kg feed'!F20+'CH4 per kg feed'!F20*CF_GWP_CH4_fossil+'N2O per kg feed'!F20*CF_GWP_N2O -> 0.32935235
A12: 02211 | B12: Raw milk of cattle | C12: Dairy | D12: France | E12: FR | F12: CO2 | G12: =SUM(H12:X12) -> 0.18854038 | H12: ='GHG detailed, absolute'!H12/Production!$C$9*AF_milk_FR -> 0.029547524 | I12: ='GHG detailed, absolute'!I12/Production!$C$9*AF_milk_FR -> 0.024440377 | L12: ='GHG detailed, absolute'!L12/Production!$C$9*AF_milk_FR -> 0.0177722 | N12: ='GHG detailed, absolute'!N12/Production!$C$9*AF_milk_FR -> 0.00035893798 | O12: ='GHG detailed, absolute'!O12/Production!$C$9*AF_milk_FR -> 0.0097955658 | P12: ='GHG detailed, absolute'!P12/Production!$C$9*AF_milk_FR -> 0.015469464 | Q12: ='GHG detailed, absolute'!Q12/Production!$C$9*AF_milk_FR -> 0.036760688 | R12: ='GHG detailed, absolute'!R12/Production!$C$9*AF_milk_FR -> 0.036760688 | W12: ='GHG detailed, absolute'!W12/Production!$C$9*AF_milk_FR -> 0.017192258 | X12: ='GHG detailed, absolute'!X12/Production!$C$9*AF_milk_FR -> 0.00044267572
A13: 02211 | B13: Raw milk of cattle | C13: Dairy | D13: France | E13: FR | F13: CH4, fossil | G13: =SUM(H13:X13) -> 0.00096964335 | H13: ='GHG detailed, absolute'!H13/Production!$C$9*AF_milk_FR -> 1.6520272e-05 | I13: ='GHG detailed, absolute'!I13/Production!$C$9*AF_milk_FR -> 8.5993918e-05 | L13: ='GHG detailed, absolute'!L13/Production!$C$9*AF_milk_FR -> 7.8724852e-06 | N13: ='GHG detailed, absolute'!N13/Production!$C$9*AF_milk_FR -> 1.1281391e-06 | O13: ='GHG detailed, absolute'!O13/Production!$C$9*AF_milk_FR -> 5.5508611e-06 | P13: ='GHG detailed, absolute'!P13/Production!$C$9*AF_milk_FR -> 0 | Q13: ='GHG detailed, absolute'!Q13/Production!$C$9*AF_milk_FR -> 0.00039877597 | R13: ='GHG detailed, absolute'!R13/Production!$C$9*AF_milk_FR -> 0.00039877597 | W13: ='GHG detailed, absolute'!W13/Production!$C$9*AF_milk_FR -> 5.33013e-05 | X13: ='GHG detailed, absolute'!X13/Production!$C$9*AF_milk_FR -> 1.724423e-06
A14: 02211 | B14: Raw milk of cattle | C14: Dairy | D14: France | E14: FR | F14: CH4, biogenic | G14: =SUM(H14:T14) -> 0.021746613 | S14: ='GHG detailed, absolute'!S14/Production!$C$9*AF_milk_FR -> 0.019538529 | T14: ='GHG detailed, absolute'!T14/Production!$C$9*AF_milk_FR -> 0.0022080844 | U14: ='GHG detailed, absolute'!U14/Production!$C$9*AF_milk_FR -> 0.0022080844
A15: 02211 | B15: Raw milk of cattle | C15: Dairy | D15: France | E15: FR | F15: N2O | G15: =SUM(H15:T15)+W15+X15 -> 0.00071830489 | H15: ='GHG detailed, absolute'!H15/Production!$C$9*AF_milk_FR -> 2.5221759e-05 | I15: ='GHG detailed, absolute'!I15/Production!$C$9*AF_milk_FR -> 9.9571906e-07 | J15: ='GHG detailed, absolute'!J15/Production!$C$9*AF_milk_FR -> 0.00037106738 | K15: ='GHG detailed, absolute'!K15/Production!$C$9*AF_milk_FR -> 3.7106738e-05 | L15: ='GHG detailed, absolute'!L15/Production!$C$9*AF_milk_FR -> 4.7754594e-07 | N15: ='GHG detailed, absolute'!N15/Production!$C$9*AF_milk_FR -> 1.5112376e-08 | O15: ='GHG detailed, absolute'!O15/Production!$C$9*AF_milk_FR -> 3.6644464e-07 | P15: ='GHG detailed, absolute'!P15/Production!$C$9*AF_milk_FR -> 0 | Q15: ='GHG detailed, absolute'!Q15/Production!$C$9*AF_milk_FR -> 3.6417159e-05 | R15: ='GHG detailed, absolute'!R15/Production!$C$9*AF_milk_FR -> 3.6417159e-05 | T15: ='GHG detailed, absolute'!T15/Production!$C$9*AF_milk_FR -> 0.00020858237 | U15: ='GHG detailed, absolute'!U15/Production!$C$9*AF_milk_FR -> 0.00014488173 | V15: ='GHG detailed, absolute'!V15/Production!$C$9*AF_milk_FR -> 6.3700635e-05 | W15: ='GHG detailed, absolute'!W15/Production!$C$9*AF_milk_FR -> 1.6112963e-06 | X15: ='GHG detailed, absolute'!X15/Production!$C$9*AF_milk_FR -> 2.6207745e-08
A16: 02211 | B16: Raw milk of cattle | C16: Dairy | D16: France | E16: FR | F16: CO2e | G16: =SUM(H16:X16) -> 1.0006915 | H16: =SUMPRODUCT(H12:H15,'Parameters, general'!$B$24:$B$27) -> 0.036925368 | I16: =SUMPRODUCT(I12:I15,'Parameters, general'!$B$24:$B$27) -> 0.027274827 | J16: =SUMPRODUCT(J12:J15,'Parameters, general'!$B$24:$B$27) -> 0.1013014 | K16: =SUMPRODUCT(K12:K15,'Parameters, general'!$B$24:$B$27) -> 0.01013014 | L16: =SUMPRODUCT(L12:L15,'Parameters, general'!$B$24:$B$27) -> 0.01813717 | M16: =SUMPRODUCT(M12:M15,'Parameters, general'!$B$24:$B$27) -> 0 | N16: =SUMPRODUCT(N12:N15,'Parameters, general'!$B$24:$B$27) -> 0.0003966822 | O16: =SUMPRODUCT(O12:O15,'Parameters, general'!$B$24:$B$27) -> 0.010061021 | ... T16: =SUMPRODUCT(T12:T15,'Parameters, general'!$B$24:$B$27) -> 0.11656127 | W16: =SUMPRODUCT(W12:W15,'Parameters, general'!$B$24:$B$27) -> 0.01922052 | X16: =SUMPRODUCT(X12:X15,'Parameters, general'!$B$24:$B$27) -> 0.00050121823 | Z16: =SUM(H16:R16) -> 0.33686826 | AA16: ='CO2 per kg feed'!F36+'CH4 per kg feed'!F36*CF_GWP_CH4_fossil+'N2O per kg feed'!F36*CF_GWP_N2O -> 0.26766924
A17: 02211 | B17: Raw milk of cattle | C17: Dairy | D17: Germany | E17: DE | F17: CO2 | G17: =SUM(H17:X17) -> 0.26771039 | H17: ='GHG detailed, absolute'!H17/Production!$D$9*AF_milk_DE -> 0.021714728 | I17: ='GHG detailed, absolute'!I17/Production!$D$9*AF_milk_DE -> 0.023669299 | L17: ='GHG detailed, absolute'!L17/Production!$D$9*AF_milk_DE -> 0.014925582 | N17: ='GHG detailed, absolute'!N17/Production!$D$9*AF_milk_DE -> 3.1603201e-05 | O17: ='GHG detailed, absolute'!O17/Production!$D$9*AF_milk_DE -> 0.0045394945 | P17: ='GHG detailed, absolute'!P17/Production!$D$9*AF_milk_DE -> 0.019267566 | Q17: ='GHG detailed, absolute'!Q17/Production!$D$9*AF_milk_DE -> 0.04387909 | R17: ='GHG detailed, absolute'!R17/Production!$D$9*AF_milk_DE -> 0.04387909 | W17: ='GHG detailed, absolute'!W17/Production!$D$9*AF_milk_DE -> 0.09478009 | X17: ='GHG detailed, absolute'!X17/Production!$D$9*AF_milk_DE -> 0.0010238523
A18: 02211 | B18: Raw milk of cattle | C18: Dairy | D18: Germany | E18: DE | F18: CH4, fossil | G18: =SUM(H18:X18) -> 0.0010654407 | H18: ='GHG detailed, absolute'!H18/Production!$D$9*AF_milk_DE -> 2.0074241e-05 | I18: ='GHG detailed, absolute'!I18/Production!$D$9*AF_milk_DE -> 8.3280866e-05 | L18: ='GHG detailed, absolute'!L18/Production!$D$9*AF_milk_DE -> 6.6115293e-06 | N18: ='GHG detailed, absolute'!N18/Production!$D$9*AF_milk_DE -> 1.0399728e-07 | O18: ='GHG detailed, absolute'!O18/Production!$D$9*AF_milk_DE -> 3.0476256e-06 | P18: ='GHG detailed, absolute'!P18/Production!$D$9*AF_milk_DE -> 0 | Q18: ='GHG detailed, absolute'!Q18/Production!$D$9*AF_milk_DE -> 0.00038427142 | R18: ='GHG detailed, absolute'!R18/Production!$D$9*AF_milk_DE -> 0.00038427142 | W18: ='GHG detailed, absolute'!W18/Production!$D$9*AF_milk_DE -> 0.0001813039 | X18: ='GHG detailed, absolute'!X18/Production!$D$9*AF_milk_DE -> 2.4757302e-06
A19: 02211 | B19: Raw milk of cattle | C19: Dairy | D19: Germany | E19: DE | F19: CH4, biogenic | G19: =SUM(H19:T19) -> 0.021556166 | S19: ='GHG detailed, absolute'!S19/Production!$D$9*AF_milk_DE -> 0.018217977 | T19: ='GHG detailed, absolute'!T19/Production!$D$9*AF_milk_DE -> 0.0033381892 | U19: ='GHG detailed, absolute'!U19/Production!$D$9*AF_milk_DE -> 0.0033381892
A20: 02211 | B20: Raw milk of cattle | C20: Dairy | D20: Germany | E20: DE | F20: N2O | G20: =SUM(H20:T20)+W20+X20 -> 0.00060727654 | H20: ='GHG detailed, absolute'!H20/Production!$D$9*AF_milk_DE -> 2.6843206e-05 | I20: ='GHG detailed, absolute'!I20/Production!$D$9*AF_milk_DE -> 9.6430477e-07 | J20: ='GHG detailed, absolute'!J20/Production!$D$9*AF_milk_DE -> 0.00026145935 | K20: ='GHG detailed, absolute'!K20/Production!$D$9*AF_milk_DE -> 2.6145935e-05 | L20: ='GHG detailed, absolute'!L20/Production!$D$9*AF_milk_DE -> 4.0105619e-07 | N20: ='GHG detailed, absolute'!N20/Production!$D$9*AF_milk_DE -> 1.3087359e-09 | O20: ='GHG detailed, absolute'!O20/Production!$D$9*AF_milk_DE -> 1.6254878e-07 | P20: ='GHG detailed, absolute'!P20/Production!$D$9*AF_milk_DE -> 0 | Q20: ='GHG detailed, absolute'!Q20/Production!$D$9*AF_milk_DE -> 3.4538071e-05 | R20: ='GHG detailed, absolute'!R20/Production!$D$9*AF_milk_DE -> 3.4538071e-05 | T20: ='GHG detailed, absolute'!T20/Production!$D$9*AF_milk_DE -> 0.00021793439 | U20: ='GHG detailed, absolute'!U20/Production!$D$9*AF_milk_DE -> 0.0001302664 | V20: ='GHG detailed, absolute'!V20/Production!$D$9*AF_milk_DE -> 8.7667986e-05 | W20: ='GHG detailed, absolute'!W20/Production!$D$9*AF_milk_DE -> 4.2449309e-06 | X20: ='GHG detailed, absolute'!X20/Production!$D$9*AF_milk_DE -> 4.3366148e-08
A21: 02211 | B21: Raw milk of cattle | C21: Dairy | D21: Germany | E21: DE | F21: CO2e | G21: =SUM(H21:X21) -> 1.0472635 | H21: =SUMPRODUCT(H17:H20,'Parameters, general'!$B$24:$B$27) -> 0.029641136 | I21: =SUMPRODUCT(I17:I20,'Parameters, general'!$B$24:$B$27) -> 0.026414324 | J21: =SUMPRODUCT(J17:J20,'Parameters, general'!$B$24:$B$27) -> 0.071378402 | K21: =SUMPRODUCT(K17:K20,'Parameters, general'!$B$24:$B$27) -> 0.0071378402 | L21: =SUMPRODUCT(L17:L20,'Parameters, general'!$B$24:$B$27) -> 0.015232093 | M21: =SUMPRODUCT(M17:M20,'Parameters, general'!$B$24:$B$27) -> 0 | N21: =SUMPRODUCT(N17:N20,'Parameters, general'!$B$24:$B$27) -> 3.5059605e-05 | O21: =SUMPRODUCT(O17:O20,'Parameters, general'!$B$24:$B$27) -> 0.0046746896 | ... T21: =SUMPRODUCT(T17:T20,'Parameters, general'!$B$24:$B$27) -> 0.1496272 | W21: =SUMPRODUCT(W17:W20,'Parameters, general'!$B$24:$B$27) -> 0.10134181 | X21: =SUMPRODUCT(X17:X20,'Parameters, general'!$B$24:$B$27) -> 0.001109468 | Z21: =SUM(H21:R21) -> 0.30329965 | AA21: ='CO2 per kg feed'!F52+'CH4 per kg feed'!F52*CF_GWP_CH4_fossil+'N2O per kg feed'!F52*CF_GWP_N2O -> 0.25510784
A22: 02211 | B22: Raw milk of cattle | C22: Dairy | D22: Greece | E22: GR | F22: CO2 | G22: =SUM(H22:X22) -> 0.43306998 | H22: ='GHG detailed, absolute'!H22/Production!$E$9*AF_milk_GR -> 0.057680424 | I22: ='GHG detailed, absolute'!I22/Production!$E$9*AF_milk_GR -> 0.024171613 | L22: ='GHG detailed, absolute'!L22/Production!$E$9*AF_milk_GR -> 0.031904429 | N22: ='GHG detailed, absolute'!N22/Production!$E$9*AF_milk_GR -> 0.0040057675 | O22: ='GHG detailed, absolute'!O22/Production!$E$9*AF_milk_GR -> 0.019621094 | P22: ='GHG detailed, absolute'!P22/Production!$E$9*AF_milk_GR -> 0.025821298 | Q22: ='GHG detailed, absolute'!Q22/Production!$E$9*AF_milk_GR -> 0.053472638 | R22: ='GHG detailed, absolute'!R22/Production!$E$9*AF_milk_GR -> 0.053472638 | W22: ='GHG detailed, absolute'!W22/Production!$E$9*AF_milk_GR -> 0.16142909 | X22: ='GHG detailed, absolute'!X22/Production!$E$9*AF_milk_GR -> 0.0014909874
A23: 02211 | B23: Raw milk of cattle | C23: Dairy | D23: Greece | E23: GR | F23: CH4, fossil | G23: =SUM(H23:X23) -> 0.0010722308 | H23: ='GHG detailed, absolute'!H23/Production!$E$9*AF_milk_GR -> 1.2116124e-06 | I23: ='GHG detailed, absolute'!I23/Production!$E$9*AF_milk_GR -> 8.5048268e-05 | L23: ='GHG detailed, absolute'!L23/Production!$E$9*AF_milk_GR -> 1.4132586e-05 | N23: ='GHG detailed, absolute'!N23/Production!$E$9*AF_milk_GR -> 1.2197882e-05 | O23: ='GHG detailed, absolute'!O23/Production!$E$9*AF_milk_GR -> 1.6098129e-05 | P23: ='GHG detailed, absolute'!P23/Production!$E$9*AF_milk_GR -> 0 | Q23: ='GHG detailed, absolute'!Q23/Production!$E$9*AF_milk_GR -> 0.0003097814 | R23: ='GHG detailed, absolute'!R23/Production!$E$9*AF_milk_GR -> 0.0003097814 | W23: ='GHG detailed, absolute'!W23/Production!$E$9*AF_milk_GR -> 0.00032045938 | X23: ='GHG detailed, absolute'!X23/Production!$E$9*AF_milk_GR -> 3.5201736e-06
A24: 02211 | B24: Raw milk of cattle | C24: Dairy | D24: Greece | E24: GR | F24: CH4, biogenic | G24: =SUM(H24:T24) -> 0.019491261 | S24: ='GHG detailed, absolute'!S24/Production!$E$9*AF_milk_GR -> 0.017815051 | T24: ='GHG detailed, absolute'!T24/Production!$E$9*AF_milk_GR -> 0.0016762093 | U24: ='GHG detailed, absolute'!U24/Production!$E$9*AF_milk_GR -> 0.0016762093
A25: 02211 | B25: Raw milk of cattle | C25: Dairy | D25: Greece | E25: GR | F25: N2O | G25: =SUM(H25:T25)+W25+X25 -> 0.00090498954 | H25: ='GHG detailed, absolute'!H25/Production!$E$9*AF_milk_GR -> 6.6610742e-06 | I25: ='GHG detailed, absolute'!I25/Production!$E$9*AF_milk_GR -> 9.8476942e-07 | J25: ='GHG detailed, absolute'!J25/Production!$E$9*AF_milk_GR -> 0.00047961454 | K25: ='GHG detailed, absolute'!K25/Production!$E$9*AF_milk_GR -> 4.7961454e-05 | L25: ='GHG detailed, absolute'!L25/Production!$E$9*AF_milk_GR -> 8.5728444e-07 | N25: ='GHG detailed, absolute'!N25/Production!$E$9*AF_milk_GR -> 1.7049094e-07 | O25: ='GHG detailed, absolute'!O25/Production!$E$9*AF_milk_GR -> 6.9282969e-07 | P25: ='GHG detailed, absolute'!P25/Production!$E$9*AF_milk_GR -> 0 | Q25: ='GHG detailed, absolute'!Q25/Production!$E$9*AF_milk_GR -> 2.4293189e-05 | R25: ='GHG detailed, absolute'!R25/Production!$E$9*AF_milk_GR -> 2.4293189e-05 | T25: ='GHG detailed, absolute'!T25/Production!$E$9*AF_milk_GR -> 0.00031385471 | U25: ='GHG detailed, absolute'!U25/Production!$E$9*AF_milk_GR -> 0.00023593319 | V25: ='GHG detailed, absolute'!V25/Production!$E$9*AF_milk_GR -> 7.7921514e-05 | W25: ='GHG detailed, absolute'!W25/Production!$E$9*AF_milk_GR -> 5.5551883e-06 | X25: ='GHG detailed, absolute'!X25/Production!$E$9*AF_milk_GR -> 5.0831692e-08
A26: 02211 | B26: Raw milk of cattle | C26: Dairy | D26: Greece | E26: GR | F26: CO2e | G26: =SUM(H26:X26) -> 1.2383486 | H26: =SUMPRODUCT(H22:H25,'Parameters, general'!$B$24:$B$27) -> 0.059535004 | I26: =SUMPRODUCT(I22:I25,'Parameters, general'!$B$24:$B$27) -> 0.026974893 | J26: =SUMPRODUCT(J22:J25,'Parameters, general'!$B$24:$B$27) -> 0.13093477 | K26: =SUMPRODUCT(K22:K25,'Parameters, general'!$B$24:$B$27) -> 0.013093477 | L26: =SUMPRODUCT(L22:L25,'Parameters, general'!$B$24:$B$27) -> 0.032559619 | M26: =SUMPRODUCT(M22:M25,'Parameters, general'!$B$24:$B$27) -> 0 | N26: =SUMPRODUCT(N22:N25,'Parameters, general'!$B$24:$B$27) -> 0.0044158084 | O26: =SUMPRODUCT(O22:O25,'Parameters, general'!$B$24:$B$27) -> 0.020289961 | ... T26: =SUMPRODUCT(T22:T25,'Parameters, general'!$B$24:$B$27) -> 0.13093999 | W26: =SUMPRODUCT(W22:W25,'Parameters, general'!$B$24:$B$27) -> 0.17249535 | X26: =SUMPRODUCT(X22:X25,'Parameters, general'!$B$24:$B$27) -> 0.0016097656 | Z26: =SUM(H26:R26) -> 0.45229716 | AA26: ='CO2 per kg feed'!F68+'CH4 per kg feed'!F68*CF_GWP_CH4_fossil+'N2O per kg feed'!F68*CF_GWP_N2O -> 0.41434259
A27: 02211 | B27: Raw milk of cattle | C27: Dairy | D27: Hungary | E27: HU | F27: CO2 | G27: =SUM(H27:X27) -> 0.4204242 | H27: ='GHG detailed, absolute'!H27/Production!$F$9*AF_milk_HU -> 0.033344591 | I27: ='GHG detailed, absolute'!I27/Production!$F$9*AF_milk_HU -> 0.022096344 | L27: ='GHG detailed, absolute'!L27/Production!$F$9*AF_milk_HU -> 0.025864673 | N27: ='GHG detailed, absolute'!N27/Production!$F$9*AF_milk_HU -> 0.00010882727 | O27: ='GHG detailed, absolute'!O27/Production!$F$9*AF_milk_HU -> 0.015977849 | P27: ='GHG detailed, absolute'!P27/Production!$F$9*AF_milk_HU -> 0.035692686 | Q27: ='GHG detailed, absolute'!Q27/Production!$F$9*AF_milk_HU -> 0.099569605 | R27: ='GHG detailed, absolute'!R27/Production!$F$9*AF_milk_HU -> 0.099569605 | W27: ='GHG detailed, absolute'!W27/Production!$F$9*AF_milk_HU -> 0.087052366 | X27: ='GHG detailed, absolute'!X27/Production!$F$9*AF_milk_HU -> 0.0011476521
A28: 02211 | B28: Raw milk of cattle | C28: Dairy | D28: Hungary | E28: HU | F28: CH4, fossil | G28: =SUM(H28:X28) -> 0.0012766862 | H28: ='GHG detailed, absolute'!H28/Production!$F$9*AF_milk_HU -> 1.7628714e-06 | I28: ='GHG detailed, absolute'!I28/Production!$F$9*AF_milk_HU -> 7.7746396e-05 | L28: ='GHG detailed, absolute'!L28/Production!$F$9*AF_milk_HU -> 1.1457178e-05 | N28: ='GHG detailed, absolute'!N28/Production!$F$9*AF_milk_HU -> 3.2957773e-07 | O28: ='GHG detailed, absolute'!O28/Production!$F$9*AF_milk_HU -> 1.3018592e-05 | P28: ='GHG detailed, absolute'!P28/Production!$F$9*AF_milk_HU -> 0 | Q28: ='GHG detailed, absolute'!Q28/Production!$F$9*AF_milk_HU -> 0.00047460677 | R28: ='GHG detailed, absolute'!R28/Production!$F$9*AF_milk_HU -> 0.00047460677 | W28: ='GHG detailed, absolute'!W28/Production!$F$9*AF_milk_HU -> 0.00021979559 | X28: ='GHG detailed, absolute'!X28/Production!$F$9*AF_milk_HU -> 3.3624262e-06
A29: 02211 | B29: Raw milk of cattle | C29: Dairy | D29: Hungary | E29: HU | F29: CH4, biogenic | G29: =SUM(H29:T29) -> 0.021642644 | S29: ='GHG detailed, absolute'!S29/Production!$F$9*AF_milk_HU -> 0.018460353 | T29: ='GHG detailed, absolute'!T29/Production!$F$9*AF_milk_HU -> 0.0031822912 | U29: ='GHG detailed, absolute'!U29/Production!$F$9*AF_milk_HU -> 0.0031822912
A30: 02211 | B30: Raw milk of cattle | C30: Dairy | D30: Hungary | E30: HU | F30: N2O | G30: =SUM(H30:T30)+W30+X30 -> 0.00086838692 | H30: ='GHG detailed, absolute'!H30/Production!$F$9*AF_milk_HU -> 1.4524636e-05 | I30: ='GHG detailed, absolute'!I30/Production!$F$9*AF_milk_HU -> 9.0022143e-07 | J30: ='GHG detailed, absolute'!J30/Production!$F$9*AF_milk_HU -> 0.00039724193 | K30: ='GHG detailed, absolute'!K30/Production!$F$9*AF_milk_HU -> 3.9724193e-05 | L30: ='GHG detailed, absolute'!L30/Production!$F$9*AF_milk_HU -> 6.9499385e-07 | N30: ='GHG detailed, absolute'!N30/Production!$F$9*AF_milk_HU -> 4.6403099e-09 | O30: ='GHG detailed, absolute'!O30/Production!$F$9*AF_milk_HU -> 5.6905029e-07 | P30: ='GHG detailed, absolute'!P30/Production!$F$9*AF_milk_HU -> 0 | Q30: ='GHG detailed, absolute'!Q30/Production!$F$9*AF_milk_HU -> 2.9592662e-05 | R30: ='GHG detailed, absolute'!R30/Production!$F$9*AF_milk_HU -> 2.9592662e-05 | T30: ='GHG detailed, absolute'!T30/Production!$F$9*AF_milk_HU -> 0.00035245237 | U30: ='GHG detailed, absolute'!U30/Production!$F$9*AF_milk_HU -> 0.00025817282 | V30: ='GHG detailed, absolute'!V30/Production!$F$9*AF_milk_HU -> 9.4279553e-05 | W30: ='GHG detailed, absolute'!W30/Production!$F$9*AF_milk_HU -> 3.049991e-06 | X30: ='GHG detailed, absolute'!X30/Production!$F$9*AF_milk_HU -> 3.9561026e-08
A31: 02211 | B31: Raw milk of cattle | C31: Dairy | D31: Hungary | E31: HU | F31: CO2e | G31: =SUM(H31:X31) -> 1.2798905 | H31: =SUMPRODUCT(H27:H30,'Parameters, general'!$B$24:$B$27) -> 0.037362351 | I31: =SUMPRODUCT(I27:I30,'Parameters, general'!$B$24:$B$27) -> 0.024658947 | J31: =SUMPRODUCT(J27:J30,'Parameters, general'!$B$24:$B$27) -> 0.10844705 | K31: =SUMPRODUCT(K27:K30,'Parameters, general'!$B$24:$B$27) -> 0.010844705 | L31: =SUMPRODUCT(L27:L30,'Parameters, general'!$B$24:$B$27) -> 0.02639583 | M31: =SUMPRODUCT(M27:M30,'Parameters, general'!$B$24:$B$27) -> 0 | N31: =SUMPRODUCT(N27:N30,'Parameters, general'!$B$24:$B$27) -> 0.00011991549 | O31: =SUMPRODUCT(O27:O30,'Parameters, general'!$B$24:$B$27) -> 0.016521154 | ... T31: =SUMPRODUCT(T27:T30,'Parameters, general'!$B$24:$B$27) -> 0.18214136 | W31: =SUMPRODUCT(W27:W30,'Parameters, general'!$B$24:$B$27) -> 0.094434922 | X31: =SUMPRODUCT(X27:X30,'Parameters, general'!$B$24:$B$27) -> 0.0012586525 | Z31: =SUM(H31:R31) -> 0.503626 | AA31: ='CO2 per kg feed'!F84+'CH4 per kg feed'!F84*CF_GWP_CH4_fossil+'N2O per kg feed'!F84*CF_GWP_N2O -> 0.41909612
A32: 02211 | B32: Raw milk of cattle | C32: Dairy | D32: Ireland | E32: IE | F32: CO2 | G32: =SUM(H32:X32) -> 0.13988284 | H32: ='GHG detailed, absolute'!H32/Production!$G$9*AF_milk_IE -> 0.023357645 | I32: ='GHG detailed, absolute'!I32/Production!$G$9*AF_milk_IE -> 0.028358406 | L32: ='GHG detailed, absolute'!L32/Production!$G$9*AF_milk_IE -> 0.016829335 | N32: ='GHG detailed, absolute'!N32/Production!$G$9*AF_milk_IE -> 6.6962264e-05 | O32: ='GHG detailed, absolute'!O32/Production!$G$9*AF_milk_IE -> 0.0055404202 | P32: ='GHG detailed, absolute'!P32/Production!$G$9*AF_milk_IE -> 0.0026265212 | Q32: ='GHG detailed, absolute'!Q32/Production!$G$9*AF_milk_IE -> 0.0071204915 | R32: ='GHG detailed, absolute'!R32/Production!$G$9*AF_milk_IE -> 0.0071204915 | W32: ='GHG detailed, absolute'!W32/Production!$G$9*AF_milk_IE -> 0.047742952 | X32: ='GHG detailed, absolute'!X32/Production!$G$9*AF_milk_IE -> 0.0011196183
A33: 02211 | B33: Raw milk of cattle | C33: Dairy | D33: Ireland | E33: IE | F33: CH4, fossil | G33: =SUM(H33:X33) -> 0.0001907991 | H33: ='GHG detailed, absolute'!H33/Production!$G$9*AF_milk_IE -> 9.4555393e-07 | I33: ='GHG detailed, absolute'!I33/Production!$G$9*AF_milk_IE -> 9.9779578e-05 | L33: ='GHG detailed, absolute'!L33/Production!$G$9*AF_milk_IE -> 7.4548281e-06 | N33: ='GHG detailed, absolute'!N33/Production!$G$9*AF_milk_IE -> 1.9842204e-07 | O33: ='GHG detailed, absolute'!O33/Production!$G$9*AF_milk_IE -> 2.8963123e-06 | P33: ='GHG detailed, absolute'!P33/Production!$G$9*AF_milk_IE -> 0 | Q33: ='GHG detailed, absolute'!Q33/Production!$G$9*AF_milk_IE -> 1.3006337e-05 | R33: ='GHG detailed, absolute'!R33/Production!$G$9*AF_milk_IE -> 1.3006337e-05 | W33: ='GHG detailed, absolute'!W33/Production!$G$9*AF_milk_IE -> 5.1451797e-05 | X33: ='GHG detailed, absolute'!X33/Production!$G$9*AF_milk_IE -> 2.0599321e-06
A34: 02211 | B34: Raw milk of cattle | C34: Dairy | D34: Ireland | E34: IE | F34: CH4, biogenic | G34: =SUM(H34:T34) -> 0.023271936 | S34: ='GHG detailed, absolute'!S34/Production!$G$9*AF_milk_IE -> 0.020711846 | T34: ='GHG detailed, absolute'!T34/Production!$G$9*AF_milk_IE -> 0.0025600901 | U34: ='GHG detailed, absolute'!U34/Production!$G$9*AF_milk_IE -> 0.0025600901
A35: 02211 | B35: Raw milk of cattle | C35: Dairy | D35: Ireland | E35: IE | F35: N2O | G35: =SUM(H35:T35)+W35+X35 -> 0.00060627249 | H35: ='GHG detailed, absolute'!H35/Production!$G$9*AF_milk_IE -> 9.051268e-06 | I35: ='GHG detailed, absolute'!I35/Production!$G$9*AF_milk_IE -> 1.1553425e-06 | J35: ='GHG detailed, absolute'!J35/Production!$G$9*AF_milk_IE -> 0.00037061414 | K35: ='GHG detailed, absolute'!K35/Production!$G$9*AF_milk_IE -> 3.7061414e-05 | L35: ='GHG detailed, absolute'!L35/Production!$G$9*AF_milk_IE -> 4.522108e-07 | N35: ='GHG detailed, absolute'!N35/Production!$G$9*AF_milk_IE -> 2.8756737e-09 | O35: ='GHG detailed, absolute'!O35/Production!$G$9*AF_milk_IE -> 1.995777e-07 | P35: ='GHG detailed, absolute'!P35/Production!$G$9*AF_milk_IE -> 0 | Q35: ='GHG detailed, absolute'!Q35/Production!$G$9*AF_milk_IE -> 8.2317799e-07 | R35: ='GHG detailed, absolute'!R35/Production!$G$9*AF_milk_IE -> 8.2317799e-07 | T35: ='GHG detailed, absolute'!T35/Production!$G$9*AF_milk_IE -> 0.00018429537 | U35: ='GHG detailed, absolute'!U35/Production!$G$9*AF_milk_IE -> 0.00012886322 | V35: ='GHG detailed, absolute'!V35/Production!$G$9*AF_milk_IE -> 5.5432151e-05 | W35: ='GHG detailed, absolute'!W35/Production!$G$9*AF_milk_IE -> 1.753912e-06 | X35: ='GHG detailed, absolute'!X35/Production!$G$9*AF_milk_IE -> 4.0019475e-08
A36: 02211 | B36: Raw milk of cattle | C36: Dairy | D36: Ireland | E36: IE | F36: CO2e | G36: =SUM(H36:X36) -> 0.93942331 | H36: =SUMPRODUCT(H32:H35,'Parameters, general'!$B$24:$B$27) -> 0.025856819 | I36: =SUMPRODUCT(I32:I35,'Parameters, general'!$B$24:$B$27) -> 0.031647246 | J36: =SUMPRODUCT(J32:J35,'Parameters, general'!$B$24:$B$27) -> 0.10117766 | K36: =SUMPRODUCT(K32:K35,'Parameters, general'!$B$24:$B$27) -> 0.010117766 | L36: =SUMPRODUCT(L32:L35,'Parameters, general'!$B$24:$B$27) -> 0.017174943 | M36: =SUMPRODUCT(M32:M35,'Parameters, general'!$B$24:$B$27) -> 0 | N36: =SUMPRODUCT(N32:N35,'Parameters, general'!$B$24:$B$27) -> 7.36603e-05 | O36: =SUMPRODUCT(O32:O35,'Parameters, general'!$B$24:$B$27) -> 0.005681215 | ... T36: =SUMPRODUCT(T32:T35,'Parameters, general'!$B$24:$B$27) -> 0.11943507 | W36: =SUMPRODUCT(W32:W35,'Parameters, general'!$B$24:$B$27) -> 0.049755033 | X36: =SUMPRODUCT(X32:X35,'Parameters, general'!$B$24:$B$27) -> 0.0011919296 | Z36: =SUM(H36:R36) -> 0.20982145 | AA36: ='CO2 per kg feed'!F100+'CH4 per kg feed'!F100*CF_GWP_CH4_fossil+'N2O per kg feed'!F100*CF_GWP_N2O -> 0.13884603
A37: 02211 | B37: Raw milk of cattle | C37: Dairy | D37: Italy | E37: IT | F37: CO2 | G37: =SUM(H37:X37) -> 0.34128923 | H37: ='GHG detailed, absolute'!H37/Production!$H$9*AF_milk_IT -> 0.019822745 | I37: ='GHG detailed, absolute'!I37/Production!$H$9*AF_milk_IT -> 0.021540832 | L37: ='GHG detailed, absolute'!L37/Production!$H$9*AF_milk_IT -> 0.014071748 | N37: ='GHG detailed, absolute'!N37/Production!$H$9*AF_milk_IT -> 0.00023006348 | O37: ='GHG detailed, absolute'!O37/Production!$H$9*AF_milk_IT -> 0.0051846824 | P37: ='GHG detailed, absolute'!P37/Production!$H$9*AF_milk_IT -> 0.035542667 | Q37: ='GHG detailed, absolute'!Q37/Production!$H$9*AF_milk_IT -> 0.074949403 | R37: ='GHG detailed, absolute'!R37/Production!$H$9*AF_milk_IT -> 0.074949403 | W37: ='GHG detailed, absolute'!W37/Production!$H$9*AF_milk_IT -> 0.0939619 | X37: ='GHG detailed, absolute'!X37/Production!$H$9*AF_milk_IT -> 0.0010357867
A38: 02211 | B38: Raw milk of cattle | C38: Dairy | D38: Italy | E38: IT | F38: CH4, fossil | G38: =SUM(H38:X38) -> 0.0015417531 | H38: ='GHG detailed, absolute'!H38/Production!$H$9*AF_milk_IT -> 3.0269553e-06 | I38: ='GHG detailed, absolute'!I38/Production!$H$9*AF_milk_IT -> 7.5791816e-05 | L38: ='GHG detailed, absolute'!L38/Production!$H$9*AF_milk_IT -> 6.2333099e-06 | N38: ='GHG detailed, absolute'!N38/Production!$H$9*AF_milk_IT -> 7.4416453e-07 | O38: ='GHG detailed, absolute'!O38/Production!$H$9*AF_milk_IT -> 4.5275144e-06 | P38: ='GHG detailed, absolute'!P38/Production!$H$9*AF_milk_IT -> 0 | Q38: ='GHG detailed, absolute'!Q38/Production!$H$9*AF_milk_IT -> 0.00051920655 | R38: ='GHG detailed, absolute'!R38/Production!$H$9*AF_milk_IT -> 0.00051920655 | W38: ='GHG detailed, absolute'!W38/Production!$H$9*AF_milk_IT -> 0.00040847359 | X38: ='GHG detailed, absolute'!X38/Production!$H$9*AF_milk_IT -> 4.5426784e-06
A39: 02211 | B39: Raw milk of cattle | C39: Dairy | D39: Italy | E39: IT | F39: CH4, biogenic | G39: =SUM(H39:T39) -> 0.02471509 | S39: ='GHG detailed, absolute'!S39/Production!$H$9*AF_milk_IT -> 0.019963522 | T39: ='GHG detailed, absolute'!T39/Production!$H$9*AF_milk_IT -> 0.0047515677 | U39: ='GHG detailed, absolute'!U39/Production!$H$9*AF_milk_IT -> 0.0047515677
A40: 02211 | B40: Raw milk of cattle | C40: Dairy | D40: Italy | E40: IT | F40: N2O | G40: =SUM(H40:T40)+W40+X40 -> 0.00065003108 | H40: ='GHG detailed, absolute'!H40/Production!$H$9*AF_milk_IT -> 4.1284171e-06 | I40: ='GHG detailed, absolute'!I40/Production!$H$9*AF_milk_IT -> 8.7758945e-07 | J40: ='GHG detailed, absolute'!J40/Production!$H$9*AF_milk_IT -> 0.00025616828 | K40: ='GHG detailed, absolute'!K40/Production!$H$9*AF_milk_IT -> 2.5616828e-05 | L40: ='GHG detailed, absolute'!L40/Production!$H$9*AF_milk_IT -> 3.7811335e-07 | N40: ='GHG detailed, absolute'!N40/Production!$H$9*AF_milk_IT -> 9.5877063e-09 | O40: ='GHG detailed, absolute'!O40/Production!$H$9*AF_milk_IT -> 1.906293e-07 | P40: ='GHG detailed, absolute'!P40/Production!$H$9*AF_milk_IT -> 0 | Q40: ='GHG detailed, absolute'!Q40/Production!$H$9*AF_milk_IT -> 3.0526234e-05 | R40: ='GHG detailed, absolute'!R40/Production!$H$9*AF_milk_IT -> 3.0526234e-05 | T40: ='GHG detailed, absolute'!T40/Production!$H$9*AF_milk_IT -> 0.00029747782 | U40: ='GHG detailed, absolute'!U40/Production!$H$9*AF_milk_IT -> 0.00019581165 | V40: ='GHG detailed, absolute'!V40/Production!$H$9*AF_milk_IT -> 0.00010166616 | W40: ='GHG detailed, absolute'!W40/Production!$H$9*AF_milk_IT -> 4.0889399e-06 | X40: ='GHG detailed, absolute'!X40/Production!$H$9*AF_milk_IT -> 4.2415983e-08
A41: 02211 | B41: Raw milk of cattle | C41: Dairy | D41: Italy | E41: IT | F41: CO2e | G41: =SUM(H41:X41) -> 1.2319994 | H41: =SUMPRODUCT(H37:H40,'Parameters, general'!$B$24:$B$27) -> 0.021040006 | I41: =SUMPRODUCT(I37:I40,'Parameters, general'!$B$24:$B$27) -> 0.02403901 | J41: =SUMPRODUCT(J37:J40,'Parameters, general'!$B$24:$B$27) -> 0.06993394 | K41: =SUMPRODUCT(K37:K40,'Parameters, general'!$B$24:$B$27) -> 0.006993394 | L41: =SUMPRODUCT(L37:L40,'Parameters, general'!$B$24:$B$27) -> 0.014360726 | M41: =SUMPRODUCT(M37:M40,'Parameters, general'!$B$24:$B$27) -> 0 | N41: =SUMPRODUCT(N37:N40,'Parameters, general'!$B$24:$B$27) -> 0.00025485703 | O41: =SUMPRODUCT(O37:O40,'Parameters, general'!$B$24:$B$27) -> 0.0053716442 | ... T41: =SUMPRODUCT(T37:T40,'Parameters, general'!$B$24:$B$27) -> 0.20950377 | W41: =SUMPRODUCT(W37:W40,'Parameters, general'!$B$24:$B$27) -> 0.10725069 | X41: =SUMPRODUCT(X37:X40,'Parameters, general'!$B$24:$B$27) -> 0.0011827381 | Z41: =SUM(H41:R41) -> 0.37504708 | AA41: ='CO2 per kg feed'!F116+'CH4 per kg feed'!F116*CF_GWP_CH4_fossil+'N2O per kg feed'!F116*CF_GWP_N2O -> 0.2926376
A42: 02211 | B42: Raw milk of cattle | C42: Dairy | D42: Netherland | E42: NL | F42: CO2 | G42: =SUM(H42:X42) -> 0.3221955 | H42: ='GHG detailed, absolute'!H42/Production!$I$9*AF_milk_NL -> 0.049980878 | I42: ='GHG detailed, absolute'!I42/Production!$I$9*AF_milk_NL -> 0.022389735 | L42: ='GHG detailed, absolute'!L42/Production!$I$9*AF_milk_NL -> 0.01954152 | N42: ='GHG detailed, absolute'!N42/Production!$I$9*AF_milk_NL -> 7.7900021e-05 | O42: ='GHG detailed, absolute'!O42/Production!$I$9*AF_milk_NL -> 0.010162777 | P42: ='GHG detailed, absolute'!P42/Production!$I$9*AF_milk_NL -> 0.032935739 | Q42: ='GHG detailed, absolute'!Q42/Production!$I$9*AF_milk_NL -> 0.028320642 | R42: ='GHG detailed, absolute'!R42/Production!$I$9*AF_milk_NL -> 0.028320642 | W42: ='GHG detailed, absolute'!W42/Production!$I$9*AF_milk_NL -> 0.12945733 | X42: ='GHG detailed, absolute'!X42/Production!$I$9*AF_milk_NL -> 0.0010083364
A43: 02211 | B43: Raw milk of cattle | C43: Dairy | D43: Netherland | E43: NL | F43: CH4, fossil | G43: =SUM(H43:X43) -> 0.00083083679 | H43: ='GHG detailed, absolute'!H43/Production!$I$9*AF_milk_NL -> 2.6048509e-05 | I43: ='GHG detailed, absolute'!I43/Production!$I$9*AF_milk_NL -> 7.8778698e-05 | L43: ='GHG detailed, absolute'!L43/Production!$I$9*AF_milk_NL -> 8.6562345e-06 | N43: ='GHG detailed, absolute'!N43/Production!$I$9*AF_milk_NL -> 2.4958645e-07 | O43: ='GHG detailed, absolute'!O43/Production!$I$9*AF_milk_NL -> 7.1892579e-06 | P43: ='GHG detailed, absolute'!P43/Production!$I$9*AF_milk_NL -> 0 | Q43: ='GHG detailed, absolute'!Q43/Production!$I$9*AF_milk_NL -> 0.00022556911 | R43: ='GHG detailed, absolute'!R43/Production!$I$9*AF_milk_NL -> 0.00022556911 | W43: ='GHG detailed, absolute'!W43/Production!$I$9*AF_milk_NL -> 0.00025631073 | X43: ='GHG detailed, absolute'!X43/Production!$I$9*AF_milk_NL -> 2.4655499e-06
A44: 02211 | B44: Raw milk of cattle | C44: Dairy | D44: Netherland | E44: NL | F44: CH4, biogenic | G44: =SUM(H44:T44) -> 0.020716865 | S44: ='GHG detailed, absolute'!S44/Production!$I$9*AF_milk_NL -> 0.017170628 | T44: ='GHG detailed, absolute'!T44/Production!$I$9*AF_milk_NL -> 0.0035462369 | U44: ='GHG detailed, absolute'!U44/Production!$I$9*AF_milk_NL -> 0.0035462369
A45: 02211 | B45: Raw milk of cattle | C45: Dairy | D45: Netherland | E45: NL | F45: N2O | G45: =SUM(H45:T45)+W45+X45 -> 0.00085190216 | H45: ='GHG detailed, absolute'!H45/Production!$I$9*AF_milk_NL -> 4.4542904e-05 | I45: ='GHG detailed, absolute'!I45/Production!$I$9*AF_milk_NL -> 9.121744e-07 | J45: ='GHG detailed, absolute'!J45/Production!$I$9*AF_milk_NL -> 0.00050908222 | K45: ='GHG detailed, absolute'!K45/Production!$I$9*AF_milk_NL -> 5.0908222e-05 | L45: ='GHG detailed, absolute'!L45/Production!$I$9*AF_milk_NL -> 5.2508826e-07 | N45: ='GHG detailed, absolute'!N45/Production!$I$9*AF_milk_NL -> 3.2576041e-09 | O45: ='GHG detailed, absolute'!O45/Production!$I$9*AF_milk_NL -> 3.6670444e-07 | P45: ='GHG detailed, absolute'!P45/Production!$I$9*AF_milk_NL -> 0 | Q45: ='GHG detailed, absolute'!Q45/Production!$I$9*AF_milk_NL -> 2.035306e-05 | R45: ='GHG detailed, absolute'!R45/Production!$I$9*AF_milk_NL -> 2.035306e-05 | T45: ='GHG detailed, absolute'!T45/Production!$I$9*AF_milk_NL -> 0.00019961909 | U45: ='GHG detailed, absolute'!U45/Production!$I$9*AF_milk_NL -> 0.00010894459 | V45: ='GHG detailed, absolute'!V45/Production!$I$9*AF_milk_NL -> 9.0674496e-05 | W45: ='GHG detailed, absolute'!W45/Production!$I$9*AF_milk_NL -> 5.1973589e-06 | X45: ='GHG detailed, absolute'!X45/Production!$I$9*AF_milk_NL -> 3.9022599e-08
A46: 02211 | B46: Raw milk of cattle | C46: Dairy | D46: Netherland | E46: NL | F46: CO2e | G46: =SUM(H46:X46) -> 1.1388791 | H46: =SUMPRODUCT(H42:H45,'Parameters, general'!$B$24:$B$27) -> 0.062917336 | I46: =SUMPRODUCT(I42:I45,'Parameters, general'!$B$24:$B$27) -> 0.024986364 | J46: =SUMPRODUCT(J42:J45,'Parameters, general'!$B$24:$B$27) -> 0.13897945 | K46: =SUMPRODUCT(K42:K45,'Parameters, general'!$B$24:$B$27) -> 0.013897945 | L46: =SUMPRODUCT(L42:L45,'Parameters, general'!$B$24:$B$27) -> 0.019942825 | M46: =SUMPRODUCT(M42:M45,'Parameters, general'!$B$24:$B$27) -> 0 | N46: =SUMPRODUCT(N42:N45,'Parameters, general'!$B$24:$B$27) -> 8.6227023e-05 | O46: =SUMPRODUCT(O42:O45,'Parameters, general'!$B$24:$B$27) -> 0.010477127 | ... T46: =SUMPRODUCT(T42:T45,'Parameters, general'!$B$24:$B$27) -> 0.15024441 | W46: =SUMPRODUCT(W42:W45,'Parameters, general'!$B$24:$B$27) -> 0.13851426 | X46: =SUMPRODUCT(X42:X45,'Parameters, general'!$B$24:$B$27) -> 0.001092463 | Z46: =SUM(H46:R46) -> 0.38542098 | AA46: ='CO2 per kg feed'!F132+'CH4 per kg feed'!F132*CF_GWP_CH4_fossil+'N2O per kg feed'!F132*CF_GWP_N2O -> 0.3977347
A47: 02211 | B47: Raw milk of cattle | C47: Dairy | D47: Poland | E47: PL | F47: CO2 | G47: =SUM(H47:X47) -> 0.5419399 | H47: ='GHG detailed, absolute'!H47/Production!$J$9*AF_milk_PL -> 0.06429413 | I47: ='GHG detailed, absolute'!I47/Production!$J$9*AF_milk_PL -> 0.024762495 | L47: ='GHG detailed, absolute'!L47/Production!$J$9*AF_milk_PL -> 0.030457072 | N47: ='GHG detailed, absolute'!N47/Production!$J$9*AF_milk_PL -> 0.00017317497 | O47: ='GHG detailed, absolute'!O47/Production!$J$9*AF_milk_PL -> 0.022636395 | P47: ='GHG detailed, absolute'!P47/Production!$J$9*AF_milk_PL -> 0.025194435 | Q47: ='GHG detailed, absolute'!Q47/Production!$J$9*AF_milk_PL -> 0.071028559 | R47: ='GHG detailed, absolute'!R47/Production!$J$9*AF_milk_PL -> 0.071028559 | W47: ='GHG detailed, absolute'!W47/Production!$J$9*AF_milk_PL -> 0.23011567 | X47: ='GHG detailed, absolute'!X47/Production!$J$9*AF_milk_PL -> 0.0022494091
A48: 02211 | B48: Raw milk of cattle | C48: Dairy | D48: Poland | E48: PL | F48: CH4, fossil | G48: =SUM(H48:X48) -> 0.0011759614 | H48: ='GHG detailed, absolute'!H48/Production!$J$9*AF_milk_PL -> 6.0548899e-06 | I48: ='GHG detailed, absolute'!I48/Production!$J$9*AF_milk_PL -> 8.7127298e-05 | L48: ='GHG detailed, absolute'!L48/Production!$J$9*AF_milk_PL -> 1.3491456e-05 | N48: ='GHG detailed, absolute'!N48/Production!$J$9*AF_milk_PL -> 5.1873581e-07 | O48: ='GHG detailed, absolute'!O48/Production!$J$9*AF_milk_PL -> 1.9787811e-05 | P48: ='GHG detailed, absolute'!P48/Production!$J$9*AF_milk_PL -> 0 | Q48: ='GHG detailed, absolute'!Q48/Production!$J$9*AF_milk_PL -> 0.00030034278 | R48: ='GHG detailed, absolute'!R48/Production!$J$9*AF_milk_PL -> 0.00030034278 | W48: ='GHG detailed, absolute'!W48/Production!$J$9*AF_milk_PL -> 0.0004433637 | X48: ='GHG detailed, absolute'!X48/Production!$J$9*AF_milk_PL -> 4.9319151e-06
A49: 02211 | B49: Raw milk of cattle | C49: Dairy | D49: Poland | E49: PL | F49: CH4, biogenic | G49: =SUM(H49:T49) -> 0.020093092 | S49: ='GHG detailed, absolute'!S49/Production!$J$9*AF_milk_PL -> 0.018775408 | T49: ='GHG detailed, absolute'!T49/Production!$J$9*AF_milk_PL -> 0.0013176837 | U49: ='GHG detailed, absolute'!U49/Production!$J$9*AF_milk_PL -> 0.0013176837
A50: 02211 | B50: Raw milk of cattle | C50: Dairy | D50: Poland | E50: PL | F50: N2O | G50: =SUM(H50:T50)+W50+X50 -> 0.00083638531 | H50: ='GHG detailed, absolute'!H50/Production!$J$9*AF_milk_PL -> 1.9895456e-05 | I50: ='GHG detailed, absolute'!I50/Production!$J$9*AF_milk_PL -> 1.0088424e-06 | J50: ='GHG detailed, absolute'!J50/Production!$J$9*AF_milk_PL -> 0.00038904501 | K50: ='GHG detailed, absolute'!K50/Production!$J$9*AF_milk_PL -> 3.8904501e-05 | L50: ='GHG detailed, absolute'!L50/Production!$J$9*AF_milk_PL -> 8.183934e-07 | N50: ='GHG detailed, absolute'!N50/Production!$J$9*AF_milk_PL -> 7.4108012e-09 | O50: ='GHG detailed, absolute'!O50/Production!$J$9*AF_milk_PL -> 7.3381711e-07 | P50: ='GHG detailed, absolute'!P50/Production!$J$9*AF_milk_PL -> 0 | Q50: ='GHG detailed, absolute'!Q50/Production!$J$9*AF_milk_PL -> 1.9540398e-05 | R50: ='GHG detailed, absolute'!R50/Production!$J$9*AF_milk_PL -> 1.9540398e-05 | T50: ='GHG detailed, absolute'!T50/Production!$J$9*AF_milk_PL -> 0.00034269513 | U50: ='GHG detailed, absolute'!U50/Production!$J$9*AF_milk_PL -> 0.00025565265 | V50: ='GHG detailed, absolute'!V50/Production!$J$9*AF_milk_PL -> 8.7042484e-05 | W50: ='GHG detailed, absolute'!W50/Production!$J$9*AF_milk_PL -> 4.1520784e-06 | X50: ='GHG detailed, absolute'!X50/Production!$J$9*AF_milk_PL -> 4.3869681e-08
A51: 02211 | B51: Raw milk of cattle | C51: Dairy | D51: Poland | E51: PL | F51: CO2e | G51: =SUM(H51:X51) -> 1.3478302 | H51: =SUMPRODUCT(H47:H50,'Parameters, general'!$B$24:$B$27) -> 0.069906025 | I51: =SUMPRODUCT(I47:I50,'Parameters, general'!$B$24:$B$27) -> 0.027634303 | J51: =SUMPRODUCT(J47:J50,'Parameters, general'!$B$24:$B$27) -> 0.10620929 | K51: =SUMPRODUCT(K47:K50,'Parameters, general'!$B$24:$B$27) -> 0.010620929 | L51: =SUMPRODUCT(L47:L50,'Parameters, general'!$B$24:$B$27) -> 0.031082539 | M51: =SUMPRODUCT(M47:M50,'Parameters, general'!$B$24:$B$27) -> 0 | N51: =SUMPRODUCT(N47:N50,'Parameters, general'!$B$24:$B$27) -> 0.00019065645 | O51: =SUMPRODUCT(O47:O50,'Parameters, general'!$B$24:$B$27) -> 0.023426404 | ... T51: =SUMPRODUCT(T47:T50,'Parameters, general'!$B$24:$B$27) -> 0.12913323 | W51: =SUMPRODUCT(W47:W50,'Parameters, general'!$B$24:$B$27) -> 0.24446143 | X51: =SUMPRODUCT(X47:X50,'Parameters, general'!$B$24:$B$27) -> 0.0024083566 | Z51: =SUM(H51:R51) -> 0.46489118 | AA51: ='CO2 per kg feed'!F148+'CH4 per kg feed'!F148*CF_GWP_CH4_fossil+'N2O per kg feed'!F148*CF_GWP_N2O -> 0.37726692
A52: 02211 | B52: Raw milk of cattle | C52: Dairy | D52: Spain | E52: ES | F52: CO2 | G52: =SUM(H52:X52) -> 0.27884907 | H52: ='GHG detailed, absolute'!H52/Production!$K$9*AF_milk_ES -> 0.039752199 | I52: ='GHG detailed, absolute'!I52/Production!$K$9*AF_milk_ES -> 0.022490896 | L52: ='GHG detailed, absolute'!L52/Production!$K$9*AF_milk_ES -> 0.028389898 | N52: ='GHG detailed, absolute'!N52/Production!$K$9*AF_milk_ES -> 0.0035994795 | O52: ='GHG detailed, absolute'!O52/Production!$K$9*AF_milk_ES -> 0.016610221 | P52: ='GHG detailed, absolute'!P52/Production!$K$9*AF_milk_ES -> 0.030633719 | Q52: ='GHG detailed, absolute'!Q52/Production!$K$9*AF_milk_ES -> 0.033907859 | R52: ='GHG detailed, absolute'!R52/Production!$K$9*AF_milk_ES -> 0.033907859 | W52: ='GHG detailed, absolute'!W52/Production!$K$9*AF_milk_ES -> 0.068856934 | X52: ='GHG detailed, absolute'!X52/Production!$K$9*AF_milk_ES -> 0.00070000748
A53: 02211 | B53: Raw milk of cattle | C53: Dairy | D53: Spain | E53: ES | F53: CH4, fossil | G53: =SUM(H53:X53) -> 0.00077041442 | H53: ='GHG detailed, absolute'!H53/Production!$K$9*AF_milk_ES -> 4.7948937e-06 | I53: ='GHG detailed, absolute'!I53/Production!$K$9*AF_milk_ES -> 7.9134635e-05 | L53: ='GHG detailed, absolute'!L53/Production!$K$9*AF_milk_ES -> 1.2575768e-05 | N53: ='GHG detailed, absolute'!N53/Production!$K$9*AF_milk_ES -> 1.0736026e-05 | O53: ='GHG detailed, absolute'!O53/Production!$K$9*AF_milk_ES -> 1.2533398e-05 | P53: ='GHG detailed, absolute'!P53/Production!$K$9*AF_milk_ES -> 0 | Q53: ='GHG detailed, absolute'!Q53/Production!$K$9*AF_milk_ES -> 0.00021766768 | R53: ='GHG detailed, absolute'!R53/Production!$K$9*AF_milk_ES -> 0.00021766768 | W53: ='GHG detailed, absolute'!W53/Production!$K$9*AF_milk_ES -> 0.00021284734 | X53: ='GHG detailed, absolute'!X53/Production!$K$9*AF_milk_ES -> 2.4569984e-06
A54: 02211 | B54: Raw milk of cattle | C54: Dairy | D54: Spain | E54: ES | F54: CH4, biogenic | G54: =SUM(H54:T54) -> 0.01975947 | S54: ='GHG detailed, absolute'!S54/Production!$K$9*AF_milk_ES -> 0.016805494 | T54: ='GHG detailed, absolute'!T54/Production!$K$9*AF_milk_ES -> 0.0029539759 | U54: ='GHG detailed, absolute'!U54/Production!$K$9*AF_milk_ES -> 0.0029539759
A55: 02211 | B55: Raw milk of cattle | C55: Dairy | D55: Spain | E55: ES | F55: N2O | G55: =SUM(H55:T55)+W55+X55 -> 0.00071328116 | H55: ='GHG detailed, absolute'!H55/Production!$K$9*AF_milk_ES -> 1.160062e-05 | I55: ='GHG detailed, absolute'!I55/Production!$K$9*AF_milk_ES -> 9.1629577e-07 | J55: ='GHG detailed, absolute'!J55/Production!$K$9*AF_milk_ES -> 0.00039683499 | K55: ='GHG detailed, absolute'!K55/Production!$K$9*AF_milk_ES -> 3.9683499e-05 | L55: ='GHG detailed, absolute'!L55/Production!$K$9*AF_milk_ES -> 7.6284763e-07 | N55: ='GHG detailed, absolute'!N55/Production!$K$9*AF_milk_ES -> 1.542505e-07 | O55: ='GHG detailed, absolute'!O55/Production!$K$9*AF_milk_ES -> 6.1022199e-07 | P55: ='GHG detailed, absolute'!P55/Production!$K$9*AF_milk_ES -> 0 | Q55: ='GHG detailed, absolute'!Q55/Production!$K$9*AF_milk_ES -> 1.5800288e-05 | R55: ='GHG detailed, absolute'!R55/Production!$K$9*AF_milk_ES -> 1.5800288e-05 | T55: ='GHG detailed, absolute'!T55/Production!$K$9*AF_milk_ES -> 0.00022797156 | U55: ='GHG detailed, absolute'!U55/Production!$K$9*AF_milk_ES -> 0.00015692948 | V55: ='GHG detailed, absolute'!V55/Production!$K$9*AF_milk_ES -> 7.104208e-05 | W55: ='GHG detailed, absolute'!W55/Production!$K$9*AF_milk_ES -> 3.1172875e-06 | X55: ='GHG detailed, absolute'!X55/Production!$K$9*AF_milk_ES -> 2.9013285e-08
A56: 02211 | B56: Raw milk of cattle | C56: Dairy | D56: Spain | E56: ES | F56: CO2e | G56: =SUM(H56:X56) -> 1.0300389 | H56: =SUMPRODUCT(H52:H55,'Parameters, general'!$B$24:$B$27) -> 0.043062056 | I56: =SUMPRODUCT(I52:I55,'Parameters, general'!$B$24:$B$27) -> 0.025099257 | J56: =SUMPRODUCT(J52:J55,'Parameters, general'!$B$24:$B$27) -> 0.10833595 | K56: =SUMPRODUCT(K52:K55,'Parameters, general'!$B$24:$B$27) -> 0.010833595 | L56: =SUMPRODUCT(L52:L55,'Parameters, general'!$B$24:$B$27) -> 0.028972913 | M56: =SUMPRODUCT(M52:M55,'Parameters, general'!$B$24:$B$27) -> 0 | N56: =SUMPRODUCT(N52:N55,'Parameters, general'!$B$24:$B$27) -> 0.0039615235 | O56: =SUMPRODUCT(O52:O55,'Parameters, general'!$B$24:$B$27) -> 0.017150307 | ... T56: =SUMPRODUCT(T52:T55,'Parameters, general'!$B$24:$B$27) -> 0.14199359 | W56: =SUMPRODUCT(W52:W55,'Parameters, general'!$B$24:$B$27) -> 0.076050804 | X56: =SUMPRODUCT(X52:X55,'Parameters, general'!$B$24:$B$27) -> 0.00078114666 | Z56: =SUM(H56:R56) -> 0.35746499 | AA56: ='CO2 per kg feed'!F164+'CH4 per kg feed'!F164*CF_GWP_CH4_fossil+'N2O per kg feed'!F164*CF_GWP_N2O -> 0.36944907
A57: 02211 | B57: Raw milk of cattle | C57: Dairy | D57: Sweden | E57: SE | F57: CO2 | G57: =SUM(H57:X57) -> 0.19760179 | H57: ='GHG detailed, absolute'!H57/Production!$L$9*AF_milk_SE -> 0.030155557 | I57: ='GHG detailed, absolute'!I57/Production!$L$9*AF_milk_SE -> 0.024476838 | L57: ='GHG detailed, absolute'!L57/Production!$L$9*AF_milk_SE -> 0.023991953 | N57: ='GHG detailed, absolute'!N57/Production!$L$9*AF_milk_SE -> 5.9132912e-05 | O57: ='GHG detailed, absolute'!O57/Production!$L$9*AF_milk_SE -> 0.008509441 | P57: ='GHG detailed, absolute'!P57/Production!$L$9*AF_milk_SE -> 0.022203399 | Q57: ='GHG detailed, absolute'!Q57/Production!$L$9*AF_milk_SE -> 0.037984351 | R57: ='GHG detailed, absolute'!R57/Production!$L$9*AF_milk_SE -> 0.037984351 | W57: ='GHG detailed, absolute'!W57/Production!$L$9*AF_milk_SE -> 0.01187839 | X57: ='GHG detailed, absolute'!X57/Production!$L$9*AF_milk_SE -> 0.00035837922
A58: 02211 | B58: Raw milk of cattle | C58: Dairy | D58: Sweden | E58: SE | F58: CH4, fossil | G58: =SUM(H58:X58) -> 0.0011064216 | H58: ='GHG detailed, absolute'!H58/Production!$L$9*AF_milk_SE -> 1.1692456e-05 | I58: ='GHG detailed, absolute'!I58/Production!$L$9*AF_milk_SE -> 8.6122209e-05 | L58: ='GHG detailed, absolute'!L58/Production!$L$9*AF_milk_SE -> 1.0627626e-05 | N58: ='GHG detailed, absolute'!N58/Production!$L$9*AF_milk_SE -> 1.8124291e-07 | O58: ='GHG detailed, absolute'!O58/Production!$L$9*AF_milk_SE -> 4.3575196e-06 | P58: ='GHG detailed, absolute'!P58/Production!$L$9*AF_milk_SE -> 0 | Q58: ='GHG detailed, absolute'!Q58/Production!$L$9*AF_milk_SE -> 0.00048958169 | R58: ='GHG detailed, absolute'!R58/Production!$L$9*AF_milk_SE -> 0.00048958169 | W58: ='GHG detailed, absolute'!W58/Production!$L$9*AF_milk_SE -> 1.3198264e-05 | X58: ='GHG detailed, absolute'!X58/Production!$L$9*AF_milk_SE -> 1.078949e-06
A59: 02211 | B59: Raw milk of cattle | C59: Dairy | D59: Sweden | E59: SE | F59: CH4, biogenic | G59: =SUM(H59:T59) -> 0.019524873 | S59: ='GHG detailed, absolute'!S59/Production!$L$9*AF_milk_SE -> 0.018439099 | T59: ='GHG detailed, absolute'!T59/Production!$L$9*AF_milk_SE -> 0.0010857736 | U59: ='GHG detailed, absolute'!U59/Production!$L$9*AF_milk_SE -> 0.0010857736
A60: 02211 | B60: Raw milk of cattle | C60: Dairy | D60: Sweden | E60: SE | F60: N2O | G60: =SUM(H60:T60)+W60+X60 -> 0.00070869247 | H60: ='GHG detailed, absolute'!H60/Production!$L$9*AF_milk_SE -> 2.6148663e-05 | I60: ='GHG detailed, absolute'!I60/Production!$L$9*AF_milk_SE -> 9.9720452e-07 | J60: ='GHG detailed, absolute'!J60/Production!$L$9*AF_milk_SE -> 0.0003724017 | K60: ='GHG detailed, absolute'!K60/Production!$L$9*AF_milk_SE -> 3.724017e-05 | L60: ='GHG detailed, absolute'!L60/Production!$L$9*AF_milk_SE -> 6.4467314e-07 | N60: ='GHG detailed, absolute'!N60/Production!$L$9*AF_milk_SE -> 2.5112609e-09 | O60: ='GHG detailed, absolute'!O60/Production!$L$9*AF_milk_SE -> 3.1874884e-07 | P60: ='GHG detailed, absolute'!P60/Production!$L$9*AF_milk_SE -> 0 | Q60: ='GHG detailed, absolute'!Q60/Production!$L$9*AF_milk_SE -> 4.7074569e-05 | R60: ='GHG detailed, absolute'!R60/Production!$L$9*AF_milk_SE -> 4.7074569e-05 | T60: ='GHG detailed, absolute'!T60/Production!$L$9*AF_milk_SE -> 0.00017567106 | U60: ='GHG detailed, absolute'!U60/Production!$L$9*AF_milk_SE -> 9.8896568e-05 | V60: ='GHG detailed, absolute'!V60/Production!$L$9*AF_milk_SE -> 7.6774492e-05 | W60: ='GHG detailed, absolute'!W60/Production!$L$9*AF_milk_SE -> 1.0975081e-06 | X60: ='GHG detailed, absolute'!X60/Production!$L$9*AF_milk_SE -> 2.1089611e-08
A61: 02211 | B61: Raw milk of cattle | C61: Dairy | D61: Sweden | E61: SE | F61: CO2e | G61: =SUM(H61:X61) -> 0.95121776 | H61: =SUMPRODUCT(H57:H60,'Parameters, general'!$B$24:$B$27) -> 0.037642578 | I61: =SUMPRODUCT(I57:I60,'Parameters, general'!$B$24:$B$27) -> 0.027315517 | J61: =SUMPRODUCT(J57:J60,'Parameters, general'!$B$24:$B$27) -> 0.10166567 | K61: =SUMPRODUCT(K57:K60,'Parameters, general'!$B$24:$B$27) -> 0.010166567 | L61: =SUMPRODUCT(L57:L60,'Parameters, general'!$B$24:$B$27) -> 0.024484652 | M61: =SUMPRODUCT(M57:M60,'Parameters, general'!$B$24:$B$27) -> 0 | N61: =SUMPRODUCT(N57:N60,'Parameters, general'!$B$24:$B$27) -> 6.5219525e-05 | O61: =SUMPRODUCT(O57:O60,'Parameters, general'!$B$24:$B$27) -> 0.0087263135 | ... T61: =SUMPRODUCT(T57:T60,'Parameters, general'!$B$24:$B$27) -> 0.077274085 | W61: =SUMPRODUCT(W57:W60,'Parameters, general'!$B$24:$B$27) -> 0.012571318 | X61: =SUMPRODUCT(X57:X60,'Parameters, general'!$B$24:$B$27) -> 0.00039628936 | Z61: =SUM(H61:R61) -> 0.3631204 | AA61: ='CO2 per kg feed'!F180+'CH4 per kg feed'!F180*CF_GWP_CH4_fossil+'N2O per kg feed'!F180*CF_GWP_N2O -> 0.31750016

Sheet Footprints, per kg meat
A2: Footprints (per kg of meat)
A5: Animal products | F5: Climate | L5: Land | M5: Nitrogen | N5: Phosphorus | O5: Water | P5: Pesticides | Q5: Biodiversity | R5: Ammonia | S5: Labour | T5: Animal welfare | U5: Use of antibiotics
A6: Code | B6: Name | C6: Category | D6: Country | E6: Country code | F6: Carbon footprint, kg CO2e/kg | G6: Carbon dioxide, kg CO2/kg | H6: Methane, fossil, kg CH4/kg | I6: Methane, biogenic, kg CH4/kg | J6: Nitrous oxide, kg N2O/kg | K6: HFCs, kg HFCs/kg | L6: Cropland use, m2/kg | M6: New N input, kg N/kg | N6: New P input, kg P/kg | O6: Blue freshwater use, m3/kg | P6: Pesticide use, g a.i./kg | Q6: Extinction rate, E/MSY/kg | R6: Ammonia emission, kg NH3/kg | S6: Labour requirements, h/kg | T6: Animal welfare index per kg of bonefree meat | U6: Antibiotics use indicator/kg
A7: 21111.02_dc | B7: Beef meat from dairy cows | C7: Red meat | D7: Denmark | E7: DK | F7: ='GHG det, per kg meat'!G11 -> 14.766986 | G7: ='GHG det, per kg meat'!G7 -> 2.1330201 | H7: ='GHG det, per kg meat'!G8 -> 0.012417935 | I7: ='GHG det, per kg meat'!G9 -> 0.34213638 | J7: ='GHG det, per kg meat'!G10 -> 0.011085089 | L7: ='Footprints, absolute'!L7/Production!$B$17*AF_beef_DK -> 13.833453 | M7: ='Footprints, absolute'!M7/Production!$B$17*AF_beef_DK -> 0.18381557 | N7: ='Footprints, absolute'!N7/Production!$B$17*AF_beef_DK -> 0.015090951 | O7: ='Footprints, absolute'!O7/Production!$B$17*AF_beef_DK -> 0.11073106 | P7: ='Footprints, absolute'!P7/Production!$B$17*AF_beef_DK -> 0.96800776 | Q7: ='Footprints, absolute'!Q7/Production!$B$17*AF_beef_DK -> 1.5025678e-10 | R7: ='Footprints, absolute'!R7/Production!$B$17*AF_beef_DK -> 0.0069531515 | T7: 0 | U7: 0
A8: 21111.02_dc | B8: Beef meat from dairy cows | C8: Red meat | D8: France | E8: FR | F8: ='GHG det, per kg meat'!G16 -> 14.704813 | G8: ='GHG det, per kg meat'!G12 -> 2.7705351 | H8: ='GHG det, per kg meat'!G13 -> 0.014248571 | I8: ='GHG det, per kg meat'!G14 -> 0.31955889 | J8: ='GHG det, per kg meat'!G15 -> 0.01055524 | L8: ='Footprints, absolute'!L8/Production!$C$17*AF_beef_FR -> 14.783148 | M8: ='Footprints, absolute'!M8/Production!$C$17*AF_beef_FR -> 0.21089585 | N8: ='Footprints, absolute'!N8/Production!$C$17*AF_beef_FR -> 0.017340456 | O8: ='Footprints, absolute'!O8/Production!$C$17*AF_beef_FR -> 0.15824327 | P8: ='Footprints, absolute'!P8/Production!$C$17*AF_beef_FR -> 1.4545867 | Q8: ='Footprints, absolute'!Q8/Production!$C$17*AF_beef_FR -> 3.1213203e-10 | R8: ='Footprints, absolute'!R8/Production!$C$17*AF_beef_FR -> 0.0092363622 | T8: 0 | U8: 0
A9: 21111.02_dc | B9: Beef meat from dairy cows | C9: Red meat | D9: Germany | E9: DE | F9: ='GHG det, per kg meat'!G21 -> 15.389172 | G9: ='GHG det, per kg meat'!G17 -> 3.9339109 | H9: ='GHG det, per kg meat'!G18 -> 0.01565628 | I9: ='GHG det, per kg meat'!G19 -> 0.31676034 | J9: ='GHG det, per kg meat'!G20 -> 0.0089237168 | L9: ='Footprints, absolute'!L9/Production!$D$17*AF_beef_DE -> 8.8848613 | M9: ='Footprints, absolute'!M9/Production!$D$17*AF_beef_DE -> 0.15981903 | N9: ='Footprints, absolute'!N9/Production!$D$17*AF_beef_DE -> 0.0081296711 | O9: ='Footprints, absolute'!O9/Production!$D$17*AF_beef_DE -> 0.07868727 | P9: ='Footprints, absolute'!P9/Production!$D$17*AF_beef_DE -> 0.55987847 | Q9: ='Footprints, absolute'!Q9/Production!$D$17*AF_beef_DE -> 2.4866313e-10 | R9: ='Footprints, absolute'!R9/Production!$D$17*AF_beef_DE -> 0.004636772 | T9: 0 | U9: 0
A10: 21111.02_dc | B10: Beef meat from dairy cows | C10: Red meat | D10: Greece | E10: GR | F10: ='GHG det, per kg meat'!G26 -> 18.197101 | G10: ='GHG det, per kg meat'!G22 -> 6.3638123 | H10: ='GHG det, per kg meat'!G23 -> 0.015756058 | I10: ='GHG det, per kg meat'!G24 -> 0.28641728 | J10: ='GHG det, per kg meat'!G25 -> 0.013298506 | L10: ='Footprints, absolute'!L10/Production!$E$17*AF_beef_GR -> 24.090351 | M10: ='Footprints, absolute'!M10/Production!$E$17*AF_beef_GR -> 0.34140948 | N10: ='Footprints, absolute'!N10/Production!$E$17*AF_beef_GR -> 0.034488458 | O10: ='Footprints, absolute'!O10/Production!$E$17*AF_beef_GR -> 0.91136487 | P10: ='Footprints, absolute'!P10/Production!$E$17*AF_beef_GR -> 1.1557033 | Q10: ='Footprints, absolute'!Q10/Production!$E$17*AF_beef_GR -> 1.4798528e-09 | R10: ='Footprints, absolute'!R10/Production!$E$17*AF_beef_GR -> 0.025056596 | T10: 0 | U10: 0
A11: 21111.02_dc | B11: Beef meat from dairy cows | C11: Red meat | D11: Hungary | E11: HU | F11: ='GHG det, per kg meat'!G31 -> 18.807544 | G11: ='GHG det, per kg meat'!G27 -> 6.1779869 | H11: ='GHG det, per kg meat'!G28 -> 0.018760458 | I11: ='GHG det, per kg meat'!G29 -> 0.31803111 | J11: ='GHG det, per kg meat'!G30 -> 0.012760643 | L11: ='Footprints, absolute'!L11/Production!$F$17*AF_beef_HU -> 22.593135 | M11: ='Footprints, absolute'!M11/Production!$F$17*AF_beef_HU -> 0.30662925 | N11: ='Footprints, absolute'!N11/Production!$F$17*AF_beef_HU -> 0.032722897 | O11: ='Footprints, absolute'!O11/Production!$F$17*AF_beef_HU -> 0.18234959 | P11: ='Footprints, absolute'!P11/Production!$F$17*AF_beef_HU -> 1.60306 | Q11: ='Footprints, absolute'!Q11/Production!$F$17*AF_beef_HU -> 4.8098261e-10 | R11: ='Footprints, absolute'!R11/Production!$F$17*AF_beef_HU -> 0.011161995 | T11: 0 | U11: 0
A12: 21111.02_dc | B12: Beef meat from dairy cows | C12: Red meat | D12: Ireland | E12: IE | F12: ='GHG det, per kg meat'!G36 -> 13.804498 | G12: ='GHG det, per kg meat'!G32 -> 2.0555296 | H12: ='GHG det, per kg meat'!G33 -> 0.0028037262 | I12: ='GHG det, per kg meat'!G34 -> 0.34197298 | J12: ='GHG det, per kg meat'!G35 -> 0.0089089628 | L12: ='Footprints, absolute'!L12/Production!$G$17*AF_beef_IE -> 3.2119613 | M12: ='Footprints, absolute'!M12/Production!$G$17*AF_beef_IE -> 0.22856978 | N12: ='Footprints, absolute'!N12/Production!$G$17*AF_beef_IE -> 0.0074688847 | O12: ='Footprints, absolute'!O12/Production!$G$17*AF_beef_IE -> 0.1172331 | P12: ='Footprints, absolute'!P12/Production!$G$17*AF_beef_IE -> 1.0641662 | Q12: ='Footprints, absolute'!Q12/Production!$G$17*AF_beef_IE -> 8.0364315e-11 | R12: ='Footprints, absolute'!R12/Production!$G$17*AF_beef_IE -> 0.0072490624 | T12: 0 | U12: 0
A13: 21111.02_dc | B13: Beef meat from dairy cows | C13: Red meat | D13: Italy | E13: IT | F13: ='GHG det, per kg meat'!G41 -> 18.103801 | G13: ='GHG det, per kg meat'!G37 -> 5.0151262 | H13: ='GHG det, per kg meat'!G38 -> 0.022655524 | I13: ='GHG det, per kg meat'!G39 -> 0.36317962 | J13: ='GHG det, per kg meat'!G40 -> 0.00955198 | L13: ='Footprints, absolute'!L13/Production!$H$17*AF_beef_IT -> 15.179418 | M13: ='Footprints, absolute'!M13/Production!$H$17*AF_beef_IT -> 0.26402644 | N13: ='Footprints, absolute'!N13/Production!$H$17*AF_beef_IT -> 0.016582672 | O13: ='Footprints, absolute'!O13/Production!$H$17*AF_beef_IT -> 0.14632246 | P13: ='Footprints, absolute'!P13/Production!$H$17*AF_beef_IT -> 0.88384738 | Q13: ='Footprints, absolute'!Q13/Production!$H$17*AF_beef_IT -> 1.1442876e-09 | R13: ='Footprints, absolute'!R13/Production!$H$17*AF_beef_IT -> 0.012122147 | T13: 0 | U13: 0
A14: 21111.02_dc | B14: Beef meat from dairy cows | C14: Red meat | D14: Netherlands | E14: NL | F14: ='GHG det, per kg meat'!G46 -> 16.735431 | G14: ='GHG det, per kg meat'!G42 -> 4.7345504 | H14: ='GHG det, per kg meat'!G43 -> 0.012208857 | I14: ='GHG det, per kg meat'!G44 -> 0.3044271 | J14: ='GHG det, per kg meat'!G45 -> 0.012518405 | L14: ='Footprints, absolute'!L14/Production!$I$17*AF_beef_NL -> 11.262185 | M14: ='Footprints, absolute'!M14/Production!$I$17*AF_beef_NL -> 0.32436289 | N14: ='Footprints, absolute'!N14/Production!$I$17*AF_beef_NL -> 0.01245229 | O14: ='Footprints, absolute'!O14/Production!$I$17*AF_beef_NL -> 0.085095061 | P14: ='Footprints, absolute'!P14/Production!$I$17*AF_beef_NL -> 1.0325975 | Q14: ='Footprints, absolute'!Q14/Production!$I$17*AF_beef_NL -> 3.5074471e-10 | R14: ='Footprints, absolute'!R14/Production!$I$17*AF_beef_NL -> 0.012509417 | T14: 0 | U14: 0
A15: 21111.02_dc | B15: Beef meat from dairy cows | C15: Red meat | D15: Poland | E15: PL | F15: ='GHG det, per kg meat'!G51 -> 19.805895 | G15: ='GHG det, per kg meat'!G47 -> 7.9636178 | H15: ='GHG det, per kg meat'!G48 -> 0.017280342 | I15: ='GHG det, per kg meat'!G49 -> 0.29526098 | J15: ='GHG det, per kg meat'!G50 -> 0.01229039 | L15: ='Footprints, absolute'!L15/Production!$J$17*AF_beef_PL -> 15.175002 | M15: ='Footprints, absolute'!M15/Production!$J$17*AF_beef_PL -> 0.25202335 | N15: ='Footprints, absolute'!N15/Production!$J$17*AF_beef_PL -> 0.023973179 | O15: ='Footprints, absolute'!O15/Production!$J$17*AF_beef_PL -> 0.090368764 | P15: ='Footprints, absolute'!P15/Production!$J$17*AF_beef_PL -> 1.1672158 | Q15: ='Footprints, absolute'!Q15/Production!$J$17*AF_beef_PL -> 2.3994032e-10 | R15: ='Footprints, absolute'!R15/Production!$J$17*AF_beef_PL -> 0.010355238 | T15: 0 | U15: 0
A16: 21111.02_dc | B16: Beef meat from dairy cows | C16: Red meat | D16: Spain | E16: ES | F16: ='GHG det, per kg meat'!G56 -> 15.136062 | G16: ='GHG det, per kg meat'!G52 -> 4.0975898 | H16: ='GHG det, per kg meat'!G53 -> 0.011320971 | I16: ='GHG det, per kg meat'!G54 -> 0.29035851 | J16: ='GHG det, per kg meat'!G55 -> 0.010481418 | L16: ='Footprints, absolute'!L16/Production!$K$17*AF_beef_ES -> 16.414509 | M16: ='Footprints, absolute'!M16/Production!$K$17*AF_beef_ES -> 0.30866681 | N16: ='Footprints, absolute'!N16/Production!$K$17*AF_beef_ES -> 0.027727341 | O16: ='Footprints, absolute'!O16/Production!$K$17*AF_beef_ES -> 0.74839527 | P16: ='Footprints, absolute'!P16/Production!$K$17*AF_beef_ES -> 1.2578368 | Q16: ='Footprints, absolute'!Q16/Production!$K$17*AF_beef_ES -> 4.7578566e-10 | R16: ='Footprints, absolute'!R16/Production!$K$17*AF_beef_ES -> 0.0096024009 | T16: 0 | U16: 0
A17: 21111.02_dc | B17: Beef meat from dairy cows | C17: Red meat | D17: Sweden | E17: SE | F17: ='GHG det, per kg meat'!G61 -> 13.977813 | G17: ='GHG det, per kg meat'!G57 -> 2.9036894 | H17: ='GHG det, per kg meat'!G58 -> 0.01625848 | I17: ='GHG det, per kg meat'!G59 -> 0.28691119 | J17: ='GHG det, per kg meat'!G60 -> 0.010413989 | L17: ='Footprints, absolute'!L17/Production!$L$17*AF_beef_SE -> 26.072834 | M17: ='Footprints, absolute'!M17/Production!$L$17*AF_beef_SE -> 0.25948201 | N17: ='Footprints, absolute'!N17/Production!$L$17*AF_beef_SE -> 0.013027084 | O17: ='Footprints, absolute'!O17/Production!$L$17*AF_beef_SE -> 0.081915995 | P17: ='Footprints, absolute'!P17/Production!$L$17*AF_beef_SE -> 0.64172208 | Q17: ='Footprints, absolute'!Q17/Production!$L$17*AF_beef_SE -> 1.6327448e-10 | R17: ='Footprints, absolute'!R17/Production!$L$17*AF_beef_SE -> 0.0075946197 | T17: 0 | U17: 0
A18: 21111.02_dc | B18: Beef meat from dairy cows | C18: Red meat | D18: UK | E18: GB | F18: =F12 -> 13.804498 | G18: =G12 -> 2.0555296 | H18: =H12 -> 0.0028037262 | I18: =I12 -> 0.34197298 | J18: =J12 -> 0.0089089628 | L18: =L12 -> 3.2119613 | M18: =M12 -> 0.22856978 | N18: =N12 -> 0.0074688847 | O18: =O12 -> 0.1172331 | P18: =P12 -> 1.0641662 | Q18: =Q12 -> 8.0364315e-11 | R18: =R12 -> 0.0072490624 | T18: =T12 -> 0 | U18: =U12 -> 0

Sheet GHG det, per kg meat
A2: GHG emissions (per kg of meat)
K3: * Calculated as percentage of direct emissions due to assumption due to data limitations regarding nitrogen leaching and volatilization from soils in different regions.
S4: Animals | W4: Stables | X4: Slaughter | Z4: Control
A5: Animal products | G5: Sum | H5: Inputs | J5: Soil emissions | L5: Energy use | P5: Land use change | Q5: Feed processing | R5: Transports | AA5: Dairy cows
A6: Code | B6: Name | C6: Category | D6: Country | E6: Country code | F6: Gas | G6: GHG | H6: Production of mineral fertilizer | I6: Production of capital goods | J6: Direct emissions | K6: Indirect emissions* | L6: Diesel use field mach | M6: Energy use in greenhouses | N6: Energy use for irrigation | O6: Energy use for post-harvest proc | P6: LUC emissions | Q6: Feed processing | R6: Feed transports | S6: Enteric fermentation* | T6: Manure management - tot | U6: Manure management - direct | V6: Manure management - indirect | W6: Energy use in stables | X6: Energy use for slaughter | Z6: Total feed, excl LUC | AA6: Feed mix emissions, kg CO2E per kg feed, excl. adjustement manure
A7: 21111.02_dc | B7: Beef meat from dairy cows | C7: Red meat | D7: Denmark | E7: DK | F7: CO2 | G7: =SUM(H7:X7) -> 2.1330201 | H7: ='GHG detailed, absolute'!H7/Production!$B$17*AF_beef_DK -> 0.49628664 | I7: ='GHG detailed, absolute'!I7/Production!$B$17*AF_beef_DK -> 0.28130985 | L7: ='GHG detailed, absolute'!L7/Production!$B$17*AF_beef_DK -> 0.21820172 | N7: ='GHG detailed, absolute'!N7/Production!$B$17*AF_beef_DK -> 0.00044963151 | O7: ='GHG detailed, absolute'!O7/Production!$B$17*AF_beef_DK -> 0.14625317 | P7: ='GHG detailed, absolute'!P7/Production!$B$17*AF_beef_DK -> 0.19457773 | Q7: ='GHG detailed, absolute'!Q7/Production!$B$17*AF_beef_DK -> 0.39181581 | R7: ='GHG detailed, absolute'!R7/Production!$B$17*AF_beef_DK -> 0.39181581 | W7: ='GHG detailed, absolute'!W7/Production!$B$17*AF_beef_DK -> 0 | X7: ='GHG detailed, absolute'!X7/Production!$B$17*AF_beef_DK -> 0.012309726
A8: 21111.02_dc | B8: Beef meat from dairy cows | C8: Red meat | D8: Denmark | E8: DK | F8: CH4, fossil | G8: =SUM(H8:X8) -> 0.012417935 | H8: ='GHG detailed, absolute'!H8/Production!$B$17*AF_beef_DK -> 0.0005474352 | I8: ='GHG detailed, absolute'!I8/Production!$B$17*AF_beef_DK -> 0.00098979392 | L8: ='GHG detailed, absolute'!L8/Production!$B$17*AF_beef_DK -> 9.6656006e-05 | N8: ='GHG detailed, absolute'!N8/Production!$B$17*AF_beef_DK -> 1.5037756e-06 | O8: ='GHG detailed, absolute'!O8/Production!$B$17*AF_beef_DK -> 8.8004146e-05 | P8: ='GHG detailed, absolute'!P8/Production!$B$17*AF_beef_DK -> 0 | Q8: ='GHG detailed, absolute'!Q8/Production!$B$17*AF_beef_DK -> 0.0050922691 | R8: ='GHG detailed, absolute'!R8/Production!$B$17*AF_beef_DK -> 0.0050922691 | W8: ='GHG detailed, absolute'!W8/Production!$B$17*AF_beef_DK -> 0.00048408696 | X8: ='GHG detailed, absolute'!X8/Production!$B$17*AF_beef_DK -> 2.5916735e-05
A9: 21111.02_dc | B9: Beef meat from dairy cows | C9: Red meat | D9: Denmark | E9: DK | F9: CH4, biogenic | G9: =SUM(H9:T9) -> 0.34213638 | S9: ='GHG detailed, absolute'!S9/Production!$B$17*AF_beef_DK -> 0.25766437 | T9: ='GHG detailed, absolute'!T9/Production!$B$17*AF_beef_DK -> 0.084472012 | U9: ='GHG detailed, absolute'!U9/Production!$B$17*AF_beef_DK -> 0.084472012
A10: 21111.02_dc | B10: Beef meat from dairy cows | C10: Red meat | D10: Denmark | E10: DK | F10: N2O | G10: =SUM(H10:T10)+W10+X10 -> 0.011085089 | H10: ='GHG detailed, absolute'!H10/Production!$B$17*AF_beef_DK -> 0.00072672617 | I10: ='GHG detailed, absolute'!I10/Production!$B$17*AF_beef_DK -> 1.1460772e-05 | J10: ='GHG detailed, absolute'!J10/Production!$B$17*AF_beef_DK -> 0.0052994756 | K10: ='GHG detailed, absolute'!K10/Production!$B$17*AF_beef_DK -> 0.00052994756 | L10: ='GHG detailed, absolute'!L10/Production!$B$17*AF_beef_DK -> 5.8631654e-06 | N10: ='GHG detailed, absolute'!N10/Production!$B$17*AF_beef_DK -> 1.8506799e-08 | O10: ='GHG detailed, absolute'!O10/Production!$B$17*AF_beef_DK -> 5.345837e-06 | P10: ='GHG detailed, absolute'!P10/Production!$B$17*AF_beef_DK -> 0 | Q10: ='GHG detailed, absolute'!Q10/Production!$B$17*AF_beef_DK -> 0.0004893458 | R10: ='GHG detailed, absolute'!R10/Production!$B$17*AF_beef_DK -> 0.0004893458 | T10: ='GHG detailed, absolute'!T10/Production!$B$17*AF_beef_DK -> 0.0035089246 | U10: ='GHG detailed, absolute'!U10/Production!$B$17*AF_beef_DK -> 0.0020675835 | V10: ='GHG detailed, absolute'!V10/Production!$B$17*AF_beef_DK -> 0.0014413411 | W10: ='GHG detailed, absolute'!W10/Production!$B$17*AF_beef_DK -> 1.8057001e-05 | X10: ='GHG detailed, absolute'!X10/Production!$B$17*AF_beef_DK -> 5.7864543e-07
A11: 21111.02_dc | B11: Beef meat from dairy cows | C11: Red meat | D11: Denmark | E11: DK | F11: CO2e | G11: =SUM(H11:X11) -> 14.766986 | H11: =SUMPRODUCT(H7:H10,'Parameters, general'!$B$24:$B$27) -> 0.71099645 | I11: =SUMPRODUCT(I7:I10,'Parameters, general'!$B$24:$B$27) -> 0.3139345 | J11: =SUMPRODUCT(J7:J10,'Parameters, general'!$B$24:$B$27) -> 1.4467568 | K11: =SUMPRODUCT(K7:K10,'Parameters, general'!$B$24:$B$27) -> 0.14467568 | L11: =SUMPRODUCT(L7:L10,'Parameters, general'!$B$24:$B$27) -> 0.22268272 | M11: =SUMPRODUCT(M7:M10,'Parameters, general'!$B$24:$B$27) -> 0 | N11: =SUMPRODUCT(N7:N10,'Parameters, general'!$B$24:$B$27) -> 0.00049949638 | O11: =SUMPRODUCT(O7:O10,'Parameters, general'!$B$24:$B$27) -> 0.15033511 | ... T11: =SUMPRODUCT(T7:T10,'Parameters, general'!$B$24:$B$27) -> 3.2386807 | W11: =SUMPRODUCT(W7:W10,'Parameters, general'!$B$24:$B$27) -> 0.019355353 | X11: =SUMPRODUCT(X7:X10,'Parameters, general'!$B$24:$B$27) -> 0.013240015 | Z11: =SUM(H11:R11) -> 4.5387722 | AA11: ='CO2 per kg feed'!F20+'CH4 per kg feed'!F20*CF_GWP_CH4_fossil+'N2O per kg feed'!F20*CF_GWP_N2O -> 0.32935235
A12: 21111.02_dc | B12: Beef meat from dairy cows | C12: Red meat | D12: France | E12: FR | F12: CO2 | G12: =SUM(H12:X12) -> 2.7705351 | H12: ='GHG detailed, absolute'!H12/Production!$C$17*AF_beef_FR -> 0.43419056 | I12: ='GHG detailed, absolute'!I12/Production!$C$17*AF_beef_FR -> 0.35914281 | L12: ='GHG detailed, absolute'!L12/Production!$C$17*AF_beef_FR -> 0.26115628 | N12: ='GHG detailed, absolute'!N12/Production!$C$17*AF_beef_FR -> 0.0052744684 | O12: ='GHG detailed, absolute'!O12/Production!$C$17*AF_beef_FR -> 0.14394242 | P12: ='GHG detailed, absolute'!P12/Production!$C$17*AF_beef_FR -> 0.22731838 | Q12: ='GHG detailed, absolute'!Q12/Production!$C$17*AF_beef_FR -> 0.54018549 | R12: ='GHG detailed, absolute'!R12/Production!$C$17*AF_beef_FR -> 0.54018549 | W12: ='GHG detailed, absolute'!W12/Production!$C$17*AF_beef_FR -> 0.25263423 | X12: ='GHG detailed, absolute'!X12/Production!$C$17*AF_beef_FR -> 0.0065049652
A13: 21111.02_dc | B13: Beef meat from dairy cows | C13: Red meat | D13: France | E13: FR | F13: CH4, fossil | G13: =SUM(H13:X13) -> 0.014248571 | H13: ='GHG detailed, absolute'!H13/Production!$C$17*AF_beef_FR -> 0.00024275963 | I13: ='GHG detailed, absolute'!I13/Production!$C$17*AF_beef_FR -> 0.0012636506 | L13: ='GHG detailed, absolute'!L13/Production!$C$17*AF_beef_FR -> 0.00011568342 | N13: ='GHG detailed, absolute'!N13/Production!$C$17*AF_beef_FR -> 1.657761e-05 | O13: ='GHG detailed, absolute'!O13/Production!$C$17*AF_beef_FR -> 8.1567967e-05 | P13: ='GHG detailed, absolute'!P13/Production!$C$17*AF_beef_FR -> 0 | Q13: ='GHG detailed, absolute'!Q13/Production!$C$17*AF_beef_FR -> 0.0058598738 | R13: ='GHG detailed, absolute'!R13/Production!$C$17*AF_beef_FR -> 0.0058598738 | W13: ='GHG detailed, absolute'!W13/Production!$C$17*AF_beef_FR -> 0.000783244 | X13: ='GHG detailed, absolute'!X13/Production!$C$17*AF_beef_FR -> 2.5339794e-05
A14: 21111.02_dc | B14: Beef meat from dairy cows | C14: Red meat | D14: France | E14: FR | F14: CH4, biogenic | G14: =SUM(H14:T14) -> 0.31955889 | S14: ='GHG detailed, absolute'!S14/Production!$C$17*AF_beef_FR -> 0.28711186 | T14: ='GHG detailed, absolute'!T14/Production!$C$17*AF_beef_FR -> 0.03244703 | U14: ='GHG detailed, absolute'!U14/Production!$C$17*AF_beef_FR -> 0.03244703
A15: 21111.02_dc | B15: Beef meat from dairy cows | C15: Red meat | D15: France | E15: FR | F15: N2O | G15: =SUM(H15:T15)+W15+X15 -> 0.01055524 | H15: ='GHG detailed, absolute'!H15/Production!$C$17*AF_beef_FR -> 0.00037062495 | I15: ='GHG detailed, absolute'!I15/Production!$C$17*AF_beef_FR -> 1.4631744e-05 | J15: ='GHG detailed, absolute'!J15/Production!$C$17*AF_beef_FR -> 0.0054527057 | K15: ='GHG detailed, absolute'!K15/Production!$C$17*AF_beef_FR -> 0.00054527057 | L15: ='GHG detailed, absolute'!L15/Production!$C$17*AF_beef_FR -> 7.017371e-06 | N15: ='GHG detailed, absolute'!N15/Production!$C$17*AF_beef_FR -> 2.220711e-07 | O15: ='GHG detailed, absolute'!O15/Production!$C$17*AF_beef_FR -> 5.3847761e-06 | P15: ='GHG detailed, absolute'!P15/Production!$C$17*AF_beef_FR -> 0 | Q15: ='GHG detailed, absolute'!Q15/Production!$C$17*AF_beef_FR -> 0.00053513745 | R15: ='GHG detailed, absolute'!R15/Production!$C$17*AF_beef_FR -> 0.00053513745 | T15: ='GHG detailed, absolute'!T15/Production!$C$17*AF_beef_FR -> 0.0030650452 | U15: ='GHG detailed, absolute'!U15/Production!$C$17*AF_beef_FR -> 0.0021289865 | V15: ='GHG detailed, absolute'!V15/Production!$C$17*AF_beef_FR -> 0.00093605861 | W15: ='GHG detailed, absolute'!W15/Production!$C$17*AF_beef_FR -> 2.3677438e-05 | X15: ='GHG detailed, absolute'!X15/Production!$C$17*AF_beef_FR -> 3.8511366e-07
A16: 21111.02_dc | B16: Beef meat from dairy cows | C16: Red meat | D16: France | E16: FR | F16: CO2e | G16: =SUM(H16:X16) -> 14.704813 | H16: =SUMPRODUCT(H12:H15,'Parameters, general'!$B$24:$B$27) -> 0.54260541 | I16: =SUMPRODUCT(I12:I15,'Parameters, general'!$B$24:$B$27) -> 0.40079407 | J16: =SUMPRODUCT(J12:J15,'Parameters, general'!$B$24:$B$27) -> 1.4885887 | K16: =SUMPRODUCT(K12:K15,'Parameters, general'!$B$24:$B$27) -> 0.14885887 | L16: =SUMPRODUCT(L12:L15,'Parameters, general'!$B$24:$B$27) -> 0.26651938 | M16: =SUMPRODUCT(M12:M15,'Parameters, general'!$B$24:$B$27) -> 0 | N16: =SUMPRODUCT(N12:N15,'Parameters, general'!$B$24:$B$27) -> 0.0058291066 | O16: =SUMPRODUCT(O12:O15,'Parameters, general'!$B$24:$B$27) -> 0.14784319 | ... T16: =SUMPRODUCT(T12:T15,'Parameters, general'!$B$24:$B$27) -> 1.7128271 | W16: =SUMPRODUCT(W12:W15,'Parameters, general'!$B$24:$B$27) -> 0.28243884 | X16: =SUMPRODUCT(X12:X15,'Parameters, general'!$B$24:$B$27) -> 0.0073652271 | Z16: =SUM(H16:R16) -> 4.9501616 | AA16: ='CO2 per kg feed'!F36+'CH4 per kg feed'!F36*CF_GWP_CH4_fossil+'N2O per kg feed'!F36*CF_GWP_N2O -> 0.26766924
A17: 21111.02_dc | B17: Beef meat from dairy cows | C17: Red meat | D17: Germany | E17: DE | F17: CO2 | G17: =SUM(H17:X17) -> 3.9339109 | H17: ='GHG detailed, absolute'!H17/Production!$D$17*AF_beef_DE -> 0.31909036 | I17: ='GHG detailed, absolute'!I17/Production!$D$17*AF_beef_DE -> 0.34781209 | L17: ='GHG detailed, absolute'!L17/Production!$D$17*AF_beef_DE -> 0.21932621 | N17: ='GHG detailed, absolute'!N17/Production!$D$17*AF_beef_DE -> 0.00046439802 | O17: ='GHG detailed, absolute'!O17/Production!$D$17*AF_beef_DE -> 0.066706289 | P17: ='GHG detailed, absolute'!P17/Production!$D$17*AF_beef_DE -> 0.28313016 | Q17: ='GHG detailed, absolute'!Q17/Production!$D$17*AF_beef_DE -> 0.64478792 | R17: ='GHG detailed, absolute'!R17/Production!$D$17*AF_beef_DE -> 0.64478792 | W17: ='GHG detailed, absolute'!W17/Production!$D$17*AF_beef_DE -> 1.3927604 | X17: ='GHG detailed, absolute'!X17/Production!$D$17*AF_beef_DE -> 0.015045153
A18: 21111.02_dc | B18: Beef meat from dairy cows | C18: Red meat | D18: Germany | E18: DE | F18: CH4, fossil | G18: =SUM(H18:X18) -> 0.01565628 | H18: ='GHG detailed, absolute'!H18/Production!$D$17*AF_beef_DE -> 0.00029498398 | I18: ='GHG detailed, absolute'!I18/Production!$D$17*AF_beef_DE -> 0.0012237833 | L18: ='GHG detailed, absolute'!L18/Production!$D$17*AF_beef_DE -> 9.7154117e-05 | N18: ='GHG detailed, absolute'!N18/Production!$D$17*AF_beef_DE -> 1.5282038e-06 | O18: ='GHG detailed, absolute'!O18/Production!$D$17*AF_beef_DE -> 4.4783795e-05 | P18: ='GHG detailed, absolute'!P18/Production!$D$17*AF_beef_DE -> 0 | Q18: ='GHG detailed, absolute'!Q18/Production!$D$17*AF_beef_DE -> 0.0056467345 | R18: ='GHG detailed, absolute'!R18/Production!$D$17*AF_beef_DE -> 0.0056467345 | W18: ='GHG detailed, absolute'!W18/Production!$D$17*AF_beef_DE -> 0.0026641975 | X18: ='GHG detailed, absolute'!X18/Production!$D$17*AF_beef_DE -> 3.6379992e-05
A19: 21111.02_dc | B19: Beef meat from dairy cows | C19: Red meat | D19: Germany | E19: DE | F19: CH4, biogenic | G19: =SUM(H19:T19) -> 0.31676034 | S19: ='GHG detailed, absolute'!S19/Production!$D$17*AF_beef_DE -> 0.26770681 | T19: ='GHG detailed, absolute'!T19/Production!$D$17*AF_beef_DE -> 0.049053526 | U19: ='GHG detailed, absolute'!U19/Production!$D$17*AF_beef_DE -> 0.049053526
A20: 21111.02_dc | B20: Beef meat from dairy cows | C20: Red meat | D20: Germany | E20: DE | F20: N2O | G20: =SUM(H20:T20)+W20+X20 -> 0.0089237168 | H20: ='GHG detailed, absolute'!H20/Production!$D$17*AF_beef_DE -> 0.00039445154 | I20: ='GHG detailed, absolute'!I20/Production!$D$17*AF_beef_DE -> 1.4170122e-05 | J20: ='GHG detailed, absolute'!J20/Production!$D$17*AF_beef_DE -> 0.0038420539 | K20: ='GHG detailed, absolute'!K20/Production!$D$17*AF_beef_DE -> 0.00038420539 | L20: ='GHG detailed, absolute'!L20/Production!$D$17*AF_beef_DE -> 5.8933809e-06 | N20: ='GHG detailed, absolute'!N20/Production!$D$17*AF_beef_DE -> 1.9231418e-08 | O20: ='GHG detailed, absolute'!O20/Production!$D$17*AF_beef_DE -> 2.3885976e-06 | P20: ='GHG detailed, absolute'!P20/Production!$D$17*AF_beef_DE -> 0 | Q20: ='GHG detailed, absolute'!Q20/Production!$D$17*AF_beef_DE -> 0.00050752491 | R20: ='GHG detailed, absolute'!R20/Production!$D$17*AF_beef_DE -> 0.00050752491 | T20: ='GHG detailed, absolute'!T20/Production!$D$17*AF_beef_DE -> 0.0032024698 | U20: ='GHG detailed, absolute'!U20/Production!$D$17*AF_beef_DE -> 0.0019142193 | V20: ='GHG detailed, absolute'!V20/Production!$D$17*AF_beef_DE -> 0.0012882505 | W20: ='GHG detailed, absolute'!W20/Production!$D$17*AF_beef_DE -> 6.2377779e-05 | X20: ='GHG detailed, absolute'!X20/Production!$D$17*AF_beef_DE -> 6.3725042e-07
A21: 21111.02_dc | B21: Beef meat from dairy cows | C21: Red meat | D21: Germany | E21: DE | F21: CO2e | G21: =SUM(H21:X21) -> 15.389172 | H21: =SUMPRODUCT(H17:H20,'Parameters, general'!$B$24:$B$27) -> 0.43556615 | I21: =SUMPRODUCT(I17:I20,'Parameters, general'!$B$24:$B$27) -> 0.38814928 | J21: =SUMPRODUCT(J17:J20,'Parameters, general'!$B$24:$B$27) -> 1.0488807 | K21: =SUMPRODUCT(K17:K20,'Parameters, general'!$B$24:$B$27) -> 0.10488807 | L21: =SUMPRODUCT(L17:L20,'Parameters, general'!$B$24:$B$27) -> 0.2238303 | M21: =SUMPRODUCT(M17:M20,'Parameters, general'!$B$24:$B$27) -> 0 | N21: =SUMPRODUCT(N17:N20,'Parameters, general'!$B$24:$B$27) -> 0.00051518867 | O21: =SUMPRODUCT(O17:O20,'Parameters, general'!$B$24:$B$27) -> 0.068692933 | ... T21: =SUMPRODUCT(T17:T20,'Parameters, general'!$B$24:$B$27) -> 2.1987195 | W21: =SUMPRODUCT(W17:W20,'Parameters, general'!$B$24:$B$27) -> 1.4891826 | X21: =SUMPRODUCT(X17:X20,'Parameters, general'!$B$24:$B$27) -> 0.016303246 | Z21: =SUM(H21:R21) -> 4.4568826 | AA21: ='CO2 per kg feed'!F52+'CH4 per kg feed'!F52*CF_GWP_CH4_fossil+'N2O per kg feed'!F52*CF_GWP_N2O -> 0.25510784
A22: 21111.02_dc | B22: Beef meat from dairy cows | C22: Red meat | D22: Greece | E22: GR | F22: CO2 | G22: =SUM(H22:X22) -> 6.3638123 | H22: ='GHG detailed, absolute'!H22/Production!$E$17*AF_beef_GR -> 0.84759371 | I22: ='GHG detailed, absolute'!I22/Production!$E$17*AF_beef_GR -> 0.35519342 | L22: ='GHG detailed, absolute'!L22/Production!$E$17*AF_beef_GR -> 0.46882445 | N22: ='GHG detailed, absolute'!N22/Production!$E$17*AF_beef_GR -> 0.058863356 | O22: ='GHG detailed, absolute'!O22/Production!$E$17*AF_beef_GR -> 0.28832513 | P22: ='GHG detailed, absolute'!P22/Production!$E$17*AF_beef_GR -> 0.37943497 | Q22: ='GHG detailed, absolute'!Q22/Production!$E$17*AF_beef_GR -> 0.78576176 | R22: ='GHG detailed, absolute'!R22/Production!$E$17*AF_beef_GR -> 0.78576176 | W22: ='GHG detailed, absolute'!W22/Production!$E$17*AF_beef_GR -> 2.3721442 | X22: ='GHG detailed, absolute'!X22/Production!$E$17*AF_beef_GR -> 0.021909539
A23: 21111.02_dc | B23: Beef meat from dairy cows | C23: Red meat | D23: Greece | E23: GR | F23: CH4, fossil | G23: =SUM(H23:X23) -> 0.015756058 | H23: ='GHG detailed, absolute'!H23/Production!$E$17*AF_beef_GR -> 1.7804221e-05 | I23: ='GHG detailed, absolute'!I23/Production!$E$17*AF_beef_GR -> 0.0012497546 | L23: ='GHG detailed, absolute'!L23/Production!$E$17*AF_beef_GR -> 0.00020767342 | N23: ='GHG detailed, absolute'!N23/Production!$E$17*AF_beef_GR -> 0.00017924362 | O23: ='GHG detailed, absolute'!O23/Production!$E$17*AF_beef_GR -> 0.00023655639 | P23: ='GHG detailed, absolute'!P23/Production!$E$17*AF_beef_GR -> 0 | Q23: ='GHG detailed, absolute'!Q23/Production!$E$17*AF_beef_GR -> 0.0045521297 | R23: ='GHG detailed, absolute'!R23/Production!$E$17*AF_beef_GR -> 0.0045521297 | W23: ='GHG detailed, absolute'!W23/Production!$E$17*AF_beef_GR -> 0.0047090388 | X23: ='GHG detailed, absolute'!X23/Production!$E$17*AF_beef_GR -> 5.1727723e-05
A24: 21111.02_dc | B24: Beef meat from dairy cows | C24: Red meat | D24: Greece | E24: GR | F24: CH4, biogenic | G24: =SUM(H24:T24) -> 0.28641728 | S24: ='GHG detailed, absolute'!S24/Production!$E$17*AF_beef_GR -> 0.26178596 | T24: ='GHG detailed, absolute'!T24/Production!$E$17*AF_beef_GR -> 0.024631312 | U24: ='GHG detailed, absolute'!U24/Production!$E$17*AF_beef_GR -> 0.024631312
A25: 21111.02_dc | B25: Beef meat from dairy cows | C25: Red meat | D25: Greece | E25: GR | F25: N2O | G25: =SUM(H25:T25)+W25+X25 -> 0.013298506 | H25: ='GHG detailed, absolute'!H25/Production!$E$17*AF_beef_GR -> 9.7882161e-05 | I25: ='GHG detailed, absolute'!I25/Production!$E$17*AF_beef_GR -> 1.4470843e-05 | J25: ='GHG detailed, absolute'!J25/Production!$E$17*AF_beef_GR -> 0.0070477683 | K25: ='GHG detailed, absolute'!K25/Production!$E$17*AF_beef_GR -> 0.00070477683 | L25: ='GHG detailed, absolute'!L25/Production!$E$17*AF_beef_GR -> 1.2597496e-05 | N25: ='GHG detailed, absolute'!N25/Production!$E$17*AF_beef_GR -> 2.5053048e-06 | O25: ='GHG detailed, absolute'!O25/Production!$E$17*AF_beef_GR -> 1.0180891e-05 | P25: ='GHG detailed, absolute'!P25/Production!$E$17*AF_beef_GR -> 0 | Q25: ='GHG detailed, absolute'!Q25/Production!$E$17*AF_beef_GR -> 0.00035697994 | R25: ='GHG detailed, absolute'!R25/Production!$E$17*AF_beef_GR -> 0.00035697994 | T25: ='GHG detailed, absolute'!T25/Production!$E$17*AF_beef_GR -> 0.0046119854 | U25: ='GHG detailed, absolute'!U25/Production!$E$17*AF_beef_GR -> 0.0034669559 | V25: ='GHG detailed, absolute'!V25/Production!$E$17*AF_beef_GR -> 0.0011450295 | W25: ='GHG detailed, absolute'!W25/Production!$E$17*AF_beef_GR -> 8.1631555e-05 | X25: ='GHG detailed, absolute'!X25/Production!$E$17*AF_beef_GR -> 7.4695398e-07
A26: 21111.02_dc | B26: Beef meat from dairy cows | C26: Red meat | D26: Greece | E26: GR | F26: CO2e | G26: =SUM(H26:X26) -> 18.197101 | H26: =SUMPRODUCT(H22:H25,'Parameters, general'!$B$24:$B$27) -> 0.87484611 | I26: =SUMPRODUCT(I22:I25,'Parameters, general'!$B$24:$B$27) -> 0.39638665 | J26: =SUMPRODUCT(J22:J25,'Parameters, general'!$B$24:$B$27) -> 1.9240407 | K26: =SUMPRODUCT(K22:K25,'Parameters, general'!$B$24:$B$27) -> 0.19240407 | L26: =SUMPRODUCT(L22:L25,'Parameters, general'!$B$24:$B$27) -> 0.47845224 | M26: =SUMPRODUCT(M22:M25,'Parameters, general'!$B$24:$B$27) -> 0 | N26: =SUMPRODUCT(N22:N25,'Parameters, general'!$B$24:$B$27) -> 0.064888764 | O26: =SUMPRODUCT(O22:O25,'Parameters, general'!$B$24:$B$27) -> 0.2981539 | ... T26: =SUMPRODUCT(T22:T25,'Parameters, general'!$B$24:$B$27) -> 1.9241174 | W26: =SUMPRODUCT(W22:W25,'Parameters, general'!$B$24:$B$27) -> 2.534759 | X26: =SUMPRODUCT(X22:X25,'Parameters, general'!$B$24:$B$27) -> 0.023654944 | Z26: =SUM(H26:R26) -> 6.6463489 | AA26: ='CO2 per kg feed'!F68+'CH4 per kg feed'!F68*CF_GWP_CH4_fossil+'N2O per kg feed'!F68*CF_GWP_N2O -> 0.41434259
A27: 21111.02_dc | B27: Beef meat from dairy cows | C27: Red meat | D27: Hungary | E27: HU | F27: CO2 | G27: =SUM(H27:X27) -> 6.1779869 | H27: ='GHG detailed, absolute'!H27/Production!$F$17*AF_beef_HU -> 0.48998714 | I27: ='GHG detailed, absolute'!I27/Production!$F$17*AF_beef_HU -> 0.32469807 | L27: ='GHG detailed, absolute'!L27/Production!$F$17*AF_beef_HU -> 0.38007235 | N27: ='GHG detailed, absolute'!N27/Production!$F$17*AF_beef_HU -> 0.0015991788 | O27: ='GHG detailed, absolute'!O27/Production!$F$17*AF_beef_HU -> 0.23478892 | P27: ='GHG detailed, absolute'!P27/Production!$F$17*AF_beef_HU -> 0.52449157 | Q27: ='GHG detailed, absolute'!Q27/Production!$F$17*AF_beef_HU -> 1.4631406 | R27: ='GHG detailed, absolute'!R27/Production!$F$17*AF_beef_HU -> 1.4631406 | W27: ='GHG detailed, absolute'!W27/Production!$F$17*AF_beef_HU -> 1.2792042 | X27: ='GHG detailed, absolute'!X27/Production!$F$17*AF_beef_HU -> 0.016864347
A28: 21111.02_dc | B28: Beef meat from dairy cows | C28: Red meat | D28: Hungary | E28: HU | F28: CH4, fossil | G28: =SUM(H28:X28) -> 0.018760458 | H28: ='GHG detailed, absolute'!H28/Production!$F$17*AF_beef_HU -> 2.590478e-05 | I28: ='GHG detailed, absolute'!I28/Production!$F$17*AF_beef_HU -> 0.0011424562 | L28: ='GHG detailed, absolute'!L28/Production!$F$17*AF_beef_HU -> 0.00016835923 | N28: ='GHG detailed, absolute'!N28/Production!$F$17*AF_beef_HU -> 4.8430298e-06 | O28: ='GHG detailed, absolute'!O28/Production!$F$17*AF_beef_HU -> 0.00019130367 | P28: ='GHG detailed, absolute'!P28/Production!$F$17*AF_beef_HU -> 0 | Q28: ='GHG detailed, absolute'!Q28/Production!$F$17*AF_beef_HU -> 0.006974181 | R28: ='GHG detailed, absolute'!R28/Production!$F$17*AF_beef_HU -> 0.006974181 | W28: ='GHG detailed, absolute'!W28/Production!$F$17*AF_beef_HU -> 0.0032298195 | X28: ='GHG detailed, absolute'!X28/Production!$F$17*AF_beef_HU -> 4.940968e-05
A29: 21111.02_dc | B29: Beef meat from dairy cows | C29: Red meat | D29: Hungary | E29: HU | F29: CH4, biogenic | G29: =SUM(H29:T29) -> 0.31803111 | S29: ='GHG detailed, absolute'!S29/Production!$F$17*AF_beef_HU -> 0.27126845 | T29: ='GHG detailed, absolute'!T29/Production!$F$17*AF_beef_HU -> 0.046762658 | U29: ='GHG detailed, absolute'!U29/Production!$F$17*AF_beef_HU -> 0.046762658
A30: 21111.02_dc | B30: Beef meat from dairy cows | C30: Red meat | D30: Hungary | E30: HU | F30: N2O | G30: =SUM(H30:T30)+W30+X30 -> 0.012760643 | H30: ='GHG detailed, absolute'!H30/Production!$F$17*AF_beef_HU -> 0.00021343447 | I30: ='GHG detailed, absolute'!I30/Production!$F$17*AF_beef_HU -> 1.322844e-05 | J30: ='GHG detailed, absolute'!J30/Production!$F$17*AF_beef_HU -> 0.0058373316 | K30: ='GHG detailed, absolute'!K30/Production!$F$17*AF_beef_HU -> 0.00058373316 | L30: ='GHG detailed, absolute'!L30/Production!$F$17*AF_beef_HU -> 1.0212692e-05 | N30: ='GHG detailed, absolute'!N30/Production!$F$17*AF_beef_HU -> 6.8187736e-08 | O30: ='GHG detailed, absolute'!O30/Production!$F$17*AF_beef_HU -> 8.3619955e-06 | P30: ='GHG detailed, absolute'!P30/Production!$F$17*AF_beef_HU -> 0 | Q30: ='GHG detailed, absolute'!Q30/Production!$F$17*AF_beef_HU -> 0.00043485385 | R30: ='GHG detailed, absolute'!R30/Production!$F$17*AF_beef_HU -> 0.00043485385 | T30: ='GHG detailed, absolute'!T30/Production!$F$17*AF_beef_HU -> 0.0051791647 | U30: ='GHG detailed, absolute'!U30/Production!$F$17*AF_beef_HU -> 0.0037937595 | V30: ='GHG detailed, absolute'!V30/Production!$F$17*AF_beef_HU -> 0.0013854051 | W30: ='GHG detailed, absolute'!W30/Production!$F$17*AF_beef_HU -> 4.4818553e-05 | X30: ='GHG detailed, absolute'!X30/Production!$F$17*AF_beef_HU -> 5.8133547e-07
A31: 21111.02_dc | B31: Beef meat from dairy cows | C31: Red meat | D31: Hungary | E31: HU | F31: CO2e | G31: =SUM(H31:X31) -> 18.807544 | H31: =SUMPRODUCT(H27:H30,'Parameters, general'!$B$24:$B$27) -> 0.54902671 | I31: =SUMPRODUCT(I27:I30,'Parameters, general'!$B$24:$B$27) -> 0.36235463 | J31: =SUMPRODUCT(J27:J30,'Parameters, general'!$B$24:$B$27) -> 1.5935915 | K31: =SUMPRODUCT(K27:K30,'Parameters, general'!$B$24:$B$27) -> 0.15935915 | L31: =SUMPRODUCT(L27:L30,'Parameters, general'!$B$24:$B$27) -> 0.38787752 | M31: =SUMPRODUCT(M27:M30,'Parameters, general'!$B$24:$B$27) -> 0 | N31: =SUMPRODUCT(N27:N30,'Parameters, general'!$B$24:$B$27) -> 0.0017621163 | O31: =SUMPRODUCT(O27:O30,'Parameters, general'!$B$24:$B$27) -> 0.24277259 | ... T31: =SUMPRODUCT(T27:T30,'Parameters, general'!$B$24:$B$27) -> 2.6765037 | W31: =SUMPRODUCT(W27:W30,'Parameters, general'!$B$24:$B$27) -> 1.3876882 | X31: =SUMPRODUCT(X27:X30,'Parameters, general'!$B$24:$B$27) -> 0.01849546 | Z31: =SUM(H31:R31) -> 7.4006084 | AA31: ='CO2 per kg feed'!F84+'CH4 per kg feed'!F84*CF_GWP_CH4_fossil+'N2O per kg feed'!F84*CF_GWP_N2O -> 0.41909612
A32: 21111.02_dc | B32: Beef meat from dairy cows | C32: Red meat | D32: Ireland | E32: IE | F32: CO2 | G32: =SUM(H32:X32) -> 2.0555296 | H32: ='GHG detailed, absolute'!H32/Production!$G$17*AF_beef_IE -> 0.34323245 | I32: ='GHG detailed, absolute'!I32/Production!$G$17*AF_beef_IE -> 0.41671689 | L32: ='GHG detailed, absolute'!L32/Production!$G$17*AF_beef_IE -> 0.24730121 | N32: ='GHG detailed, absolute'!N32/Production!$G$17*AF_beef_IE -> 0.00098398711 | O32: ='GHG detailed, absolute'!O32/Production!$G$17*AF_beef_IE -> 0.081414542 | P32: ='GHG detailed, absolute'!P32/Production!$G$17*AF_beef_IE -> 0.038595812 | Q32: ='GHG detailed, absolute'!Q32/Production!$G$17*AF_beef_IE -> 0.10463314 | R32: ='GHG detailed, absolute'!R32/Production!$G$17*AF_beef_IE -> 0.10463314 | W32: ='GHG detailed, absolute'!W32/Production!$G$17*AF_beef_IE -> 0.70156602 | X32: ='GHG detailed, absolute'!X32/Production!$G$17*AF_beef_IE -> 0.0164524
A33: 21111.02_dc | B33: Beef meat from dairy cows | C33: Red meat | D33: Ireland | E33: IE | F33: CH4, fossil | G33: =SUM(H33:X33) -> 0.0028037262 | H33: ='GHG detailed, absolute'!H33/Production!$G$17*AF_beef_IE -> 1.3894585e-05 | I33: ='GHG detailed, absolute'!I33/Production!$G$17*AF_beef_IE -> 0.0014662261 | L33: ='GHG detailed, absolute'!L33/Production!$G$17*AF_beef_IE -> 0.0001095461 | N33: ='GHG detailed, absolute'!N33/Production!$G$17*AF_beef_IE -> 2.9157427e-06 | O33: ='GHG detailed, absolute'!O33/Production!$G$17*AF_beef_IE -> 4.2560299e-05 | P33: ='GHG detailed, absolute'!P33/Production!$G$17*AF_beef_IE -> 0 | Q33: ='GHG detailed, absolute'!Q33/Production!$G$17*AF_beef_IE -> 0.00019112359 | R33: ='GHG detailed, absolute'!R33/Production!$G$17*AF_beef_IE -> 0.00019112359 | W33: ='GHG detailed, absolute'!W33/Production!$G$17*AF_beef_IE -> 0.00075606621 | X33: ='GHG detailed, absolute'!X33/Production!$G$17*AF_beef_IE -> 3.0269984e-05
A34: 21111.02_dc | B34: Beef meat from dairy cows | C34: Red meat | D34: Ireland | E34: IE | F34: CH4, biogenic | G34: =SUM(H34:T34) -> 0.34197298 | S34: ='GHG detailed, absolute'!S34/Production!$G$17*AF_beef_IE -> 0.30435335 | T34: ='GHG detailed, absolute'!T34/Production!$G$17*AF_beef_IE -> 0.037619631 | U34: ='GHG detailed, absolute'!U34/Production!$G$17*AF_beef_IE -> 0.037619631
A35: 21111.02_dc | B35: Beef meat from dairy cows | C35: Red meat | D35: Ireland | E35: IE | F35: N2O | G35: =SUM(H35:T35)+W35+X35 -> 0.0089089628 | H35: ='GHG detailed, absolute'!H35/Production!$G$17*AF_beef_IE -> 0.00013300523 | I35: ='GHG detailed, absolute'!I35/Production!$G$17*AF_beef_IE -> 1.6977355e-05 | J35: ='GHG detailed, absolute'!J35/Production!$G$17*AF_beef_IE -> 0.0054460455 | K35: ='GHG detailed, absolute'!K35/Production!$G$17*AF_beef_IE -> 0.00054460455 | L35: ='GHG detailed, absolute'!L35/Production!$G$17*AF_beef_IE -> 6.64508e-06 | N35: ='GHG detailed, absolute'!N35/Production!$G$17*AF_beef_IE -> 4.2257022e-08 | O35: ='GHG detailed, absolute'!O35/Production!$G$17*AF_beef_IE -> 2.9327247e-06 | P35: ='GHG detailed, absolute'!P35/Production!$G$17*AF_beef_IE -> 0 | Q35: ='GHG detailed, absolute'!Q35/Production!$G$17*AF_beef_IE -> 1.2096313e-05 | R35: ='GHG detailed, absolute'!R35/Production!$G$17*AF_beef_IE -> 1.2096313e-05 | T35: ='GHG detailed, absolute'!T35/Production!$G$17*AF_beef_IE -> 0.0027081562 | U35: ='GHG detailed, absolute'!U35/Production!$G$17*AF_beef_IE -> 0.0018936001 | V35: ='GHG detailed, absolute'!V35/Production!$G$17*AF_beef_IE -> 0.00081455612 | W35: ='GHG detailed, absolute'!W35/Production!$G$17*AF_beef_IE -> 2.5773125e-05 | X35: ='GHG detailed, absolute'!X35/Production!$G$17*AF_beef_IE -> 5.8807223e-07
A36: 21111.02_dc | B36: Beef meat from dairy cows | C36: Red meat | D36: Ireland | E36: IE | F36: CO2e | G36: =SUM(H36:X36) -> 13.804498 | H36: =SUMPRODUCT(H32:H35,'Parameters, general'!$B$24:$B$27) -> 0.37995694 | I36: =SUMPRODUCT(I32:I35,'Parameters, general'!$B$24:$B$27) -> 0.46504524 | J36: =SUMPRODUCT(J32:J35,'Parameters, general'!$B$24:$B$27) -> 1.4867704 | K36: =SUMPRODUCT(K32:K35,'Parameters, general'!$B$24:$B$27) -> 0.14867704 | L36: =SUMPRODUCT(L32:L35,'Parameters, general'!$B$24:$B$27) -> 0.25237979 | M36: =SUMPRODUCT(M32:M35,'Parameters, general'!$B$24:$B$27) -> 0 | N36: =SUMPRODUCT(N32:N35,'Parameters, general'!$B$24:$B$27) -> 0.0010824124 | O36: =SUMPRODUCT(O32:O35,'Parameters, general'!$B$24:$B$27) -> 0.083483473 | ... T36: =SUMPRODUCT(T32:T35,'Parameters, general'!$B$24:$B$27) -> 1.7550567 | W36: =SUMPRODUCT(W32:W35,'Parameters, general'!$B$24:$B$27) -> 0.73113286 | X36: =SUMPRODUCT(X32:X35,'Parameters, general'!$B$24:$B$27) -> 0.01751499 | Z36: =SUM(H36:R36) -> 3.083253 | AA36: ='CO2 per kg feed'!F100+'CH4 per kg feed'!F100*CF_GWP_CH4_fossil+'N2O per kg feed'!F100*CF_GWP_N2O -> 0.13884603
A37: 21111.02_dc | B37: Beef meat from dairy cows | C37: Red meat | D37: Italy | E37: IT | F37: CO2 | G37: =SUM(H37:X37) -> 5.0151262 | H37: ='GHG detailed, absolute'!H37/Production!$H$17*AF_beef_IT -> 0.29128833 | I37: ='GHG detailed, absolute'!I37/Production!$H$17*AF_beef_IT -> 0.31653501 | L37: ='GHG detailed, absolute'!L37/Production!$H$17*AF_beef_IT -> 0.20677943 | N37: ='GHG detailed, absolute'!N37/Production!$H$17*AF_beef_IT -> 0.0033807026 | O37: ='GHG detailed, absolute'!O37/Production!$H$17*AF_beef_IT -> 0.0761871 | P37: ='GHG detailed, absolute'!P37/Production!$H$17*AF_beef_IT -> 0.52228709 | Q37: ='GHG detailed, absolute'!Q37/Production!$H$17*AF_beef_IT -> 1.1013553 | R37: ='GHG detailed, absolute'!R37/Production!$H$17*AF_beef_IT -> 1.1013553 | W37: ='GHG detailed, absolute'!W37/Production!$H$17*AF_beef_IT -> 1.3807373 | X37: ='GHG detailed, absolute'!X37/Production!$H$17*AF_beef_IT -> 0.015220524
A38: 21111.02_dc | B38: Beef meat from dairy cows | C38: Red meat | D38: Italy | E38: IT | F38: CH4, fossil | G38: =SUM(H38:X38) -> 0.022655524 | H38: ='GHG detailed, absolute'!H38/Production!$H$17*AF_beef_IT -> 4.4480052e-05 | I38: ='GHG detailed, absolute'!I38/Production!$H$17*AF_beef_IT -> 0.0011137343 | L38: ='GHG detailed, absolute'!L38/Production!$H$17*AF_beef_IT -> 9.1596314e-05 | N38: ='GHG detailed, absolute'!N38/Production!$H$17*AF_beef_IT -> 1.0935238e-05 | O38: ='GHG detailed, absolute'!O38/Production!$H$17*AF_beef_IT -> 6.6530244e-05 | P38: ='GHG detailed, absolute'!P38/Production!$H$17*AF_beef_IT -> 0 | Q38: ='GHG detailed, absolute'!Q38/Production!$H$17*AF_beef_IT -> 0.0076295591 | R38: ='GHG detailed, absolute'!R38/Production!$H$17*AF_beef_IT -> 0.0076295591 | W38: ='GHG detailed, absolute'!W38/Production!$H$17*AF_beef_IT -> 0.0060023769 | X38: ='GHG detailed, absolute'!X38/Production!$H$17*AF_beef_IT -> 6.6753074e-05
A39: 21111.02_dc | B39: Beef meat from dairy cows | C39: Red meat | D39: Italy | E39: IT | F39: CH4, biogenic | G39: =SUM(H39:T39) -> 0.36317962 | S39: ='GHG detailed, absolute'!S39/Production!$H$17*AF_beef_IT -> 0.29335699 | T39: ='GHG detailed, absolute'!T39/Production!$H$17*AF_beef_IT -> 0.06982263 | U39: ='GHG detailed, absolute'!U39/Production!$H$17*AF_beef_IT -> 0.06982263
A40: 21111.02_dc | B40: Beef meat from dairy cows | C40: Red meat | D40: Italy | E40: IT | F40: N2O | G40: =SUM(H40:T40)+W40+X40 -> 0.00955198 | H40: ='GHG detailed, absolute'!H40/Production!$H$17*AF_beef_IT -> 6.066565e-05 | I40: ='GHG detailed, absolute'!I40/Production!$H$17*AF_beef_IT -> 1.2895871e-05 | J40: ='GHG detailed, absolute'!J40/Production!$H$17*AF_beef_IT -> 0.0037643035 | K40: ='GHG detailed, absolute'!K40/Production!$H$17*AF_beef_IT -> 0.00037643035 | L40: ='GHG detailed, absolute'!L40/Production!$H$17*AF_beef_IT -> 5.5562438e-06 | N40: ='GHG detailed, absolute'!N40/Production!$H$17*AF_beef_IT -> 1.40888e-07 | O40: ='GHG detailed, absolute'!O40/Production!$H$17*AF_beef_IT -> 2.8012311e-06 | P40: ='GHG detailed, absolute'!P40/Production!$H$17*AF_beef_IT -> 0 | Q40: ='GHG detailed, absolute'!Q40/Production!$H$17*AF_beef_IT -> 0.00044857236 | R40: ='GHG detailed, absolute'!R40/Production!$H$17*AF_beef_IT -> 0.00044857236 | T40: ='GHG detailed, absolute'!T40/Production!$H$17*AF_beef_IT -> 0.0043713327 | U40: ='GHG detailed, absolute'!U40/Production!$H$17*AF_beef_IT -> 0.0028773839 | V40: ='GHG detailed, absolute'!V40/Production!$H$17*AF_beef_IT -> 0.0014939488 | W40: ='GHG detailed, absolute'!W40/Production!$H$17*AF_beef_IT -> 6.0085545e-05 | X40: ='GHG detailed, absolute'!X40/Production!$H$17*AF_beef_IT -> 6.2328808e-07
A41: 21111.02_dc | B41: Beef meat from dairy cows | C41: Red meat | D41: Italy | E41: IT | F41: CO2e | G41: =SUM(H41:X41) -> 18.103801 | H41: =SUMPRODUCT(H37:H40,'Parameters, general'!$B$24:$B$27) -> 0.30917555 | I41: =SUMPRODUCT(I37:I40,'Parameters, general'!$B$24:$B$27) -> 0.35324487 | J41: =SUMPRODUCT(J37:J40,'Parameters, general'!$B$24:$B$27) -> 1.0276549 | K41: =SUMPRODUCT(K37:K40,'Parameters, general'!$B$24:$B$27) -> 0.10276549 | L41: =SUMPRODUCT(L37:L40,'Parameters, general'!$B$24:$B$27) -> 0.21102585 | M41: =SUMPRODUCT(M37:M40,'Parameters, general'!$B$24:$B$27) -> 0 | N41: =SUMPRODUCT(N37:N40,'Parameters, general'!$B$24:$B$27) -> 0.0037450351 | O41: =SUMPRODUCT(O37:O40,'Parameters, general'!$B$24:$B$27) -> 0.078934437 | ... T41: =SUMPRODUCT(T37:T40,'Parameters, general'!$B$24:$B$27) -> 3.0785848 | W41: =SUMPRODUCT(W37:W40,'Parameters, general'!$B$24:$B$27) -> 1.5760115 | X41: =SUMPRODUCT(X37:X40,'Parameters, general'!$B$24:$B$27) -> 0.017379924 | Z41: =SUM(H41:R41) -> 5.5111861 | AA41: ='CO2 per kg feed'!F116+'CH4 per kg feed'!F116*CF_GWP_CH4_fossil+'N2O per kg feed'!F116*CF_GWP_N2O -> 0.2926376
A42: 21111.02_dc | B42: Beef meat from dairy cows | C42: Red meat | D42: Netherland | E42: NL | F42: CO2 | G42: =SUM(H42:X42) -> 4.7345504 | H42: ='GHG detailed, absolute'!H42/Production!$I$17*AF_beef_NL -> 0.73445156 | I42: ='GHG detailed, absolute'!I42/Production!$I$17*AF_beef_NL -> 0.32900935 | L42: ='GHG detailed, absolute'!L42/Production!$I$17*AF_beef_NL -> 0.28715582 | N42: ='GHG detailed, absolute'!N42/Production!$I$17*AF_beef_NL -> 0.0011447136 | O42: ='GHG detailed, absolute'!O42/Production!$I$17*AF_beef_NL -> 0.14933846 | P42: ='GHG detailed, absolute'!P42/Production!$I$17*AF_beef_NL -> 0.4839792 | Q42: ='GHG detailed, absolute'!Q42/Production!$I$17*AF_beef_NL -> 0.41616196 | R42: ='GHG detailed, absolute'!R42/Production!$I$17*AF_beef_NL -> 0.41616196 | W42: ='GHG detailed, absolute'!W42/Production!$I$17*AF_beef_NL -> 1.9023302 | X42: ='GHG detailed, absolute'!X42/Production!$I$17*AF_beef_NL -> 0.014817152
A43: 21111.02_dc | B43: Beef meat from dairy cows | C43: Red meat | D43: Netherland | E43: NL | F43: CH4, fossil | G43: =SUM(H43:X43) -> 0.012208857 | H43: ='GHG detailed, absolute'!H43/Production!$I$17*AF_beef_NL -> 0.00038277375 | I43: ='GHG detailed, absolute'!I43/Production!$I$17*AF_beef_NL -> 0.0011576255 | L43: ='GHG detailed, absolute'!L43/Production!$I$17*AF_beef_NL -> 0.00012720035 | N43: ='GHG detailed, absolute'!N43/Production!$I$17*AF_beef_NL -> 3.6675858e-06 | O43: ='GHG detailed, absolute'!O43/Production!$I$17*AF_beef_NL -> 0.00010564364 | P43: ='GHG detailed, absolute'!P43/Production!$I$17*AF_beef_NL -> 0 | Q43: ='GHG detailed, absolute'!Q43/Production!$I$17*AF_beef_NL -> 0.0033146594 | R43: ='GHG detailed, absolute'!R43/Production!$I$17*AF_beef_NL -> 0.0033146594 | W43: ='GHG detailed, absolute'!W43/Production!$I$17*AF_beef_NL -> 0.0037663968 | X43: ='GHG detailed, absolute'!X43/Production!$I$17*AF_beef_NL -> 3.6230396e-05
A44: 21111.02_dc | B44: Beef meat from dairy cows | C44: Red meat | D44: Netherland | E44: NL | F44: CH4, biogenic | G44: =SUM(H44:T44) -> 0.3044271 | S44: ='GHG detailed, absolute'!S44/Production!$I$17*AF_beef_NL -> 0.25231639 | T44: ='GHG detailed, absolute'!T44/Production!$I$17*AF_beef_NL -> 0.052110714 | U44: ='GHG detailed, absolute'!U44/Production!$I$17*AF_beef_NL -> 0.052110714
A45: 21111.02_dc | B45: Beef meat from dairy cows | C45: Red meat | D45: Netherland | E45: NL | F45: N2O | G45: =SUM(H45:T45)+W45+X45 -> 0.012518405 | H45: ='GHG detailed, absolute'!H45/Production!$I$17*AF_beef_NL -> 0.00065454244 | I45: ='GHG detailed, absolute'!I45/Production!$I$17*AF_beef_NL -> 1.3404085e-05 | J45: ='GHG detailed, absolute'!J45/Production!$I$17*AF_beef_NL -> 0.0074807856 | K45: ='GHG detailed, absolute'!K45/Production!$I$17*AF_beef_NL -> 0.00074807856 | L45: ='GHG detailed, absolute'!L45/Production!$I$17*AF_beef_NL -> 7.7159889e-06 | N45: ='GHG detailed, absolute'!N45/Production!$I$17*AF_beef_NL -> 4.7869356e-08 | O45: ='GHG detailed, absolute'!O45/Production!$I$17*AF_beef_NL -> 5.3885938e-06 | P45: ='GHG detailed, absolute'!P45/Production!$I$17*AF_beef_NL -> 0 | Q45: ='GHG detailed, absolute'!Q45/Production!$I$17*AF_beef_NL -> 0.00029908111 | R45: ='GHG detailed, absolute'!R45/Production!$I$17*AF_beef_NL -> 0.00029908111 | T45: ='GHG detailed, absolute'!T45/Production!$I$17*AF_beef_NL -> 0.0029333329 | U45: ='GHG detailed, absolute'!U45/Production!$I$17*AF_beef_NL -> 0.0016009028 | V45: ='GHG detailed, absolute'!V45/Production!$I$17*AF_beef_NL -> 0.0013324301 | W45: ='GHG detailed, absolute'!W45/Production!$I$17*AF_beef_NL -> 7.6373376e-05 | X45: ='GHG detailed, absolute'!X45/Production!$I$17*AF_beef_NL -> 5.7342348e-07
A46: 21111.02_dc | B46: Beef meat from dairy cows | C46: Red meat | D46: Netherland | E46: NL | F46: CO2e | G46: =SUM(H46:X46) -> 16.735431 | H46: =SUMPRODUCT(H42:H45,'Parameters, general'!$B$24:$B$27) -> 0.92454831 | I46: =SUMPRODUCT(I42:I45,'Parameters, general'!$B$24:$B$27) -> 0.3671659 | J46: =SUMPRODUCT(J42:J45,'Parameters, general'!$B$24:$B$27) -> 2.0422545 | K46: =SUMPRODUCT(K42:K45,'Parameters, general'!$B$24:$B$27) -> 0.20422545 | L46: =SUMPRODUCT(L42:L45,'Parameters, general'!$B$24:$B$27) -> 0.29305286 | M46: =SUMPRODUCT(M42:M45,'Parameters, general'!$B$24:$B$27) -> 0 | N46: =SUMPRODUCT(N42:N45,'Parameters, general'!$B$24:$B$27) -> 0.001267076 | O46: =SUMPRODUCT(O42:O45,'Parameters, general'!$B$24:$B$27) -> 0.15395773 | ... T46: =SUMPRODUCT(T42:T45,'Parameters, general'!$B$24:$B$27) -> 2.2077892 | W46: =SUMPRODUCT(W42:W45,'Parameters, general'!$B$24:$B$27) -> 2.0354188 | X46: =SUMPRODUCT(X42:X45,'Parameters, general'!$B$24:$B$27) -> 0.016053362 | Z46: =SUM(H46:R46) -> 5.6636269 | AA46: ='CO2 per kg feed'!F132+'CH4 per kg feed'!F132*CF_GWP_CH4_fossil+'N2O per kg feed'!F132*CF_GWP_N2O -> 0.3977347
A47: 21111.02_dc | B47: Beef meat from dairy cows | C47: Red meat | D47: Poland | E47: PL | F47: CO2 | G47: =SUM(H47:X47) -> 7.9636178 | H47: ='GHG detailed, absolute'!H47/Production!$J$17*AF_beef_PL -> 0.94477981 | I47: ='GHG detailed, absolute'!I47/Production!$J$17*AF_beef_PL -> 0.36387623 | L47: ='GHG detailed, absolute'!L47/Production!$J$17*AF_beef_PL -> 0.44755605 | N47: ='GHG detailed, absolute'!N47/Production!$J$17*AF_beef_PL -> 0.0025447458 | O47: ='GHG detailed, absolute'!O47/Production!$J$17*AF_beef_PL -> 0.33263393 | P47: ='GHG detailed, absolute'!P47/Production!$J$17*AF_beef_PL -> 0.37022343 | Q47: ='GHG detailed, absolute'!Q47/Production!$J$17*AF_beef_PL -> 1.0437399 | R47: ='GHG detailed, absolute'!R47/Production!$J$17*AF_beef_PL -> 1.0437399 | W47: ='GHG detailed, absolute'!W47/Production!$J$17*AF_beef_PL -> 3.3814696 | X47: ='GHG detailed, absolute'!X47/Production!$J$17*AF_beef_PL -> 0.033054283
A48: 21111.02_dc | B48: Beef meat from dairy cows | C48: Red meat | D48: Poland | E48: PL | F48: CH4, fossil | G48: =SUM(H48:X48) -> 0.017280342 | H48: ='GHG detailed, absolute'!H48/Production!$J$17*AF_beef_PL -> 8.8974495e-05 | I48: ='GHG detailed, absolute'!I48/Production!$J$17*AF_beef_PL -> 0.0012803053 | L48: ='GHG detailed, absolute'!L48/Production!$J$17*AF_beef_PL -> 0.00019825224 | N48: ='GHG detailed, absolute'!N48/Production!$J$17*AF_beef_PL -> 7.6226417e-06 | O48: ='GHG detailed, absolute'!O48/Production!$J$17*AF_beef_PL -> 0.00029077498 | P48: ='GHG detailed, absolute'!P48/Production!$J$17*AF_beef_PL -> 0 | Q48: ='GHG detailed, absolute'!Q48/Production!$J$17*AF_beef_PL -> 0.0044134323 | R48: ='GHG detailed, absolute'!R48/Production!$J$17*AF_beef_PL -> 0.0044134323 | W48: ='GHG detailed, absolute'!W48/Production!$J$17*AF_beef_PL -> 0.0065150748 | X48: ='GHG detailed, absolute'!X48/Production!$J$17*AF_beef_PL -> 7.2472773e-05
A49: 21111.02_dc | B49: Beef meat from dairy cows | C49: Red meat | D49: Poland | E49: PL | F49: CH4, biogenic | G49: =SUM(H49:T49) -> 0.29526098 | S49: ='GHG detailed, absolute'!S49/Production!$J$17*AF_beef_PL -> 0.27589808 | T49: ='GHG detailed, absolute'!T49/Production!$J$17*AF_beef_PL -> 0.019362902 | U49: ='GHG detailed, absolute'!U49/Production!$J$17*AF_beef_PL -> 0.019362902
A50: 21111.02_dc | B50: Beef meat from dairy cows | C50: Red meat | D50: Poland | E50: PL | F50: N2O | G50: =SUM(H50:T50)+W50+X50 -> 0.01229039 | H50: ='GHG detailed, absolute'!H50/Production!$J$17*AF_beef_PL -> 0.00029235678 | I50: ='GHG detailed, absolute'!I50/Production!$J$17*AF_beef_PL -> 1.4824587e-05 | J50: ='GHG detailed, absolute'!J50/Production!$J$17*AF_beef_PL -> 0.0057168807 | K50: ='GHG detailed, absolute'!K50/Production!$J$17*AF_beef_PL -> 0.00057168807 | L50: ='GHG detailed, absolute'!L50/Production!$J$17*AF_beef_PL -> 1.2026006e-05 | N50: ='GHG detailed, absolute'!N50/Production!$J$17*AF_beef_PL -> 1.0889914e-07 | O50: ='GHG detailed, absolute'!O50/Production!$J$17*AF_beef_PL -> 1.0783187e-05 | P50: ='GHG detailed, absolute'!P50/Production!$J$17*AF_beef_PL -> 0 | Q50: ='GHG detailed, absolute'!Q50/Production!$J$17*AF_beef_PL -> 0.00028713933 | R50: ='GHG detailed, absolute'!R50/Production!$J$17*AF_beef_PL -> 0.00028713933 | T50: ='GHG detailed, absolute'!T50/Production!$J$17*AF_beef_PL -> 0.0050357854 | U50: ='GHG detailed, absolute'!U50/Production!$J$17*AF_beef_PL -> 0.0037567264 | V50: ='GHG detailed, absolute'!V50/Production!$J$17*AF_beef_PL -> 0.0012790589 | W50: ='GHG detailed, absolute'!W50/Production!$J$17*AF_beef_PL -> 6.1013344e-05 | X50: ='GHG detailed, absolute'!X50/Production!$J$17*AF_beef_PL -> 6.4464965e-07
A51: 21111.02_dc | B51: Beef meat from dairy cows | C51: Red meat | D51: Poland | E51: PL | F51: CO2e | G51: =SUM(H51:X51) -> 19.805895 | H51: =SUMPRODUCT(H47:H50,'Parameters, general'!$B$24:$B$27) -> 1.0272446 | I51: =SUMPRODUCT(I47:I50,'Parameters, general'!$B$24:$B$27) -> 0.40607644 | J51: =SUMPRODUCT(J47:J50,'Parameters, general'!$B$24:$B$27) -> 1.5607084 | K51: =SUMPRODUCT(K47:K50,'Parameters, general'!$B$24:$B$27) -> 0.15607084 | L51: =SUMPRODUCT(L47:L50,'Parameters, general'!$B$24:$B$27) -> 0.45674707 | M51: =SUMPRODUCT(M47:M50,'Parameters, general'!$B$24:$B$27) -> 0 | N51: =SUMPRODUCT(N47:N50,'Parameters, general'!$B$24:$B$27) -> 0.00280163 | O51: =SUMPRODUCT(O47:O50,'Parameters, general'!$B$24:$B$27) -> 0.34424283 | ... T51: =SUMPRODUCT(T47:T50,'Parameters, general'!$B$24:$B$27) -> 1.8975678 | W51: =SUMPRODUCT(W47:W50,'Parameters, general'!$B$24:$B$27) -> 3.5922754 | X51: =SUMPRODUCT(X47:X50,'Parameters, general'!$B$24:$B$27) -> 0.035389961 | Z51: =SUM(H51:R51) -> 6.8314138 | AA51: ='CO2 per kg feed'!F148+'CH4 per kg feed'!F148*CF_GWP_CH4_fossil+'N2O per kg feed'!F148*CF_GWP_N2O -> 0.37726692
A52: 21111.02_dc | B52: Beef meat from dairy cows | C52: Red meat | D52: Spain | E52: ES | F52: CO2 | G52: =SUM(H52:X52) -> 4.0975898 | H52: ='GHG detailed, absolute'!H52/Production!$K$17*AF_beef_ES -> 0.5841447 | I52: ='GHG detailed, absolute'!I52/Production!$K$17*AF_beef_ES -> 0.33049587 | L52: ='GHG detailed, absolute'!L52/Production!$K$17*AF_beef_ES -> 0.41717965 | N52: ='GHG detailed, absolute'!N52/Production!$K$17*AF_beef_ES -> 0.052893096 | O52: ='GHG detailed, absolute'!O52/Production!$K$17*AF_beef_ES -> 0.24408141 | P52: ='GHG detailed, absolute'!P52/Production!$K$17*AF_beef_ES -> 0.45015182 | Q52: ='GHG detailed, absolute'!Q52/Production!$K$17*AF_beef_ES -> 0.49826415 | R52: ='GHG detailed, absolute'!R52/Production!$K$17*AF_beef_ES -> 0.49826415 | W52: ='GHG detailed, absolute'!W52/Production!$K$17*AF_beef_ES -> 1.0118286 | X52: ='GHG detailed, absolute'!X52/Production!$K$17*AF_beef_ES -> 0.010286366
A53: 21111.02_dc | B53: Beef meat from dairy cows | C53: Red meat | D53: Spain | E53: ES | F53: CH4, fossil | G53: =SUM(H53:X53) -> 0.011320971 | H53: ='GHG detailed, absolute'!H53/Production!$K$17*AF_beef_ES -> 7.0459291e-05 | I53: ='GHG detailed, absolute'!I53/Production!$K$17*AF_beef_ES -> 0.0011628559 | L53: ='GHG detailed, absolute'!L53/Production!$K$17*AF_beef_ES -> 0.00018479652 | N53: ='GHG detailed, absolute'!N53/Production!$K$17*AF_beef_ES -> 0.00015776216 | O53: ='GHG detailed, absolute'!O53/Production!$K$17*AF_beef_ES -> 0.00018417391 | P53: ='GHG detailed, absolute'!P53/Production!$K$17*AF_beef_ES -> 0 | Q53: ='GHG detailed, absolute'!Q53/Production!$K$17*AF_beef_ES -> 0.0031985506 | R53: ='GHG detailed, absolute'!R53/Production!$K$17*AF_beef_ES -> 0.0031985506 | W53: ='GHG detailed, absolute'!W53/Production!$K$17*AF_beef_ES -> 0.0031277174 | X53: ='GHG detailed, absolute'!X53/Production!$K$17*AF_beef_ES -> 3.6104734e-05
A54: 21111.02_dc | B54: Beef meat from dairy cows | C54: Red meat | D54: Spain | E54: ES | F54: CH4, biogenic | G54: =SUM(H54:T54) -> 0.29035851 | S54: ='GHG detailed, absolute'!S54/Production!$K$17*AF_beef_ES -> 0.24695087 | T54: ='GHG detailed, absolute'!T54/Production!$K$17*AF_beef_ES -> 0.043407646 | U54: ='GHG detailed, absolute'!U54/Production!$K$17*AF_beef_ES -> 0.043407646
A55: 21111.02_dc | B55: Beef meat from dairy cows | C55: Red meat | D55: Spain | E55: ES | F55: N2O | G55: =SUM(H55:T55)+W55+X55 -> 0.010481418 | H55: ='GHG detailed, absolute'!H55/Production!$K$17*AF_beef_ES -> 0.00017046706 | I55: ='GHG detailed, absolute'!I55/Production!$K$17*AF_beef_ES -> 1.3464647e-05 | J55: ='GHG detailed, absolute'!J55/Production!$K$17*AF_beef_ES -> 0.0058313517 | K55: ='GHG detailed, absolute'!K55/Production!$K$17*AF_beef_ES -> 0.00058313517 | L55: ='GHG detailed, absolute'!L55/Production!$K$17*AF_beef_ES -> 1.120978e-05 | N55: ='GHG detailed, absolute'!N55/Production!$K$17*AF_beef_ES -> 2.2666572e-06 | O55: ='GHG detailed, absolute'!O55/Production!$K$17*AF_beef_ES -> 8.9669992e-06 | P55: ='GHG detailed, absolute'!P55/Production!$K$17*AF_beef_ES -> 0 | Q55: ='GHG detailed, absolute'!Q55/Production!$K$17*AF_beef_ES -> 0.00023217972 | R55: ='GHG detailed, absolute'!R55/Production!$K$17*AF_beef_ES -> 0.00023217972 | T55: ='GHG detailed, absolute'!T55/Production!$K$17*AF_beef_ES -> 0.0033499626 | U55: ='GHG detailed, absolute'!U55/Production!$K$17*AF_beef_ES -> 0.002306024 | V55: ='GHG detailed, absolute'!V55/Production!$K$17*AF_beef_ES -> 0.0010439386 | W55: ='GHG detailed, absolute'!W55/Production!$K$17*AF_beef_ES -> 4.5807452e-05 | X55: ='GHG detailed, absolute'!X55/Production!$K$17*AF_beef_ES -> 4.2634011e-07
A56: 21111.02_dc | B56: Beef meat from dairy cows | C56: Red meat | D56: Spain | E56: ES | F56: CO2e | G56: =SUM(H56:X56) -> 15.136062 | H56: =SUMPRODUCT(H52:H55,'Parameters, general'!$B$24:$B$27) -> 0.63278189 | I56: =SUMPRODUCT(I52:I55,'Parameters, general'!$B$24:$B$27) -> 0.36882483 | J56: =SUMPRODUCT(J52:J55,'Parameters, general'!$B$24:$B$27) -> 1.591959 | K56: =SUMPRODUCT(K52:K55,'Parameters, general'!$B$24:$B$27) -> 0.1591959 | L56: =SUMPRODUCT(L52:L55,'Parameters, general'!$B$24:$B$27) -> 0.42574686 | M56: =SUMPRODUCT(M52:M55,'Parameters, general'!$B$24:$B$27) -> 0 | N56: =SUMPRODUCT(N52:N55,'Parameters, general'!$B$24:$B$27) -> 0.058213206 | O56: =SUMPRODUCT(O52:O55,'Parameters, general'!$B$24:$B$27) -> 0.25201778 | ... T56: =SUMPRODUCT(T52:T55,'Parameters, general'!$B$24:$B$27) -> 2.0865462 | W56: =SUMPRODUCT(W52:W55,'Parameters, general'!$B$24:$B$27) -> 1.11754 | X56: =SUMPRODUCT(X52:X55,'Parameters, general'!$B$24:$B$27) -> 0.011478678 | Z56: =SUM(H56:R56) -> 5.2528234 | AA56: ='CO2 per kg feed'!F164+'CH4 per kg feed'!F164*CF_GWP_CH4_fossil+'N2O per kg feed'!F164*CF_GWP_N2O -> 0.36944907
A57: 21111.02_dc | B57: Beef meat from dairy cows | C57: Red meat | D57: Sweden | E57: SE | F57: CO2 | G57: =SUM(H57:X57) -> 2.9036894 | H57: ='GHG detailed, absolute'!H57/Production!$L$17*AF_beef_SE -> 0.4431254 | I57: ='GHG detailed, absolute'!I57/Production!$L$17*AF_beef_SE -> 0.3596786 | L57: ='GHG detailed, absolute'!L57/Production!$L$17*AF_beef_SE -> 0.35255339 | N57: ='GHG detailed, absolute'!N57/Production!$L$17*AF_beef_SE -> 0.00086893751 | O57: ='GHG detailed, absolute'!O57/Production!$L$17*AF_beef_SE -> 0.12504327 | P57: ='GHG detailed, absolute'!P57/Production!$L$17*AF_beef_SE -> 0.32627121 | Q57: ='GHG detailed, absolute'!Q57/Production!$L$17*AF_beef_SE -> 0.55816678 | R57: ='GHG detailed, absolute'!R57/Production!$L$17*AF_beef_SE -> 0.55816678 | W57: ='GHG detailed, absolute'!W57/Production!$L$17*AF_beef_SE -> 0.1745488 | X57: ='GHG detailed, absolute'!X57/Production!$L$17*AF_beef_SE -> 0.0052662576
A58: 21111.02_dc | B58: Beef meat from dairy cows | C58: Red meat | D58: Sweden | E58: SE | F58: CH4, fossil | G58: =SUM(H58:X58) -> 0.01625848 | H58: ='GHG detailed, absolute'!H58/Production!$L$17*AF_beef_SE -> 0.00017181656 | I58: ='GHG detailed, absolute'!I58/Production!$L$17*AF_beef_SE -> 0.0012655358 | L58: ='GHG detailed, absolute'!L58/Production!$L$17*AF_beef_SE -> 0.00015616926 | N58: ='GHG detailed, absolute'!N58/Production!$L$17*AF_beef_SE -> 2.6633013e-06 | O58: ='GHG detailed, absolute'!O58/Production!$L$17*AF_beef_SE -> 6.403223e-05 | P58: ='GHG detailed, absolute'!P58/Production!$L$17*AF_beef_SE -> 0 | Q58: ='GHG detailed, absolute'!Q58/Production!$L$17*AF_beef_SE -> 0.0071942321 | R58: ='GHG detailed, absolute'!R58/Production!$L$17*AF_beef_SE -> 0.0071942321 | W58: ='GHG detailed, absolute'!W58/Production!$L$17*AF_beef_SE -> 0.00019394389 | X58: ='GHG detailed, absolute'!X58/Production!$L$17*AF_beef_SE -> 1.5854779e-05
A59: 21111.02_dc | B59: Beef meat from dairy cows | C59: Red meat | D59: Sweden | E59: SE | F59: CH4, biogenic | G59: =SUM(H59:T59) -> 0.28691119 | S59: ='GHG detailed, absolute'!S59/Production!$L$17*AF_beef_SE -> 0.27095613 | T59: ='GHG detailed, absolute'!T59/Production!$L$17*AF_beef_SE -> 0.015955064 | U59: ='GHG detailed, absolute'!U59/Production!$L$17*AF_beef_SE -> 0.015955064
A60: 21111.02_dc | B60: Beef meat from dairy cows | C60: Red meat | D60: Sweden | E60: SE | F60: N2O | G60: =SUM(H60:T60)+W60+X60 -> 0.010413989 | H60: ='GHG detailed, absolute'!H60/Production!$L$17*AF_beef_SE -> 0.00038424548 | I60: ='GHG detailed, absolute'!I60/Production!$L$17*AF_beef_SE -> 1.4653573e-05 | J60: ='GHG detailed, absolute'!J60/Production!$L$17*AF_beef_SE -> 0.0054723131 | K60: ='GHG detailed, absolute'!K60/Production!$L$17*AF_beef_SE -> 0.00054723131 | L60: ='GHG detailed, absolute'!L60/Production!$L$17*AF_beef_SE -> 9.4732469e-06 | N60: ='GHG detailed, absolute'!N60/Production!$L$17*AF_beef_SE -> 3.6902103e-08 | O60: ='GHG detailed, absolute'!O60/Production!$L$17*AF_beef_SE -> 4.6839031e-06 | P60: ='GHG detailed, absolute'!P60/Production!$L$17*AF_beef_SE -> 0 | Q60: ='GHG detailed, absolute'!Q60/Production!$L$17*AF_beef_SE -> 0.00069174436 | R60: ='GHG detailed, absolute'!R60/Production!$L$17*AF_beef_SE -> 0.00069174436 | T60: ='GHG detailed, absolute'!T60/Production!$L$17*AF_beef_SE -> 0.0025814249 | U60: ='GHG detailed, absolute'!U60/Production!$L$17*AF_beef_SE -> 0.0014532506 | V60: ='GHG detailed, absolute'!V60/Production!$L$17*AF_beef_SE -> 0.0011281744 | W60: ='GHG detailed, absolute'!W60/Production!$L$17*AF_beef_SE -> 1.6127499e-05 | X60: ='GHG detailed, absolute'!X60/Production!$L$17*AF_beef_SE -> 3.0990447e-07
A61: 21111.02_dc | B61: Beef meat from dairy cows | C61: Red meat | D61: Sweden | E61: SE | F61: CO2e | G61: =SUM(H61:X61) -> 13.977813 | H61: =SUMPRODUCT(H57:H60,'Parameters, general'!$B$24:$B$27) -> 0.55314455 | I61: =SUMPRODUCT(I57:I60,'Parameters, general'!$B$24:$B$27) -> 0.40139199 | J61: =SUMPRODUCT(J57:J60,'Parameters, general'!$B$24:$B$27) -> 1.4939415 | K61: =SUMPRODUCT(K57:K60,'Parameters, general'!$B$24:$B$27) -> 0.14939415 | L61: =SUMPRODUCT(L57:L60,'Parameters, general'!$B$24:$B$27) -> 0.35979343 | M61: =SUMPRODUCT(M57:M60,'Parameters, general'!$B$24:$B$27) -> 0 | N61: =SUMPRODUCT(N57:N60,'Parameters, general'!$B$24:$B$27) -> 0.00095837816 | O61: =SUMPRODUCT(O57:O60,'Parameters, general'!$B$24:$B$27) -> 0.12823013 | ... T61: =SUMPRODUCT(T57:T60,'Parameters, general'!$B$24:$B$27) -> 1.1355157 | W61: =SUMPRODUCT(W57:W60,'Parameters, general'!$B$24:$B$27) -> 0.18473114 | X61: =SUMPRODUCT(X57:X60,'Parameters, general'!$B$24:$B$27) -> 0.005823334 | Z61: =SUM(H61:R61) -> 5.3359275 | AA61: ='CO2 per kg feed'!F180+'CH4 per kg feed'!F180*CF_GWP_CH4_fossil+'N2O per kg feed'!F180*CF_GWP_N2O -> 0.31750016
A62: 21111.02_dc | B62: Beef meat from dairy cows | C62: Red meat | D62: UK | E62: GB | F62: CO2 | G62: =SUM(H62:X62) -> 2.0555296 | H62: =H32 -> 0.34323245 | I62: =I32 -> 0.41671689 | L62: =L32 -> 0.24730121 | N62: =N32 -> 0.00098398711 | O62: =O32 -> 0.081414542 | P62: =P32 -> 0.038595812 | Q62: =Q32 -> 0.10463314 | R62: =R32 -> 0.10463314 | W62: =W32 -> 0.70156602 | X62: =X32 -> 0.0164524 | AB62: Approx Ireland for now because we only need the UK-value for the meat from dairy cows (not dairy)
A63: 21111.02_dc | B63: Beef meat from dairy cows | C63: Red meat | D63: UK | E63: GB | F63: CH4, fossil | G63: =SUM(H63:X63) -> 0.0028037262 | H63: =H33 -> 1.3894585e-05 | I63: =I33 -> 0.0014662261 | L63: =L33 -> 0.0001095461 | N63: =N33 -> 2.9157427e-06 | O63: =O33 -> 4.2560299e-05 | P63: =P33 -> 0 | Q63: =Q33 -> 0.00019112359 | R63: =R33 -> 0.00019112359 | W63: =W33 -> 0.00075606621 | X63: =X33 -> 3.0269984e-05
A64: 21111.02_dc | B64: Beef meat from dairy cows | C64: Red meat | D64: UK | E64: GB | F64: CH4, biogenic | G64: =SUM(H64:T64) -> 0.34197298 | S64: =S34 -> 0.30435335 | T64: =T34 -> 0.037619631 | U64: =U34 -> 0.037619631
A65: 21111.02_dc | B65: Beef meat from dairy cows | C65: Red meat | D65: UK | E65: GB | F65: N2O | G65: =SUM(H65:T65)+W65+X65 -> 0.0089089628 | H65: =H35 -> 0.00013300523 | I65: =I35 -> 1.6977355e-05 | J65: =J35 -> 0.0054460455 | K65: =K35 -> 0.00054460455 | L65: =L35 -> 6.64508e-06 | M65: =M35 -> 0 | N65: =N35 -> 4.2257022e-08 | O65: =O35 -> 2.9327247e-06 | ... R65: =R35 -> 1.2096313e-05 | T65: =T35 -> 0.0027081562 | U65: =U35 -> 0.0018936001 | V65: =V35 -> 0.00081455612 | W65: =W35 -> 2.5773125e-05 | X65: =X35 -> 5.8807223e-07
A66: 21111.02_dc | B66: Beef meat from dairy cows | C66: Red meat | D66: UK | E66: GB | F66: CO2e | G66: =SUM(H66:X66) -> 13.804498 | H66: =SUMPRODUCT(H62:H65,'Parameters, general'!$B$24:$B$27) -> 0.37995694 | I66: =SUMPRODUCT(I62:I65,'Parameters, general'!$B$24:$B$27) -> 0.46504524 | J66: =SUMPRODUCT(J62:J65,'Parameters, general'!$B$24:$B$27) -> 1.4867704 | K66: =SUMPRODUCT(K62:K65,'Parameters, general'!$B$24:$B$27) -> 0.14867704 | L66: =SUMPRODUCT(L62:L65,'Parameters, general'!$B$24:$B$27) -> 0.25237979 | M66: =SUMPRODUCT(M62:M65,'Parameters, general'!$B$24:$B$27) -> 0 | N66: =SUMPRODUCT(N62:N65,'Parameters, general'!$B$24:$B$27) -> 0.0010824124 | O66: =SUMPRODUCT(O62:O65,'Parameters, general'!$B$24:$B$27) -> 0.083483473 | ... T66: =SUMPRODUCT(T62:T65,'Parameters, general'!$B$24:$B$27) -> 1.7550567 | W66: =SUMPRODUCT(W62:W65,'Parameters, general'!$B$24:$B$27) -> 0.73113286 | X66: =SUMPRODUCT(X62:X65,'Parameters, general'!$B$24:$B$27) -> 0.01751499 | Z66: =SUM(H66:R66) -> 3.083253 | AA66: ='CO2 per kg feed'!F185+'CH4 per kg feed'!F185*CF_GWP_CH4_fossil+'N2O per kg feed'!F185*CF_GWP_N2O -> 0

Sheet Footprints, results per calf
A2: Footprints (per calf) | T2: ** All animal welfare and antibiotics impacts allocated to the milk
A5: Animal products | F5: Climate | L5: Land | M5: Nitrogen | N5: Phosphorus | O5: Water | P5: Pesticides | Q5: Biodiversity | R5: Ammonia | S5: Labour | T5: Animal welfare** | U5: Use of antibiotics**
A6: Code | B6: Name | C6: Category | D6: Country | E6: Country code | F6: Carbon footprint, kg CO2e/kg | G6: Carbon dioxide, kg CO2/kg | H6: Methane, fossil, kg CH4/kg | I6: Methane, biogenic, kg CH4/kg | J6: Nitrous oxide, kg N2O/kg | K6: HFCs, kg HFCs/kg | L6: Cropland use, m2/kg | M6: New N input, kg N/kg | N6: New P input, kg P/kg | O6: Blue freshwater use, m3/kg | P6: Pesticide use, g a.i./kg | Q6: Extinction rate, E/MSY/kg | R6: Ammonia emission, kg NH3/kg | S6: Labour requirements, h/kg | T6: Animal welfare index per calf | U6: Antibiotics use indicator per calf
B7: Calf | C7: Calves | D7: Denmark | E7: DK | F7: ='GHG det, results per calf'!G11 -> 891.46355 | G7: ='GHG det, results per calf'!G7 -> 128.76762 | H7: ='GHG det, results per calf'!G8 -> 0.74965441 | I7: ='GHG det, results per calf'!G9 -> 20.654324 | J7: ='GHG det, results per calf'!G10 -> 0.66919228 | L7: ='Footprints, absolute'!L7/Production!$B$13*AF_calves_DK -> 835.10736 | M7: ='Footprints, absolute'!M7/Production!$B$13*AF_calves_DK -> 11.096704 | N7: ='Footprints, absolute'!N7/Production!$B$13*AF_calves_DK -> 0.9110209 | O7: ='Footprints, absolute'!O7/Production!$B$13*AF_calves_DK -> 6.6846885 | P7: ='Footprints, absolute'!P7/Production!$B$13*AF_calves_DK -> 58.437356 | Q7: ='Footprints, absolute'!Q7/Production!$B$13*AF_calves_DK -> 9.0708041e-09 | R7: ='Footprints, absolute'!R7/Production!$B$13*AF_calves_DK -> 0.41975261 | T7: 0 | U7: 0
B8: Calf | C8: Calves | D8: France | E8: FR | F8: ='GHG det, results per calf'!G16 -> 887.71023 | G8: ='GHG det, results per calf'!G12 -> 167.25356 | H8: ='GHG det, results per calf'!G13 -> 0.86016749 | I8: ='GHG det, results per calf'!G14 -> 19.29135 | J8: ='GHG det, results per calf'!G15 -> 0.63720595 | L8: ='Footprints, absolute'!L8/Production!$C$13*AF_calves_FR -> 892.43924 | M8: ='Footprints, absolute'!M8/Production!$C$13*AF_calves_FR -> 12.731505 | N8: ='Footprints, absolute'!N8/Production!$C$13*AF_calves_FR -> 1.0468205 | O8: ='Footprints, absolute'!O8/Production!$C$13*AF_calves_FR -> 9.5529379 | P8: ='Footprints, absolute'!P8/Production!$C$13*AF_calves_FR -> 87.81149 | Q8: ='Footprints, absolute'!Q8/Production!$C$13*AF_calves_FR -> 1.8843e-08 | R8: ='Footprints, absolute'!R8/Production!$C$13*AF_calves_FR -> 0.55758705 | T8: 0 | U8: 0
B9: Calf | C9: Calves | D9: Germany | E9: DE | F9: ='GHG det, results per calf'!G21 -> 929.02407 | G9: ='GHG det, results per calf'!G17 -> 237.48503 | H9: ='GHG det, results per calf'!G18 -> 0.94514904 | I9: ='GHG det, results per calf'!G19 -> 19.122405 | J9: ='GHG det, results per calf'!G20 -> 0.53871306 | L9: ='Footprints, absolute'!L9/Production!$D$13*AF_calves_DE -> 536.36739 | M9: ='Footprints, absolute'!M9/Production!$D$13*AF_calves_DE -> 9.648065 | N9: ='Footprints, absolute'!N9/Production!$D$13*AF_calves_DE -> 0.49077756 | O9: ='Footprints, absolute'!O9/Production!$D$13*AF_calves_DE -> 4.7502471 | P9: ='Footprints, absolute'!P9/Production!$D$13*AF_calves_DE -> 33.799127 | Q9: ='Footprints, absolute'!Q9/Production!$D$13*AF_calves_DE -> 1.5011466e-08 | R9: ='Footprints, absolute'!R9/Production!$D$13*AF_calves_DE -> 0.27991583 | T9: 0 | U9: 0
B10: Calf | C10: Calves | D10: Greece | E10: GR | F10: ='GHG det, results per calf'!G26 -> 1098.5351 | G10: ='GHG det, results per calf'!G22 -> 384.17498 | H10: ='GHG det, results per calf'!G23 -> 0.95117252 | I10: ='GHG det, results per calf'!G24 -> 17.290634 | J10: ='GHG det, results per calf'!G25 -> 0.8028133 | L10: ='Footprints, absolute'!L10/Production!$E$13*AF_calves_GR -> 1454.3028 | M10: ='Footprints, absolute'!M10/Production!$E$13*AF_calves_GR -> 20.610441 | N10: ='Footprints, absolute'!N10/Production!$E$13*AF_calves_GR -> 2.0820229 | O10: ='Footprints, absolute'!O10/Production!$E$13*AF_calves_GR -> 55.017899 | P10: ='Footprints, absolute'!P10/Production!$E$13*AF_calves_GR -> 69.768289 | Q10: ='Footprints, absolute'!Q10/Production!$E$13*AF_calves_GR -> 8.933677e-08 | R10: ='Footprints, absolute'!R10/Production!$E$13*AF_calves_GR -> 1.5126338 | T10: 0 | U10: 0
B11: Calf | C11: Calves | D11: Hungary | E11: HU | F11: ='GHG det, results per calf'!G31 -> 1135.3867 | G11: ='GHG det, results per calf'!G27 -> 372.95695 | H11: ='GHG det, results per calf'!G28 -> 1.1325442 | I11: ='GHG det, results per calf'!G29 -> 19.19912 | J11: ='GHG det, results per calf'!G30 -> 0.77034323 | L11: ='Footprints, absolute'!L11/Production!$F$13*AF_calves_HU -> 1363.9179 | M11: ='Footprints, absolute'!M11/Production!$F$13*AF_calves_HU -> 18.510805 | N11: ='Footprints, absolute'!N11/Production!$F$13*AF_calves_HU -> 1.9754383 | O11: ='Footprints, absolute'!O11/Production!$F$13*AF_calves_HU -> 11.008205 | P11: ='Footprints, absolute'!P11/Production!$F$13*AF_calves_HU -> 96.774624 | Q11: ='Footprints, absolute'!Q11/Production!$F$13*AF_calves_HU -> 2.9036288e-08 | R11: ='Footprints, absolute'!R11/Production!$F$13*AF_calves_HU -> 0.67383499 | T11: 0 | U11: 0
B12: Calf | C12: Calves | D12: Ireland | E12: IE | F12: ='GHG det, results per calf'!G36 -> 833.35939 | G12: ='GHG det, results per calf'!G32 -> 124.08962 | H12: ='GHG det, results per calf'!G33 -> 0.16925726 | I12: ='GHG det, results per calf'!G34 -> 20.644459 | J12: ='GHG det, results per calf'!G35 -> 0.53782237 | L12: ='Footprints, absolute'!L12/Production!$G$13*AF_calves_IE -> 193.90188 | M12: ='Footprints, absolute'!M12/Production!$G$13*AF_calves_IE -> 13.798457 | N12: ='Footprints, absolute'!N12/Production!$G$13*AF_calves_IE -> 0.45088675 | O12: ='Footprints, absolute'!O12/Production!$G$13*AF_calves_IE -> 7.0772081 | P12: ='Footprints, absolute'!P12/Production!$G$13*AF_calves_IE -> 64.242313 | Q12: ='Footprints, absolute'!Q12/Production!$G$13*AF_calves_IE -> 4.851488e-09 | R12: ='Footprints, absolute'!R12/Production!$G$13*AF_calves_IE -> 0.43761637 | T12: 0 | U12: 0
B13: Calf | C13: Calves | D13: Italy | E13: IT | F13: ='GHG det, results per calf'!G41 -> 1092.9027 | G13: ='GHG det, results per calf'!G37 -> 302.75658 | H13: ='GHG det, results per calf'!G38 -> 1.3676842 | I13: ='GHG det, results per calf'!G39 -> 21.924676 | J13: ='GHG det, results per calf'!G40 -> 0.57664048 | L13: ='Footprints, absolute'!L13/Production!$H$13*AF_calves_IT -> 916.36149 | M13: ='Footprints, absolute'!M13/Production!$H$13*AF_calves_IT -> 15.938929 | N13: ='Footprints, absolute'!N13/Production!$H$13*AF_calves_IT -> 1.0010741 | O13: ='Footprints, absolute'!O13/Production!$H$13*AF_calves_IT -> 8.8332945 | P13: ='Footprints, absolute'!P13/Production!$H$13*AF_calves_IT -> 53.356705 | Q13: ='Footprints, absolute'!Q13/Production!$H$13*AF_calves_IT -> 6.9079138e-08 | R13: ='Footprints, absolute'!R13/Production!$H$13*AF_calves_IT -> 0.73179809 | T13: 0 | U13: 0
B14: Calf | C14: Calves | D14: Netherlands | E14: NL | F14: ='GHG det, results per calf'!G46 -> 1010.2959 | G14: ='GHG det, results per calf'!G42 -> 285.81859 | H14: ='GHG det, results per calf'!G43 -> 0.73703264 | I14: ='GHG det, results per calf'!G44 -> 18.377864 | J14: ='GHG det, results per calf'!G45 -> 0.75571966 | L14: ='Footprints, absolute'!L14/Production!$I$13*AF_calves_NL -> 679.8833 | M14: ='Footprints, absolute'!M14/Production!$I$13*AF_calves_NL -> 19.581361 | N14: ='Footprints, absolute'!N14/Production!$I$13*AF_calves_NL -> 0.75172838 | O14: ='Footprints, absolute'!O14/Production!$I$13*AF_calves_NL -> 5.137077 | P14: ='Footprints, absolute'!P14/Production!$I$13*AF_calves_NL -> 62.336554 | Q14: ='Footprints, absolute'!Q14/Production!$I$13*AF_calves_NL -> 2.1173997e-08 | R14: ='Footprints, absolute'!R14/Production!$I$13*AF_calves_NL -> 0.75517708 | T14: 0 | U14: 0
B15: Calf | C15: Calves | D15: Poland | E15: PL | F15: ='GHG det, results per calf'!G51 -> 1195.6558 | G15: ='GHG det, results per calf'!G47 -> 480.75314 | H15: ='GHG det, results per calf'!G48 -> 1.0431915 | I15: ='GHG det, results per calf'!G49 -> 17.824517 | J15: ='GHG det, results per calf'!G50 -> 0.74195471 | L15: ='Footprints, absolute'!L15/Production!$J$13*AF_calves_PL -> 916.09493 | M15: ='Footprints, absolute'!M15/Production!$J$13*AF_calves_PL -> 15.214319 | N15: ='Footprints, absolute'!N15/Production!$J$13*AF_calves_PL -> 1.4472293 | O15: ='Footprints, absolute'!O15/Production!$J$13*AF_calves_PL -> 5.4554435 | P15: ='Footprints, absolute'!P15/Production!$J$13*AF_calves_PL -> 70.463281 | Q15: ='Footprints, absolute'!Q15/Production!$J$13*AF_calves_PL -> 1.4484882e-08 | R15: ='Footprints, absolute'!R15/Production!$J$13*AF_calves_PL -> 0.62513212 | T15: 0 | U15: 0
B16: Calf | C16: Calves | D16: Spain | E16: ES | F16: ='GHG det, results per calf'!G56 -> 913.74415 | G16: ='GHG det, results per calf'!G52 -> 247.36611 | H16: ='GHG det, results per calf'!G53 -> 0.68343214 | I16: ='GHG det, results per calf'!G54 -> 17.528562 | J16: ='GHG det, results per calf'!G55 -> 0.63274942 | L16: ='Footprints, absolute'!L16/Production!$K$13*AF_calves_ES -> 990.92232 | M16: ='Footprints, absolute'!M16/Production!$K$13*AF_calves_ES -> 18.633809 | N16: ='Footprints, absolute'!N16/Production!$K$13*AF_calves_ES -> 1.6738632 | O16: ='Footprints, absolute'!O16/Production!$K$13*AF_calves_ES -> 45.179639 | P16: ='Footprints, absolute'!P16/Production!$K$13*AF_calves_ES -> 75.933951 | Q16: ='Footprints, absolute'!Q16/Production!$K$13*AF_calves_ES -> 2.8722555e-08 | R16: ='Footprints, absolute'!R16/Production!$K$13*AF_calves_ES -> 0.57968432 | T16: 0 | U16: 0
B17: Calf | C17: Calves | D17: Sweden | E17: SE | F17: ='GHG det, results per calf'!G61 -> 843.82221 | G17: ='GHG det, results per calf'!G57 -> 175.29191 | H17: ='GHG det, results per calf'!G58 -> 0.98150307 | I17: ='GHG det, results per calf'!G59 -> 17.320451 | J17: ='GHG det, results per calf'!G60 -> 0.6286788 | L17: ='Footprints, absolute'!L17/Production!$L$13*AF_calves_SE -> 1573.9827 | M17: ='Footprints, absolute'!M17/Production!$L$13*AF_calves_SE -> 15.664588 | N17: ='Footprints, absolute'!N17/Production!$L$13*AF_calves_SE -> 0.78642796 | O17: ='Footprints, absolute'!O17/Production!$L$13*AF_calves_SE -> 4.9451609 | P17: ='Footprints, absolute'!P17/Production!$L$13*AF_calves_SE -> 38.739918 | Q17: ='Footprints, absolute'!Q17/Production!$L$13*AF_calves_SE -> 9.8566656e-09 | R17: ='Footprints, absolute'!R17/Production!$L$13*AF_calves_SE -> 0.45847721 | T17: 0 | U17: 0
B18: Calf | C18: Calves | D18: UK | E18: GB | F18: =F12 -> 833.35939 | G18: =G12 -> 124.08962 | H18: =H12 -> 0.16925726 | I18: =I12 -> 20.644459 | J18: =J12 -> 0.53782237 | K18: =K12 -> 0 | L18: =L12 -> 193.90188 | M18: =M12 -> 13.798457 | ... R18: =R12 -> 0.43761637 | V18: Approx Ireland for now because we only need the UK-value for the meat from dairy cows (not dairy)

Sheet GHG det, results per calf
A2: GHG emissions (per calf)
K3: * Calculated as percentage of direct emissions due to assumption due to data limitations regarding nitrogen leaching and volatilization from soils in different regions.
S4: Animals | W4: Stables | X4: Slaughter
A5: Animal products | G5: Sum | H5: Inputs | J5: Soil emissions | L5: Energy use | P5: Land use change | Q5: Feed processing | R5: Transports
A6: Code | B6: Name | C6: Category | D6: Country | E6: Country code | F6: Gas | G6: GHG | H6: Production of mineral fertilizer | I6: Production of capital goods | J6: Direct emissions | K6: Indirect emissions* | L6: Diesel use field mach | M6: Energy use in greenhouses | N6: Energy use for irrigation | O6: Energy use for post-harvest proc | P6: LUC emissions | Q6: Feed processing | R6: Feed transports | S6: Enteric fermentation* | T6: Manure management - tot | U6: Manure management - direct | V6: Manure management - indirect | W6: Energy use in stables | X6: Energy use for slaughter
B7: Calf | C7: Calves | D7: Denmark | E7: DK | F7: CO2 | G7: =SUM(H7:X7) -> 128.76762 | H7: ='GHG detailed, absolute'!H7/Production!$B$13*AF_calves_DK -> 29.960172 | I7: ='GHG detailed, absolute'!I7/Production!$B$13*AF_calves_DK -> 16.982306 | L7: ='GHG detailed, absolute'!L7/Production!$B$13*AF_calves_DK -> 13.172551 | N7: ='GHG detailed, absolute'!N7/Production!$B$13*AF_calves_DK -> 0.027143663 | O7: ='GHG detailed, absolute'!O7/Production!$B$13*AF_calves_DK -> 8.8291116 | P7: ='GHG detailed, absolute'!P7/Production!$B$13*AF_calves_DK -> 11.746402 | Q7: ='GHG detailed, absolute'!Q7/Production!$B$13*AF_calves_DK -> 23.653405 | R7: ='GHG detailed, absolute'!R7/Production!$B$13*AF_calves_DK -> 23.653405 | W7: ='GHG detailed, absolute'!W7/Production!$B$13*AF_calves_DK -> 0 | X7: ='GHG detailed, absolute'!X7/Production!$B$13*AF_calves_DK -> 0.74312198
B8: Calf | C8: Calves | D8: Denmark | E8: DK | F8: CH4, fossil | G8: =SUM(H8:X8) -> 0.74965441 | H8: ='GHG detailed, absolute'!H8/Production!$B$13*AF_calves_DK -> 0.033047943 | I8: ='GHG detailed, absolute'!I8/Production!$B$13*AF_calves_DK -> 0.059752558 | L8: ='GHG detailed, absolute'!L8/Production!$B$13*AF_calves_DK -> 0.005834996 | N8: ='GHG detailed, absolute'!N8/Production!$B$13*AF_calves_DK -> 9.0780956e-05 | O8: ='GHG detailed, absolute'!O8/Production!$B$13*AF_calves_DK -> 0.0053126946 | P8: ='GHG detailed, absolute'!P8/Production!$B$13*AF_calves_DK -> 0 | Q8: ='GHG detailed, absolute'!Q8/Production!$B$13*AF_calves_DK -> 0.30741359 | R8: ='GHG detailed, absolute'!R8/Production!$B$13*AF_calves_DK -> 0.30741359 | W8: ='GHG detailed, absolute'!W8/Production!$B$13*AF_calves_DK -> 0.029223694 | X8: ='GHG detailed, absolute'!X8/Production!$B$13*AF_calves_DK -> 0.0015645592
B9: Calf | C9: Calves | D9: Denmark | E9: DK | F9: CH4, biogenic | G9: =SUM(H9:T9) -> 20.654324 | S9: ='GHG detailed, absolute'!S9/Production!$B$13*AF_calves_DK -> 15.554859 | T9: ='GHG detailed, absolute'!T9/Production!$B$13*AF_calves_DK -> 5.0994643 | U9: ='GHG detailed, absolute'!U9/Production!$B$13*AF_calves_DK -> 5.0994643
B10: Calf | C10: Calves | D10: Denmark | E10: DK | F10: N2O | G10: =SUM(H10:T10)+W10+X10 -> 0.66919228 | H10: ='GHG detailed, absolute'!H10/Production!$B$13*AF_calves_DK -> 0.043871504 | I10: ='GHG detailed, absolute'!I10/Production!$B$13*AF_calves_DK -> 0.00069187172 | J10: ='GHG detailed, absolute'!J10/Production!$B$13*AF_calves_DK -> 0.31992238 | K10: ='GHG detailed, absolute'!K10/Production!$B$13*AF_calves_DK -> 0.031992238 | L10: ='GHG detailed, absolute'!L10/Production!$B$13*AF_calves_DK -> 0.00035395159 | N10: ='GHG detailed, absolute'!N10/Production!$B$13*AF_calves_DK -> 1.1172311e-06 | O10: ='GHG detailed, absolute'!O10/Production!$B$13*AF_calves_DK -> 0.00032272116 | P10: ='GHG detailed, absolute'!P10/Production!$B$13*AF_calves_DK -> 0 | Q10: ='GHG detailed, absolute'!Q10/Production!$B$13*AF_calves_DK -> 0.029541162 | R10: ='GHG detailed, absolute'!R10/Production!$B$13*AF_calves_DK -> 0.029541162 | T10: ='GHG detailed, absolute'!T10/Production!$B$13*AF_calves_DK -> 0.21182916 | U10: ='GHG detailed, absolute'!U10/Production!$B$13*AF_calves_DK -> 0.1248173 | V10: ='GHG detailed, absolute'!V10/Production!$B$13*AF_calves_DK -> 0.087011864 | W10: ='GHG detailed, absolute'!W10/Production!$B$13*AF_calves_DK -> 0.0010900774 | X10: ='GHG detailed, absolute'!X10/Production!$B$13*AF_calves_DK -> 3.4932064e-05
B11: Calf | C11: Calves | D11: Denmark | E11: DK | F11: CO2e | G11: =SUM(H11:X11) -> 891.46355 | H11: =SUMPRODUCT(H7:H10,'Parameters, general'!$B$24:$B$27) -> 42.921921 | I11: =SUMPRODUCT(I7:I10,'Parameters, general'!$B$24:$B$27) -> 18.951813 | J11: =SUMPRODUCT(J7:J10,'Parameters, general'!$B$24:$B$27) -> 87.338809 | K11: =SUMPRODUCT(K7:K10,'Parameters, general'!$B$24:$B$27) -> 8.7338809 | L11: =SUMPRODUCT(L7:L10,'Parameters, general'!$B$24:$B$27) -> 13.443063 | M11: =SUMPRODUCT(M7:M10,'Parameters, general'!$B$24:$B$27) -> 0 | N11: =SUMPRODUCT(N7:N10,'Parameters, general'!$B$24:$B$27) -> 0.03015394 | O11: =SUMPRODUCT(O7:O10,'Parameters, general'!$B$24:$B$27) -> 9.0755328 | ... T11: =SUMPRODUCT(T7:T10,'Parameters, general'!$B$24:$B$27) -> 195.5149 | W11: =SUMPRODUCT(W7:W10,'Parameters, general'!$B$24:$B$27) -> 1.1684572 | X11: =SUMPRODUCT(X7:X10,'Parameters, general'!$B$24:$B$27) -> 0.7992823
B12: Calf | C12: Calves | D12: France | E12: FR | F12: CO2 | G12: =SUM(H12:X12) -> 167.25356 | H12: ='GHG detailed, absolute'!H12/Production!$C$13*AF_calves_FR -> 26.211513 | I12: ='GHG detailed, absolute'!I12/Production!$C$13*AF_calves_FR -> 21.680979 | L12: ='GHG detailed, absolute'!L12/Production!$C$13*AF_calves_FR -> 15.765661 | N12: ='GHG detailed, absolute'!N12/Production!$C$13*AF_calves_FR -> 0.31841272 | O12: ='GHG detailed, absolute'!O12/Production!$C$13*AF_calves_FR -> 8.6896149 | P12: ='GHG detailed, absolute'!P12/Production!$C$13*AF_calves_FR -> 13.722912 | Q12: ='GHG detailed, absolute'!Q12/Production!$C$13*AF_calves_FR -> 32.610288 | R12: ='GHG detailed, absolute'!R12/Production!$C$13*AF_calves_FR -> 32.610288 | W12: ='GHG detailed, absolute'!W12/Production!$C$13*AF_calves_FR -> 15.251196 | X12: ='GHG detailed, absolute'!X12/Production!$C$13*AF_calves_FR -> 0.3926962
B13: Calf | C13: Calves | D13: France | E13: FR | F13: CH4, fossil | G13: =SUM(H13:X13) -> 0.86016749 | H13: ='GHG detailed, absolute'!H13/Production!$C$13*AF_calves_FR -> 0.01465508 | I13: ='GHG detailed, absolute'!I13/Production!$C$13*AF_calves_FR -> 0.076284928 | L13: ='GHG detailed, absolute'!L13/Production!$C$13*AF_calves_FR -> 0.0069836562 | N13: ='GHG detailed, absolute'!N13/Production!$C$13*AF_calves_FR -> 0.0010007686 | O13: ='GHG detailed, absolute'!O13/Production!$C$13*AF_calves_FR -> 0.004924151 | P13: ='GHG detailed, absolute'!P13/Production!$C$13*AF_calves_FR -> 0 | Q13: ='GHG detailed, absolute'!Q13/Production!$C$13*AF_calves_FR -> 0.35375288 | R13: ='GHG detailed, absolute'!R13/Production!$C$13*AF_calves_FR -> 0.35375288 | W13: ='GHG detailed, absolute'!W13/Production!$C$13*AF_calves_FR -> 0.047283411 | X13: ='GHG detailed, absolute'!X13/Production!$C$13*AF_calves_FR -> 0.0015297301
B14: Calf | C14: Calves | D14: France | E14: FR | F14: CH4, biogenic | G14: =SUM(H14:T14) -> 19.29135 | S14: ='GHG detailed, absolute'!S14/Production!$C$13*AF_calves_FR -> 17.332566 | T14: ='GHG detailed, absolute'!T14/Production!$C$13*AF_calves_FR -> 1.9587845 | U14: ='GHG detailed, absolute'!U14/Production!$C$13*AF_calves_FR -> 1.9587845
B15: Calf | C15: Calves | D15: France | E15: FR | F15: N2O | G15: =SUM(H15:T15)+W15+X15 -> 0.63720595 | H15: ='GHG detailed, absolute'!H15/Production!$C$13*AF_calves_FR -> 0.022374141 | I15: ='GHG detailed, absolute'!I15/Production!$C$13*AF_calves_FR -> 0.00088329916 | J15: ='GHG detailed, absolute'!J15/Production!$C$13*AF_calves_FR -> 0.32917268 | K15: ='GHG detailed, absolute'!K15/Production!$C$13*AF_calves_FR -> 0.032917268 | L15: ='GHG detailed, absolute'!L15/Production!$C$13*AF_calves_FR -> 0.00042362946 | N15: ='GHG detailed, absolute'!N15/Production!$C$13*AF_calves_FR -> 1.340614e-05 | O15: ='GHG detailed, absolute'!O15/Production!$C$13*AF_calves_FR -> 0.00032507186 | P15: ='GHG detailed, absolute'!P15/Production!$C$13*AF_calves_FR -> 0 | Q15: ='GHG detailed, absolute'!Q15/Production!$C$13*AF_calves_FR -> 0.032305545 | R15: ='GHG detailed, absolute'!R15/Production!$C$13*AF_calves_FR -> 0.032305545 | T15: ='GHG detailed, absolute'!T15/Production!$C$13*AF_calves_FR -> 0.18503275 | U15: ='GHG detailed, absolute'!U15/Production!$C$13*AF_calves_FR -> 0.12852412 | V15: ='GHG detailed, absolute'!V15/Production!$C$13*AF_calves_FR -> 0.056508628 | W15: ='GHG detailed, absolute'!W15/Production!$C$13*AF_calves_FR -> 0.0014293758 | X15: ='GHG detailed, absolute'!X15/Production!$C$13*AF_calves_FR -> 2.3248806e-05
B16: Calf | C16: Calves | D16: France | E16: FR | F16: CO2e | G16: =SUM(H16:X16) -> 887.71023 | H16: =SUMPRODUCT(H12:H15,'Parameters, general'!$B$24:$B$27) -> 32.756375 | I16: =SUMPRODUCT(I12:I15,'Parameters, general'!$B$24:$B$27) -> 24.195411 | J16: =SUMPRODUCT(J12:J15,'Parameters, general'!$B$24:$B$27) -> 89.864141 | K16: =SUMPRODUCT(K12:K15,'Parameters, general'!$B$24:$B$27) -> 8.9864141 | L16: =SUMPRODUCT(L12:L15,'Parameters, general'!$B$24:$B$27) -> 16.089425 | M16: =SUMPRODUCT(M12:M15,'Parameters, general'!$B$24:$B$27) -> 0 | N16: =SUMPRODUCT(N12:N15,'Parameters, general'!$B$24:$B$27) -> 0.3518955 | O16: =SUMPRODUCT(O12:O15,'Parameters, general'!$B$24:$B$27) -> 8.9250992 | ... T16: =SUMPRODUCT(T12:T15,'Parameters, general'!$B$24:$B$27) -> 103.40112 | W16: =SUMPRODUCT(W12:W15,'Parameters, general'!$B$24:$B$27) -> 17.050462 | X16: =SUMPRODUCT(X12:X15,'Parameters, general'!$B$24:$B$27) -> 0.44462908
B17: Calf | C17: Calves | D17: Germany | E17: DE | F17: CO2 | G17: =SUM(H17:X17) -> 237.48503 | H17: ='GHG detailed, absolute'!H17/Production!$D$13*AF_calves_DE -> 19.263065 | I17: ='GHG detailed, absolute'!I17/Production!$D$13*AF_calves_DE -> 20.996959 | L17: ='GHG detailed, absolute'!L17/Production!$D$13*AF_calves_DE -> 13.240435 | N17: ='GHG detailed, absolute'!N17/Production!$D$13*AF_calves_DE -> 0.028035098 | O17: ='GHG detailed, absolute'!O17/Production!$D$13*AF_calves_DE -> 4.026971 | P17: ='GHG detailed, absolute'!P17/Production!$D$13*AF_calves_DE -> 17.092196 | Q17: ='GHG detailed, absolute'!Q17/Production!$D$13*AF_calves_DE -> 38.924999 | R17: ='GHG detailed, absolute'!R17/Production!$D$13*AF_calves_DE -> 38.924999 | W17: ='GHG detailed, absolute'!W17/Production!$D$13*AF_calves_DE -> 84.079112 | X17: ='GHG detailed, absolute'!X17/Production!$D$13*AF_calves_DE -> 0.90825609
B18: Calf | C18: Calves | D18: Germany | E18: DE | F18: CH4, fossil | G18: =SUM(H18:X18) -> 0.94514904 | H18: ='GHG detailed, absolute'!H18/Production!$D$13*AF_calves_DE -> 0.017807795 | I18: ='GHG detailed, absolute'!I18/Production!$D$13*AF_calves_DE -> 0.073878188 | L18: ='GHG detailed, absolute'!L18/Production!$D$13*AF_calves_DE -> 0.0058650663 | N18: ='GHG detailed, absolute'!N18/Production!$D$13*AF_calves_DE -> 9.2255656e-05 | O18: ='GHG detailed, absolute'!O18/Production!$D$13*AF_calves_DE -> 0.0027035388 | P18: ='GHG detailed, absolute'!P18/Production!$D$13*AF_calves_DE -> 0 | Q18: ='GHG detailed, absolute'!Q18/Production!$D$13*AF_calves_DE -> 0.34088594 | R18: ='GHG detailed, absolute'!R18/Production!$D$13*AF_calves_DE -> 0.34088594 | W18: ='GHG detailed, absolute'!W18/Production!$D$13*AF_calves_DE -> 0.1608341 | X18: ='GHG detailed, absolute'!X18/Production!$D$13*AF_calves_DE -> 0.0021962123
B19: Calf | C19: Calves | D19: Germany | E19: DE | F19: CH4, biogenic | G19: =SUM(H19:T19) -> 19.122405 | S19: ='GHG detailed, absolute'!S19/Production!$D$13*AF_calves_DE -> 16.161108 | T19: ='GHG detailed, absolute'!T19/Production!$D$13*AF_calves_DE -> 2.9612969 | U19: ='GHG detailed, absolute'!U19/Production!$D$13*AF_calves_DE -> 2.9612969
B20: Calf | C20: Calves | D20: Germany | E20: DE | F20: N2O | G20: =SUM(H20:T20)+W20+X20 -> 0.53871306 | H20: ='GHG detailed, absolute'!H20/Production!$D$13*AF_calves_DE -> 0.023812521 | I20: ='GHG detailed, absolute'!I20/Production!$D$13*AF_calves_DE -> 0.00085543165 | J20: ='GHG detailed, absolute'!J20/Production!$D$13*AF_calves_DE -> 0.23193974 | K20: ='GHG detailed, absolute'!K20/Production!$D$13*AF_calves_DE -> 0.023193974 | L20: ='GHG detailed, absolute'!L20/Production!$D$13*AF_calves_DE -> 0.00035577566 | N20: ='GHG detailed, absolute'!N20/Production!$D$13*AF_calves_DE -> 1.1609754e-06 | O20: ='GHG detailed, absolute'!O20/Production!$D$13*AF_calves_DE -> 0.00014419649 | P20: ='GHG detailed, absolute'!P20/Production!$D$13*AF_calves_DE -> 0 | Q20: ='GHG detailed, absolute'!Q20/Production!$D$13*AF_calves_DE -> 0.030638612 | R20: ='GHG detailed, absolute'!R20/Production!$D$13*AF_calves_DE -> 0.030638612 | T20: ='GHG detailed, absolute'!T20/Production!$D$13*AF_calves_DE -> 0.19332889 | U20: ='GHG detailed, absolute'!U20/Production!$D$13*AF_calves_DE -> 0.1155589 | V20: ='GHG detailed, absolute'!V20/Production!$D$13*AF_calves_DE -> 0.077769988 | W20: ='GHG detailed, absolute'!W20/Production!$D$13*AF_calves_DE -> 0.0037656645 | X20: ='GHG detailed, absolute'!X20/Production!$D$13*AF_calves_DE -> 3.846997e-05
B21: Calf | C21: Calves | D21: Germany | E21: DE | F21: CO2e | G21: =SUM(H21:X21) -> 929.02407 | H21: =SUMPRODUCT(H17:H20,'Parameters, general'!$B$24:$B$27) -> 26.294556 | I21: =SUMPRODUCT(I17:I20,'Parameters, general'!$B$24:$B$27) -> 23.432062 | J21: =SUMPRODUCT(J17:J20,'Parameters, general'!$B$24:$B$27) -> 63.31955 | K21: =SUMPRODUCT(K17:K20,'Parameters, general'!$B$24:$B$27) -> 6.331955 | L21: =SUMPRODUCT(L17:L20,'Parameters, general'!$B$24:$B$27) -> 13.512341 | M21: =SUMPRODUCT(M17:M20,'Parameters, general'!$B$24:$B$27) -> 0 | N21: =SUMPRODUCT(N17:N20,'Parameters, general'!$B$24:$B$27) -> 0.031101263 | O21: =SUMPRODUCT(O17:O20,'Parameters, general'!$B$24:$B$27) -> 4.1469021 | ... T21: =SUMPRODUCT(T17:T20,'Parameters, general'!$B$24:$B$27) -> 132.7338 | W21: =SUMPRODUCT(W17:W20,'Parameters, general'!$B$24:$B$27) -> 89.899995 | X21: =SUMPRODUCT(X17:X20,'Parameters, general'!$B$24:$B$27) -> 0.98420552
B22: Calf | C22: Calves | D22: Greece | E22: GR | F22: CO2 | G22: =SUM(H22:X22) -> 384.17498 | H22: ='GHG detailed, absolute'!H22/Production!$E$13*AF_calves_GR -> 51.168118 | I22: ='GHG detailed, absolute'!I22/Production!$E$13*AF_calves_GR -> 21.44256 | L22: ='GHG detailed, absolute'!L22/Production!$E$13*AF_calves_GR -> 28.302316 | N22: ='GHG detailed, absolute'!N22/Production!$E$13*AF_calves_GR -> 3.5535034 | O22: ='GHG detailed, absolute'!O22/Production!$E$13*AF_calves_GR -> 17.405809 | P22: ='GHG detailed, absolute'!P22/Production!$E$13*AF_calves_GR -> 22.90599 | Q22: ='GHG detailed, absolute'!Q22/Production!$E$13*AF_calves_GR -> 47.435404 | R22: ='GHG detailed, absolute'!R22/Production!$E$13*AF_calves_GR -> 47.435404 | W22: ='GHG detailed, absolute'!W22/Production!$E$13*AF_calves_GR -> 143.20323 | X22: ='GHG detailed, absolute'!X22/Production!$E$13*AF_calves_GR -> 1.3226501
B23: Calf | C23: Calves | D23: Greece | E23: GR | F23: CH4, fossil | G23: =SUM(H23:X23) -> 0.95117252 | H23: ='GHG detailed, absolute'!H23/Production!$E$13*AF_calves_GR -> 0.0010748174 | I23: ='GHG detailed, absolute'!I23/Production!$E$13*AF_calves_GR -> 0.075446044 | L23: ='GHG detailed, absolute'!L23/Production!$E$13*AF_calves_GR -> 0.012536972 | N23: ='GHG detailed, absolute'!N23/Production!$E$13*AF_calves_GR -> 0.010820702 | O23: ='GHG detailed, absolute'!O23/Production!$E$13*AF_calves_GR -> 0.014280599 | P23: ='GHG detailed, absolute'!P23/Production!$E$13*AF_calves_GR -> 0 | Q23: ='GHG detailed, absolute'!Q23/Production!$E$13*AF_calves_GR -> 0.27480608 | R23: ='GHG detailed, absolute'!R23/Production!$E$13*AF_calves_GR -> 0.27480608 | W23: ='GHG detailed, absolute'!W23/Production!$E$13*AF_calves_GR -> 0.28427848 | X23: ='GHG detailed, absolute'!X23/Production!$E$13*AF_calves_GR -> 0.0031227346
B24: Calf | C24: Calves | D24: Greece | E24: GR | F24: CH4, biogenic | G24: =SUM(H24:T24) -> 17.290634 | S24: ='GHG detailed, absolute'!S24/Production!$E$13*AF_calves_GR -> 15.803675 | T24: ='GHG detailed, absolute'!T24/Production!$E$13*AF_calves_GR -> 1.4869599 | U24: ='GHG detailed, absolute'!U24/Production!$E$13*AF_calves_GR -> 1.4869599
B25: Calf | C25: Calves | D25: Greece | E25: GR | F25: N2O | G25: =SUM(H25:T25)+W25+X25 -> 0.8028133 | H25: ='GHG detailed, absolute'!H25/Production!$E$13*AF_calves_GR -> 0.0059090174 | I25: ='GHG detailed, absolute'!I25/Production!$E$13*AF_calves_GR -> 0.00087358578 | J25: ='GHG detailed, absolute'!J25/Production!$E$13*AF_calves_GR -> 0.42546451 | K25: ='GHG detailed, absolute'!K25/Production!$E$13*AF_calves_GR -> 0.042546451 | L25: ='GHG detailed, absolute'!L25/Production!$E$13*AF_calves_GR -> 0.00076049426 | N25: ='GHG detailed, absolute'!N25/Production!$E$13*AF_calves_GR -> 0.00015124196 | O25: ='GHG detailed, absolute'!O25/Production!$E$13*AF_calves_GR -> 0.00061460698 | P25: ='GHG detailed, absolute'!P25/Production!$E$13*AF_calves_GR -> 0 | Q25: ='GHG detailed, absolute'!Q25/Production!$E$13*AF_calves_GR -> 0.02155041 | R25: ='GHG detailed, absolute'!R25/Production!$E$13*AF_calves_GR -> 0.02155041 | T25: ='GHG detailed, absolute'!T25/Production!$E$13*AF_calves_GR -> 0.2784195 | U25: ='GHG detailed, absolute'!U25/Production!$E$13*AF_calves_GR -> 0.20929557 | V25: ='GHG detailed, absolute'!V25/Production!$E$13*AF_calves_GR -> 0.069123924 | W25: ='GHG detailed, absolute'!W25/Production!$E$13*AF_calves_GR -> 0.0049279896 | X25: ='GHG detailed, absolute'!X25/Production!$E$13*AF_calves_GR -> 4.509263e-05
B26: Calf | C26: Calves | D26: Greece | E26: GR | F26: CO2e | G26: =SUM(H26:X26) -> 1098.5351 | H26: =SUMPRODUCT(H22:H25,'Parameters, general'!$B$24:$B$27) -> 52.81331 | I26: =SUMPRODUCT(I22:I25,'Parameters, general'!$B$24:$B$27) -> 23.929341 | J26: =SUMPRODUCT(J22:J25,'Parameters, general'!$B$24:$B$27) -> 116.15181 | K26: =SUMPRODUCT(K22:K25,'Parameters, general'!$B$24:$B$27) -> 11.615181 | L26: =SUMPRODUCT(L22:L25,'Parameters, general'!$B$24:$B$27) -> 28.883533 | M26: =SUMPRODUCT(M22:M25,'Parameters, general'!$B$24:$B$27) -> 0 | N26: =SUMPRODUCT(N22:N25,'Parameters, general'!$B$24:$B$27) -> 3.9172494 | O26: =SUMPRODUCT(O22:O25,'Parameters, general'!$B$24:$B$27) -> 17.999159 | ... T26: =SUMPRODUCT(T22:T25,'Parameters, general'!$B$24:$B$27) -> 116.15644 | W26: =SUMPRODUCT(W22:W25,'Parameters, general'!$B$24:$B$27) -> 153.02007 | X26: =SUMPRODUCT(X22:X25,'Parameters, general'!$B$24:$B$27) -> 1.4280179
B27: Calf | C27: Calves | D27: Hungary | E27: HU | F27: CO2 | G27: =SUM(H27:X27) -> 372.95695 | H27: ='GHG detailed, absolute'!H27/Production!$F$13*AF_calves_HU -> 29.579879 | I27: ='GHG detailed, absolute'!I27/Production!$F$13*AF_calves_HU -> 19.601596 | L27: ='GHG detailed, absolute'!L27/Production!$F$13*AF_calves_HU -> 22.944468 | N27: ='GHG detailed, absolute'!N27/Production!$F$13*AF_calves_HU -> 0.09654032 | O27: ='GHG detailed, absolute'!O27/Production!$F$13*AF_calves_HU -> 14.173898 | P27: ='GHG detailed, absolute'!P27/Production!$F$13*AF_calves_HU -> 31.662866 | Q27: ='GHG detailed, absolute'!Q27/Production!$F$13*AF_calves_HU -> 88.327875 | R27: ='GHG detailed, absolute'!R27/Production!$F$13*AF_calves_HU -> 88.327875 | W27: ='GHG detailed, absolute'!W27/Production!$F$13*AF_calves_HU -> 77.223873 | X27: ='GHG detailed, absolute'!X27/Production!$F$13*AF_calves_HU -> 1.0180784
B28: Calf | C28: Calves | D28: Hungary | E28: HU | F28: CH4, fossil | G28: =SUM(H28:X28) -> 1.1325442 | H28: ='GHG detailed, absolute'!H28/Production!$F$13*AF_calves_HU -> 0.0015638375 | I28: ='GHG detailed, absolute'!I28/Production!$F$13*AF_calves_HU -> 0.068968577 | L28: ='GHG detailed, absolute'!L28/Production!$F$13*AF_calves_HU -> 0.010163626 | N28: ='GHG detailed, absolute'!N28/Production!$F$13*AF_calves_HU -> 0.00029236735 | O28: ='GHG detailed, absolute'!O28/Production!$F$13*AF_calves_HU -> 0.011548751 | P28: ='GHG detailed, absolute'!P28/Production!$F$13*AF_calves_HU -> 0 | Q28: ='GHG detailed, absolute'!Q28/Production!$F$13*AF_calves_HU -> 0.42102214 | R28: ='GHG detailed, absolute'!R28/Production!$F$13*AF_calves_HU -> 0.42102214 | W28: ='GHG detailed, absolute'!W28/Production!$F$13*AF_calves_HU -> 0.19497996 | X28: ='GHG detailed, absolute'!X28/Production!$F$13*AF_calves_HU -> 0.0029827974
B29: Calf | C29: Calves | D29: Hungary | E29: HU | F29: CH4, biogenic | G29: =SUM(H29:T29) -> 19.19912 | S29: ='GHG detailed, absolute'!S29/Production!$F$13*AF_calves_HU -> 16.37612 | T29: ='GHG detailed, absolute'!T29/Production!$F$13*AF_calves_HU -> 2.8230002 | U29: ='GHG detailed, absolute'!U29/Production!$F$13*AF_calves_HU -> 2.8230002
B30: Calf | C30: Calves | D30: Hungary | E30: HU | F30: N2O | G30: =SUM(H30:T30)+W30+X30 -> 0.77034323 | H30: ='GHG detailed, absolute'!H30/Production!$F$13*AF_calves_HU -> 0.012884758 | I30: ='GHG detailed, absolute'!I30/Production!$F$13*AF_calves_HU -> 0.00079858353 | J30: ='GHG detailed, absolute'!J30/Production!$F$13*AF_calves_HU -> 0.35239204 | K30: ='GHG detailed, absolute'!K30/Production!$F$13*AF_calves_HU -> 0.035239204 | L30: ='GHG detailed, absolute'!L30/Production!$F$13*AF_calves_HU -> 0.0006165268 | N30: ='GHG detailed, absolute'!N30/Production!$F$13*AF_calves_HU -> 4.116404e-06 | O30: ='GHG detailed, absolute'!O30/Production!$F$13*AF_calves_HU -> 0.00050480267 | P30: ='GHG detailed, absolute'!P30/Production!$F$13*AF_calves_HU -> 0 | Q30: ='GHG detailed, absolute'!Q30/Production!$F$13*AF_calves_HU -> 0.026251555 | R30: ='GHG detailed, absolute'!R30/Production!$F$13*AF_calves_HU -> 0.026251555 | T30: ='GHG detailed, absolute'!T30/Production!$F$13*AF_calves_HU -> 0.31265936 | U30: ='GHG detailed, absolute'!U30/Production!$F$13*AF_calves_HU -> 0.22902428 | V30: ='GHG detailed, absolute'!V30/Production!$F$13*AF_calves_HU -> 0.083635088 | W30: ='GHG detailed, absolute'!W30/Production!$F$13*AF_calves_HU -> 0.0027056371 | X30: ='GHG detailed, absolute'!X30/Production!$F$13*AF_calves_HU -> 3.5094458e-05
B31: Calf | C31: Calves | D31: Hungary | E31: HU | F31: CO2e | G31: =SUM(H31:X31) -> 1135.3867 | H31: =SUMPRODUCT(H27:H30,'Parameters, general'!$B$24:$B$27) -> 33.144021 | I31: =SUMPRODUCT(I27:I30,'Parameters, general'!$B$24:$B$27) -> 21.874873 | J31: =SUMPRODUCT(J27:J30,'Parameters, general'!$B$24:$B$27) -> 96.203026 | K31: =SUMPRODUCT(K27:K30,'Parameters, general'!$B$24:$B$27) -> 9.6203026 | L31: =SUMPRODUCT(L27:L30,'Parameters, general'!$B$24:$B$27) -> 23.415656 | M31: =SUMPRODUCT(M27:M30,'Parameters, general'!$B$24:$B$27) -> 0 | N31: =SUMPRODUCT(N27:N30,'Parameters, general'!$B$24:$B$27) -> 0.10637664 | O31: =SUMPRODUCT(O27:O30,'Parameters, general'!$B$24:$B$27) -> 14.655862 | ... T31: =SUMPRODUCT(T27:T30,'Parameters, general'!$B$24:$B$27) -> 161.57701 | W31: =SUMPRODUCT(W27:W30,'Parameters, general'!$B$24:$B$27) -> 83.772915 | X31: =SUMPRODUCT(X27:X30,'Parameters, general'!$B$24:$B$27) -> 1.1165466
B32: Calf | C32: Calves | D32: Ireland | E32: IE | F32: CO2 | G32: =SUM(H32:X32) -> 124.08962 | H32: ='GHG detailed, absolute'!H32/Production!$G$13*AF_calves_IE -> 20.720492 | I32: ='GHG detailed, absolute'!I32/Production!$G$13*AF_calves_IE -> 25.156651 | L32: ='GHG detailed, absolute'!L32/Production!$G$13*AF_calves_IE -> 14.929249 | N32: ='GHG detailed, absolute'!N32/Production!$G$13*AF_calves_IE -> 0.059402008 | O32: ='GHG detailed, absolute'!O32/Production!$G$13*AF_calves_IE -> 4.9148889 | P32: ='GHG detailed, absolute'!P32/Production!$G$13*AF_calves_IE -> 2.3299785 | Q32: ='GHG detailed, absolute'!Q32/Production!$G$13*AF_calves_IE -> 6.3165651 | R32: ='GHG detailed, absolute'!R32/Production!$G$13*AF_calves_IE -> 6.3165651 | W32: ='GHG detailed, absolute'!W32/Production!$G$13*AF_calves_IE -> 42.352619 | X32: ='GHG detailed, absolute'!X32/Production!$G$13*AF_calves_IE -> 0.99320979
B33: Calf | C33: Calves | D33: Ireland | E33: IE | F33: CH4, fossil | G33: =SUM(H33:X33) -> 0.16925726 | H33: ='GHG detailed, absolute'!H33/Production!$G$13*AF_calves_IE -> 0.00083879784 | I33: ='GHG detailed, absolute'!I33/Production!$G$13*AF_calves_IE -> 0.088514141 | L33: ='GHG detailed, absolute'!L33/Production!$G$13*AF_calves_IE -> 0.0066131539 | N33: ='GHG detailed, absolute'!N33/Production!$G$13*AF_calves_IE -> 0.00017601955 | O33: ='GHG detailed, absolute'!O33/Production!$G$13*AF_calves_IE -> 0.0025693093 | P33: ='GHG detailed, absolute'!P33/Production!$G$13*AF_calves_IE -> 0 | Q33: ='GHG detailed, absolute'!Q33/Production!$G$13*AF_calves_IE -> 0.01153788 | R33: ='GHG detailed, absolute'!R33/Production!$G$13*AF_calves_IE -> 0.01153788 | W33: ='GHG detailed, absolute'!W33/Production!$G$13*AF_calves_IE -> 0.045642723 | X33: ='GHG detailed, absolute'!X33/Production!$G$13*AF_calves_IE -> 0.0018273591
B34: Calf | C34: Calves | D34: Ireland | E34: IE | F34: CH4, biogenic | G34: =SUM(H34:T34) -> 20.644459 | S34: ='GHG detailed, absolute'!S34/Production!$G$13*AF_calves_IE -> 18.373411 | T34: ='GHG detailed, absolute'!T34/Production!$G$13*AF_calves_IE -> 2.2710477 | U34: ='GHG detailed, absolute'!U34/Production!$G$13*AF_calves_IE -> 2.2710477
B35: Calf | C35: Calves | D35: Ireland | E35: IE | F35: N2O | G35: =SUM(H35:T35)+W35+X35 -> 0.53782237 | H35: ='GHG detailed, absolute'!H35/Production!$G$13*AF_calves_IE -> 0.0080293506 | I35: ='GHG detailed, absolute'!I35/Production!$G$13*AF_calves_IE -> 0.0010249006 | J35: ='GHG detailed, absolute'!J35/Production!$G$13*AF_calves_IE -> 0.32877061 | K35: ='GHG detailed, absolute'!K35/Production!$G$13*AF_calves_IE -> 0.032877061 | L35: ='GHG detailed, absolute'!L35/Production!$G$13*AF_calves_IE -> 0.00040115474 | N35: ='GHG detailed, absolute'!N35/Production!$G$13*AF_calves_IE -> 2.5510009e-06 | O35: ='GHG detailed, absolute'!O35/Production!$G$13*AF_calves_IE -> 0.00017704474 | P35: ='GHG detailed, absolute'!P35/Production!$G$13*AF_calves_IE -> 0 | Q35: ='GHG detailed, absolute'!Q35/Production!$G$13*AF_calves_IE -> 0.00073023854 | R35: ='GHG detailed, absolute'!R35/Production!$G$13*AF_calves_IE -> 0.00073023854 | T35: ='GHG detailed, absolute'!T35/Production!$G$13*AF_calves_IE -> 0.16348783 | U35: ='GHG detailed, absolute'!U35/Production!$G$13*AF_calves_IE -> 0.11431415 | V35: ='GHG detailed, absolute'!V35/Production!$G$13*AF_calves_IE -> 0.049173682 | W35: ='GHG detailed, absolute'!W35/Production!$G$13*AF_calves_IE -> 0.0015558897 | X35: ='GHG detailed, absolute'!X35/Production!$G$13*AF_calves_IE -> 3.5501147e-05
B36: Calf | C36: Calves | D36: Ireland | E36: IE | F36: CO2e | G36: =SUM(H36:X36) -> 833.35939 | H36: =SUMPRODUCT(H32:H35,'Parameters, general'!$B$24:$B$27) -> 22.937501 | I36: =SUMPRODUCT(I32:I35,'Parameters, general'!$B$24:$B$27) -> 28.07417 | J36: =SUMPRODUCT(J32:J35,'Parameters, general'!$B$24:$B$27) -> 89.754377 | K36: =SUMPRODUCT(K32:K35,'Parameters, general'!$B$24:$B$27) -> 8.9754377 | L36: =SUMPRODUCT(L32:L35,'Parameters, general'!$B$24:$B$27) -> 15.235836 | M36: =SUMPRODUCT(M32:M35,'Parameters, general'!$B$24:$B$27) -> 0 | N36: =SUMPRODUCT(N32:N35,'Parameters, general'!$B$24:$B$27) -> 0.065343814 | O36: =SUMPRODUCT(O32:O35,'Parameters, general'!$B$24:$B$27) -> 5.0397875 | ... T36: =SUMPRODUCT(T32:T35,'Parameters, general'!$B$24:$B$27) -> 105.95046 | W36: =SUMPRODUCT(W32:W35,'Parameters, general'!$B$24:$B$27) -> 44.13753 | X36: =SUMPRODUCT(X32:X35,'Parameters, general'!$B$24:$B$27) -> 1.0573569
B37: Calf | C37: Calves | D37: Italy | E37: IT | F37: CO2 | G37: =SUM(H37:X37) -> 302.75658 | H37: ='GHG detailed, absolute'!H37/Production!$H$13*AF_calves_IT -> 17.584693 | I37: ='GHG detailed, absolute'!I37/Production!$H$13*AF_calves_IT -> 19.108802 | L37: ='GHG detailed, absolute'!L37/Production!$H$13*AF_calves_IT -> 12.483002 | N37: ='GHG detailed, absolute'!N37/Production!$H$13*AF_calves_IT -> 0.20408857 | O37: ='GHG detailed, absolute'!O37/Production!$H$13*AF_calves_IT -> 4.5993151 | P37: ='GHG detailed, absolute'!P37/Production!$H$13*AF_calves_IT -> 31.529785 | Q37: ='GHG detailed, absolute'!Q37/Production!$H$13*AF_calves_IT -> 66.487374 | R37: ='GHG detailed, absolute'!R37/Production!$H$13*AF_calves_IT -> 66.487374 | W37: ='GHG detailed, absolute'!W37/Production!$H$13*AF_calves_IT -> 83.353298 | X37: ='GHG detailed, absolute'!X37/Production!$H$13*AF_calves_IT -> 0.91884305
B38: Calf | C38: Calves | D38: Italy | E38: IT | F38: CH4, fossil | G38: =SUM(H38:X38) -> 1.3676842 | H38: ='GHG detailed, absolute'!H38/Production!$H$13*AF_calves_IT -> 0.0026852023 | I38: ='GHG detailed, absolute'!I38/Production!$H$13*AF_calves_IT -> 0.067234675 | L38: ='GHG detailed, absolute'!L38/Production!$H$13*AF_calves_IT -> 0.0055295491 | N38: ='GHG detailed, absolute'!N38/Production!$H$13*AF_calves_IT -> 0.00066014595 | O38: ='GHG detailed, absolute'!O38/Production!$H$13*AF_calves_IT -> 0.0040163434 | P38: ='GHG detailed, absolute'!P38/Production!$H$13*AF_calves_IT -> 0 | Q38: ='GHG detailed, absolute'!Q38/Production!$H$13*AF_calves_IT -> 0.46058646 | R38: ='GHG detailed, absolute'!R38/Production!$H$13*AF_calves_IT -> 0.46058646 | W38: ='GHG detailed, absolute'!W38/Production!$H$13*AF_calves_IT -> 0.3623556 | X38: ='GHG detailed, absolute'!X38/Production!$H$13*AF_calves_IT -> 0.0040297953
B39: Calf | C39: Calves | D39: Italy | E39: IT | F39: CH4, biogenic | G39: =SUM(H39:T39) -> 21.924676 | S39: ='GHG detailed, absolute'!S39/Production!$H$13*AF_calves_IT -> 17.709576 | T39: ='GHG detailed, absolute'!T39/Production!$H$13*AF_calves_IT -> 4.2151004 | U39: ='GHG detailed, absolute'!U39/Production!$H$13*AF_calves_IT -> 4.2151004
B40: Calf | C40: Calves | D40: Italy | E40: IT | F40: N2O | G40: =SUM(H40:T40)+W40+X40 -> 0.57664048 | H40: ='GHG detailed, absolute'!H40/Production!$H$13*AF_calves_IT -> 0.0036623055 | I40: ='GHG detailed, absolute'!I40/Production!$H$13*AF_calves_IT -> 0.00077850677 | J40: ='GHG detailed, absolute'!J40/Production!$H$13*AF_calves_IT -> 0.22724605 | K40: ='GHG detailed, absolute'!K40/Production!$H$13*AF_calves_IT -> 0.022724605 | L40: ='GHG detailed, absolute'!L40/Production!$H$13*AF_calves_IT -> 0.00033542314 | N40: ='GHG detailed, absolute'!N40/Production!$H$13*AF_calves_IT -> 8.5052234e-06 | O40: ='GHG detailed, absolute'!O40/Production!$H$13*AF_calves_IT -> 0.00016910664 | P40: ='GHG detailed, absolute'!P40/Production!$H$13*AF_calves_IT -> 0 | Q40: ='GHG detailed, absolute'!Q40/Production!$H$13*AF_calves_IT -> 0.027079723 | R40: ='GHG detailed, absolute'!R40/Production!$H$13*AF_calves_IT -> 0.027079723 | T40: ='GHG detailed, absolute'!T40/Production!$H$13*AF_calves_IT -> 0.26389161 | U40: ='GHG detailed, absolute'!U40/Production!$H$13*AF_calves_IT -> 0.17370388 | V40: ='GHG detailed, absolute'!V40/Production!$H$13*AF_calves_IT -> 0.090187726 | W40: ='GHG detailed, absolute'!W40/Production!$H$13*AF_calves_IT -> 0.0036272854 | X40: ='GHG detailed, absolute'!X40/Production!$H$13*AF_calves_IT -> 3.7627082e-05
B41: Calf | C41: Calves | D41: Italy | E41: IT | F41: CO2e | G41: =SUM(H41:X41) -> 1092.9027 | H41: =SUMPRODUCT(H37:H40,'Parameters, general'!$B$24:$B$27) -> 18.664522 | I41: =SUMPRODUCT(I37:I40,'Parameters, general'!$B$24:$B$27) -> 21.324928 | J41: =SUMPRODUCT(J37:J40,'Parameters, general'!$B$24:$B$27) -> 62.038173 | K41: =SUMPRODUCT(K37:K40,'Parameters, general'!$B$24:$B$27) -> 6.2038173 | L41: =SUMPRODUCT(L37:L40,'Parameters, general'!$B$24:$B$27) -> 12.739353 | M41: =SUMPRODUCT(M37:M40,'Parameters, general'!$B$24:$B$27) -> 0 | N41: =SUMPRODUCT(N37:N40,'Parameters, general'!$B$24:$B$27) -> 0.22608285 | O41: =SUMPRODUCT(O37:O40,'Parameters, general'!$B$24:$B$27) -> 4.7651682 | ... T41: =SUMPRODUCT(T37:T40,'Parameters, general'!$B$24:$B$27) -> 185.85012 | W41: =SUMPRODUCT(W37:W40,'Parameters, general'!$B$24:$B$27) -> 95.141744 | X41: =SUMPRODUCT(X37:X40,'Parameters, general'!$B$24:$B$27) -> 1.0492031
B42: Calf | C42: Calves | D42: Netherland | E42: NL | F42: CO2 | G42: =SUM(H42:X42) -> 285.81859 | H42: ='GHG detailed, absolute'!H42/Production!$I$13*AF_calves_NL -> 44.337875 | I42: ='GHG detailed, absolute'!I42/Production!$I$13*AF_calves_NL -> 19.861862 | L42: ='GHG detailed, absolute'!L42/Production!$I$13*AF_calves_NL -> 17.335219 | N42: ='GHG detailed, absolute'!N42/Production!$I$13*AF_calves_NL -> 0.069104857 | O42: ='GHG detailed, absolute'!O42/Production!$I$13*AF_calves_NL -> 9.0153668 | P42: ='GHG detailed, absolute'!P42/Production!$I$13*AF_calves_NL -> 29.217188 | Q42: ='GHG detailed, absolute'!Q42/Production!$I$13*AF_calves_NL -> 25.12315 | R42: ='GHG detailed, absolute'!R42/Production!$I$13*AF_calves_NL -> 25.12315 | W42: ='GHG detailed, absolute'!W42/Production!$I$13*AF_calves_NL -> 114.84118 | X42: ='GHG detailed, absolute'!X42/Production!$I$13*AF_calves_NL -> 0.89449199
B43: Calf | C43: Calves | D43: Netherland | E43: NL | F43: CH4, fossil | G43: =SUM(H43:X43) -> 0.73703264 | H43: ='GHG detailed, absolute'!H43/Production!$I$13*AF_calves_NL -> 0.023107548 | I43: ='GHG detailed, absolute'!I43/Production!$I$13*AF_calves_NL -> 0.069884329 | L43: ='GHG detailed, absolute'!L43/Production!$I$13*AF_calves_NL -> 0.0076789177 | N43: ='GHG detailed, absolute'!N43/Production!$I$13*AF_calves_NL -> 0.00022140733 | O43: ='GHG detailed, absolute'!O43/Production!$I$13*AF_calves_NL -> 0.0063775675 | P43: ='GHG detailed, absolute'!P43/Production!$I$13*AF_calves_NL -> 0 | Q43: ='GHG detailed, absolute'!Q43/Production!$I$13*AF_calves_NL -> 0.20010163 | R43: ='GHG detailed, absolute'!R43/Production!$I$13*AF_calves_NL -> 0.20010163 | W43: ='GHG detailed, absolute'!W43/Production!$I$13*AF_calves_NL -> 0.22737242 | X43: ='GHG detailed, absolute'!X43/Production!$I$13*AF_calves_NL -> 0.0021871814
B44: Calf | C44: Calves | D44: Netherland | E44: NL | F44: CH4, biogenic | G44: =SUM(H44:T44) -> 18.377864 | S44: ='GHG detailed, absolute'!S44/Production!$I$13*AF_calves_NL -> 15.232009 | T44: ='GHG detailed, absolute'!T44/Production!$I$13*AF_calves_NL -> 3.1458553 | U44: ='GHG detailed, absolute'!U44/Production!$I$13*AF_calves_NL -> 3.1458553
B45: Calf | C45: Calves | D45: Netherland | E45: NL | F45: N2O | G45: =SUM(H45:T45)+W45+X45 -> 0.75571966 | H45: ='GHG detailed, absolute'!H45/Production!$I$13*AF_calves_NL -> 0.039513866 | I45: ='GHG detailed, absolute'!I45/Production!$I$13*AF_calves_NL -> 0.00080918697 | J45: ='GHG detailed, absolute'!J45/Production!$I$13*AF_calves_NL -> 0.45160519 | K45: ='GHG detailed, absolute'!K45/Production!$I$13*AF_calves_NL -> 0.045160519 | L45: ='GHG detailed, absolute'!L45/Production!$I$13*AF_calves_NL -> 0.0004658041 | N45: ='GHG detailed, absolute'!N45/Production!$I$13*AF_calves_NL -> 2.8898101e-06 | O45: ='GHG detailed, absolute'!O45/Production!$I$13*AF_calves_NL -> 0.00032530232 | P45: ='GHG detailed, absolute'!P45/Production!$I$13*AF_calves_NL -> 0 | Q45: ='GHG detailed, absolute'!Q45/Production!$I$13*AF_calves_NL -> 0.018055134 | R45: ='GHG detailed, absolute'!R45/Production!$I$13*AF_calves_NL -> 0.018055134 | T45: ='GHG detailed, absolute'!T45/Production!$I$13*AF_calves_NL -> 0.17708145 | U45: ='GHG detailed, absolute'!U45/Production!$I$13*AF_calves_NL -> 0.096644398 | V45: ='GHG detailed, absolute'!V45/Production!$I$13*AF_calves_NL -> 0.080437053 | W45: ='GHG detailed, absolute'!W45/Production!$I$13*AF_calves_NL -> 0.0046105603 | X45: ='GHG detailed, absolute'!X45/Production!$I$13*AF_calves_NL -> 3.4616822e-05
B46: Calf | C46: Calves | D46: Netherland | E46: NL | F46: CO2e | G46: =SUM(H46:X46) -> 1010.2959 | H46: =SUMPRODUCT(H42:H45,'Parameters, general'!$B$24:$B$27) -> 55.813766 | I46: =SUMPRODUCT(I42:I45,'Parameters, general'!$B$24:$B$27) -> 22.165323 | J46: =SUMPRODUCT(J42:J45,'Parameters, general'!$B$24:$B$27) -> 123.28822 | K46: =SUMPRODUCT(K42:K45,'Parameters, general'!$B$24:$B$27) -> 12.328822 | L46: =SUMPRODUCT(L42:L45,'Parameters, general'!$B$24:$B$27) -> 17.691216 | M46: =SUMPRODUCT(M42:M45,'Parameters, general'!$B$24:$B$27) -> 0 | N46: =SUMPRODUCT(N42:N45,'Parameters, general'!$B$24:$B$27) -> 0.076491714 | O46: =SUMPRODUCT(O42:O45,'Parameters, general'!$B$24:$B$27) -> 9.2942258 | ... T46: =SUMPRODUCT(T42:T45,'Parameters, general'!$B$24:$B$27) -> 133.28133 | W46: =SUMPRODUCT(W42:W45,'Parameters, general'!$B$24:$B$27) -> 122.87556 | X46: =SUMPRODUCT(X42:X45,'Parameters, general'!$B$24:$B$27) -> 0.96912038
B47: Calf | C47: Calves | D47: Poland | E47: PL | F47: CO2 | G47: =SUM(H47:X47) -> 480.75314 | H47: ='GHG detailed, absolute'!H47/Production!$J$13*AF_calves_PL -> 57.035115 | I47: ='GHG detailed, absolute'!I47/Production!$J$13*AF_calves_PL -> 21.96673 | L47: ='GHG detailed, absolute'!L47/Production!$J$13*AF_calves_PL -> 27.01837 | N47: ='GHG detailed, absolute'!N47/Production!$J$13*AF_calves_PL -> 0.15362296 | O47: ='GHG detailed, absolute'!O47/Production!$J$13*AF_calves_PL -> 20.080673 | P47: ='GHG detailed, absolute'!P47/Production!$J$13*AF_calves_PL -> 22.349902 | Q47: ='GHG detailed, absolute'!Q47/Production!$J$13*AF_calves_PL -> 63.009205 | R47: ='GHG detailed, absolute'!R47/Production!$J$13*AF_calves_PL -> 63.009205 | W47: ='GHG detailed, absolute'!W47/Production!$J$13*AF_calves_PL -> 204.13487 | X47: ='GHG detailed, absolute'!X47/Production!$J$13*AF_calves_PL -> 1.9954436
B48: Calf | C48: Calves | D48: Poland | E48: PL | F48: CH4, fossil | G48: =SUM(H48:X48) -> 1.0431915 | H48: ='GHG detailed, absolute'!H48/Production!$J$13*AF_calves_PL -> 0.0053712733 | I48: ='GHG detailed, absolute'!I48/Production!$J$13*AF_calves_PL -> 0.077290345 | L48: ='GHG detailed, absolute'!L48/Production!$J$13*AF_calves_PL -> 0.011968227 | N48: ='GHG detailed, absolute'!N48/Production!$J$13*AF_calves_PL -> 0.00046016886 | O48: ='GHG detailed, absolute'!O48/Production!$J$13*AF_calves_PL -> 0.017553703 | P48: ='GHG detailed, absolute'!P48/Production!$J$13*AF_calves_PL -> 0 | Q48: ='GHG detailed, absolute'!Q48/Production!$J$13*AF_calves_PL -> 0.26643311 | R48: ='GHG detailed, absolute'!R48/Production!$J$13*AF_calves_PL -> 0.26643311 | W48: ='GHG detailed, absolute'!W48/Production!$J$13*AF_calves_PL -> 0.3933065 | X48: ='GHG detailed, absolute'!X48/Production!$J$13*AF_calves_PL -> 0.004375086
B49: Calf | C49: Calves | D49: Poland | E49: PL | F49: CH4, biogenic | G49: =SUM(H49:T49) -> 17.824517 | S49: ='GHG detailed, absolute'!S49/Production!$J$13*AF_calves_PL -> 16.655604 | T49: ='GHG detailed, absolute'!T49/Production!$J$13*AF_calves_PL -> 1.1689129 | U49: ='GHG detailed, absolute'!U49/Production!$J$13*AF_calves_PL -> 1.1689129
B50: Calf | C50: Calves | D50: Poland | E50: PL | F50: N2O | G50: =SUM(H50:T50)+W50+X50 -> 0.74195471 | H50: ='GHG detailed, absolute'!H50/Production!$J$13*AF_calves_PL -> 0.017649195 | I50: ='GHG detailed, absolute'!I50/Production!$J$13*AF_calves_PL -> 0.00089494084 | J50: ='GHG detailed, absolute'!J50/Production!$J$13*AF_calves_PL -> 0.34512058 | K50: ='GHG detailed, absolute'!K50/Production!$J$13*AF_calves_PL -> 0.034512058 | L50: ='GHG detailed, absolute'!L50/Production!$J$13*AF_calves_PL -> 0.00072599415 | N50: ='GHG detailed, absolute'!N50/Production!$J$13*AF_calves_PL -> 6.5740978e-06 | O50: ='GHG detailed, absolute'!O50/Production!$J$13*AF_calves_PL -> 0.0006509668 | P50: ='GHG detailed, absolute'!P50/Production!$J$13*AF_calves_PL -> 0 | Q50: ='GHG detailed, absolute'!Q50/Production!$J$13*AF_calves_PL -> 0.017334224 | R50: ='GHG detailed, absolute'!R50/Production!$J$13*AF_calves_PL -> 0.017334224 | T50: ='GHG detailed, absolute'!T50/Production!$J$13*AF_calves_PL -> 0.30400374 | U50: ='GHG detailed, absolute'!U50/Production!$J$13*AF_calves_PL -> 0.22678864 | V50: ='GHG detailed, absolute'!V50/Production!$J$13*AF_calves_PL -> 0.077215107 | W50: ='GHG detailed, absolute'!W50/Production!$J$13*AF_calves_PL -> 0.0036832954 | X50: ='GHG detailed, absolute'!X50/Production!$J$13*AF_calves_PL -> 3.8916652e-05
B51: Calf | C51: Calves | D51: Poland | E51: PL | F51: CO2e | G51: =SUM(H51:X51) -> 1195.6558 | H51: =SUMPRODUCT(H47:H50,'Parameters, general'!$B$24:$B$27) -> 62.013409 | I51: =SUMPRODUCT(I47:I50,'Parameters, general'!$B$24:$B$27) -> 24.514301 | J51: =SUMPRODUCT(J47:J50,'Parameters, general'!$B$24:$B$27) -> 94.217917 | K51: =SUMPRODUCT(K47:K50,'Parameters, general'!$B$24:$B$27) -> 9.4217917 | L51: =SUMPRODUCT(L47:L50,'Parameters, general'!$B$24:$B$27) -> 27.57322 | M51: =SUMPRODUCT(M47:M50,'Parameters, general'!$B$24:$B$27) -> 0 | N51: =SUMPRODUCT(N47:N50,'Parameters, general'!$B$24:$B$27) -> 0.16913072 | O51: =SUMPRODUCT(O47:O50,'Parameters, general'!$B$24:$B$27) -> 20.781487 | ... T51: =SUMPRODUCT(T47:T50,'Parameters, general'!$B$24:$B$27) -> 114.55367 | W51: =SUMPRODUCT(W47:W50,'Parameters, general'!$B$24:$B$27) -> 216.86095 | X51: =SUMPRODUCT(X47:X50,'Parameters, general'!$B$24:$B$27) -> 2.1364454
B52: Calf | C52: Calves | D52: Spain | E52: ES | F52: CO2 | G52: =SUM(H52:X52) -> 247.36611 | H52: ='GHG detailed, absolute'!H52/Production!$K$13*AF_calves_ES -> 35.264047 | I52: ='GHG detailed, absolute'!I52/Production!$K$13*AF_calves_ES -> 19.951601 | L52: ='GHG detailed, absolute'!L52/Production!$K$13*AF_calves_ES -> 25.184587 | N52: ='GHG detailed, absolute'!N52/Production!$K$13*AF_calves_ES -> 3.1930867 | O52: ='GHG detailed, absolute'!O52/Production!$K$13*AF_calves_ES -> 14.734874 | P52: ='GHG detailed, absolute'!P52/Production!$K$13*AF_calves_ES -> 27.175074 | Q52: ='GHG detailed, absolute'!Q52/Production!$K$13*AF_calves_ES -> 30.079552 | R52: ='GHG detailed, absolute'!R52/Production!$K$13*AF_calves_ES -> 30.079552 | W52: ='GHG detailed, absolute'!W52/Production!$K$13*AF_calves_ES -> 61.082764 | X52: ='GHG detailed, absolute'!X52/Production!$K$13*AF_calves_ES -> 0.62097438
B53: Calf | C53: Calves | D53: Spain | E53: ES | F53: CH4, fossil | G53: =SUM(H53:X53) -> 0.68343214 | H53: ='GHG detailed, absolute'!H53/Production!$K$13*AF_calves_ES -> 0.0042535348 | I53: ='GHG detailed, absolute'!I53/Production!$K$13*AF_calves_ES -> 0.070200079 | L53: ='GHG detailed, absolute'!L53/Production!$K$13*AF_calves_ES -> 0.011155923 | N53: ='GHG detailed, absolute'!N53/Production!$K$13*AF_calves_ES -> 0.0095238941 | O53: ='GHG detailed, absolute'!O53/Production!$K$13*AF_calves_ES -> 0.011118337 | P53: ='GHG detailed, absolute'!P53/Production!$K$13*AF_calves_ES -> 0 | Q53: ='GHG detailed, absolute'!Q53/Production!$K$13*AF_calves_ES -> 0.1930923 | R53: ='GHG detailed, absolute'!R53/Production!$K$13*AF_calves_ES -> 0.1930923 | W53: ='GHG detailed, absolute'!W53/Production!$K$13*AF_calves_ES -> 0.18881619 | X53: ='GHG detailed, absolute'!X53/Production!$K$13*AF_calves_ES -> 0.0021795954
B54: Calf | C54: Calves | D54: Spain | E54: ES | F54: CH4, biogenic | G54: =SUM(H54:T54) -> 17.528562 | S54: ='GHG detailed, absolute'!S54/Production!$K$13*AF_calves_ES -> 14.908099 | T54: ='GHG detailed, absolute'!T54/Production!$K$13*AF_calves_ES -> 2.6204625 | U54: ='GHG detailed, absolute'!U54/Production!$K$13*AF_calves_ES -> 2.6204625
