Workbook
Name _Ref32411070: 'Input - Microbial Protein'!$I$187
Name _Ref45878722: 'Input - Microbial Protein'!$I$149
Name _Ref45878756: 'Input - Microbial Protein'!$I$150
Name _Toc62923992: 'Input - Microbial Protein'!$I$169
Name _Toc62924001: 'Input - Microbial Protein'!$A$149
Name Bonefree_outof_CW_DE: '[1]Parameters, country spec'!$D$8
Name Bonefree_outof_CW_DK: '[1]Parameters, country spec'!$B$8
Name Bonefree_outof_CW_ES: '[1]Parameters, country spec'!$K$8
Name Bonefree_outof_CW_FR: '[1]Parameters, country spec'!$C$8
Name Bonefree_outof_CW_GR: '[1]Parameters, country spec'!$E$8
Name Bonefree_outof_CW_HU: '[1]Parameters, country spec'!$F$8
Name Bonefree_outof_CW_IE: '[1]Parameters, country spec'!$G$8
Name Bonefree_outof_CW_IT: '[1]Parameters, country spec'!$H$8
Name Bonefree_outof_CW_NL: '[1]Parameters, country spec'!$I$8
Name Bonefree_outof_CW_PL: '[1]Parameters, country spec'!$J$8
Name Bonefree_outof_CW_SE: '[1]Parameters, country spec'!$L$8
Name CF_CH4_bio: 'CF climate'!$C$5
Name CF_CH4_foss: 'CF climate'!$D$5
Name CF_CO2: 'CF climate'!$B$5
Name CF_N2O: 'CF climate'!$E$5
Name EF_biofuel_CH4: #REF!
Name EF_biofuel_N2O: #REF!
Name EF_biofuels_CO2: #REF!
Name EF_el_CH4_BR: #REF!
Name EF_el_CH4_DE: '[1]Parameters, country spec'!$D$91
Name EF_el_CH4_DK: '[1]Parameters, country spec'!$B$91
Name EF_el_CH4_ES: '[1]Parameters, country spec'!$K$91
Name EF_el_CH4_FR: #REF!
Name EF_el_CH4_GR: '[1]Parameters, country spec'!$E$91
Name EF_el_CH4_HU: '[1]Parameters, country spec'!$F$91
Name EF_el_CH4_IE: '[1]Parameters, country spec'!$G$91
Name EF_el_CH4_IT: '[1]Parameters, country spec'!$H$91
Name EF_el_CH4_NL: '[1]Parameters, country spec'!$I$91
Name EF_el_CH4_PL: '[1]Parameters, country spec'!$J$91
Name EF_el_CH4_SE: '[1]Parameters, country spec'!$L$91
Name EF_el_CO2_BR: #REF!
Name EF_el_CO2_DE: '[1]Parameters, country spec'!$D$90
Name EF_el_CO2_DK: '[1]Parameters, country spec'!$B$90
Name EF_el_CO2_ES: '[1]Parameters, country spec'!$K$90
Name EF_el_CO2_FR: #REF!
Name EF_el_CO2_GR: '[1]Parameters, country spec'!$E$90
Name EF_el_CO2_HU: '[1]Parameters, country spec'!$F$90
Name EF_el_CO2_IE: '[1]Parameters, country spec'!$G$90
Name EF_el_CO2_IT: '[1]Parameters, country spec'!$H$90
Name EF_el_CO2_NL: '[1]Parameters, country spec'!$I$90
Name EF_el_CO2_PL: '[1]Parameters, country spec'!$J$90
Name EF_el_CO2_SE: '[1]Parameters, country spec'!$L$90
Name EF_el_N2O_BR: #REF!
Name EF_el_N2O_DE: '[1]Parameters, country spec'!$D$92
Name EF_el_N2O_DK: '[1]Parameters, country spec'!$B$92
Name EF_el_N2O_ES: '[1]Parameters, country spec'!$K$92
Name EF_el_N2O_FR: #REF!
Name EF_el_N2O_GR: '[1]Parameters, country spec'!$E$92
Name EF_el_N2O_HU: '[1]Parameters, country spec'!$F$92
Name EF_el_N2O_IE: '[1]Parameters, country spec'!$G$92
Name EF_el_N2O_IT: '[1]Parameters, country spec'!$H$92
Name EF_el_N2O_NL: '[1]Parameters, country spec'!$I$92
Name EF_el_N2O_PL: '[1]Parameters, country spec'!$J$92
Name EF_el_N2O_SE: '[1]Parameters, country spec'!$L$92
Name EF_ent_ferm_DE: '[1]Parameters, country spec'!$D$75

Sheet Footprints, results per kg
A2: Novel foods
A4: Species | F4: Climate | L4: Land | M4: Nitrogen | N4: Phosphorus | O4: Water | P4: Pesticides | Q4: Biodiversity | R4: Ammonia | S4: Labour | T4: Animal welfare | U4: Use of antibiotics
A5: Code | B5: Species | C5: Category | D5: Country | E5: Country code | F5: Carbon footprint, kg CO2e/kg | G5: Carbon dioxide, kg CO2/kg | H5: Methane, fossil, kg CH4/kg | I5: Methane, biogenic, kg CH4/kg | J5: Nitrous oxide, kg N2O/kg | K5: HFCs, kg HFCs/kg | L5: Cropland use, m2/kg | M5: New N input, kg N/kg | N5: New P input, kg P/kg | O5: Blue freshwater use, m3/kg | P5: Pesticide use, g a.i./kg | Q5: Extinction rate, E/MSY/kg | R5: Ammonia emission, kg NH3/kg | S5: Labour requirements, h/kg | T5: Animal welfare index per kg of novel food
A6: NF-01 | B6: Cultured Meat (Bos. Spp.) | C6: Novel food | D6: Israel | E6: IL | F6: ='GHG detailed, results per kg'!G10 -> 17.194275 | G6: ='GHG detailed, results per kg'!G6 -> 15.279234 | H6: ='GHG detailed, results per kg'!G7 -> 0.046008135 | I6: ='GHG detailed, results per kg'!G8 -> 0 | J6: ='GHG detailed, results per kg'!G9 -> 0.0019926707 | L6: ='Novel foods, input data'!$AB$6*'Agri ing'!$P$27 -> 3.3515324 | M6: ='Novel foods, input data'!$AB$6*'Agri ing'!$Q$27 -> 0.04569437 | N6: ='Novel foods, input data'!$AB$6*'Agri ing'!$R$27 -> 0.014952789 | O6: ='Novel foods, input data'!$AB$6*'Agri ing'!$S$27 -> 0.17035718 | P6: ='Novel foods, input data'!$AB$6*'Agri ing'!$T$27 -> 0.85916204 | Q6: ='Novel foods, input data'!$AB$6*'Agri ing'!$U$27*100 -> 3.124086e-11 | R6: ='Novel foods, input data'!$AB$6*'Agri ing'!$V$27 -> 0.0027779711 | T6: 0 | U6: 0
A7: NF-01 | B7: Cultured Meat (Bos. Spp.) | C7: Novel food | D7: Netherlands | E7: NL | F7: ='GHG detailed, results per kg'!G15 -> 4.2362683 | G7: ='GHG detailed, results per kg'!G11 -> 3.5498417 | H7: ='GHG detailed, results per kg'!G12 -> 0.0070766997 | I7: ='GHG detailed, results per kg'!G13 -> 0 | J7: ='GHG detailed, results per kg'!G14 -> 0.0017419081 | L7: ='Novel foods, input data'!$AB$6*'Agri ing'!$P$27 -> 3.3515324 | M7: ='Novel foods, input data'!$AB$6*'Agri ing'!$Q$27 -> 0.04569437 | N7: ='Novel foods, input data'!$AB$6*'Agri ing'!$R$27 -> 0.014952789 | O7: ='Novel foods, input data'!$AB$6*'Agri ing'!$S$27 -> 0.17035718 | P7: ='Novel foods, input data'!$AB$6*'Agri ing'!$T$27 -> 0.85916204 | Q7: ='Novel foods, input data'!$AB$6*'Agri ing'!$U$27*100 -> 3.124086e-11 | R7: ='Novel foods, input data'!$AB$6*'Agri ing'!$V$27 -> 0.0027779711 | T7: 0 | U7: 0
A8: NF-01 | B8: Cultured Meat (Bos. Spp.) | C8: Novel food | D8: Sweden | E8: SE | F8: ='GHG detailed, results per kg'!G20 -> 1.61596 | G8: ='GHG detailed, results per kg'!G16 -> 1.1066169 | H8: ='GHG detailed, results per kg'!G17 -> 0.0017795518 | I8: ='GHG detailed, results per kg'!G18 -> 0 | J8: ='GHG detailed, results per kg'!G19 -> 0.0016714742 | L8: ='Novel foods, input data'!$AB$6*'Agri ing'!$P$27 -> 3.3515324 | M8: ='Novel foods, input data'!$AB$6*'Agri ing'!$Q$27 -> 0.04569437 | N8: ='Novel foods, input data'!$AB$6*'Agri ing'!$R$27 -> 0.014952789 | O8: ='Novel foods, input data'!$AB$6*'Agri ing'!$S$27 -> 0.17035718 | P8: ='Novel foods, input data'!$AB$6*'Agri ing'!$T$27 -> 0.85916204 | Q8: ='Novel foods, input data'!$AB$6*'Agri ing'!$U$27*100 -> 3.124086e-11 | R8: ='Novel foods, input data'!$AB$6*'Agri ing'!$V$27 -> 0.0027779711 | T8: 0 | U8: 0
A9: NF-01 | B9: Cultured Meat (Bos. Spp.) | C9: Novel food | D9: USA | E9: US | F9: ='GHG detailed, results per kg'!G25 -> 4.3700633 | G9: ='GHG detailed, results per kg'!G21 -> 3.7219655 | H9: ='GHG detailed, results per kg'!G22 -> 0.0060709677 | I9: ='GHG detailed, results per kg'!G23 -> 0 | J9: ='GHG detailed, results per kg'!G24 -> 0.001711293 | L9: ='Novel foods, input data'!$AB$6*'Agri ing'!$P$27 -> 3.3515324 | M9: ='Novel foods, input data'!$AB$6*'Agri ing'!$Q$27 -> 0.04569437 | N9: ='Novel foods, input data'!$AB$6*'Agri ing'!$R$27 -> 0.014952789 | O9: ='Novel foods, input data'!$AB$6*'Agri ing'!$S$27 -> 0.17035718 | P9: ='Novel foods, input data'!$AB$6*'Agri ing'!$T$27 -> 0.85916204 | Q9: ='Novel foods, input data'!$AB$6*'Agri ing'!$U$27*100 -> 3.124086e-11 | R9: ='Novel foods, input data'!$AB$6*'Agri ing'!$V$27 -> 0.0027779711 | T9: 0 | U9: 0
A10: NF-02 | B10: Microbial Milk (T. reesei) | C10: Novel food | D10: Denmark | E10: DK | F10: ='GHG detailed, results per kg'!G30 -> 1.3241574 | G10: ='GHG detailed, results per kg'!G26 -> 1.054122 | H10: ='GHG detailed, results per kg'!G27 -> 0.001308799 | I10: ='GHG detailed, results per kg'!G28 -> 0 | J10: ='GHG detailed, results per kg'!G29 -> 0.00084627547 | L10: ='Novel foods, input data'!$AB$7*'Agri ing'!$P$27 -> 1.6935889 | M10: ='Novel foods, input data'!$AB$7*'Agri ing'!$O$27 -> 0.00081991307 | N10: ='Novel foods, input data'!$AB$7*'Agri ing'!$R$27 -> 0.0075559101 | O10: ='Novel foods, input data'!$AB$7*'Agri ing'!$S$27 -> 0.086084513 | P10: ='Novel foods, input data'!$AB$7*'Agri ing'!$T$27 -> 0.43414986 | Q10: ='Novel foods, input data'!$AB$7*'Agri ing'!$U$27*100 -> 1.5786562e-11 | R10: ='Novel foods, input data'!$AB$7*'Agri ing'!$V$27 -> 0.0014037582 | T10: 0 | U10: 0
A11: NF-02 | B11: Microbial Milk (T. reesei) | C11: Novel food | D11: Germany | E11: DE | F11: ='GHG detailed, results per kg'!G35 -> 1.4688404 | G11: ='GHG detailed, results per kg'!G31 -> 1.1826885 | H11: ='GHG detailed, results per kg'!G32 -> 0.0018281417 | I11: ='GHG detailed, results per kg'!G33 -> 0 | J11: ='GHG detailed, results per kg'!G34 -> 0.00084861989 | L11: ='Novel foods, input data'!$AB$7*'Agri ing'!$P$27 -> 1.6935889 | M11: ='Novel foods, input data'!$AB$7*'Agri ing'!$O$27 -> 0.00081991307 | N11: ='Novel foods, input data'!$AB$7*'Agri ing'!$R$27 -> 0.0075559101 | O11: ='Novel foods, input data'!$AB$7*'Agri ing'!$S$27 -> 0.086084513 | P11: ='Novel foods, input data'!$AB$7*'Agri ing'!$T$27 -> 0.43414986 | Q11: ='Novel foods, input data'!$AB$7*'Agri ing'!$U$27*100 -> 1.5786562e-11 | R11: ='Novel foods, input data'!$AB$7*'Agri ing'!$V$27 -> 0.0014037582 | T11: 0 | U11: 0
A12: NF-02 | B12: Microbial Milk (T. reesei) | C12: Novel food | D12: Sweden | E12: SE | F12: ='GHG detailed, results per kg'!G40 -> 0.91295494 | G12: ='GHG detailed, results per kg'!G36 -> 0.66404222 | H12: ='GHG detailed, results per kg'!G37 -> 0.00073795969 | I12: ='GHG detailed, results per kg'!G38 -> 0 | J12: ='GHG detailed, results per kg'!G35 -> 1.4688404 | L12: ='Novel foods, input data'!$AB$7*'Agri ing'!$P$27 -> 1.6935889 | M12: ='Novel foods, input data'!$AB$7*'Agri ing'!$O$27 -> 0.00081991307 | N12: ='Novel foods, input data'!$AB$7*'Agri ing'!$R$27 -> 0.0075559101 | O12: ='Novel foods, input data'!$AB$7*'Agri ing'!$S$27 -> 0.086084513 | P12: ='Novel foods, input data'!$AB$7*'Agri ing'!$T$27 -> 0.43414986 | Q12: ='Novel foods, input data'!$AB$7*'Agri ing'!$U$27*100 -> 1.5786562e-11 | R12: ='Novel foods, input data'!$AB$7*'Agri ing'!$V$27 -> 0.0014037582 | T12: 0 | U12: 0
A13: NF-02 | B13: Microbial Milk (T. reesei) | C13: Novel food | D13: Switzerland | E13: CH | F13: ='GHG detailed, results per kg'!G45 -> 0.91295494 | G13: ='GHG detailed, results per kg'!G41 -> 0.66404222 | H13: ='GHG detailed, results per kg'!G42 -> 0.00073795969 | I13: ='GHG detailed, results per kg'!G43 -> 0 | J13: ='GHG detailed, results per kg'!G39 -> 0.00083121437 | L13: ='Novel foods, input data'!$AB$7*'Agri ing'!$P$27 -> 1.6935889 | M13: ='Novel foods, input data'!$AB$7*'Agri ing'!$O$27 -> 0.00081991307 | N13: ='Novel foods, input data'!$AB$7*'Agri ing'!$R$27 -> 0.0075559101 | O13: ='Novel foods, input data'!$AB$7*'Agri ing'!$S$27 -> 0.086084513 | P13: ='Novel foods, input data'!$AB$7*'Agri ing'!$T$27 -> 0.43414986 | Q13: ='Novel foods, input data'!$AB$7*'Agri ing'!$U$27*100 -> 1.5786562e-11 | R13: ='Novel foods, input data'!$AB$7*'Agri ing'!$V$27 -> 0.0014037582 | T13: 0 | U13: 0
A14: NF-02 | B14: Microbial Milk (T. reesei) | C14: Novel food | D14: USA | E14: US | F14: ='GHG detailed, results per kg'!G50 -> 1.5493915 | G14: ='GHG detailed, results per kg'!G46 -> 1.2684144 | H14: ='GHG detailed, results per kg'!G47 -> 0.0017296487 | I14: ='GHG detailed, results per kg'!G48 -> 0 | J14: ='GHG detailed, results per kg'!G44 -> 0.00083121437 | L14: ='Novel foods, input data'!$AB$7*'Agri ing'!$P$27 -> 1.6935889 | M14: ='Novel foods, input data'!$AB$7*'Agri ing'!$O$27 -> 0.00081991307 | N14: ='Novel foods, input data'!$AB$7*'Agri ing'!$R$27 -> 0.0075559101 | O14: ='Novel foods, input data'!$AB$7*'Agri ing'!$S$27 -> 0.086084513 | P14: ='Novel foods, input data'!$AB$7*'Agri ing'!$T$27 -> 0.43414986 | Q14: ='Novel foods, input data'!$AB$7*'Agri ing'!$U$27*100 -> 1.5786562e-11 | R14: ='Novel foods, input data'!$AB$7*'Agri ing'!$V$27 -> 0.0014037582 | T14: 0 | U14: 0
A15: NF-03 | B15: Microbial Ovalbumin (T. reesei) | C15: Novel food | D15: Denmark | E15: DK | F15: ='GHG detailed, results per kg'!G55 -> 6.183196 | G15: ='GHG detailed, results per kg'!G51 -> 5.4401856 | H15: ='GHG detailed, results per kg'!G52 -> 0.004702669 | I15: ='GHG detailed, results per kg'!G53 -> 0 | J15: ='GHG detailed, results per kg'!G49 -> 0.00084041596 | L15: ='Novel foods, input data'!$AB$8*'Agri ing'!$P$27 -> 4.3173585 | M15: ='Novel foods, input data'!$AB$8*'Agri ing'!$O$27 -> 0.0020901522 | N15: ='Novel foods, input data'!$AB$8*'Agri ing'!$R$27 -> 0.019261801 | O15: ='Novel foods, input data'!$AB$8*'Agri ing'!$S$27 -> 0.21944977 | P15: ='Novel foods, input data'!$AB$8*'Agri ing'!$T$27 -> 1.1067506 | Q15: ='Novel foods, input data'!$AB$8*'Agri ing'!$U$27*100 -> 4.0243678e-11 | R15: ='Novel foods, input data'!$AB$8*'Agri ing'!$V$27 -> 0.0035785114 | T15: 0 | U15: 0
A16: NF-03 | B16: Microbial Ovalbumin (T. reesei) | C16: Novel food | D16: Germany | E16: DE | F16: ='GHG detailed, results per kg'!G60 -> 6.8317181 | G16: ='GHG detailed, results per kg'!G56 -> 6.0164679 | H16: ='GHG detailed, results per kg'!G57 -> 0.007030554 | I16: ='GHG detailed, results per kg'!G58 -> 0 | J16: ='GHG detailed, results per kg'!G54 -> 0.0022083182 | L16: ='Novel foods, input data'!$AB$8*'Agri ing'!$P$27 -> 4.3173585 | M16: ='Novel foods, input data'!$AB$8*'Agri ing'!$O$27 -> 0.0020901522 | N16: ='Novel foods, input data'!$AB$8*'Agri ing'!$R$27 -> 0.019261801 | O16: ='Novel foods, input data'!$AB$8*'Agri ing'!$S$27 -> 0.21944977 | P16: ='Novel foods, input data'!$AB$8*'Agri ing'!$T$27 -> 1.1067506 | Q16: ='Novel foods, input data'!$AB$8*'Agri ing'!$U$27*100 -> 4.0243678e-11 | R16: ='Novel foods, input data'!$AB$8*'Agri ing'!$V$27 -> 0.0035785114 | T16: 0 | U16: 0
A17: NF-03 | B17: Microbial Ovalbumin (T. reesei) | C17: Novel food | D17: Sweden | E17: SE | F17: ='GHG detailed, results per kg'!G65 -> 4.3400351 | G17: ='GHG detailed, results per kg'!G61 -> 3.6917044 | H17: ='GHG detailed, results per kg'!G62 -> 0.0021439571 | I17: ='GHG detailed, results per kg'!G63 -> 0 | J17: ='GHG detailed, results per kg'!G59 -> 0.0022188267 | L17: ='Novel foods, input data'!$AB$8*'Agri ing'!$P$27 -> 4.3173585 | M17: ='Novel foods, input data'!$AB$8*'Agri ing'!$O$27 -> 0.0020901522 | N17: ='Novel foods, input data'!$AB$8*'Agri ing'!$R$27 -> 0.019261801 | O17: ='Novel foods, input data'!$AB$8*'Agri ing'!$S$27 -> 0.21944977 | P17: ='Novel foods, input data'!$AB$8*'Agri ing'!$T$27 -> 1.1067506 | Q17: ='Novel foods, input data'!$AB$8*'Agri ing'!$U$27*100 -> 4.0243678e-11 | R17: ='Novel foods, input data'!$AB$8*'Agri ing'!$V$27 -> 0.0035785114 | T17: 0 | U17: 0
A18: NF-03 | B18: Microbial Ovalbumin (T. reesei) | C18: Novel food | D18: Switzerland | E18: CH | F18: ='GHG detailed, results per kg'!G70 -> 4.3400351 | G18: ='GHG detailed, results per kg'!G66 -> 3.6917044 | H18: ='GHG detailed, results per kg'!G67 -> 0.0021439571 | I18: ='GHG detailed, results per kg'!G68 -> 0 | J18: ='GHG detailed, results per kg'!G64 -> 0.0021408088 | L18: ='Novel foods, input data'!$AB$8*'Agri ing'!$P$27 -> 4.3173585 | M18: ='Novel foods, input data'!$AB$8*'Agri ing'!$O$27 -> 0.0020901522 | N18: ='Novel foods, input data'!$AB$8*'Agri ing'!$R$27 -> 0.019261801 | O18: ='Novel foods, input data'!$AB$8*'Agri ing'!$S$27 -> 0.21944977 | P18: ='Novel foods, input data'!$AB$8*'Agri ing'!$T$27 -> 1.1067506 | Q18: ='Novel foods, input data'!$AB$8*'Agri ing'!$U$27*100 -> 4.0243678e-11 | R18: ='Novel foods, input data'!$AB$8*'Agri ing'!$V$27 -> 0.0035785114 | T18: 0 | U18: 0
A19: NF-03 | B19: Microbial Ovalbumin (T. reesei) | C19: Novel food | D19: USA | E19: US | F19: ='GHG detailed, results per kg'!G75 -> 7.1927779 | G19: ='GHG detailed, results per kg'!G71 -> 6.4007229 | H19: ='GHG detailed, results per kg'!G72 -> 0.0065890719 | I19: ='GHG detailed, results per kg'!G73 -> 0 | J19: ='GHG detailed, results per kg'!G69 -> 0.0021408088 | L19: ='Novel foods, input data'!$AB$8*'Agri ing'!$P$27 -> 4.3173585 | M19: ='Novel foods, input data'!$AB$8*'Agri ing'!$O$27 -> 0.0020901522 | N19: ='Novel foods, input data'!$AB$8*'Agri ing'!$R$27 -> 0.019261801 | O19: ='Novel foods, input data'!$AB$8*'Agri ing'!$S$27 -> 0.21944977 | P19: ='Novel foods, input data'!$AB$8*'Agri ing'!$T$27 -> 1.1067506 | Q19: ='Novel foods, input data'!$AB$8*'Agri ing'!$U$27*100 -> 4.0243678e-11 | R19: ='Novel foods, input data'!$AB$8*'Agri ing'!$V$27 -> 0.0035785114 | T19: 0 | U19: 0
A20: NF-04 | B20: Microbial Protein (Solein) | C20: Novel food | D20: Finland | E20: FI | F20: ='GHG detailed, results per kg'!G80 -> 6.2223283 | G20: ='GHG detailed, results per kg'!G76 -> 5.8015207 | H20: ='GHG detailed, results per kg'!G77 -> 0.0109117 | I20: ='GHG detailed, results per kg'!G78 -> 0 | J20: ='GHG detailed, results per kg'!G74 -> 0.0021820537 | L20: 0 | M20: 0 | N20: 0 | O20: 0 | P20: 0 | Q20: 0 | R20: 0 | T20: 0 | U20: 0
A21: NF-04 | B21: Microbial Protein (Solein) | C21: Novel food | D21: Sweden | E21: SE | F21: ='GHG detailed, results per kg'!G85 -> 2.1205044 | G21: ='GHG detailed, results per kg'!G81 -> 2.0272184 | H21: ='GHG detailed, results per kg'!G82 -> 0.001776827 | I21: ='GHG detailed, results per kg'!G83 -> 0 | J21: ='GHG detailed, results per kg'!G79 -> 0.00035032584 | L21: 0 | M21: 0 | N21: 0 | O21: 0 | P21: 0 | Q21: 0 | R21: 0 | T21: 0 | U21: 0
A22: NF-05 | B22: Mycoprotein (Quorn) | C22: Novel food | D22: Sweden | E22: SE | F22: ='GHG detailed, results per kg'!G90 -> 1.9266956 | G22: ='GHG detailed, results per kg'!G86 -> 1.065323 | H22: ='GHG detailed, results per kg'!G87 -> 0.0024494886 | I22: ='GHG detailed, results per kg'!G88 -> 7.0753259e-05 | J22: ='GHG detailed, results per kg'!G84 -> 0.00014775292 | L22: ='Novel foods, input data'!$AD$10*'Agri ing'!N21+'Novel foods, input data'!$AE$10*'Agri ing'!P26 -> 4.0200759 | M22: ='Novel foods, input data'!$AD$10*'Agri ing'!O21+'Novel foods, input data'!$AE$10*'Agri ing'!Q26 -> 0.051406516 | N22: ='Novel foods, input data'!$AD$10*'Agri ing'!P21+'Novel foods, input data'!$AE$10*'Agri ing'!R26 -> 0.0047428771 | O22: ='Novel foods, input data'!$AD$10*'Agri ing'!Q21+'Novel foods, input data'!$AE$10*'Agri ing'!S26 -> 0.01731524 | P22: ='Novel foods, input data'!$AD$10*'Agri ing'!R21+'Novel foods, input data'!$AE$10*'Agri ing'!T26 -> 0.51524659 | Q22: =('Novel foods, input data'!$AD$10*'Agri ing'!S21+'Novel foods, input data'!$AE$10*'Agri ing'!U26)*100 -> 1.0074487e-10 | R22: ='Novel foods, input data'!$AD$10*'Agri ing'!T21+'Novel foods, input data'!$AE$10*'Agri ing'!V26 -> 0.0031181532 | T22: ='Novel foods, input data'!$AD$10*'Agri ing'!U21+'Novel foods, input data'!$AE$10*'Agri ing'!W26 -> 0.29204351 | U22: ='Novel foods, input data'!$AD$10*'Agri ing'!V21+'Novel foods, input data'!$AE$10*'Agri ing'!X26 -> 0.0082673929
A23: NF-05 | B23: Mycoprotein (Quorn) | C23: Novel food | D23: UK | E23: GB | F23: ='GHG detailed, results per kg'!G95 -> 2.0031952 | G23: ='GHG detailed, results per kg'!G91 -> 1.1247856 | H23: ='GHG detailed, results per kg'!G92 -> 0.0027051407 | I23: ='GHG detailed, results per kg'!G93 -> 7.0753259e-05 | J23: ='GHG detailed, results per kg'!G89 -> 0.0028808334 | L23: ='Novel foods, input data'!$AD$10*'Agri ing'!N21+'Novel foods, input data'!$AE$10*'Agri ing'!P26 -> 4.0200759 | M23: ='Novel foods, input data'!$AD$10*'Agri ing'!O21+'Novel foods, input data'!$AE$10*'Agri ing'!Q26 -> 0.051406516 | N23: ='Novel foods, input data'!$AD$10*'Agri ing'!P21+'Novel foods, input data'!$AE$10*'Agri ing'!R26 -> 0.0047428771 | O23: ='Novel foods, input data'!$AD$10*'Agri ing'!Q21+'Novel foods, input data'!$AE$10*'Agri ing'!S26 -> 0.01731524 | P23: ='Novel foods, input data'!$AD$10*'Agri ing'!R21+'Novel foods, input data'!$AE$10*'Agri ing'!T26 -> 0.51524659 | Q23: =('Novel foods, input data'!$AD$10*'Agri ing'!S21+'Novel foods, input data'!$AE$10*'Agri ing'!U26)*100 -> 1.0074487e-10 | R23: ='Novel foods, input data'!$AD$10*'Agri ing'!T21+'Novel foods, input data'!$AE$10*'Agri ing'!V26 -> 0.0031181532 | T23: ='Novel foods, input data'!$AD$10*'Agri ing'!U21+'Novel foods, input data'!$AE$10*'Agri ing'!W26 -> 0.29204351 | U23: ='Novel foods, input data'!$AD$10*'Agri ing'!V21+'Novel foods, input data'!$AE$10*'Agri ing'!X26 -> 0.0082673929
A24: NF-06 | B24: Yeast Fat (Rhodotorula babjevae) | C24: Novel food | D24: Israel | E24: IL | F24: ='GHG detailed, results per kg'!G100 -> 0.93463893 | G24: ='GHG detailed, results per kg'!G96 -> 0.85944291 | H24: ='GHG detailed, results per kg'!G97 -> 0.0020750212 | I24: ='GHG detailed, results per kg'!G98 -> 0 | J24: ='GHG detailed, results per kg'!G94 -> 0.0029153335 | L24: 0 | M24: 0 | N24: 0 | O24: 0 | P24: 0 | Q24: 0 | R24: 0 | T24: 0 | U24: 0
A25: NF-06 | B25: Yeast Fat (Rhodotorula babjevae) | C25: Novel food | D25: Netherlands | E25: NL | F25: ='GHG detailed, results per kg'!G105 -> 0.66161793 | G25: ='GHG detailed, results per kg'!G101 -> 0.61230844 | H25: ='GHG detailed, results per kg'!G102 -> 0.0012547486 | I25: ='GHG detailed, results per kg'!G103 -> 0 | J25: ='GHG detailed, results per kg'!G104 -> 4.365563e-05 | L25: 0 | M25: 0 | N25: 0 | O25: 0 | P25: 0 | Q25: 0 | R25: 0 | T25: 0 | U25: 0
A26: NF-06 | B26: Yeast Fat (Rhodotorula babjevae) | C26: Novel food | D26: Sweden | E26: SE | F26: ='GHG detailed, results per kg'!G110 -> 0.60640889 | G26: ='GHG detailed, results per kg'!G106 -> 0.56083048 | H26: ='GHG detailed, results per kg'!G107 -> 0.0011431394 | I26: ='GHG detailed, results per kg'!G108 -> 0 | J26: ='GHG detailed, results per kg'!G109 -> 4.2171613e-05 | L26: 0 | M26: 0 | N26: 0 | O26: 0 | P26: 0 | Q26: 0 | R26: 0 | T26: 0 | U26: 0
A27: NF-06 | B27: Yeast Fat (Rhodotorula babjevae) | C27: Novel food | D27: USA | E27: US | F27: ='GHG detailed, results per kg'!G115 -> 0.66443695 | G27: ='GHG detailed, results per kg'!G111 -> 0.61593503 | H27: ='GHG detailed, results per kg'!G112 -> 0.0012335581 | I27: ='GHG detailed, results per kg'!G113 -> 0 | J27: ='GHG detailed, results per kg'!G114 -> 4.3010581e-05 | L27: 0 | M27: 0 | N27: 0 | O27: 0 | P27: 0 | Q27: 0 | R27: 0 | T27: 0 | U27: 0
A28: NF-07 | B28: Algae Fat (Schizochytrium) | C28: Novel food | D28: Denmark | E28: DK | F28: ='GHG detailed, results per kg'!G120 -> 3.4589034 | G28: ='GHG detailed, results per kg'!G116 -> 2.5190595 | H28: ='GHG detailed, results per kg'!G117 -> 0.0037988689 | I28: ='GHG detailed, results per kg'!G118 -> 0 | J28: ='GHG detailed, results per kg'!G119 -> 0.0030279764 | L28: ='Novel foods, input data'!$AB$12*'Agri ing'!P27 -> 6.1296969 | M28: ='Novel foods, input data'!$AB$12*'Agri ing'!Q27 -> 0.083571514 | N28: ='Novel foods, input data'!$AB$12*'Agri ing'!R27 -> 0.027347509 | O28: ='Novel foods, input data'!$AB$12*'Agri ing'!S27 -> 0.31157027 | P28: ='Novel foods, input data'!$AB$12*'Agri ing'!T27 -> 1.5713418 | Q28: ='Novel foods, input data'!$AB$12*'Agri ing'!U27*100 -> 5.7137148e-11 | R28: ='Novel foods, input data'!$AB$12*'Agri ing'!V27 -> 0.005080697 | T28: 0 | U28: 0
A29: NF-07 | B29: Algae Fat (Schizochytrium) | C29: Novel food | D29: Germany | E29: DE | F29: ='GHG detailed, results per kg'!G125 -> 3.790509 | G29: ='GHG detailed, results per kg'!G121 -> 2.8137271 | H29: ='GHG detailed, results per kg'!G122 -> 0.0049891751 | I29: ='GHG detailed, results per kg'!G123 -> 0 | J29: ='GHG detailed, results per kg'!G124 -> 0.0030333497 | L29: ='Novel foods, input data'!$AB$12*'Agri ing'!P27 -> 6.1296969 | M29: ='Novel foods, input data'!$AB$12*'Agri ing'!Q27 -> 0.083571514 | N29: ='Novel foods, input data'!$AB$12*'Agri ing'!R27 -> 0.027347509 | O29: ='Novel foods, input data'!$AB$12*'Agri ing'!S27 -> 0.31157027 | P29: ='Novel foods, input data'!$AB$12*'Agri ing'!T27 -> 1.5713418 | Q29: ='Novel foods, input data'!$AB$12*'Agri ing'!U27*100 -> 5.7137148e-11 | R29: ='Novel foods, input data'!$AB$12*'Agri ing'!V27 -> 0.005080697 | T29: 0 | U29: 0
A30: NF-07 | B30: Algae Fat (Schizochytrium) | C30: Novel food | D30: Sweden | E30: SE | F30: ='GHG detailed, results per kg'!G130 -> 2.5164488 | G30: ='GHG detailed, results per kg'!G126 -> 1.6250171 | H30: ='GHG detailed, results per kg'!G127 -> 0.0024905351 | I30: ='GHG detailed, results per kg'!G128 -> 0 | J30: ='GHG detailed, results per kg'!G129 -> 0.0029934572 | L30: ='Novel foods, input data'!$AB$12*'Agri ing'!P27 -> 6.1296969 | M30: ='Novel foods, input data'!$AB$12*'Agri ing'!Q27 -> 0.083571514 | N30: ='Novel foods, input data'!$AB$12*'Agri ing'!R27 -> 0.027347509 | O30: ='Novel foods, input data'!$AB$12*'Agri ing'!S27 -> 0.31157027 | P30: ='Novel foods, input data'!$AB$12*'Agri ing'!T27 -> 1.5713418 | Q30: ='Novel foods, input data'!$AB$12*'Agri ing'!U27*100 -> 5.7137148e-11 | R30: ='Novel foods, input data'!$AB$12*'Agri ing'!V27 -> 0.005080697 | T30: 0 | U30: 0
A31: NF-07 | B31: Algae Fat (Schizochytrium) | C31: Novel food | D31: Switzerland | E31: CH | F31: ='GHG detailed, results per kg'!G135 -> 2.5164488 | G31: ='GHG detailed, results per kg'!G131 -> 1.6250171 | H31: ='GHG detailed, results per kg'!G132 -> 0.0024905351 | I31: ='GHG detailed, results per kg'!G133 -> 0 | J31: ='GHG detailed, results per kg'!G134 -> 0.0029934572 | L31: ='Novel foods, input data'!$AB$12*'Agri ing'!P27 -> 6.1296969 | M31: ='Novel foods, input data'!$AB$12*'Agri ing'!Q27 -> 0.083571514 | N31: ='Novel foods, input data'!$AB$12*'Agri ing'!R27 -> 0.027347509 | O31: ='Novel foods, input data'!$AB$12*'Agri ing'!S27 -> 0.31157027 | P31: ='Novel foods, input data'!$AB$12*'Agri ing'!T27 -> 1.5713418 | Q31: ='Novel foods, input data'!$AB$12*'Agri ing'!U27*100 -> 5.7137148e-11 | R31: ='Novel foods, input data'!$AB$12*'Agri ing'!V27 -> 0.005080697 | T31: 0 | U31: 0
A32: NF-07 | B32: Algae Fat (Schizochytrium) | C32: Novel food | D32: USA | E32: US | F32: ='GHG detailed, results per kg'!G140 -> 3.975128 | G32: ='GHG detailed, results per kg'!G136 -> 3.0102064 | H32: ='GHG detailed, results per kg'!G137 -> 0.0047634341 | I32: ='GHG detailed, results per kg'!G138 -> 0 | J32: ='GHG detailed, results per kg'!G139 -> 0.0030145467 | L32: ='Novel foods, input data'!$AB$12*'Agri ing'!P27 -> 6.1296969 | M32: ='Novel foods, input data'!$AB$12*'Agri ing'!Q27 -> 0.083571514 | N32: ='Novel foods, input data'!$AB$12*'Agri ing'!R27 -> 0.027347509 | O32: ='Novel foods, input data'!$AB$12*'Agri ing'!S27 -> 0.31157027 | P32: ='Novel foods, input data'!$AB$12*'Agri ing'!T27 -> 1.5713418 | Q32: ='Novel foods, input data'!$AB$12*'Agri ing'!U27*100 -> 5.7137148e-11 | R32: ='Novel foods, input data'!$AB$12*'Agri ing'!V27 -> 0.005080697 | T32: 0 | U32: 0

Sheet GHG detailed, results per kg
A2: GHG emissions (per kg of novel food)
A4: Product | G4: Sum | H4: Inputs | J4: Soil emissions | L4: Energy use | P4: Land use change | Q4: Feed processing | R4: Transports
A5: Code | B5: Species | C5: Category | D5: Country | E5: Country code | F5: Gas | G5: GHG | H5: Production of mineral fertilizer | I5: Production of capital goods | J5: Direct emissions | K5: Indirect emissions | L5: Diesel use field mach | M5: Energy use in greenhouses | N5: Energy use for irrigation | O5: Energy use for processing of novel foods and for minor ingredients | P5: LUC emissions | Q5: Feed processing | R5: Feed transports | S5: Enteric fermentation | T5: Manure management - tot | U5: Manure management - direct | V5: Manure management - indirect | W5: Energy use in stables | X5: Energy use for slaughter
A6: NF-01 | B6: Cultured Meat (Bos. Spp.) | C6: Novel food | D6: Israel | E6: IL | F6: CO2 | G6: =SUM(H6:X6) -> 15.279234 | H6: ='Novel foods, input data'!$AB$6*'Agri ing'!$AF$27 -> 0.16530307 | I6: ='Novel foods, input data'!$AB$6*'Agri ing'!$AG$27 -> 0.19564101 | J6: 0 | K6: 0 | L6: ='Novel foods, input data'!$AB$6*'Agri ing'!$AH$27 -> 0.21637121 | M6: 0 | N6: 0 | O6: ='Novel foods, input data'!$D$6*'Emission factors'!$B$12+'Novel foods, input data'!$AF$6 -> 14.701919 | P6: 0 | Q6: 0 | R6: 0 | S6: 0 | T6: 0 | U6: 0 | V6: 0 | W6: 0 | X6: 0
A7: NF-01 | B7: Cultured Meat (Bos. Spp.) | C7: Novel food | D7: Israel | E7: IL | F7: CH4, fossil | G7: =SUM(H7:X7) -> 0.046008135 | H7: ='Novel foods, input data'!$AB$6*'Agri ing'!$AJ$27 -> 0.00028384273 | I7: ='Novel foods, input data'!$AB$6*'Agri ing'!$AK$27 -> 0.00068836653 | J7: 0 | K7: 0 | L7: ='Novel foods, input data'!$AB$6*'Agri ing'!$AL$27 -> 0.00021922736 | M7: 0 | N7: 0 | O7: ='Novel foods, input data'!$D$6*'Emission factors'!$C$12+'Novel foods, input data'!$AG$6 -> 0.044816698 | P7: 0 | Q7: 0 | R7: 0 | S7: 0 | T7: 0 | U7: 0 | V7: 0 | W7: 0 | X7: 0
A8: NF-01 | B8: Cultured Meat (Bos. Spp.) | C8: Novel food | D8: Israel | E8: IL | F8: CH4, biogenic | G8: =SUM(H8:T8)+SUM(W8:X8) -> 0 | H8: 0 | I8: 0 | J8: 0 | K8: 0 | L8: 0 | M8: 0 | N8: 0 | O8: 0 | P8: 0 | Q8: 0 | R8: 0 | S8: 0 | T8: 0 | U8: 0 | V8: 0 | W8: 0 | X8: 0
A9: NF-01 | B9: Cultured Meat (Bos. Spp.) | C9: Novel food | D9: Israel | E9: IL | F9: N2O | G9: =SUM(H9:T9)+SUM(W9:X9) -> 0.0019926707 | H9: ='Novel foods, input data'!$AB$6*'Agri ing'!$AP$27 -> 0.00036002414 | I9: ='Novel foods, input data'!$AB$6*'Agri ing'!$AQ$27 -> 7.9705599e-06 | J9: ='Novel foods, input data'!$AB$6*'Agri ing'!$AR$27 -> 0.0012460278 | K9: 0 | L9: ='Novel foods, input data'!$AB$6*'Agri ing'!$AS$27 -> 8.5467492e-06 | M9: 0 | N9: 0 | O9: ='Novel foods, input data'!$D$6*'Emission factors'!$D$12+'Novel foods, input data'!$AH$6 -> 0.0003701015 | P9: 0 | Q9: 0 | R9: 0 | S9: 0 | T9: 0 | U9: 0 | V9: 0 | W9: 0 | X9: 0
A10: NF-01 | B10: Cultured Meat (Bos. Spp.) | C10: Novel food | D10: Israel | E10: IL | F10: CO2e | G10: =SUM(H10:X10) -> 17.194275 | H10: =H6+H7*CF_CH4_foss+H8*CF_CH4_bio+H9*CF_N2O -> 0.27204817 | I10: =I6+I7*CF_CH4_foss+I8*CF_CH4_bio+I9*CF_N2O -> 0.2183303 | J10: =J6+J7*CF_CH4_foss+J8*CF_CH4_bio+J9*CF_N2O -> 0.34016558 | K10: =K6+K7*CF_CH4_foss+K8*CF_CH4_bio+K9*CF_N2O -> 0 | L10: =L6+L7*CF_CH4_foss+L8*CF_CH4_bio+L9*CF_N2O -> 0.22523744 | M10: =M6+M7*CF_CH4_foss+M8*CF_CH4_bio+M9*CF_N2O -> 0 | N10: =N6+N7*CF_CH4_foss+N8*CF_CH4_bio+N9*CF_N2O -> 0 | O10: =O6+O7*CF_CH4_foss+O8*CF_CH4_bio+O9*CF_N2O -> 16.138494 | ... T10: =T6+T7*CF_CH4_foss+T8*CF_CH4_bio+T9*CF_N2O -> 0 | W10: =W6+W7*CF_CH4_foss+W8*CF_CH4_bio+W9*CF_N2O -> 0 | X10: =X6+X7*CF_CH4_foss+X8*CF_CH4_bio+X9*CF_N2O -> 0
A11: NF-01 | B11: Cultured Meat (Bos. Spp.) | C11: Novel food | D11: Netherlands | E11: NL | F11: CO2 | G11: =SUM(H11:X11) -> 3.5498417 | H11: ='Novel foods, input data'!$AB$6*'Agri ing'!$AF$27 -> 0.16530307 | I11: ='Novel foods, input data'!$AB$6*'Agri ing'!$AG$27 -> 0.19564101 | J11: 0 | K11: 0 | L11: ='Novel foods, input data'!$AB$6*'Agri ing'!$AH$27 -> 0.21637121 | M11: 0 | N11: 0 | O11: ='Novel foods, input data'!$D$6*'Emission factors'!$B$7+'Novel foods, input data'!$AF$6 -> 2.9725264 | P11: 0 | Q11: 0 | R11: 0 | S11: 0 | T11: 0 | U11: 0 | V11: 0 | W11: 0 | X11: 0
A12: NF-01 | B12: Cultured Meat (Bos. Spp.) | C12: Novel food | D12: Netherlands | E12: NL | F12: CH4, fossil | G12: =SUM(H12:X12) -> 0.0070766997 | H12: ='Novel foods, input data'!$AB$6*'Agri ing'!$AJ$27 -> 0.00028384273 | I12: ='Novel foods, input data'!$AB$6*'Agri ing'!$AK$27 -> 0.00068836653 | J12: 0 | K12: 0 | L12: ='Novel foods, input data'!$AB$6*'Agri ing'!$AL$27 -> 0.00021922736 | M12: 0 | N12: 0 | O12: ='Novel foods, input data'!$D$6*'Emission factors'!$C$7+'Novel foods, input data'!$AG$6 -> 0.0058852631 | P12: 0 | Q12: 0 | R12: 0 | S12: 0 | T12: 0 | U12: 0 | V12: 0 | W12: 0 | X12: 0
A13: NF-01 | B13: Cultured Meat (Bos. Spp.) | C13: Novel food | D13: Netherlands | E13: NL | F13: CH4, biogenic | G13: =SUM(H13:T13)+SUM(W13:X13) -> 0 | H13: 0 | I13: 0 | J13: 0 | K13: 0 | L13: 0 | M13: 0 | N13: 0 | O13: 0 | P13: 0 | Q13: 0 | R13: 0 | S13: 0 | T13: 0 | U13: 0 | V13: 0 | W13: 0 | X13: 0
A14: NF-01 | B14: Cultured Meat (Bos. Spp.) | C14: Novel food | D14: Netherlands | E14: NL | F14: N2O | G14: =SUM(H14:T14)+SUM(W14:X14) -> 0.0017419081 | H14: ='Novel foods, input data'!$AB$6*'Agri ing'!$AP$27 -> 0.00036002414 | I14: ='Novel foods, input data'!$AB$6*'Agri ing'!$AQ$27 -> 7.9705599e-06 | J14: ='Novel foods, input data'!$AB$6*'Agri ing'!$AR$27 -> 0.0012460278 | K14: 0 | L14: ='Novel foods, input data'!$AB$6*'Agri ing'!$AS$27 -> 8.5467492e-06 | M14: 0 | N14: 0 | O14: ='Novel foods, input data'!$D$6*'Emission factors'!$D$7+'Novel foods, input data'!$AH$6 -> 0.00011933884 | P14: 0 | Q14: 0 | R14: 0 | S14: 0 | T14: 0 | U14: 0 | V14: 0 | W14: 0 | X14: 0
A15: NF-01 | B15: Cultured Meat (Bos. Spp.) | C15: Novel food | D15: Netherlands | E15: NL | F15: CO2e | G15: =SUM(H15:X15) -> 4.2362683 | H15: =H11+H12*CF_CH4_foss+H13*CF_CH4_bio+H14*CF_N2O -> 0.27204817 | I15: =I11+I12*CF_CH4_foss+I13*CF_CH4_bio+I14*CF_N2O -> 0.2183303 | J15: =J11+J12*CF_CH4_foss+J13*CF_CH4_bio+J14*CF_N2O -> 0.34016558 | K15: =K11+K12*CF_CH4_foss+K13*CF_CH4_bio+K14*CF_N2O -> 0 | L15: =L11+L12*CF_CH4_foss+L13*CF_CH4_bio+L14*CF_N2O -> 0.22523744 | M15: =M11+M12*CF_CH4_foss+M13*CF_CH4_bio+M14*CF_N2O -> 0 | N15: =N11+N12*CF_CH4_foss+N13*CF_CH4_bio+N14*CF_N2O -> 0 | O15: =O11+O12*CF_CH4_foss+O13*CF_CH4_bio+O14*CF_N2O -> 3.1804868 | ... T15: =T11+T12*CF_CH4_foss+T13*CF_CH4_bio+T14*CF_N2O -> 0 | W15: =W11+W12*CF_CH4_foss+W13*CF_CH4_bio+W14*CF_N2O -> 0 | X15: =X11+X12*CF_CH4_foss+X13*CF_CH4_bio+X14*CF_N2O -> 0
A16: NF-01 | B16: Cultured Meat (Bos. Spp.) | C16: Novel food | D16: Sweden | E16: SE | F16: CO2 | G16: =SUM(H16:X16) -> 1.1066169 | H16: ='Novel foods, input data'!$AB$6*'Agri ing'!$AF$27 -> 0.16530307 | I16: ='Novel foods, input data'!$AB$6*'Agri ing'!$AG$27 -> 0.19564101 | J16: 0 | K16: 0 | L16: ='Novel foods, input data'!$AB$6*'Agri ing'!$AH$27 -> 0.21637121 | M16: 0 | N16: 0 | O16: ='Novel foods, input data'!$D$6*'Emission factors'!$B$11+'Novel foods, input data'!$AF$6 -> 0.52930157 | P16: 0 | Q16: 0 | R16: 0 | S16: 0 | T16: 0 | U16: 0 | V16: 0 | W16: 0 | X16: 0
A17: NF-01 | B17: Cultured Meat (Bos. Spp.) | C17: Novel food | D17: Sweden | E17: SE | F17: CH4, fossil | G17: =SUM(H17:X17) -> 0.0017795518 | H17: ='Novel foods, input data'!$AB$6*'Agri ing'!$AJ$27 -> 0.00028384273 | I17: ='Novel foods, input data'!$AB$6*'Agri ing'!$AK$27 -> 0.00068836653 | J17: 0 | K17: 0 | L17: ='Novel foods, input data'!$AB$6*'Agri ing'!$AL$27 -> 0.00021922736 | M17: 0 | N17: 0 | O17: ='Novel foods, input data'!$D$6*'Emission factors'!$C$11+'Novel foods, input data'!$AG$6 -> 0.00058811521 | P17: 0 | Q17: 0 | R17: 0 | S17: 0 | T17: 0 | U17: 0 | V17: 0 | W17: 0 | X17: 0
A18: NF-01 | B18: Cultured Meat (Bos. Spp.) | C18: Novel food | D18: Sweden | E18: SE | F18: CH4, biogenic | G18: =SUM(H18:T18)+SUM(W18:X18) -> 0 | H18: 0 | I18: 0 | J18: 0 | K18: 0 | L18: 0 | M18: 0 | N18: 0 | O18: 0 | P18: 0 | Q18: 0 | R18: 0 | S18: 0 | T18: 0 | U18: 0 | V18: 0 | W18: 0 | X18: 0
A19: NF-01 | B19: Cultured Meat (Bos. Spp.) | C19: Novel food | D19: Sweden | E19: SE | F19: N2O | G19: =SUM(H19:T19)+SUM(W19:X19) -> 0.0016714742 | H19: ='Novel foods, input data'!$AB$6*'Agri ing'!$AP$27 -> 0.00036002414 | I19: ='Novel foods, input data'!$AB$6*'Agri ing'!$AQ$27 -> 7.9705599e-06 | J19: ='Novel foods, input data'!$AB$6*'Agri ing'!$AR$27 -> 0.0012460278 | K19: 0 | L19: ='Novel foods, input data'!$AB$6*'Agri ing'!$AS$27 -> 8.5467492e-06 | M19: 0 | N19: 0 | O19: ='Novel foods, input data'!$D$6*'Emission factors'!$D$11+'Novel foods, input data'!$AH$6 -> 4.8905009e-05 | P19: 0 | Q19: 0 | R19: 0 | S19: 0 | T19: 0 | U19: 0 | V19: 0 | W19: 0 | X19: 0
A20: NF-01 | B20: Cultured Meat (Bos. Spp.) | C20: Novel food | D20: Sweden | E20: SE | F20: CO2e | G20: =SUM(H20:X20) -> 1.61596 | H20: =H16+H17*CF_CH4_foss+H18*CF_CH4_bio+H19*CF_N2O -> 0.27204817 | I20: =I16+I17*CF_CH4_foss+I18*CF_CH4_bio+I19*CF_N2O -> 0.2183303 | J20: =J16+J17*CF_CH4_foss+J18*CF_CH4_bio+J19*CF_N2O -> 0.34016558 | K20: =K16+K17*CF_CH4_foss+K18*CF_CH4_bio+K19*CF_N2O -> 0 | L20: =L16+L17*CF_CH4_foss+L18*CF_CH4_bio+L19*CF_N2O -> 0.22523744 | M20: =M16+M17*CF_CH4_foss+M18*CF_CH4_bio+M19*CF_N2O -> 0 | N20: =N16+N17*CF_CH4_foss+N18*CF_CH4_bio+N19*CF_N2O -> 0 | O20: =O16+O17*CF_CH4_foss+O18*CF_CH4_bio+O19*CF_N2O -> 0.56017848 | ... T20: =T16+T17*CF_CH4_foss+T18*CF_CH4_bio+T19*CF_N2O -> 0 | W20: =W16+W17*CF_CH4_foss+W18*CF_CH4_bio+W19*CF_N2O -> 0 | X20: =X16+X17*CF_CH4_foss+X18*CF_CH4_bio+X19*CF_N2O -> 0
A21: NF-01 | B21: Cultured Meat (Bos. Spp.) | C21: Novel food | D21: USA | E21: US | F21: CO2 | G21: =SUM(H21:X21) -> 3.7219655 | H21: ='Novel foods, input data'!$AB$6*'Agri ing'!$AF$27 -> 0.16530307 | I21: ='Novel foods, input data'!$AB$6*'Agri ing'!$AG$27 -> 0.19564101 | J21: 0 | K21: 0 | L21: ='Novel foods, input data'!$AB$6*'Agri ing'!$AH$27 -> 0.21637121 | M21: 0 | N21: 0 | O21: ='Novel foods, input data'!$D$6*'Emission factors'!$B$13+'Novel foods, input data'!$AF$6 -> 3.1446502 | P21: 0 | Q21: 0 | R21: 0 | S21: 0 | T21: 0 | U21: 0 | V21: 0 | W21: 0 | X21: 0
A22: NF-01 | B22: Cultured Meat (Bos. Spp.) | C22: Novel food | D22: USA | E22: US | F22: CH4, fossil | G22: =SUM(H22:X22) -> 0.0060709677 | H22: ='Novel foods, input data'!$AB$6*'Agri ing'!$AJ$27 -> 0.00028384273 | I22: ='Novel foods, input data'!$AB$6*'Agri ing'!$AK$27 -> 0.00068836653 | J22: 0 | K22: 0 | L22: ='Novel foods, input data'!$AB$6*'Agri ing'!$AL$27 -> 0.00021922736 | M22: 0 | N22: 0 | O22: ='Novel foods, input data'!$D$6*'Emission factors'!$C$13+'Novel foods, input data'!$AG$6 -> 0.0048795311 | P22: 0 | Q22: 0 | R22: 0 | S22: 0 | T22: 0 | U22: 0 | V22: 0 | W22: 0 | X22: 0
A23: NF-01 | B23: Cultured Meat (Bos. Spp.) | C23: Novel food | D23: USA | E23: US | F23: CH4, biogenic | G23: =SUM(H23:T23)+SUM(W23:X23) -> 0 | H23: 0 | I23: 0 | J23: 0 | K23: 0 | L23: 0 | M23: 0 | N23: 0 | O23: 0 | P23: 0 | Q23: 0 | R23: 0 | S23: 0 | T23: 0 | U23: 0 | V23: 0 | W23: 0 | X23: 0
A24: NF-01 | B24: Cultured Meat (Bos. Spp.) | C24: Novel food | D24: USA | E24: US | F24: N2O | G24: =SUM(H24:T24)+SUM(W24:X24) -> 0.001711293 | H24: ='Novel foods, input data'!$AB$6*'Agri ing'!$AP$27 -> 0.00036002414 | I24: ='Novel foods, input data'!$AB$6*'Agri ing'!$AQ$27 -> 7.9705599e-06 | J24: ='Novel foods, input data'!$AB$6*'Agri ing'!$AR$27 -> 0.0012460278 | K24: 0 | L24: ='Novel foods, input data'!$AB$6*'Agri ing'!$AS$27 -> 8.5467492e-06 | M24: 0 | N24: 0 | O24: ='Novel foods, input data'!$D$6*'Emission factors'!$D$13+'Novel foods, input data'!$AH$6 -> 8.8723775e-05 | P24: 0 | Q24: 0 | R24: 0 | S24: 0 | T24: 0 | U24: 0 | V24: 0 | W24: 0 | X24: 0
A25: NF-01 | B25: Cultured Meat (Bos. Spp.) | C25: Novel food | D25: USA | E25: US | F25: CO2e | G25: =SUM(H25:X25) -> 4.3700633 | H25: =H21+H22*CF_CH4_foss+H23*CF_CH4_bio+H24*CF_N2O -> 0.27204817 | I25: =I21+I22*CF_CH4_foss+I23*CF_CH4_bio+I24*CF_N2O -> 0.2183303 | J25: =J21+J22*CF_CH4_foss+J23*CF_CH4_bio+J24*CF_N2O -> 0.34016558 | K25: =K21+K22*CF_CH4_foss+K23*CF_CH4_bio+K24*CF_N2O -> 0 | L25: =L21+L22*CF_CH4_foss+L23*CF_CH4_bio+L24*CF_N2O -> 0.22523744 | M25: =M21+M22*CF_CH4_foss+M23*CF_CH4_bio+M24*CF_N2O -> 0 | N25: =N21+N22*CF_CH4_foss+N23*CF_CH4_bio+N24*CF_N2O -> 0 | O25: =O21+O22*CF_CH4_foss+O23*CF_CH4_bio+O24*CF_N2O -> 3.3142818 | ... T25: =T21+T22*CF_CH4_foss+T23*CF_CH4_bio+T24*CF_N2O -> 0 | W25: =W21+W22*CF_CH4_foss+W23*CF_CH4_bio+W24*CF_N2O -> 0 | X25: =X21+X22*CF_CH4_foss+X23*CF_CH4_bio+X24*CF_N2O -> 0
A26: NF-02 | B26: Microbial Milk (T. reesei) | C26: Novel food | D26: Denmark | E26: DK | F26: CO2 | G26: =SUM(H26:X26) -> 1.054122 | H26: ='Novel foods, input data'!$AB$7*'Agri ing'!$AF$27 -> 0.083530581 | I26: ='Novel foods, input data'!$AB$7*'Agri ing'!$AG$27 -> 0.098860883 | J26: 0 | K26: 0 | L26: ='Novel foods, input data'!$AB$7*'Agri ing'!$AH$27 -> 0.10933622 | M26: 0 | N26: 0 | O26: ='Novel foods, input data'!$D$7*'Emission factors'!$B$6+'Novel foods, input data'!$AF$7 -> 0.76239434 | P26: 0 | Q26: 0 | R26: 0 | S26: 0 | T26: 0 | U26: 0 | V26: 0 | W26: 0 | X26: 0
A27: NF-02 | B27: Microbial Milk (T. reesei) | C27: Novel food | D27: Denmark | E27: DK | F27: CH4, fossil | G27: =SUM(H27:X27) -> 0.001308799 | H27: ='Novel foods, input data'!$AB$7*'Agri ing'!$AJ$27 -> 0.00014343078 | I27: ='Novel foods, input data'!$AB$7*'Agri ing'!$AK$27 -> 0.00034784385 | J27: 0 | K27: 0 | L27: ='Novel foods, input data'!$AB$7*'Agri ing'!$AL$27 -> 0.00011077948 | M27: 0 | N27: 0 | O27: ='Novel foods, input data'!$D$7*'Emission factors'!$C$6+'Novel foods, input data'!$AG$7 -> 0.00070674494 | P27: 0 | Q27: 0 | R27: 0 | S27: 0 | T27: 0 | U27: 0 | V27: 0 | W27: 0 | X27: 0
A28: NF-02 | B28: Microbial Milk (T. reesei) | C28: Novel food | D28: Denmark | E28: DK | F28: CH4, biogenic | G28: =SUM(H28:T28)+SUM(W28:X28) -> 0 | H28: 0 | I28: 0 | J28: 0 | K28: 0 | L28: 0 | M28: 0 | N28: 0 | O28: 0 | P28: 0 | Q28: 0 | R28: 0 | S28: 0 | T28: 0 | U28: 0 | V28: 0 | W28: 0 | X28: 0
A29: NF-02 | B29: Microbial Milk (T. reesei) | C29: Novel food | D29: Denmark | E29: DK | F29: N2O | G29: =SUM(H29:T29)+SUM(W29:X29) -> 0.00084627547 | H29: ='Novel foods, input data'!$AB$7*'Agri ing'!$AP$27 -> 0.0001819266 | I29: ='Novel foods, input data'!$AB$7*'Agri ing'!$AQ$27 -> 4.0276656e-06 | J29: ='Novel foods, input data'!$AB$7*'Agri ing'!$AR$27 -> 0.00062963999 | K29: 0 | L29: ='Novel foods, input data'!$AB$7*'Agri ing'!$AS$27 -> 4.3188243e-06 | M29: 0 | N29: 0 | O29: ='Novel foods, input data'!$D$7*'Emission factors'!$D$6+'Novel foods, input data'!$AH$7 -> 2.63624e-05 | P29: 0 | Q29: 0 | R29: 0 | S29: 0 | T29: 0 | U29: 0 | V29: 0 | W29: 0 | X29: 0
A30: NF-02 | B30: Microbial Milk (T. reesei) | C30: Novel food | D30: Denmark | E30: DK | F30: CO2e | G30: =SUM(H30:X30) -> 1.3241574 | H30: =H26+H27*CF_CH4_foss+H28*CF_CH4_bio+H29*CF_N2O -> 0.13747078 | I30: =I26+I27*CF_CH4_foss+I28*CF_CH4_bio+I29*CF_N2O -> 0.11032618 | J30: =J26+J27*CF_CH4_foss+J28*CF_CH4_bio+J29*CF_N2O -> 0.17189172 | K30: =K26+K27*CF_CH4_foss+K28*CF_CH4_bio+K29*CF_N2O -> 0 | L30: =L26+L27*CF_CH4_foss+L28*CF_CH4_bio+L29*CF_N2O -> 0.11381649 | M30: =M26+M27*CF_CH4_foss+M28*CF_CH4_bio+M29*CF_N2O -> 0 | N30: =N26+N27*CF_CH4_foss+N28*CF_CH4_bio+N29*CF_N2O -> 0 | O30: =O26+O27*CF_CH4_foss+O28*CF_CH4_bio+O29*CF_N2O -> 0.79065228 | ... T30: =T26+T27*CF_CH4_foss+T28*CF_CH4_bio+T29*CF_N2O -> 0 | W30: =W26+W27*CF_CH4_foss+W28*CF_CH4_bio+W29*CF_N2O -> 0 | X30: =X26+X27*CF_CH4_foss+X28*CF_CH4_bio+X29*CF_N2O -> 0
A31: NF-02 | B31: Microbial Milk (T. reesei) | C31: Novel food | D31: Germany | E31: DE | F31: CO2 | G31: =SUM(H31:X31) -> 1.1826885 | H31: ='Novel foods, input data'!$AB$7*'Agri ing'!$AF$27 -> 0.083530581 | I31: ='Novel foods, input data'!$AB$7*'Agri ing'!$AG$27 -> 0.098860883 | J31: 0 | K31: 0 | L31: ='Novel foods, input data'!$AB$7*'Agri ing'!$AH$27 -> 0.10933622 | M31: 0 | N31: 0 | O31: ='Novel foods, input data'!$D$7*'Emission factors'!$B$8+'Novel foods, input data'!$AF$7 -> 0.89096082 | P31: 0 | Q31: 0 | R31: 0 | S31: 0 | T31: 0 | U31: 0 | V31: 0 | W31: 0 | X31: 0
A32: NF-02 | B32: Microbial Milk (T. reesei) | C32: Novel food | D32: Germany | E32: DE | F32: CH4, fossil | G32: =SUM(H32:X32) -> 0.0018281417 | H32: ='Novel foods, input data'!$AB$7*'Agri ing'!$AJ$27 -> 0.00014343078 | I32: ='Novel foods, input data'!$AB$7*'Agri ing'!$AK$27 -> 0.00034784385 | J32: 0 | K32: 0 | L32: ='Novel foods, input data'!$AB$7*'Agri ing'!$AL$27 -> 0.00011077948 | M32: 0 | N32: 0 | O32: ='Novel foods, input data'!$D$7*'Emission factors'!$C$8+'Novel foods, input data'!$AG$7 -> 0.0012260876 | P32: 0 | Q32: 0 | R32: 0 | S32: 0 | T32: 0 | U32: 0 | V32: 0 | W32: 0 | X32: 0
A33: NF-02 | B33: Microbial Milk (T. reesei) | C33: Novel food | D33: Germany | E33: DE | F33: CH4, biogenic | G33: =SUM(H33:T33)+SUM(W33:X33) -> 0 | H33: 0 | I33: 0 | J33: 0 | K33: 0 | L33: 0 | M33: 0 | N33: 0 | O33: 0 | P33: 0 | Q33: 0 | R33: 0 | S33: 0 | T33: 0 | U33: 0 | V33: 0 | W33: 0 | X33: 0
A34: NF-02 | B34: Microbial Milk (T. reesei) | C34: Novel food | D34: Germany | E34: DE | F34: N2O | G34: =SUM(H34:T34)+SUM(W34:X34) -> 0.00084861989 | H34: ='Novel foods, input data'!$AB$7*'Agri ing'!$AP$27 -> 0.0001819266 | I34: ='Novel foods, input data'!$AB$7*'Agri ing'!$AQ$27 -> 4.0276656e-06 | J34: ='Novel foods, input data'!$AB$7*'Agri ing'!$AR$27 -> 0.00062963999 | K34: 0 | L34: ='Novel foods, input data'!$AB$7*'Agri ing'!$AS$27 -> 4.3188243e-06 | M34: 0 | N34: 0 | O34: ='Novel foods, input data'!$D$7*'Emission factors'!$D$8+'Novel foods, input data'!$AH$7 -> 2.8706814e-05 | P34: 0 | Q34: 0 | R34: 0 | S34: 0 | T34: 0 | U34: 0 | V34: 0 | W34: 0 | X34: 0
A35: NF-02 | B35: Microbial Milk (T. reesei) | C35: Novel food | D35: Germany | E35: DE | F35: CO2e | G35: =SUM(H35:X35) -> 1.4688404 | H35: =H31+H32*CF_CH4_foss+H33*CF_CH4_bio+H34*CF_N2O -> 0.13747078 | I35: =I31+I32*CF_CH4_foss+I33*CF_CH4_bio+I34*CF_N2O -> 0.11032618 | J35: =J31+J32*CF_CH4_foss+J33*CF_CH4_bio+J34*CF_N2O -> 0.17189172 | K35: =K31+K32*CF_CH4_foss+K33*CF_CH4_bio+K34*CF_N2O -> 0 | L35: =L31+L32*CF_CH4_foss+L33*CF_CH4_bio+L34*CF_N2O -> 0.11381649 | M35: =M31+M32*CF_CH4_foss+M33*CF_CH4_bio+M34*CF_N2O -> 0 | N35: =N31+N32*CF_CH4_foss+N33*CF_CH4_bio+N34*CF_N2O -> 0 | O35: =O31+O32*CF_CH4_foss+O33*CF_CH4_bio+O34*CF_N2O -> 0.93533519 | ... T35: =T31+T32*CF_CH4_foss+T33*CF_CH4_bio+T34*CF_N2O -> 0 | W35: =W31+W32*CF_CH4_foss+W33*CF_CH4_bio+W34*CF_N2O -> 0 | X35: =X31+X32*CF_CH4_foss+X33*CF_CH4_bio+X34*CF_N2O -> 0
A36: NF-02 | B36: Microbial Milk (T. reesei) | C36: Novel food | D36: Sweden | E36: SE | F36: CO2 | G36: =SUM(H36:X36) -> 0.66404222 | H36: ='Novel foods, input data'!$AB$7*'Agri ing'!$AF$27 -> 0.083530581 | I36: ='Novel foods, input data'!$AB$7*'Agri ing'!$AG$27 -> 0.098860883 | J36: 0 | K36: 0 | L36: ='Novel foods, input data'!$AB$7*'Agri ing'!$AH$27 -> 0.10933622 | M36: 0 | N36: 0 | O36: ='Novel foods, input data'!$D$7*'Emission factors'!$B$11+'Novel foods, input data'!$AF$7 -> 0.37231454 | P36: 0 | Q36: 0 | R36: 0 | S36: 0 | T36: 0 | U36: 0 | V36: 0 | W36: 0 | X36: 0
A37: NF-02 | B37: Microbial Milk (T. reesei) | C37: Novel food | D37: Sweden | E37: SE | F37: CH4, fossil | G37: =SUM(H37:X37) -> 0.00073795969 | H37: ='Novel foods, input data'!$AB$7*'Agri ing'!$AJ$27 -> 0.00014343078 | I37: ='Novel foods, input data'!$AB$7*'Agri ing'!$AK$27 -> 0.00034784385 | J37: 0 | K37: 0 | L37: ='Novel foods, input data'!$AB$7*'Agri ing'!$AL$27 -> 0.00011077948 | M37: 0 | N37: 0 | O37: ='Novel foods, input data'!$D$7*'Emission factors'!$C$11+'Novel foods, input data'!$AG$7 -> 0.00013590558 | P37: 0 | Q37: 0 | R37: 0 | S37: 0 | T37: 0 | U37: 0 | V37: 0 | W37: 0 | X37: 0
A38: NF-02 | B38: Microbial Milk (T. reesei) | C38: Novel food | D38: Sweden | E38: SE | F38: CH4, biogenic | G38: =SUM(H38:T38)+SUM(W38:X38) -> 0 | H38: 0 | I38: 0 | J38: 0 | K38: 0 | L38: 0 | M38: 0 | N38: 0 | O38: 0 | P38: 0 | Q38: 0 | R38: 0 | S38: 0 | T38: 0 | U38: 0 | V38: 0 | W38: 0 | X38: 0
A39: NF-02 | B39: Microbial Milk (T. reesei) | C39: Novel food | D39: Sweden | E39: SE | F39: N2O | G39: =SUM(H39:T39)+SUM(W39:X39) -> 0.00083121437 | H39: ='Novel foods, input data'!$AB$7*'Agri ing'!$AP$27 -> 0.0001819266 | I39: ='Novel foods, input data'!$AB$7*'Agri ing'!$AQ$27 -> 4.0276656e-06 | J39: ='Novel foods, input data'!$AB$7*'Agri ing'!$AR$27 -> 0.00062963999 | K39: 0 | L39: ='Novel foods, input data'!$AB$7*'Agri ing'!$AS$27 -> 4.3188243e-06 | M39: 0 | N39: 0 | O39: ='Novel foods, input data'!$D$7*'Emission factors'!$D$11+'Novel foods, input data'!$AH$7 -> 1.1301295e-05 | P39: 0 | Q39: 0 | R39: 0 | S39: 0 | T39: 0 | U39: 0 | V39: 0 | W39: 0 | X39: 0
A40: NF-02 | B40: Microbial Milk (T. reesei) | C40: Novel food | D40: Sweden | E40: SE | F40: CO2e | G40: =SUM(H40:X40) -> 0.91295494 | H40: =H36+H37*CF_CH4_foss+H38*CF_CH4_bio+H39*CF_N2O -> 0.13747078 | I40: =I36+I37*CF_CH4_foss+I38*CF_CH4_bio+I39*CF_N2O -> 0.11032618 | J40: =J36+J37*CF_CH4_foss+J38*CF_CH4_bio+J39*CF_N2O -> 0.17189172 | K40: =K36+K37*CF_CH4_foss+K38*CF_CH4_bio+K39*CF_N2O -> 0 | L40: =L36+L37*CF_CH4_foss+L38*CF_CH4_bio+L39*CF_N2O -> 0.11381649 | M40: =M36+M37*CF_CH4_foss+M38*CF_CH4_bio+M39*CF_N2O -> 0 | N40: =N36+N37*CF_CH4_foss+N38*CF_CH4_bio+N39*CF_N2O -> 0 | O40: =O36+O37*CF_CH4_foss+O38*CF_CH4_bio+O39*CF_N2O -> 0.37944978 | ... T40: =T36+T37*CF_CH4_foss+T38*CF_CH4_bio+T39*CF_N2O -> 0 | W40: =W36+W37*CF_CH4_foss+W38*CF_CH4_bio+W39*CF_N2O -> 0 | X40: =X36+X37*CF_CH4_foss+X38*CF_CH4_bio+X39*CF_N2O -> 0
A41: NF-02 | B41: Microbial Milk (T. reesei) | C41: Novel food | D41: Switzerland | E41: CH | F41: CO2 | G41: =SUM(H41:X41) -> 0.66404222 | H41: ='Novel foods, input data'!$AB$7*'Agri ing'!$AF$27 -> 0.083530581 | I41: ='Novel foods, input data'!$AB$7*'Agri ing'!$AG$27 -> 0.098860883 | J41: 0 | K41: 0 | L41: ='Novel foods, input data'!$AB$7*'Agri ing'!$AH$27 -> 0.10933622 | M41: 0 | N41: 0 | O41: ='Novel foods, input data'!$D$7*'Emission factors'!$B$9+'Novel foods, input data'!$AF$7 -> 0.37231454 | P41: 0 | Q41: 0 | R41: 0 | S41: 0 | T41: 0 | U41: 0 | V41: 0 | W41: 0 | X41: 0
A42: NF-02 | B42: Microbial Milk (T. reesei) | C42: Novel food | D42: Switzerland | E42: CH | F42: CH4, fossil | G42: =SUM(H42:X42) -> 0.00073795969 | H42: ='Novel foods, input data'!$AB$7*'Agri ing'!$AJ$27 -> 0.00014343078 | I42: ='Novel foods, input data'!$AB$7*'Agri ing'!$AK$27 -> 0.00034784385 | J42: 0 | K42: 0 | L42: ='Novel foods, input data'!$AB$7*'Agri ing'!$AL$27 -> 0.00011077948 | M42: 0 | N42: 0 | O42: ='Novel foods, input data'!$D$7*'Emission factors'!$C$9+'Novel foods, input data'!$AG$7 -> 0.00013590558 | P42: 0 | Q42: 0 | R42: 0 | S42: 0 | T42: 0 | U42: 0 | V42: 0 | W42: 0 | X42: 0
A43: NF-02 | B43: Microbial Milk (T. reesei) | C43: Novel food | D43: Switzerland | E43: CH | F43: CH4, biogenic | G43: =SUM(H43:T43)+SUM(W43:X43) -> 0 | H43: 0 | I43: 0 | J43: 0 | K43: 0 | L43: 0 | M43: 0 | N43: 0 | O43: 0 | P43: 0 | Q43: 0 | R43: 0 | S43: 0 | T43: 0 | U43: 0 | V43: 0 | W43: 0 | X43: 0
A44: NF-02 | B44: Microbial Milk (T. reesei) | C44: Novel food | D44: Switzerland | E44: CH | F44: N2O | G44: =SUM(H44:T44)+SUM(W44:X44) -> 0.00083121437 | H44: ='Novel foods, input data'!$AB$7*'Agri ing'!$AP$27 -> 0.0001819266 | I44: ='Novel foods, input data'!$AB$7*'Agri ing'!$AQ$27 -> 4.0276656e-06 | J44: ='Novel foods, input data'!$AB$7*'Agri ing'!$AR$27 -> 0.00062963999 | K44: 0 | L44: ='Novel foods, input data'!$AB$7*'Agri ing'!$AS$27 -> 4.3188243e-06 | M44: 0 | N44: 0 | O44: ='Novel foods, input data'!$D$7*'Emission factors'!$D$9+'Novel foods, input data'!$AH$7 -> 1.1301295e-05 | P44: 0 | Q44: 0 | R44: 0 | S44: 0 | T44: 0 | U44: 0 | V44: 0 | W44: 0 | X44: 0
A45: NF-02 | B45: Microbial Milk (T. reesei) | C45: Novel food | D45: Switzerland | E45: CH | F45: CO2e | G45: =SUM(H45:X45) -> 0.91295494 | H45: =H41+H42*CF_CH4_foss+H43*CF_CH4_bio+H44*CF_N2O -> 0.13747078 | I45: =I41+I42*CF_CH4_foss+I43*CF_CH4_bio+I44*CF_N2O -> 0.11032618 | J45: =J41+J42*CF_CH4_foss+J43*CF_CH4_bio+J44*CF_N2O -> 0.17189172 | K45: =K41+K42*CF_CH4_foss+K43*CF_CH4_bio+K44*CF_N2O -> 0 | L45: =L41+L42*CF_CH4_foss+L43*CF_CH4_bio+L44*CF_N2O -> 0.11381649 | M45: =M41+M42*CF_CH4_foss+M43*CF_CH4_bio+M44*CF_N2O -> 0 | N45: =N41+N42*CF_CH4_foss+N43*CF_CH4_bio+N44*CF_N2O -> 0 | O45: =O41+O42*CF_CH4_foss+O43*CF_CH4_bio+O44*CF_N2O -> 0.37944978 | ... T45: =T41+T42*CF_CH4_foss+T43*CF_CH4_bio+T44*CF_N2O -> 0 | W45: =W41+W42*CF_CH4_foss+W43*CF_CH4_bio+W44*CF_N2O -> 0 | X45: =X41+X42*CF_CH4_foss+X43*CF_CH4_bio+X44*CF_N2O -> 0
A46: NF-02 | B46: Microbial Milk (T. reesei) | C46: Novel food | D46: USA | E46: US | F46: CO2 | G46: =SUM(H46:X46) -> 1.2684144 | H46: ='Novel foods, input data'!$AB$7*'Agri ing'!$AF$27 -> 0.083530581 | I46: ='Novel foods, input data'!$AB$7*'Agri ing'!$AG$27 -> 0.098860883 | J46: 0 | K46: 0 | L46: ='Novel foods, input data'!$AB$7*'Agri ing'!$AH$27 -> 0.10933622 | M46: 0 | N46: 0 | O46: ='Novel foods, input data'!$D$7*'Emission factors'!$B$13+'Novel foods, input data'!$AF$7 -> 0.97668673 | P46: 0 | Q46: 0 | R46: 0 | S46: 0 | T46: 0 | U46: 0 | V46: 0 | W46: 0 | X46: 0
A47: NF-02 | B47: Microbial Milk (T. reesei) | C47: Novel food | D47: USA | E47: US | F47: CH4, fossil | G47: =SUM(H47:X47) -> 0.0017296487 | H47: ='Novel foods, input data'!$AB$7*'Agri ing'!$AJ$27 -> 0.00014343078 | I47: ='Novel foods, input data'!$AB$7*'Agri ing'!$AK$27 -> 0.00034784385 | J47: 0 | K47: 0 | L47: ='Novel foods, input data'!$AB$7*'Agri ing'!$AL$27 -> 0.00011077948 | M47: 0 | N47: 0 | O47: ='Novel foods, input data'!$D$7*'Emission factors'!$C$13+'Novel foods, input data'!$AG$7 -> 0.0011275946 | P47: 0 | Q47: 0 | R47: 0 | S47: 0 | T47: 0 | U47: 0 | V47: 0 | W47: 0 | X47: 0
A48: NF-02 | B48: Microbial Milk (T. reesei) | C48: Novel food | D48: USA | E48: US | F48: CH4, biogenic | G48: =SUM(H48:T48)+SUM(W48:X48) -> 0 | H48: 0 | I48: 0 | J48: 0 | K48: 0 | L48: 0 | M48: 0 | N48: 0 | O48: 0 | P48: 0 | Q48: 0 | R48: 0 | S48: 0 | T48: 0 | U48: 0 | V48: 0 | W48: 0 | X48: 0
A49: NF-02 | B49: Microbial Milk (T. reesei) | C49: Novel food | D49: USA | E49: US | F49: N2O | G49: =SUM(H49:T49)+SUM(W49:X49) -> 0.00084041596 | H49: ='Novel foods, input data'!$AB$7*'Agri ing'!$AP$27 -> 0.0001819266 | I49: ='Novel foods, input data'!$AB$7*'Agri ing'!$AQ$27 -> 4.0276656e-06 | J49: ='Novel foods, input data'!$AB$7*'Agri ing'!$AR$27 -> 0.00062963999 | K49: 0 | L49: ='Novel foods, input data'!$AB$7*'Agri ing'!$AS$27 -> 4.3188243e-06 | M49: 0 | N49: 0 | O49: ='Novel foods, input data'!$D$7*'Emission factors'!$D$13+'Novel foods, input data'!$AH$7 -> 2.0502881e-05 | P49: 0 | Q49: 0 | R49: 0 | S49: 0 | T49: 0 | U49: 0 | V49: 0 | W49: 0 | X49: 0
A50: NF-02 | B50: Microbial Milk (T. reesei) | C50: Novel food | D50: USA | E50: US | F50: CO2e | G50: =SUM(H50:X50) -> 1.5493915 | H50: =H46+H47*CF_CH4_foss+H48*CF_CH4_bio+H49*CF_N2O -> 0.13747078 | I50: =I46+I47*CF_CH4_foss+I48*CF_CH4_bio+I49*CF_N2O -> 0.11032618 | J50: =J46+J47*CF_CH4_foss+J48*CF_CH4_bio+J49*CF_N2O -> 0.17189172 | K50: =K46+K47*CF_CH4_foss+K48*CF_CH4_bio+K49*CF_N2O -> 0 | L50: =L46+L47*CF_CH4_foss+L48*CF_CH4_bio+L49*CF_N2O -> 0.11381649 | M50: =M46+M47*CF_CH4_foss+M48*CF_CH4_bio+M49*CF_N2O -> 0 | N50: =N46+N47*CF_CH4_foss+N48*CF_CH4_bio+N49*CF_N2O -> 0 | O50: =O46+O47*CF_CH4_foss+O48*CF_CH4_bio+O49*CF_N2O -> 1.0158863 | ... T50: =T46+T47*CF_CH4_foss+T48*CF_CH4_bio+T49*CF_N2O -> 0 | W50: =W46+W47*CF_CH4_foss+W48*CF_CH4_bio+W49*CF_N2O -> 0 | X50: =X46+X47*CF_CH4_foss+X48*CF_CH4_bio+X49*CF_N2O -> 0
A51: NF-03 | B51: Microbial Ovalbumin (T. reesei) | C51: Novel food | D51: Denmark | E51: DK | F51: CO2 | G51: =SUM(H51:X51) -> 5.4401856 | H51: ='Novel foods, input data'!$AB$8*'Agri ing'!$AF$27 -> 0.2129392 | I51: ='Novel foods, input data'!$AB$8*'Agri ing'!$AG$27 -> 0.25201976 | J51: 0 | K51: 0 | L51: ='Novel foods, input data'!$AB$8*'Agri ing'!$AH$27 -> 0.27872386 | M51: 0 | N51: 0 | O51: ='Novel foods, input data'!$D$8*'Emission factors'!$B$6+'Novel foods, input data'!$AF$8 -> 4.6965028 | P51: 0 | Q51: 0 | R51: 0 | S51: 0 | T51: 0 | U51: 0 | V51: 0 | W51: 0 | X51: 0
A52: NF-03 | B52: Microbial Ovalbumin (T. reesei) | C52: Novel food | D52: Denmark | E52: DK | F52: CH4, fossil | G52: =SUM(H52:X52) -> 0.004702669 | H52: ='Novel foods, input data'!$AB$8*'Agri ing'!$AJ$27 -> 0.00036563896 | I52: ='Novel foods, input data'!$AB$8*'Agri ing'!$AK$27 -> 0.00088673619 | J52: 0 | K52: 0 | L52: ='Novel foods, input data'!$AB$8*'Agri ing'!$AL$27 -> 0.00028240309 | M52: 0 | N52: 0 | O52: ='Novel foods, input data'!$D$8*'Emission factors'!$C$6+'Novel foods, input data'!$AG8 -> 0.0031678908 | P52: 0 | Q52: 0 | R52: 0 | S52: 0 | T52: 0 | U52: 0 | V52: 0 | W52: 0 | X52: 0
A53: NF-03 | B53: Microbial Ovalbumin (T. reesei) | C53: Novel food | D53: Denmark | E53: DK | F53: CH4, biogenic | G53: =SUM(H53:T53)+SUM(W53:X53) -> 0 | H53: 0 | I53: 0 | J53: 0 | K53: 0 | L53: 0 | M53: 0 | N53: 0 | O53: 0 | P53: 0 | Q53: 0 | R53: 0 | S53: 0 | T53: 0 | U53: 0 | V53: 0 | W53: 0 | X53: 0
A54: NF-03 | B54: Microbial Ovalbumin (T. reesei) | C54: Novel food | D54: Denmark | E54: DK | F54: N2O | G54: =SUM(H54:T54)+SUM(W54:X54) -> 0.0022083182 | H54: ='Novel foods, input data'!$AB$8*'Agri ing'!$AP$27 -> 0.0004637739 | I54: ='Novel foods, input data'!$AB$8*'Agri ing'!$AQ$27 -> 1.0267472e-05 | J54: ='Novel foods, input data'!$AB$8*'Agri ing'!$AR$27 -> 0.0016051011 | K54: 0 | L54: ='Novel foods, input data'!$AB$8*'Agri ing'!$AS$27 -> 1.1009704e-05 | M54: 0 | N54: 0 | O54: ='Novel foods, input data'!$D$8*'Emission factors'!$D$6+'Novel foods, input data'!$AH$8 -> 0.00011816597 | P54: 0 | Q54: 0 | R54: 0 | S54: 0 | T54: 0 | U54: 0 | V54: 0 | W54: 0 | X54: 0
A55: NF-03 | B55: Microbial Ovalbumin (T. reesei) | C55: Novel food | D55: Denmark | E55: DK | F55: CO2e | G55: =SUM(H55:X55) -> 6.183196 | H55: =H51+H52*CF_CH4_foss+H53*CF_CH4_bio+H54*CF_N2O -> 0.35044551 | I55: =I51+I52*CF_CH4_foss+I53*CF_CH4_bio+I54*CF_N2O -> 0.28124752 | J55: =J51+J52*CF_CH4_foss+J53*CF_CH4_bio+J54*CF_N2O -> 0.43819261 | K55: =K51+K52*CF_CH4_foss+K53*CF_CH4_bio+K54*CF_N2O -> 0 | L55: =L51+L52*CF_CH4_foss+L53*CF_CH4_bio+L54*CF_N2O -> 0.29014512 | M55: =M51+M52*CF_CH4_foss+M53*CF_CH4_bio+M54*CF_N2O -> 0 | N55: =N51+N52*CF_CH4_foss+N53*CF_CH4_bio+N54*CF_N2O -> 0 | O55: =O51+O52*CF_CH4_foss+O53*CF_CH4_bio+O54*CF_N2O -> 4.8231653 | ... T55: =T51+T52*CF_CH4_foss+T53*CF_CH4_bio+T54*CF_N2O -> 0 | W55: =W51+W52*CF_CH4_foss+W53*CF_CH4_bio+W54*CF_N2O -> 0 | X55: =X51+X52*CF_CH4_foss+X53*CF_CH4_bio+X54*CF_N2O -> 0
A56: NF-03 | B56: Microbial Ovalbumin (T. reesei) | C56: Novel food | D56: Germany | E56: DE | F56: CO2 | G56: =SUM(H56:X56) -> 6.0164679 | H56: ='Novel foods, input data'!$AB$8*'Agri ing'!$AF$27 -> 0.2129392 | I56: ='Novel foods, input data'!$AB$8*'Agri ing'!$AG$27 -> 0.25201976 | J56: 0 | K56: 0 | L56: ='Novel foods, input data'!$AB$8*'Agri ing'!$AH$27 -> 0.27872386 | M56: 0 | N56: 0 | O56: ='Novel foods, input data'!$D$8*'Emission factors'!$B$8+'Novel foods, input data'!$AF$8 -> 5.2727851 | P56: 0 | Q56: 0 | R56: 0 | S56: 0 | T56: 0 | U56: 0 | V56: 0 | W56: 0 | X56: 0
A57: NF-03 | B57: Microbial Ovalbumin (T. reesei) | C57: Novel food | D57: Germany | E57: DE | F57: CH4, fossil | G57: =SUM(H57:X57) -> 0.007030554 | H57: ='Novel foods, input data'!$AB$8*'Agri ing'!$AJ$27 -> 0.00036563896 | I57: ='Novel foods, input data'!$AB$8*'Agri ing'!$AK$27 -> 0.00088673619 | J57: 0 | K57: 0 | L57: ='Novel foods, input data'!$AB$8*'Agri ing'!$AL$27 -> 0.00028240309 | M57: 0 | N57: 0 | O57: ='Novel foods, input data'!$D$8*'Emission factors'!$C$8+'Novel foods, input data'!$AG$8 -> 0.0054957758 | P57: 0 | Q57: 0 | R57: 0 | S57: 0 | T57: 0 | U57: 0 | V57: 0 | W57: 0 | X57: 0
A58: NF-03 | B58: Microbial Ovalbumin (T. reesei) | C58: Novel food | D58: Germany | E58: DE | F58: CH4, biogenic | G58: =SUM(H58:T58)+SUM(W58:X58) -> 0 | H58: 0 | I58: 0 | J58: 0 | K58: 0 | L58: 0 | M58: 0 | N58: 0 | O58: 0 | P58: 0 | Q58: 0 | R58: 0 | S58: 0 | T58: 0 | U58: 0 | V58: 0 | W58: 0 | X58: 0
A59: NF-03 | B59: Microbial Ovalbumin (T. reesei) | C59: Novel food | D59: Germany | E59: DE | F59: N2O | G59: =SUM(H59:T59)+SUM(W59:X59) -> 0.0022188267 | H59: ='Novel foods, input data'!$AB$8*'Agri ing'!$AP$27 -> 0.0004637739 | I59: ='Novel foods, input data'!$AB$8*'Agri ing'!$AQ$27 -> 1.0267472e-05 | J59: ='Novel foods, input data'!$AB$8*'Agri ing'!$AR$27 -> 0.0016051011 | K59: 0 | L59: ='Novel foods, input data'!$AB$8*'Agri ing'!$AS$27 -> 1.1009704e-05 | M59: 0 | N59: 0 | O59: ='Novel foods, input data'!$D$8*'Emission factors'!$D$8+'Novel foods, input data'!$AH$8 -> 0.0001286745 | P59: 0 | Q59: 0 | R59: 0 | S59: 0 | T59: 0 | U59: 0 | V59: 0 | W59: 0 | X59: 0
A60: NF-03 | B60: Microbial Ovalbumin (T. reesei) | C60: Novel food | D60: Germany | E60: DE | F60: CO2e | G60: =SUM(H60:X60) -> 6.8317181 | H60: =H56+H57*CF_CH4_foss+H58*CF_CH4_bio+H59*CF_N2O -> 0.35044551 | I60: =I56+I57*CF_CH4_foss+I58*CF_CH4_bio+I59*CF_N2O -> 0.28124752 | J60: =J56+J57*CF_CH4_foss+J58*CF_CH4_bio+J59*CF_N2O -> 0.43819261 | K60: =K56+K57*CF_CH4_foss+K58*CF_CH4_bio+K59*CF_N2O -> 0 | L60: =L56+L57*CF_CH4_foss+L58*CF_CH4_bio+L59*CF_N2O -> 0.29014512 | M60: =M56+M57*CF_CH4_foss+M58*CF_CH4_bio+M59*CF_N2O -> 0 | N60: =N56+N57*CF_CH4_foss+N58*CF_CH4_bio+N59*CF_N2O -> 0 | O60: =O56+O57*CF_CH4_foss+O58*CF_CH4_bio+O59*CF_N2O -> 5.4716873 | ... T60: =T56+T57*CF_CH4_foss+T58*CF_CH4_bio+T59*CF_N2O -> 0 | W60: =W56+W57*CF_CH4_foss+W58*CF_CH4_bio+W59*CF_N2O -> 0 | X60: =X56+X57*CF_CH4_foss+X58*CF_CH4_bio+X59*CF_N2O -> 0
A61: NF-03 | B61: Microbial Ovalbumin (T. reesei) | C61: Novel food | D61: Sweden | E61: SE | F61: CO2 | G61: =SUM(H61:X61) -> 3.6917044 | H61: ='Novel foods, input data'!$AB$8*'Agri ing'!$AF$27 -> 0.2129392 | I61: ='Novel foods, input data'!$AB$8*'Agri ing'!$AG$27 -> 0.25201976 | J61: 0 | K61: 0 | L61: ='Novel foods, input data'!$AB$8*'Agri ing'!$AH$27 -> 0.27872386 | M61: 0 | N61: 0 | O61: ='Novel foods, input data'!$D$8*'Emission factors'!$B$11+'Novel foods, input data'!$AF$8 -> 2.9480216 | P61: 0 | Q61: 0 | R61: 0 | S61: 0 | T61: 0 | U61: 0 | V61: 0 | W61: 0 | X61: 0
A62: NF-03 | B62: Microbial Ovalbumin (T. reesei) | C62: Novel food | D62: Sweden | E62: SE | F62: CH4, fossil | G62: =SUM(H62:X62) -> 0.0021439571 | H62: ='Novel foods, input data'!$AB$8*'Agri ing'!$AJ$27 -> 0.00036563896 | I62: ='Novel foods, input data'!$AB$8*'Agri ing'!$AK$27 -> 0.00088673619 | J62: 0 | K62: 0 | L62: ='Novel foods, input data'!$AB$8*'Agri ing'!$AL$27 -> 0.00028240309 | M62: 0 | N62: 0 | O62: ='Novel foods, input data'!$D$8*'Emission factors'!$C$11+'Novel foods, input data'!$AG$8 -> 0.00060917882 | P62: 0 | Q62: 0 | R62: 0 | S62: 0 | T62: 0 | U62: 0 | V62: 0 | W62: 0 | X62: 0
A63: NF-03 | B63: Microbial Ovalbumin (T. reesei) | C63: Novel food | D63: Sweden | E63: SE | F63: CH4, biogenic | G63: =SUM(H63:T63)+SUM(W63:X63) -> 0 | H63: 0 | I63: 0 | J63: 0 | K63: 0 | L63: 0 | M63: 0 | N63: 0 | O63: 0 | P63: 0 | Q63: 0 | R63: 0 | S63: 0 | T63: 0 | U63: 0 | V63: 0 | W63: 0 | X63: 0
A64: NF-03 | B64: Microbial Ovalbumin (T. reesei) | C64: Novel food | D64: Sweden | E64: SE | F64: N2O | G64: =SUM(H64:T64)+SUM(W64:X64) -> 0.0021408088 | H64: ='Novel foods, input data'!$AB$8*'Agri ing'!$AP$27 -> 0.0004637739 | I64: ='Novel foods, input data'!$AB$8*'Agri ing'!$AQ$27 -> 1.0267472e-05 | J64: ='Novel foods, input data'!$AB$8*'Agri ing'!$AR$27 -> 0.0016051011 | K64: 0 | L64: ='Novel foods, input data'!$AB$8*'Agri ing'!$AS$27 -> 1.1009704e-05 | M64: 0 | N64: 0 | O64: ='Novel foods, input data'!$D$8*'Emission factors'!$D$11+'Novel foods, input data'!$AH$8 -> 5.0656563e-05 | P64: 0 | Q64: 0 | R64: 0 | S64: 0 | T64: 0 | U64: 0 | V64: 0 | W64: 0 | X64: 0
A65: NF-03 | B65: Microbial Ovalbumin (T. reesei) | C65: Novel food | D65: Sweden | E65: SE | F65: CO2e | G65: =SUM(H65:X65) -> 4.3400351 | H65: =H61+H62*CF_CH4_foss+H63*CF_CH4_bio+H64*CF_N2O -> 0.35044551 | I65: =I61+I62*CF_CH4_foss+I63*CF_CH4_bio+I64*CF_N2O -> 0.28124752 | J65: =J61+J62*CF_CH4_foss+J63*CF_CH4_bio+J64*CF_N2O -> 0.43819261 | K65: =K61+K62*CF_CH4_foss+K63*CF_CH4_bio+K64*CF_N2O -> 0 | L65: =L61+L62*CF_CH4_foss+L63*CF_CH4_bio+L64*CF_N2O -> 0.29014512 | M65: =M61+M62*CF_CH4_foss+M63*CF_CH4_bio+M64*CF_N2O -> 0 | N65: =N61+N62*CF_CH4_foss+N63*CF_CH4_bio+N64*CF_N2O -> 0 | O65: =O61+O62*CF_CH4_foss+O63*CF_CH4_bio+O64*CF_N2O -> 2.9800044 | ... T65: =T61+T62*CF_CH4_foss+T63*CF_CH4_bio+T64*CF_N2O -> 0 | W65: =W61+W62*CF_CH4_foss+W63*CF_CH4_bio+W64*CF_N2O -> 0 | X65: =X61+X62*CF_CH4_foss+X63*CF_CH4_bio+X64*CF_N2O -> 0
A66: NF-03 | B66: Microbial Ovalbumin (T. reesei) | C66: Novel food | D66: Switzerland | E66: CH | F66: CO2 | G66: =SUM(H66:X66) -> 3.6917044 | H66: ='Novel foods, input data'!$AB$8*'Agri ing'!$AF$27 -> 0.2129392 | I66: ='Novel foods, input data'!$AB$8*'Agri ing'!$AG$27 -> 0.25201976 | J66: 0 | K66: 0 | L66: ='Novel foods, input data'!$AB$8*'Agri ing'!$AH$27 -> 0.27872386 | M66: 0 | N66: 0 | O66: ='Novel foods, input data'!$D$8*'Emission factors'!$B$9+'Novel foods, input data'!$AF$8 -> 2.9480216 | P66: 0 | Q66: 0 | R66: 0 | S66: 0 | T66: 0 | U66: 0 | V66: 0 | W66: 0 | X66: 0
A67: NF-03 | B67: Microbial Ovalbumin (T. reesei) | C67: Novel food | D67: Switzerland | E67: CH | F67: CH4, fossil | G67: =SUM(H67:X67) -> 0.0021439571 | H67: ='Novel foods, input data'!$AB$8*'Agri ing'!$AJ$27 -> 0.00036563896 | I67: ='Novel foods, input data'!$AB$8*'Agri ing'!$AK$27 -> 0.00088673619 | J67: 0 | K67: 0 | L67: ='Novel foods, input data'!$AB$8*'Agri ing'!$AL$27 -> 0.00028240309 | M67: 0 | N67: 0 | O67: ='Novel foods, input data'!$D$8*'Emission factors'!$C$9+'Novel foods, input data'!$AG$8 -> 0.00060917882 | P67: 0 | Q67: 0 | R67: 0 | S67: 0 | T67: 0 | U67: 0 | V67: 0 | W67: 0 | X67: 0
A68: NF-03 | B68: Microbial Ovalbumin (T. reesei) | C68: Novel food | D68: Switzerland | E68: CH | F68: CH4, biogenic | G68: =SUM(H68:T68)+SUM(W68:X68) -> 0 | H68: 0 | I68: 0 | J68: 0 | K68: 0 | L68: 0 | M68: 0 | N68: 0 | O68: 0 | P68: 0 | Q68: 0 | R68: 0 | S68: 0 | T68: 0 | U68: 0 | V68: 0 | W68: 0 | X68: 0
A69: NF-03 | B69: Microbial Ovalbumin (T. reesei) | C69: Novel food | D69: Switzerland | E69: CH | F69: N2O | G69: =SUM(H69:T69)+SUM(W69:X69) -> 0.0021408088 | H69: ='Novel foods, input data'!$AB$8*'Agri ing'!$AP$27 -> 0.0004637739 | I69: ='Novel foods, input data'!$AB$8*'Agri ing'!$AQ$27 -> 1.0267472e-05 | J69: ='Novel foods, input data'!$AB$8*'Agri ing'!$AR$27 -> 0.0016051011 | K69: 0 | L69: ='Novel foods, input data'!$AB$8*'Agri ing'!$AS$27 -> 1.1009704e-05 | M69: 0 | N69: 0 | O69: ='Novel foods, input data'!$D$8*'Emission factors'!$D$9+'Novel foods, input data'!$AH$8 -> 5.0656563e-05 | P69: 0 | Q69: 0 | R69: 0 | S69: 0 | T69: 0 | U69: 0 | V69: 0 | W69: 0 | X69: 0
A70: NF-03 | B70: Microbial Ovalbumin (T. reesei) | C70: Novel food | D70: Switzerland | E70: CH | F70: CO2e | G70: =SUM(H70:X70) -> 4.3400351 | H70: =H66+H67*CF_CH4_foss+H68*CF_CH4_bio+H69*CF_N2O -> 0.35044551 | I70: =I66+I67*CF_CH4_foss+I68*CF_CH4_bio+I69*CF_N2O -> 0.28124752 | J70: =J66+J67*CF_CH4_foss+J68*CF_CH4_bio+J69*CF_N2O -> 0.43819261 | K70: =K66+K67*CF_CH4_foss+K68*CF_CH4_bio+K69*CF_N2O -> 0 | L70: =L66+L67*CF_CH4_foss+L68*CF_CH4_bio+L69*CF_N2O -> 0.29014512 | M70: =M66+M67*CF_CH4_foss+M68*CF_CH4_bio+M69*CF_N2O -> 0 | N70: =N66+N67*CF_CH4_foss+N68*CF_CH4_bio+N69*CF_N2O -> 0 | O70: =O66+O67*CF_CH4_foss+O68*CF_CH4_bio+O69*CF_N2O -> 2.9800044 | ... T70: =T66+T67*CF_CH4_foss+T68*CF_CH4_bio+T69*CF_N2O -> 0 | W70: =W66+W67*CF_CH4_foss+W68*CF_CH4_bio+W69*CF_N2O -> 0 | X70: =X66+X67*CF_CH4_foss+X68*CF_CH4_bio+X69*CF_N2O -> 0
A71: NF-03 | B71: Microbial Ovalbumin (T. reesei) | C71: Novel food | D71: USA | E71: US | F71: CO2 | G71: =SUM(H71:X71) -> 6.4007229 | H71: ='Novel foods, input data'!$AB$8*'Agri ing'!$AF$27 -> 0.2129392 | I71: ='Novel foods, input data'!$AB$8*'Agri ing'!$AG$27 -> 0.25201976 | J71: 0 | K71: 0 | L71: ='Novel foods, input data'!$AB$8*'Agri ing'!$AH$27 -> 0.27872386 | M71: 0 | N71: 0 | O71: ='Novel foods, input data'!$D$8*'Emission factors'!$B$13+'Novel foods, input data'!$AF$8 -> 5.6570401 | P71: 0 | Q71: 0 | R71: 0 | S71: 0 | T71: 0 | U71: 0 | V71: 0 | W71: 0 | X71: 0
A72: NF-03 | B72: Microbial Ovalbumin (T. reesei) | C72: Novel food | D72: USA | E72: US | F72: CH4, fossil | G72: =SUM(H72:X72) -> 0.0065890719 | H72: ='Novel foods, input data'!$AB$8*'Agri ing'!$AJ$27 -> 0.00036563896 | I72: ='Novel foods, input data'!$AB$8*'Agri ing'!$AK$27 -> 0.00088673619 | J72: 0 | K72: 0 | L72: ='Novel foods, input data'!$AB$8*'Agri ing'!$AL$27 -> 0.00028240309 | M72: 0 | N72: 0 | O72: ='Novel foods, input data'!$D$8*'Emission factors'!$C$13+'Novel foods, input data'!$AG$8 -> 0.0050542936 | P72: 0 | Q72: 0 | R72: 0 | S72: 0 | T72: 0 | U72: 0 | V72: 0 | W72: 0 | X72: 0
A73: NF-03 | B73: Microbial Ovalbumin (T. reesei) | C73: Novel food | D73: USA | E73: US | F73: CH4, biogenic | G73: =SUM(H73:T73)+SUM(W73:X73) -> 0 | H73: 0 | I73: 0 | J73: 0 | K73: 0 | L73: 0 | M73: 0 | N73: 0 | O73: 0 | P73: 0 | Q73: 0 | R73: 0 | S73: 0 | T73: 0 | U73: 0 | V73: 0 | W73: 0 | X73: 0
A74: NF-03 | B74: Microbial Ovalbumin (T. reesei) | C74: Novel food | D74: USA | E74: US | F74: N2O | G74: =SUM(H74:T74)+SUM(W74:X74) -> 0.0021820537 | H74: ='Novel foods, input data'!$AB$8*'Agri ing'!$AP$27 -> 0.0004637739 | I74: ='Novel foods, input data'!$AB$8*'Agri ing'!$AQ$27 -> 1.0267472e-05 | J74: ='Novel foods, input data'!$AB$8*'Agri ing'!$AR$27 -> 0.0016051011 | K74: 0 | L74: ='Novel foods, input data'!$AB$8*'Agri ing'!$AS$27 -> 1.1009704e-05 | M74: 0 | N74: 0 | O74: ='Novel foods, input data'!$D$8*'Emission factors'!$D$13+'Novel foods, input data'!$AH$8 -> 9.1901456e-05 | P74: 0 | Q74: 0 | R74: 0 | S74: 0 | T74: 0 | U74: 0 | V74: 0 | W74: 0 | X74: 0
A75: NF-03 | B75: Microbial Ovalbumin (T. reesei) | C75: Novel food | D75: USA | E75: US | F75: CO2e | G75: =SUM(H75:X75) -> 7.1927779 | H75: =H71+H72*CF_CH4_foss+H73*CF_CH4_bio+H74*CF_N2O -> 0.35044551 | I75: =I71+I72*CF_CH4_foss+I73*CF_CH4_bio+I74*CF_N2O -> 0.28124752 | J75: =J71+J72*CF_CH4_foss+J73*CF_CH4_bio+J74*CF_N2O -> 0.43819261 | K75: =K71+K72*CF_CH4_foss+K73*CF_CH4_bio+K74*CF_N2O -> 0 | L75: =L71+L72*CF_CH4_foss+L73*CF_CH4_bio+L74*CF_N2O -> 0.29014512 | M75: =M71+M72*CF_CH4_foss+M73*CF_CH4_bio+M74*CF_N2O -> 0 | N75: =N71+N72*CF_CH4_foss+N73*CF_CH4_bio+N74*CF_N2O -> 0 | O75: =O71+O72*CF_CH4_foss+O73*CF_CH4_bio+O74*CF_N2O -> 5.8327472 | ... T75: =T71+T72*CF_CH4_foss+T73*CF_CH4_bio+T74*CF_N2O -> 0 | W75: =W71+W72*CF_CH4_foss+W73*CF_CH4_bio+W74*CF_N2O -> 0 | X75: =X71+X72*CF_CH4_foss+X73*CF_CH4_bio+X74*CF_N2O -> 0
A76: NF-04 | B76: Microbial Protein (Solein) | C76: Novel food | D76: Finland | E76: FI | F76: CO2 | G76: =SUM(H76:X76) -> 5.8015207 | H76: 0 | I76: 0 | J76: 0 | K76: 0 | L76: 0 | M76: 0 | N76: 0 | O76: ='Novel foods, input data'!$D$9*'Emission factors'!$B$10+'Novel foods, input data'!$AF$9 -> 5.8015207 | P76: 0 | Q76: 0 | R76: 0 | S76: 0 | T76: 0 | U76: 0 | V76: 0 | W76: 0 | X76: 0
A77: NF-04 | B77: Microbial Protein (Solein) | C77: Novel food | D77: Finland | E77: FI | F77: CH4, fossil | G77: =SUM(H77:X77) -> 0.0109117 | H77: 0 | I77: 0 | J77: 0 | K77: 0 | L77: 0 | M77: 0 | N77: 0 | O77: ='Novel foods, input data'!$D$9*'Emission factors'!$C$10+'Novel foods, input data'!$AG$9 -> 0.0109117 | P77: 0 | Q77: 0 | R77: 0 | S77: 0 | T77: 0 | U77: 0 | V77: 0 | W77: 0 | X77: 0
A78: NF-04 | B78: Microbial Protein (Solein) | C78: Novel food | D78: Finland | E78: FI | F78: CH4, biogenic | G78: =SUM(H78:T78)+SUM(W78:X78) -> 0 | H78: 0 | I78: 0 | J78: 0 | K78: 0 | L78: 0 | M78: 0 | N78: 0 | O78: 0 | P78: 0 | Q78: 0 | R78: 0 | S78: 0 | T78: 0 | U78: 0 | V78: 0 | W78: 0 | X78: 0
A79: NF-04 | B79: Microbial Protein (Solein) | C79: Novel food | D79: Finland | E79: FI | F79: N2O | G79: =SUM(H79:T79)+SUM(W79:X79) -> 0.00035032584 | H79: 0 | I79: 0 | J79: 0 | K79: 0 | L79: 0 | M79: 0 | N79: 0 | O79: ='Novel foods, input data'!$D$9*'Emission factors'!$D$10+'Novel foods, input data'!$AH$9 -> 0.00035032584 | P79: 0 | Q79: 0 | R79: 0 | S79: 0 | T79: 0 | U79: 0 | V79: 0 | W79: 0 | X79: 0
A80: NF-04 | B80: Microbial Protein (Solein) | C80: Novel food | D80: Finland | E80: FI | F80: CO2e | G80: =SUM(H80:X80) -> 6.2223283 | H80: =H76+H77*CF_CH4_foss+H78*CF_CH4_bio+H79*CF_N2O -> 0 | I80: =I76+I77*CF_CH4_foss+I78*CF_CH4_bio+I79*CF_N2O -> 0 | J80: =J76+J77*CF_CH4_foss+J78*CF_CH4_bio+J79*CF_N2O -> 0 | K80: =K76+K77*CF_CH4_foss+K78*CF_CH4_bio+K79*CF_N2O -> 0 | L80: =L76+L77*CF_CH4_foss+L78*CF_CH4_bio+L79*CF_N2O -> 0 | M80: =M76+M77*CF_CH4_foss+M78*CF_CH4_bio+M79*CF_N2O -> 0 | N80: =N76+N77*CF_CH4_foss+N78*CF_CH4_bio+N79*CF_N2O -> 0 | O80: =O76+O77*CF_CH4_foss+O78*CF_CH4_bio+O79*CF_N2O -> 6.2223283 | ... T80: =T76+T77*CF_CH4_foss+T78*CF_CH4_bio+T79*CF_N2O -> 0 | W80: =W76+W77*CF_CH4_foss+W78*CF_CH4_bio+W79*CF_N2O -> 0 | X80: =X76+X77*CF_CH4_foss+X78*CF_CH4_bio+X79*CF_N2O -> 0
A81: NF-04 | B81: Microbial Protein (Solein) | C81: Novel food | D81: Sweden | E81: SE | F81: CO2 | G81: =SUM(H81:X81) -> 2.0272184 | H81: 0 | I81: 0 | J81: 0 | K81: 0 | L81: 0 | M81: 0 | N81: 0 | O81: ='Novel foods, input data'!$D$9*'Emission factors'!$B$11+'Novel foods, input data'!$AF$9 -> 2.0272184 | P81: 0 | Q81: 0 | R81: 0 | S81: 0 | T81: 0 | U81: 0 | V81: 0 | W81: 0 | X81: 0
A82: NF-04 | B82: Microbial Protein (Solein) | C82: Novel food | D82: Sweden | E82: SE | F82: CH4, fossil | G82: =SUM(H82:X82) -> 0.001776827 | H82: 0 | I82: 0 | J82: 0 | K82: 0 | L82: 0 | M82: 0 | N82: 0 | O82: ='Novel foods, input data'!$D$9*'Emission factors'!$C$11+'Novel foods, input data'!$AG$9 -> 0.001776827 | P82: 0 | Q82: 0 | R82: 0 | S82: 0 | T82: 0 | U82: 0 | V82: 0 | W82: 0 | X82: 0
A83: NF-04 | B83: Microbial Protein (Solein) | C83: Novel food | D83: Sweden | E83: SE | F83: CH4, biogenic | G83: =SUM(H83:T83)+SUM(W83:X83) -> 0 | H83: 0 | I83: 0 | J83: 0 | K83: 0 | L83: 0 | M83: 0 | N83: 0 | O83: 0 | P83: 0 | Q83: 0 | R83: 0 | S83: 0 | T83: 0 | U83: 0 | V83: 0 | W83: 0 | X83: 0
A84: NF-04 | B84: Microbial Protein (Solein) | C84: Novel food | D84: Sweden | E84: SE | F84: N2O | G84: =SUM(H84:T84)+SUM(W84:X84) -> 0.00014775292 | H84: 0 | I84: 0 | J84: 0 | K84: 0 | L84: 0 | M84: 0 | N84: 0 | O84: ='Novel foods, input data'!$D$9*'Emission factors'!$D$11+'Novel foods, input data'!$AH$9 -> 0.00014775292 | P84: 0 | Q84: 0 | R84: 0 | S84: 0 | T84: 0 | U84: 0 | V84: 0 | W84: 0 | X84: 0
A85: NF-04 | B85: Microbial Protein (Solein) | C85: Novel food | D85: Sweden | E85: SE | F85: CO2e | G85: =SUM(H85:X85) -> 2.1205044 | H85: =H81+H82*CF_CH4_foss+H83*CF_CH4_bio+H84*CF_N2O -> 0 | I85: =I81+I82*CF_CH4_foss+I83*CF_CH4_bio+I84*CF_N2O -> 0 | J85: =J81+J82*CF_CH4_foss+J83*CF_CH4_bio+J84*CF_N2O -> 0 | K85: =K81+K82*CF_CH4_foss+K83*CF_CH4_bio+K84*CF_N2O -> 0 | L85: =L81+L82*CF_CH4_foss+L83*CF_CH4_bio+L84*CF_N2O -> 0 | M85: =M81+M82*CF_CH4_foss+M83*CF_CH4_bio+M84*CF_N2O -> 0 | N85: =N81+N82*CF_CH4_foss+N83*CF_CH4_bio+N84*CF_N2O -> 0 | O85: =O81+O82*CF_CH4_foss+O83*CF_CH4_bio+O84*CF_N2O -> 2.1205044 | ... T85: =T81+T82*CF_CH4_foss+T83*CF_CH4_bio+T84*CF_N2O -> 0 | W85: =W81+W82*CF_CH4_foss+W83*CF_CH4_bio+W84*CF_N2O -> 0 | X85: =X81+X82*CF_CH4_foss+X83*CF_CH4_bio+X84*CF_N2O -> 0
A86: NF-05 | B86: Mycoprotein (Quorn) | C86: Novel food | D86: Sweden | E86: SE | F86: CO2 | G86: =SUM(H86:X86) -> 1.065323 | H86: ='Novel foods, input data'!$AD$10*'Agri ing'!$AD$21+'Novel foods, input data'!$AE$10*'Agri ing'!$AF$26 -> 0.19145399 | I86: ='Novel foods, input data'!$AD$10*'Agri ing'!$AE$21+'Novel foods, input data'!$AE$10*'Agri ing'!$AG$26 -> 0.059036864 | J86: 0 | K86: 0 | L86: ='Novel foods, input data'!$AD$10*'Agri ing'!$AF$21+'Novel foods, input data'!$AE$10*'Agri ing'!$AH$26 -> 0.16993738 | M86: 0 | N86: 0 | O86: ='Novel foods, input data'!$D$10*'Emission factors'!$B$11+'Novel foods, input data'!$AF$10 -> 0.64382257 | P86: ='Novel foods, input data'!$AE$10*'Agri ing'!$AI$26 -> 0.0010722 | Q86: 0 | R86: 0 | S86: 0 | T86: 0 | U86: 0 | V86: 0 | W86: 0 | X86: 0 | Y86: These energy processes here included in Diesel use mach
A87: NF-05 | B87: Mycoprotein (Quorn) | C87: Novel food | D87: Sweden | E87: SE | F87: CH4, fossil | G87: =SUM(H87:X87) -> 0.0024494886 | H87: ='Novel foods, input data'!$AD$10*'Agri ing'!$AH$21+'Novel foods, input data'!$AE$10*'Agri ing'!$AJ$26 -> 0.00034716664 | I87: ='Novel foods, input data'!$AD$10*'Agri ing'!$AI$21+'Novel foods, input data'!$AE$10*'Agri ing'!$AK$26 -> 0.0002077688 | J87: 0 | K87: 0 | L87: ='Novel foods, input data'!$AD$10*'Agri ing'!$AJ$21+'Novel foods, input data'!$AE$10*'Agri ing'!$AL$26 -> 0.0013125258 | M87: 0 | N87: 0 | O87: ='Novel foods, input data'!$D$10*'Emission factors'!$C$11+'Novel foods, input data'!$AG$10 -> 0.0005820274 | P87: 0 | Q87: 0 | R87: 0 | S87: 0 | T87: 0 | U87: 0 | V87: 0 | W87: 0 | X87: 0
A88: NF-05 | B88: Mycoprotein (Quorn) | C88: Novel food | D88: Sweden | E88: SE | F88: CH4, biogenic | G88: =SUM(H88:T88)+SUM(W88:X88) -> 7.0753259e-05 | H88: 0 | I88: 0 | J88: 0 | K88: 0 | L88: 0 | M88: 0 | N88: 0 | O88: 0 | P88: 0 | T88: ='Novel foods, input data'!$AE$10*'Agri ing'!$AO$26 -> 7.0753259e-05
A89: NF-05 | B89: Mycoprotein (Quorn) | C89: Novel food | D89: Sweden | E89: SE | F89: N2O | G89: =SUM(H89:T89)+SUM(W89:X89) -> 0.0028808334 | H89: ='Novel foods, input data'!$AD$10*'Agri ing'!$AN$21+'Novel foods, input data'!$AE$10*'Agri ing'!$AP$26 -> 0.00042016043 | I89: ='Novel foods, input data'!$AD$10*'Agri ing'!$AO$21+'Novel foods, input data'!$AE$10*'Agri ing'!$AQ$26 -> 2.3969761e-06 | J89: ='Novel foods, input data'!$AD$10*'Agri ing'!$AP$21+'Novel foods, input data'!$AE$10*'Agri ing'!$AR$26 -> 0.0011944149 | K89: 0 | L89: ='Novel foods, input data'!$AD$10*'Agri ing'!$AQ$21+'Novel foods, input data'!$AE$10*'Agri ing'!$AS$26 -> 0.0012153694 | M89: 0 | N89: 0 | O89: ='Novel foods, input data'!$D$10*'Emission factors'!$D$11+'Novel foods, input data'!$AH$10 -> 4.8398774e-05 | P89: 0 | Q89: 0 | R89: 0 | S89: 0 | T89: ='Novel foods, input data'!$AE$10*'Agri ing'!$AT$26 -> 9.2952571e-08 | U89: 0 | V89: 0 | W89: 0 | X89: 0
A90: NF-05 | B90: Mycoprotein (Quorn) | C90: Novel food | D90: Sweden | E90: SE | F90: CO2e | G90: =SUM(H90:X90) -> 1.9266956 | H90: =H86+H87*CF_CH4_foss+H88*CF_CH4_bio+H89*CF_N2O -> 0.31650336 | I90: =I86+I87*CF_CH4_foss+I88*CF_CH4_bio+I89*CF_N2O -> 0.065882749 | J90: =J86+J87*CF_CH4_foss+J88*CF_CH4_bio+J89*CF_N2O -> 0.32607527 | K90: =K86+K87*CF_CH4_foss+K88*CF_CH4_bio+K89*CF_N2O -> 0 | L90: =L86+L87*CF_CH4_foss+L88*CF_CH4_bio+L89*CF_N2O -> 0.54084649 | M90: =M86+M87*CF_CH4_foss+M88*CF_CH4_bio+M89*CF_N2O -> 0 | N90: =N86+N87*CF_CH4_foss+N88*CF_CH4_bio+N89*CF_N2O -> 0 | O90: =O86+O87*CF_CH4_foss+O88*CF_CH4_bio+O89*CF_N2O -> 0.67437985 | ... T90: =T86+T87*CF_CH4_foss+T88*CF_CH4_bio+T89*CF_N2O -> 0.001935714 | W90: =W86+W87*CF_CH4_foss+W88*CF_CH4_bio+W89*CF_N2O -> 0 | X90: =X86+X87*CF_CH4_foss+X88*CF_CH4_bio+X89*CF_N2O -> 0
A91: NF-05 | B91: Mycoprotein (Quorn) | C91: Novel food | D91: UK | E91: GB | F91: CO2 | G91: =SUM(H91:X91) -> 1.1247856 | H91: ='Novel foods, input data'!$AD$10*'Agri ing'!$AD$21+'Novel foods, input data'!$AE$10*'Agri ing'!$AF$26 -> 0.19145399 | I91: ='Novel foods, input data'!$AD$10*'Agri ing'!$AE$21+'Novel foods, input data'!$AE$10*'Agri ing'!$AG$26 -> 0.059036864 | J91: 0 | K91: 0 | L91: ='Novel foods, input data'!$AD$10*'Agri ing'!$AF$21+'Novel foods, input data'!$AE$10*'Agri ing'!$AH$26 -> 0.16993738 | M91: 0 | N91: 0 | O91: ='Novel foods, input data'!$D$10*'Emission factors'!$B$15+'Novel foods, input data'!$AF$10 -> 0.70328513 | P91: ='Novel foods, input data'!$AE$10*'Agri ing'!$AI$26 -> 0.0010722 | Q91: 0 | R91: 0 | S91: 0 | T91: 0 | U91: 0 | V91: 0 | W91: 0 | X91: 0
A92: NF-05 | B92: Mycoprotein (Quorn) | C92: Novel food | D92: UK | E92: GB | F92: CH4, fossil | G92: =SUM(H92:X92) -> 0.0027051407 | H92: ='Novel foods, input data'!$AD$10*'Agri ing'!$AH$21+'Novel foods, input data'!$AE$10*'Agri ing'!$AJ$26 -> 0.00034716664 | I92: ='Novel foods, input data'!$AD$10*'Agri ing'!$AI$21+'Novel foods, input data'!$AE$10*'Agri ing'!$AK$26 -> 0.0002077688 | J92: 0 | K92: 0 | L92: ='Novel foods, input data'!$AD$10*'Agri ing'!$AJ$21+'Novel foods, input data'!$AE$10*'Agri ing'!$AL$26 -> 0.0013125258 | M92: 0 | N92: 0 | O92: ='Novel foods, input data'!$D$10*'Emission factors'!$C$15+'Novel foods, input data'!$AG$10 -> 0.00083767948 | P92: 0 | Q92: 0 | R92: 0 | S92: 0 | T92: 0 | U92: 0 | V92: 0 | W92: 0 | X92: 0
A93: NF-05 | B93: Mycoprotein (Quorn) | C93: Novel food | D93: UK | E93: GB | F93: CH4, biogenic | G93: =SUM(H93:T93)+SUM(W93:X93) -> 7.0753259e-05 | H93: 0 | I93: 0 | J93: 0 | K93: 0 | L93: 0 | M93: 0 | N93: 0 | O93: 0 | P93: 0 | T93: ='Novel foods, input data'!$AE$10*'Agri ing'!$AO$26 -> 7.0753259e-05
A94: NF-05 | B94: Mycoprotein (Quorn) | C94: Novel food | D94: UK | E94: GB | F94: N2O | G94: =SUM(H94:T94)+SUM(W94:X94) -> 0.0029153335 | H94: ='Novel foods, input data'!$AD$10*'Agri ing'!$AN$21+'Novel foods, input data'!$AE$10*'Agri ing'!$AP$26 -> 0.00042016043 | I94: ='Novel foods, input data'!$AD$10*'Agri ing'!$AO$21+'Novel foods, input data'!$AE$10*'Agri ing'!$AQ$26 -> 2.3969761e-06 | J94: ='Novel foods, input data'!$AD$10*'Agri ing'!$AP$21+'Novel foods, input data'!$AE$10*'Agri ing'!$AR$26 -> 0.0011944149 | K94: 0 | L94: ='Novel foods, input data'!$AD$10*'Agri ing'!$AQ$21+'Novel foods, input data'!$AE$10*'Agri ing'!$AS$26 -> 0.0012153694 | M94: 0 | N94: 0 | O94: ='Novel foods, input data'!$D$10*'Emission factors'!$D$14+'Novel foods, input data'!$AH$10 -> 8.2898894e-05 | P94: 0 | Q94: 0 | R94: 0 | S94: 0 | T94: ='Novel foods, input data'!$AE$10*'Agri ing'!$AT$26 -> 9.2952571e-08 | U94: 0 | V94: 0 | W94: 0 | X94: 0
A95: NF-05 | B95: Mycoprotein (Quorn) | C95: Novel food | D95: UK | E95: GB | F95: CO2e | G95: =SUM(H95:X95) -> 2.0031952 | H95: =H91+H92*CF_CH4_foss+H93*CF_CH4_bio+H94*CF_N2O -> 0.31650336 | I95: =I91+I92*CF_CH4_foss+I93*CF_CH4_bio+I94*CF_N2O -> 0.065882749 | J95: =J91+J92*CF_CH4_foss+J93*CF_CH4_bio+J94*CF_N2O -> 0.32607527 | K95: =K91+K92*CF_CH4_foss+K93*CF_CH4_bio+K94*CF_N2O -> 0 | L95: =L91+L92*CF_CH4_foss+L93*CF_CH4_bio+L94*CF_N2O -> 0.54084649 | M95: =M91+M92*CF_CH4_foss+M93*CF_CH4_bio+M94*CF_N2O -> 0 | N95: =N91+N92*CF_CH4_foss+N93*CF_CH4_bio+N94*CF_N2O -> 0 | O95: =O91+O92*CF_CH4_foss+O93*CF_CH4_bio+O94*CF_N2O -> 0.75087937 | ... T95: =T91+T92*CF_CH4_foss+T93*CF_CH4_bio+T94*CF_N2O -> 0.001935714 | W95: =W91+W92*CF_CH4_foss+W93*CF_CH4_bio+W94*CF_N2O -> 0 | X95: =X91+X92*CF_CH4_foss+X93*CF_CH4_bio+X94*CF_N2O -> 0
A96: NF-06 | B96: Yeast Fat (Rhodotorula babjevae) | C96: Novel food | D96: Israel | E96: IL | F96: CO2 | G96: =SUM(H96:X96) -> 0.85944291 | H96: 0 | I96: 0 | J96: 0 | K96: 0 | L96: 0 | M96: 0 | N96: 0 | O96: ='Novel foods, input data'!$D$11*'Emission factors'!$B$12+'Novel foods, input data'!$F$11*'Emission factors'!$B$12+'Novel foods, input data'!Z11*'Emission factors'!B22+'Novel foods, input data'!$AF$11 -> 0.85944291 | P96: 0 | Q96: 0 | R96: 0 | S96: 0 | T96: 0 | U96: 0 | V96: 0 | W96: 0 | X96: 0
A97: NF-06 | B97: Yeast Fat (Rhodotorula babjevae) | C97: Novel food | D97: Israel | E97: IL | F97: CH4, fossil | G97: =SUM(H97:X97) -> 0.0020750212 | H97: 0 | I97: 0 | J97: 0 | K97: 0 | L97: 0 | M97: 0 | N97: 0 | O97: ='Novel foods, input data'!$D$11*'Emission factors'!$C$12+'Novel foods, input data'!$F$11*'Emission factors'!$C$12+'Novel foods, input data'!$AG$11 -> 0.0020750212 | P97: 0 | Q97: 0 | R97: 0 | S97: 0 | T97: 0 | U97: 0 | V97: 0 | W97: 0 | X97: 0
A98: NF-06 | B98: Yeast Fat (Rhodotorula babjevae) | C98: Novel food | D98: Israel | E98: IL | F98: CH4, biogenic | G98: =SUM(H98:T98)+SUM(W98:X98) -> 0 | H98: 0 | I98: 0 | J98: 0 | K98: 0 | L98: 0 | M98: 0 | N98: 0 | O98: 0 | P98: 0 | Q98: 0 | R98: 0 | S98: 0 | T98: 0 | U98: 0 | V98: 0 | W98: 0 | X98: 0
A99: NF-06 | B99: Yeast Fat (Rhodotorula babjevae) | C99: Novel food | D99: Israel | E99: IL | F99: N2O | G99: =SUM(H99:T99)+SUM(W99:X99) -> 4.8939118e-05 | H99: 0 | I99: 0 | J99: 0 | K99: 0 | L99: 0 | M99: 0 | N99: 0 | O99: ='Novel foods, input data'!$D$11*'Emission factors'!$D$12+'Novel foods, input data'!$F$11*'Emission factors'!$D$12+'Novel foods, input data'!$AH$11 -> 4.8939118e-05 | P99: 0 | Q99: 0 | R99: 0 | S99: 0 | T99: 0 | U99: 0 | V99: 0 | W99: 0 | X99: 0
A100: NF-06 | B100: Yeast Fat (Rhodotorula babjevae) | C100: Novel food | D100: Israel | E100: IL | F100: CO2e | G100: =SUM(H100:X100) -> 0.93463893 | H100: =H96+H97*CF_CH4_foss+H98*CF_CH4_bio+H99*CF_N2O -> 0 | I100: =I96+I97*CF_CH4_foss+I98*CF_CH4_bio+I99*CF_N2O -> 0 | J100: =J96+J97*CF_CH4_foss+J98*CF_CH4_bio+J99*CF_N2O -> 0 | K100: =K96+K97*CF_CH4_foss+K98*CF_CH4_bio+K99*CF_N2O -> 0 | L100: =L96+L97*CF_CH4_foss+L98*CF_CH4_bio+L99*CF_N2O -> 0 | M100: =M96+M97*CF_CH4_foss+M98*CF_CH4_bio+M99*CF_N2O -> 0 | N100: =N96+N97*CF_CH4_foss+N98*CF_CH4_bio+N99*CF_N2O -> 0 | O100: =O96+O97*CF_CH4_foss+O98*CF_CH4_bio+O99*CF_N2O -> 0.93463893 | ... T100: =T96+T97*CF_CH4_foss+T98*CF_CH4_bio+T99*CF_N2O -> 0 | W100: =W96+W97*CF_CH4_foss+W98*CF_CH4_bio+W99*CF_N2O -> 0 | X100: =X96+X97*CF_CH4_foss+X98*CF_CH4_bio+X99*CF_N2O -> 0
A101: NF-06 | B101: Yeast Fat (Rhodotorula babjevae) | C101: Novel food | D101: Netherlands | E101: NL | F101: CO2 | G101: =SUM(H101:X101) -> 0.61230844 | H101: 0 | I101: 0 | J101: 0 | K101: 0 | L101: 0 | M101: 0 | N101: 0 | O101: ='Novel foods, input data'!$D$11*'Emission factors'!$B$7+'Novel foods, input data'!$F$11*'Emission factors'!$B$7+'Novel foods, input data'!Z11*'Emission factors'!B22+'Novel foods, input data'!$AF$11 -> 0.61230844 | P101: 0 | Q101: 0 | R101: 0 | S101: 0 | T101: 0 | U101: 0 | V101: 0 | W101: 0 | X101: 0
A102: NF-06 | B102: Yeast Fat (Rhodotorula babjevae) | C102: Novel food | D102: Netherlands | E102: NL | F102: CH4, fossil | G102: =SUM(H102:X102) -> 0.0012547486 | H102: 0 | I102: 0 | J102: 0 | K102: 0 | L102: 0 | M102: 0 | N102: 0 | O102: ='Novel foods, input data'!$D$11*'Emission factors'!$C$7+'Novel foods, input data'!$F$11*'Emission factors'!$C$7+'Novel foods, input data'!$AG$11 -> 0.0012547486 | P102: 0 | Q102: 0 | R102: 0 | S102: 0 | T102: 0 | U102: 0 | V102: 0 | W102: 0 | X102: 0
...

Sheet Novel foods, input data
A2: Novel foods, input data per kg final product | AF2: SMALL INGREDIENTS DONE FOR ALL PRODUCTS (EXCEPT CULT MEAT-not needed)
A4: Novel foods | D4: Energy (MJ/kg food) | AB4: Ingredients from agriculture (kg/kg food) | AF4: Other small ingredients/input
A5: Code | B5: Food | C5: Category | D5: Total Electicity | E5: Total Heat | F5: Energy ingredients (NOTE: this is done differently for cultured meat as the ingredients were a large part of the impacts, and not "minor") | G5: Bioreactor energy (Average) | H5: Bioreactor Cleaning/Cleaning in Place | I5: Water Sterilisation | J5: Microfiltration | K5: Combined ultra- and diafiltration | L5: Spray drying | M5: SMB system (Chromatographic separation) | N5: Fermentation (including transport, sterilization, electrolysis, and pasteurization) | O5: Separation | P5: Electricity - Feeding/harvesting/processing | Q5: Heat - Feeding/harvesting/processing | R5: Electricity - High moisture intermediate production | S5: Electricity (water pumping, lamps, sparger) - Cultivation, nursery | T5: Heat (Steam) - Pre-treatment and hydrolysis | U5: Electricity - Pre-treatment and hydrolysis | V5: Heating - nutrient production | W5: Electricity - Lipid extraction and refining | X5: Heat (steam) - Lipid extraction and refining | Y5: Electricity (fractionation) - Lipid extraction and refining | Z5: Diesel (L/kg food) | AA5: Petrol (L/kg food) | AB5: Glucose | AC5: Sugar beet | AD5: Wheat | AE5: Egg white | AF5: CO2 | AG5: CH4 | AH5: N2O
A6: NF-01 | B6: Cultured Meat (Bos. Spp.) | C6: Novel food | D6: =F6+G6+H6+I6 -> 21.543 | F6: ='Inputs - Cultured Meat'!B10 -> 4.057 | G6: ='Inputs - Cultured Meat'!B7 -> 8.407 | H6: ='Inputs - Cultured Meat'!B8 -> 0.848 | I6: ='Inputs - Cultured Meat'!B9 -> 8.231 | AB6: ='Inputs - Cultured Meat'!F7 -> 1.81404
A7: NF-02 | B7: Microbial Milk (T. reesei) | C7: Novel food | D7: =SUM(J7:M7) -> 4.9783 | J7: ='Inputs - Microbial Milk'!B8 -> 0.0072 | K7: ='Inputs - Microbial Milk'!B9 -> 0.07092 | L7: ='Inputs - Microbial Milk'!B10 -> 4.9 | M7: ='Inputs - Microbial Milk'!B11 -> 0.00018 | AB7: ='Inputs - Microbial Milk'!F8 -> 0.91666667 | AF7: ='Inputs - Microbial Milk'!J25 -> 0.25 | AG7: 0 | AH7: 0
A8: NF-03 | B8: Microbial Ovalbumin (T. reesei) | C8: Novel food | D8: =SUM(G8:H8) -> 22.314572 | G8: 20.605572 | H8: 1.709 | AB8: ='Input - Microbial Ovalbumin'!F7 -> 2.3368 | AF8: ='Input - Microbial Ovalbumin'!J28 -> 2.3997629 | AG8: 0 | AH8: 0
A9: NF-04 | B9: Microbial Protein (Solein) | C9: Novel food | D9: =SUM(G9:O9) -> 65.0862 | H9: =0.0795*3.6 -> 0.2862 | L9: =0.12*3.6 -> 0.432 | N9: =17.83*3.6 -> 64.188 | O9: =0.05*3.6 -> 0.18 | AF9: ='Input - Microbial Protein'!J36 -> 0.42808047 | AG9: 0 | AH9: 0
A10: NF-05 | B10: Mycoprotein (Quorn) | C10: Novel food | D10: =SUM(G10:O10) -> 21.32 | N10: ='Input - Mycoprotein'!B7 -> 21.32 | AD10: 2.1 | AE10: ='Input - Mycoprotein'!F8 -> 0.04 | AF10: ='Input - Mycoprotein'!J20 -> 0.12 | AG10: 0 | AH10: 0
A11: NF-06 | B11: Yeast Fat (Rhodotorula babjevae) | C11: Novel food | D11: =Z11*'Emission factors'!E22 -> 0.453904 | Z11: ='Input - Yeast Microb. Fat'!B10 -> 0.012895 | AF11: ='Input - Yeast Microb. Fat'!Q14 -> 0.54869928 | AG11: ='Input - Yeast Microb. Fat'!R14 -> 0.001130748 | AH11: ='Input - Yeast Microb. Fat'!S14 -> 4.11412e-05
A12: NF-07 | B12: Algae Fat (Schizochytrium) | C12: Novel food | D12: =SUM(N12,O12,R12,S12,W12) -> 11.410002 | N12: ='Input - Algae Microb. Fat'!B9 -> 0.42666984 | O12: ='Input - Algae Microb. Fat'!B8+'Input - Algae Microb. Fat'!B10 -> 0.54275063 | R12: ='Input - Algae Microb. Fat'!B10 -> 0.33375063 | S12: ='Input - Algae Microb. Fat'!B7 -> 10 | W12: ='Input - Algae Microb. Fat'!B11 -> 0.10683118 | AB12: ='Input - Algae Microb. Fat'!F7 -> 3.3177406 | AF12: ='Input - Algae Microb. Fat'!J27 -> 0.288813 | AG12: 0 | AH12: 0

Sheet Agri ing
A2: Agricultural ingredients
A4: Average European wheat, from SAFAD ID Footprints RPC.csv
A6: Long code | B6: FoodEx2 code | C6: FoodEx2 name | D6: SUA code | E6: SUA name | F6: Category | G6: Country name | H6: Country code | I6: Carbon footprint, primary production | J6: Carbon dioxide, primary production | K6: Methane, fossil, primary production | L6: Methane, biogenic, primary production | M6: Nitrous oxide, primary production | N6: Land | O6: N input | P6: P input | Q6: Water | R6: Pesticides | S6: Biodiversity | T6: Ammonia | U6: Animal welfare | V6: Antibiotics | W6: Mineral fertiliser production (CO2e) | X6: Capital goods (CO2e) | Y6: Soil emissions (CO2e) | Z6: Energy primary production (CO2e) | AA6: Land use change (CO2e) | AB6: Enteric fermentation (CO2e) | AC6: Manure management (CO2e) | AD6: Mineral fertiliser production (CO2) | AE6: Capital goods (CO2) | AF6: Energy primary production (CO2) | AG6: Land use change (CO2) | AH6: Mineral fertiliser production (CH4, fossil) | AI6: Capital goods (CH4, fossil) | AJ6: Energy primary production (CH4, fossil) | AK6: Soil emissions (CH4, biogenic) | AL6: Enteric fermentation (CH4, biogenic) | AM6: Manure management (CH4, biogenic) | AN6: Mineral fertiliser production (N2O) | AO6: Capital goods (N2O) | AP6: Soil emissions (N2O) | AQ6: Energy primary production (N2O) | AR6: Manure management (N2O)
A7: A.01.02.001.003 | B7: A001N | C7: Wheat grain soft | D7: 111 | E7: Wheat, average | F7: Cereals, incl feed | G7: Spain | H7: ES | I7: 0.35858385 | J7: 0.21240208 | K7: 0.00033073111 | L7: 0 | M7: 0.00049936257 | N7: 2.8117689 | O7: 0.023505915 | P7: 0.002150868 | Q7: 0.047600962 | R7: 0.21934758 | S7: 1.9212074e-12 | T7: 0.0014290328 | W7: 0.15101916 | X7: 0.0301313 | Y7: 0.080341633 | Z7: 0.097091753 | AA7: 0 | AD7: 0.090958865 | AE7: 0.027 | AF7: 0.094443212 | AH7: 0.00017394359 | AI7: 9.5e-05 | AJ7: 6.1787517e-05 | AN7: 0.00020101383 | AO7: 1.1e-06 | AP7: 0.0002942917 | AQ7: 2.9570446e-06
A8: A.01.02.001.003 | B8: A001N | C8: Wheat grain soft | D8: 111 | E8: Wheat, average | F8: Cereals, incl feed | G8: Greece | H8: GR | I8: 0.37848193 | J8: 0.23180504 | K8: 0.00034268734 | L8: 0 | M8: 0.00049987108 | N8: 3.4819669 | O8: 0.023505915 | P8: 0.002150868 | Q8: 0.028818304 | R8: 0.097309934 | S8: 1.6393528e-12 | T8: 0.0014290328 | W8: 0.15101916 | X8: 0.0301313 | Y8: 0.080341633 | Z8: 0.11698983 | AA8: 0 | AD8: 0.090958865 | AE8: 0.027 | AF8: 0.11384618 | AH8: 0.00017394359 | AI8: 9.5e-05 | AJ8: 7.3743743e-05 | AN8: 0.00020101383 | AO8: 1.1e-06 | AP8: 0.0002942917 | AQ8: 3.4655481e-06
A9: A.01.02.001.003 | B9: A001N | C9: Wheat grain soft | D9: 111 | E9: Wheat, average | F9: Cereals, incl feed | G9: Italy | H9: IT | I9: 0.35454064 | J9: 0.20809208 | K9: 0.0003406528 | L9: 0 | M9: 0.00049925678 | N9: 2.5320815 | O9: 0.023505915 | P9: 0.002150868 | Q9: 0.016090387 | R9: 0.10403672 | S9: 1.362592e-12 | T9: 0.0014290328 | W9: 0.15101916 | X9: 0.0301313 | Y9: 0.080341633 | Z9: 0.093048542 | AA9: 0 | AD9: 0.090958865 | AE9: 0.027 | AF9: 0.090133217 | AH9: 0.00017394359 | AI9: 9.5e-05 | AJ9: 7.1709208e-05 | AN9: 0.00020101383 | AO9: 1.1e-06 | AP9: 0.0002942917 | AQ9: 2.8512453e-06
A10: A.01.02.001.003 | B10: A001N | C10: Wheat grain soft | D10: 111 | E10: Wheat, average | F10: Cereals, incl feed | G10: Bulgaria | H10: BG | I10: 0.34480681 | J10: 0.199461 | K10: 0.00030775188 | L10: 0 | M10: 0.00049880882 | N10: 1.947761 | O10: 0.023505915 | P10: 0.002150868 | Q10: 2.7644003e-05 | R10: 0.17870363 | S10: 3.5470211e-13 | T10: 0.0014290328 | W10: 0.15101916 | X10: 0.0301313 | Y10: 0.080341633 | Z10: 0.083314718 | AA10: 0 | AD10: 0.090958865 | AE10: 0.027 | AF10: 0.081502132 | AH10: 0.00017394359 | AI10: 9.5e-05 | AJ10: 3.880829e-05 | AN10: 0.00020101383 | AO10: 1.1e-06 | AP10: 0.0002942917 | AQ10: 2.4032944e-06
A11: A.01.02.001.003 | B11: A001N | C11: Wheat grain soft | D11: 111 | E11: Wheat, average | F11: Cereals, incl feed | G11: Hungary | H11: HU | I11: 0.34040676 | J11: 0.19470709 | K11: 0.00031949299 | L11: 0 | M11: 0.00049882337 | N11: 1.8354416 | O11: 0.023505915 | P11: 0.002150868 | Q11: 0.0018303203 | R11: 0.17803784 | S11: 2.3049048e-13 | T11: 0.0014290328 | W11: 0.15101916 | X11: 0.0301313 | Y11: 0.080341633 | Z11: 0.078914671 | AA11: 0 | AD11: 0.090958865 | AE11: 0.027 | AF11: 0.076748228 | AH11: 0.00017394359 | AI11: 9.5e-05 | AJ11: 5.0549395e-05 | AN11: 0.00020101383 | AO11: 1.1e-06 | AP11: 0.0002942917 | AQ11: 2.4178415e-06
A12: A.01.02.001.003 | B12: A001N | C12: Wheat grain soft | D12: 111 | E12: Wheat, average | F12: Cereals, incl feed | G12: France | H12: FR | I12: 0.40512466 | J12: 0.17977536 | K12: 0.00029952406 | L12: 0 | M12: 0.00079276 | N12: 1.4134955 | O12: 0.023505915 | P12: 0.002150868 | Q12: 0.0013300634 | R12: 0.2654611 | S12: 1.6992252e-13 | T12: 0.0014290328 | W12: 0.15101916 | X12: 0.0301313 | Y12: 0.16068327 | Z12: 0.063290932 | AA12: 0 | AD12: 0.090958865 | AE12: 0.027 | AF12: 0.061816498 | AH12: 0.00017394359 | AI12: 9.5e-05 | AJ12: 3.0580471e-05 | AN12: 0.00020101383 | AO12: 1.1e-06 | AP12: 0.00058858339 | AQ12: 2.0627704e-06
A13: A.01.02.001.003 | B13: A001N | C13: Wheat grain soft | D13: 111 | E13: Wheat, average | F13: Cereals, incl feed | G13: Germany | H13: DE | I13: 0.4118356 | J13: 0.18608858 | K13: 0.00031088175 | L13: 0 | M13: 0.00079297711 | N13: 1.3573899 | O13: 0.023505915 | P13: 0.002150868 | Q13: 1.0074339e-09 | R13: 0.25897847 | S13: 1.2449839e-13 | T13: 0.0014290328 | W13: 0.15101916 | X13: 0.0301313 | Y13: 0.16068327 | Z13: 0.070001877 | AA13: 0 | AD13: 0.090958865 | AE13: 0.027 | AF13: 0.068129712 | AH13: 0.00017394359 | AI13: 9.5e-05 | AJ13: 4.1938154e-05 | AN13: 0.00020101383 | AO13: 1.1e-06 | AP13: 0.00058858339 | AQ13: 2.2798815e-06
A14: A.01.02.001.003 | B14: A001N | C14: Wheat grain soft | D14: 111 | E14: Wheat, average | F14: Cereals, incl feed | G14: Netherlands | H14: NL | I14: 0.45626277 | J14: 0.18377756 | K14: 0.00031454821 | L14: 0 | M14: 0.000963779 | N14: 1.1452051 | O14: 0.023505915 | P14: 0.002150868 | Q14: 0 | R14: 0.25898128 | S14: 9.2731183e-14 | T14: 0.0014290328 | W14: 0.15101916 | X14: 0.0301313 | Y14: 0.20733437 | Z14: 0.067777935 | AA14: 0 | AD14: 0.090958865 | AE14: 0.027 | AF14: 0.065818698 | AH14: 0.00017394359 | AI14: 9.5e-05 | AJ14: 4.5604613e-05 | AN14: 0.00020101383 | AO14: 1.1e-06 | AP14: 0.00075946656 | AQ14: 2.1986047e-06
A15: A.01.02.001.003 | B15: A001N | C15: Wheat grain soft | D15: 111 | E15: Wheat, average | F15: Cereals, incl feed | G15: Poland | H15: PL | I15: 0.43778024 | J15: 0.21115429 | K15: 0.0003373049 | L15: 0 | M15: 0.00079331234 | N15: 2.1388178 | O15: 0.023505915 | P15: 0.002150868 | Q15: 0.00039847055 | R15: 0.24782973 | S15: 8.5197036e-14 | T15: 0.0014290328 | W15: 0.15101916 | X15: 0.0301313 | Y15: 0.16068327 | Z15: 0.095946514 | AA15: 0 | AD15: 0.090958865 | AE15: 0.027 | AF15: 0.093195422 | AH15: 0.00017394359 | AI15: 9.5e-05 | AJ15: 6.8361302e-05 | AN15: 0.00020101383 | AO15: 1.1e-06 | AP15: 0.00058858339 | AQ15: 2.6151121e-06
A16: A.01.02.001.003 | B16: A001N | C16: Wheat grain soft | D16: 111 | E16: Wheat, average | F16: Cereals, incl feed | G16: UK | H16: GB | I16: 0.45494276 | J16: 0.1828115 | K16: 0.00030362931 | L16: 0 | M16: 0.00096367437 | N16: 1.2579756 | O16: 0.023505915 | P16: 0.002150868 | Q16: 0.00012489644 | R16: 0.53529283 | S16: 5.3415447e-14 | T16: 0.0014290328 | W16: 0.15101916 | X16: 0.0301313 | Y16: 0.20733437 | Z16: 0.066457927 | AA16: 0 | AD16: 0.090958865 | AE16: 0.027 | AF16: 0.064852638 | AH16: 0.00017394359 | AI16: 9.5e-05 | AJ16: 3.4685719e-05 | AN16: 0.00020101383 | AO16: 1.1e-06 | AP16: 0.00075946656 | AQ16: 2.0939751e-06
A17: A.01.02.001.003 | B17: A001N | C17: Wheat grain soft | D17: 111 | E17: Wheat, average | F17: Cereals, incl feed | G17: Ireland | H17: IE | I17: 0.45161565 | J17: 0.17963216 | K17: 0.00029937004 | L17: 0 | M17: 0.00096359803 | N17: 1.0926168 | O17: 0.023505915 | P17: 0.002150868 | Q17: 0 | R17: 0.53535264 | S17: 4.8031404e-14 | T17: 0.0014290328 | W17: 0.15101916 | X17: 0.0301313 | Y17: 0.20733437 | Z17: 0.06313082 | AA17: 0 | AD17: 0.090958865 | AE17: 0.027 | AF17: 0.061673298 | AH17: 0.00017394359 | AI17: 9.5e-05 | AJ17: 3.0426446e-05 | AN17: 0.00020101383 | AO17: 1.1e-06 | AP17: 0.00075946656 | AQ17: 2.017631e-06
A18: A.01.02.001.003 | B18: A001N | C18: Wheat grain soft | D18: 111 | E18: Wheat, average | F18: Cereals, incl feed | G18: Denmark | H18: DK | I18: 0.42374027 | J18: 0.16651572 | K18: 0.00022306585 | L18: 0 | M18: 0.00091786516 | N18: 1.311496 | O18: 0.023505915 | P18: 0.002150868 | Q18: 0.0063497346 | R18: 0.11829774 | S18: 4.6761367e-14 | T18: 0.0014290328 | W18: 0.11883716 | X18: 0.0301313 | Y18: 0.20733437 | Z18: 0.067437437 | AA18: 0 | AD18: 0.073741077 | AE18: 0.027 | AF18: 0.065774639 | AH18: 9.2769917e-05 | AI18: 9.5e-05 | AJ18: 3.5295936e-05 | AN18: 0.00015506058 | AO18: 1.1e-06 | AP18: 0.00075946656 | AQ18: 2.2380172e-06
A19: A.01.02.001.003 | B19: A001N | C19: Wheat grain soft | D19: 111 | E19: Wheat, average | F19: Cereals, incl feed | G19: Sweden | H19: SE | I19: 0.42153795 | J19: 0.16484003 | K19: 0.00021569594 | L19: 0 | M19: 0.00091674057 | N19: 1.5363343 | O19: 0.023505915 | P19: 0.002150868 | Q19: 0 | R19: 0.11368874 | S19: 3.1435368e-14 | T19: 0.0014290328 | W19: 0.11883716 | X19: 0.0301313 | Y19: 0.2070589 | Z19: 0.065510587 | AA19: 0 | AD19: 0.073741077 | AE19: 0.027 | AF19: 0.064098957 | AH19: 9.2769917e-05 | AI19: 9.5e-05 | AJ19: 2.7926026e-05 | AN19: 0.00015506058 | AO19: 1.1e-06 | AP19: 0.00075845752 | AQ19: 2.1224701e-06
A21: Average | I21: =AVERAGE(I7:I19) -> 0.40305076 | J21: =AVERAGE(J7:J19) -> 0.19238942 | K21: =AVERAGE(K7:K19) -> 0.0003034874 | L21: =AVERAGE(L7:L19) -> 0 | M21: =AVERAGE(M7:M19) -> 0.00073852532 | N21: =AVERAGE(N7:N19) -> 1.8355655 | O21: =AVERAGE(O7:O19) -> 0.023505915 | P21: =AVERAGE(P7:P19) -> 0.002150868 | ... T21: =AVERAGE(T7:T19) -> 0.0014290328 | W21: =AVERAGE(W7:W19) -> 0.14606808 | X21: =AVERAGE(X7:X19) -> 0.0301313 | Y21: =AVERAGE(Y7:Y19) -> 0.14770418 | Z21: =AVERAGE(Z7:Z19) -> 0.079147196 | AA21: =AVERAGE(AA7:AA19) -> 0 | AD21: =AVERAGE(AD7:AD19) -> 0.088309974 | AE21: =AVERAGE(AE7:AE19) -> 0.027 | AF21: =AVERAGE(AF7:AF19) -> 0.077079448 | AH21: =AVERAGE(AH7:AH19) -> 0.00016145534 | AI21: =AVERAGE(AI7:AI19) -> 9.5e-05 | AJ21: =AVERAGE(AJ7:AJ19) -> 4.7032063e-05 | AN21: =AVERAGE(AN7:AN19) -> 0.0001939441 | AO21: =AVERAGE(AO7:AO19) -> 1.1e-06 | AP21: =AVERAGE(AP7:AP19) -> 0.00054104096 | AQ21: =AVERAGE(AQ7:AQ19) -> 2.4402643e-06
A23: Glucose and egg-white from Sweden, from SAFAD OR Footprints per Food.csv
A25: Code | B25: Name | C25: L1 Category | D25: L2 Category | E25: Amount (g) | F25: Carbon footprint, total (kg CO2e) | G25: Carbon dioxide, total (kg CO2) | H25: Methane, fossil, total (kg CH4) | I25: Methane, biogenic, total (kg CH4) | J25: Nitrous oxide, total (kg N2O) | K25: Carbon footprint, primary production (kg CO2e) | L25: Carbon dioxide, primary production (kg CO2) | M25: Methane, fossil, primary production (kg CH4) | N25: Methane, biogenic, primary production (kg CH4) | O25: Nitrous oxide, primary production (kg N2O) | P25: Cropland (m2*year/kg) | Q25: New N input (kg N/kg) | R25: New P input (kg P/kg) | S25: Water (m3/kg) | T25: Pesticides (g a.i/kg) | U25: Biodiversity (E/MSY/kg) | V25: Ammonia (kg NH3/kg) | W25: Animal welfare (index) | X25: Antibiotics (index) | Y25: Mineral fertiliser production (kg CO2e) | Z25: Capital goods (kg CO2e) | AA25: Soil emissions (kg CO2e) | AB25: Energy primary production (kg CO2e) | AC25: Land use change (kg CO2e) | AD25: Enteric fermentation (kg CO2e) | AE25: Manure management (kg CO2e) | AF25: Mineral fertiliser production (kg CO2) | AG25: Capital goods (kg CO2) | AH25: Energy primary production (kg CO2) | AI25: Land use change (kg CO2) | AJ25: Mineral fertiliser production (kg CH4, fossil) | AK25: Capital goods (kg CH4, fossil) | AL25: Energy primary production (kg CH4, fossil) | AM25: Soil emissions (kg CH4, biogenic) | AN25: Enteric fermentation (kg CH4, biogenic) | AO25: Manure management (kg CH4, biogenic) | AP25: Mineral fertiliser production (kg N2O) | AQ25: Capital goods (kg N2O) | AR25: Soil emissions (kg N2O) | AS25: Energy primary production (kg N2O) | AT25: Manure management (kg N2O) | AU25: Processing (kg CO2e) | AV25: Processing (kg CO2) | AW25: Processing (kg CH4, fossil) | AX25: Processing (kg N2O) | AY25: Packaging (kg CO2e) | AZ25: Packaging (kg CO2) | BA25: Packaging (kg CH4, fossil) | BB25: Packaging (kg CH4, biogenic) | BC25: Packaging (kg N2O) | BD25: Transports (kg CO2e) | BE25: Transports (kg CO2) | BF25: Transports (kg CH4, fossil) | BG25: Transports (kg N2O) | BH25: Processes | BI25: Packaging | BJ25: RPCs with missing data
A26: A.09.01.003 | B26: Egg white, chicken | C26: Eggs and egg products | D26: Eggs, fresh | E26: 1000 | F26: 1.100993 | G26: 0.53410034 | H26: 0.00097095782 | I26: 0.0017762317 | J26: 0.0017948712 | K26: 0.98803448 | L26: 0.43539274 | M26: 0.0005394469 | N26: 0.0017688315 | O26: 0.0017905047 | P26: 4.1347098 | Q26: 0.051102373 | R26: 0.0056513559 | S26: 0.018652834 | T26: 0.31622552 | U26: 3.0792991e-13 | V26: 0.0029296108 | W26: 7.3010877 | X26: 0.20668482 | Y26: 0.24400951 | Z26: 0.065175471 | AA26: 0.39741235 | AB26: 0.2062393 | AC26: 0.026804999 | AD26: 0 | AE26: 0.048392851 | AF26: 0.15007612 | AG26: 0.058421603 | AH26: 0.20176353 | AI26: 0.026804999 | AJ26: 0.00020276087 | AK26: 0.00020672001 | AL26: 0.030343961 | AM26: 0 | AN26: 0 | AO26: 0.0017688315 | AP26: 0.00032194547 | AQ26: 2.1744035e-06 | AR26: 0.0014557229 | AS26: 0.03025612 | AT26: 2.3238143e-06 | AU26: 0 | AV26: 0 | AW26: 0 | AX26: 0 | AY26: 0.089016251 | AZ26: 0.075751878 | BA26: 0.00041101278 | BB26: 7.4002291e-06 | BC26: 2.9904245e-06 | BD26: 0.023942246 | BE26: 0.02295572 | BF26: 2.0498142e-05 | BG26: 1.3761237e-06 | BI26: P15
A27: A.10.01.008 | B27: Glucose | C27: Sugar and confectionary | D27: Sugars | E27: 1000 | F27: 1.2340466 | G27: 0.94395528 | H27: 0.0012874373 | I27: 3.1812082e-06 | J27: 0.00092175758 | K27: 0.58200563 | L27: 0.31824838 | M27: 0.0006567863 | N27: 0 | O27: 0.00089445063 | P27: 1.8475516 | Q27: 0.025189285 | R27: 0.008242811 | S27: 0.093910377 | T27: 0.47361803 | U27: 1.7221704e-13 | V27: 0.0015313726 | W27: 0 | X27: 0 | Y27: 0.14996812 | Z27: 0.12035584 | AA27: 0.18751824 | AB27: 0.12416344 | AC27: 0 | AD27: 0 | AE27: 0 | AF27: 0.091124271 | AG27: 0.10784824 | AH27: 0.11927587 | AI27: 0 | AJ27: 0.00015646994 | AK27: 0.00037946602 | AL27: 0.00012085035 | AM27: 0 | AN27: 0 | AO27: 0 | AP27: 0.00019846538 | AQ27: 4.393817e-06 | AR27: 0.00068687998 | AS27: 4.7114447e-06 | AT27: 0 | AU27: 0.52974367 | AV27: 0.51218174 | AW27: 0.00039643834 | AX27: 2.1055197e-05 | AY27: 0.034386004 | AZ27: 0.029270132 | BA27: 0.00015928617 | BB27: 3.1812082e-06 | BC27: 1.0375506e-06 | BD27: 0.08791131 | BE27: 0.084255023 | BF27: 7.4926516e-05 | BG27: 5.2142017e-06 | BH27: F28.A07MJ$F28.A0C0B$F28.A0BZV | BI27: P14

Sheet Emission factors
A1: Emission factors
A3: Emissions from production and use of electricity (ecoinvent version 3.9.1, market for electricity SE, low voltage) and fuels (Gode et al. 2011)
B5: kg CO2 per MJ | C5: kg CH4 per MJ | D5: kg N2O per MJ | E5: Heating value, MJ/l
A6: Electricity DK | B6: 0.10292557 | C6: 0.00014196512 | D6: 5.2954623e-06
A7: Electricity NL | B7: 0.13798108 | C7: 0.00027318679 | D7: 5.5395645e-06
A8: Electricity DE | B8: 0.12875094 | C8: 0.00024628641 | D8: 5.766389e-06
A9: Electricity CH | B9: 0.024569539 | C9: 2.7299597e-05 | D9: 2.2701113e-06 | F9: Appox Sweden - CHANGE!!
A10: Electricity FI | B10: 0.082558826 | C10: 0.00016764997 | D10: 5.3824904e-06
A11: Electricity SE | B11: 0.024569539 | C11: 2.7299597e-05 | D11: 2.2701113e-06
A12: Electricity IL | B12: 0.68244528 | C12: 0.0020803369 | D12: 1.7179664e-05
A13: Electricity US | B13: 0.14597086 | C13: 0.00022650193 | D13: 4.1184503e-06
A14: Electricity GB | B14: 0.10943436 | C14: 0.00015716313 | D14: 3.8883158e-06
A15: Electricity GB, Quorn | B15: =0.10943435744675*0.25 -> 0.027358589 | C15: =0.000157163129221278*0.25 -> 3.9290782e-05 | D15: =3.88831584166667E-06*0.25 -> 9.7207896e-07 | F15: This is a energy mix set to get a carbon footprint of approx. 2 kg CO2e, Quorn has updated to renewable energy and states a carbon footprint of 1.7 kg CO2e but we round upto 2 kg CO2e
A16: Heating oil | B16: 0.08056 | C16: 3.06e-05 | D16: 2.8526e-06 | E16: 41
A17: Natural gas | B17: 0.062 | C17: 0.00028 | D17: 2e-06
A18: Other fossil energy sources | B18: 0.071 | C18: 0.000155 | D18: 1.325e-06 | F18: Average of heating oil and natural gas
A19: Bark and chips | B19: 0.0017 | C19: 2.8666667e-06 | D19: 6.7666667e-07
A20: Pellets and briquettes | B20: 0.00365 | C20: 1.75e-05 | D20: 7.8e-06
A21: Other renewable energy sources | B21: 0.002675 | C21: 1.0183333e-05 | D21: 4.2383333e-06 | F21: Average of bark and chips; pellets and briquettes
A22: Diesel fuel | B22: 0.07592 | C22: 3.363e-05 | D22: 2.04e-06 | E22: 35.2
A23: District heating | B23: 0.024611111 | C23: 0 | D23: 0 | F23: Representative for Sweden
A26: Emissions from the production of N mineral fertilizer
B28: kg CO2 per kg N | C28: kg CH4 per kg N | D28: kg N2O per kg N | E28: Fraction of tech* | F28: Source:
A29: Best Available Technology (BAT) | B29: 2.3 | C29: 0 | D29: 0.0043624161 | E29: 0.6 | F29: Yara International 2010
A30: Ammonium nitrate** | B30: 4.3928214 | C30: 0.0098666567 | D30: 0.0099480316 | E30: 0.4 | F30: Ecoinvent Centre, 2021, Activity name: “Ammonium nitrate production", Rest of the world, adjusted to N content in fertilizer (33.5%)
A31: *Swedish Agency for Public Management (2010)

Sheet CF climate
A2: Characterisation factors (CF) climate change
B4: Carbon dioxide (CO2) | C4: Biogenic methane (CH4) | D4: Fossil methane (CH4) | E4: Nitrous oxide (N2O) | F4: Chlorodifluoromethane (HCFC-22) | G4: Source:
B5: 1 | C5: 27 | D5: 29.8 | E5: 273 | F5: 1960 | G5: IPCC, 2021

Sheet Types of NFs table
A1: Table 1. Examples of cellular and acellular products, their origins and cellular agricultural components.
G2: Table 2. Our novel foods for Mistra FF, WP3 diet scenarios
A3: CELLULAR AGRICULTURE PRODUCTS | G3: Input Data Collected/to be included? | H3: Consumer Category | I3: Production Type | J3: Cell origin** | K3: Notes
A4: Consumer product category | B4: Cell Origin | C4: CellAg component | G4: Cellular/Acellular/Fermentation
A5: Cellular | C5: (Cells as main product) | G5: Y | H5: Meat | I5: Cellular | J5: An | K5: Culturing the protein/meat cells
A6: Meat | B6: A | C6: Cultured meat cells | G6: N | H6: Fish | I6: Cellular | J6: An | K6: Not yet being done/no LCA--> Similar to cultured bovine meat, but with aquaculture component
A7: Fish | B7: A | C7: Cultured fish cells | G7: N | H7: Milk | I7: Acellular | J7: An | K7: Not yet being done --> Cell cultured mammalian Gland Cells for milk ingredient production
A8: Coffee | B8: P | C8: Cultured Coffee cells | G8: Y | H8: Milk | I8: Precision Fermentation* | J8: B / F | K8: Microbial production of casein or beta-lactoglobulin
A9: Chocolate | B9: P | C9: Cultured Cacao cells | G9: Y | H9: Egg white | I9: Precision Fermentation* | J9: F | K9: Microbial production of ovalbumin
A10: Fat | B10: A | C10: Cultured Fat Cells | G10: Y | H10: Protein (Solein powder) | I10: Cellular | J10: B | K10: Microbical production of protein cells
A11: Microbial protein | B11: B | C11: Solein - Protein powder | G11: Y | H11: Protein (Quorn product) | I11: Fermentation | J11: F | K11: Fungi-based protein, Similar to conventional fermentation
C12: (Proteins produced by growing microbial (cells) using carbon dioxide capture) | G12: N | H12: Fat | I12: Cellular | J12: An | K12: Not widely being done/studied/no LCA-->cultured insect or psosible other livestock (see Fats, CellAg tab)
A13: Acellular | C13: (Substances produced by the cultivated cells) | G13: Y | H13: Fat | I13: Fermentation | J13: B / F / Alg | K13: Fungus producing oils with microalgal sugars, cenventional fermentaion
A14: Gelatin | B14: A | C14: Cell culturing for gelatin production | G14: Other/Agricultural
A15: Milk | B15: B / F | C15: Precision fermentation Casein milk protein | G15: Y | H15: Insects | I15: Agriculture | J15: An | K15: Similar to livestock rearing, feed and conventional inputs
A16: Milk | B16: A | C16: Cell cultured mammalian Gland Cells for cow milk ingredient production | G16: Blue Food
A17: Baby formula | B17: A | C17: Cell cultured mammalian Gland Cells for human milk production | G17: N | H17: Kelp | I17: Mariculture | J17: P | K17: Moved to Blue food
A18: Egg white | B18: F | C18: Precision fermentation ovalbumin | G18: N | H18: Microalgae | I18: Mariculture | J18: Alg | K18: Moved to Blue food
A19: Fat | B19: B / F | C19: Precision fermentation fats that mimic animal fats | G19: **Origin: An = Animal, Alg = Algae, B = Bacteria, F = Fungi, P = Plant
A20: Heme | B20: B | C20: Precision fermentation heme
C21: (Gives the blood taste for plant based burger) | I21: *What is precision fermentation?
A22: Other | I22: Precision fermentation uses genetically modified microorganisms to produce specific proteins, enzymes, and other compounds. This is accomplished by inserting genes into the microorganisms' DNA to allow them to produce the desired product. The term "precision" refers to the ability to precisely control the process, from the genetic modification of the microorganisms to the optimization of fermentation conditions.
A23: Mycoprotein | B23: F | C23: Fermentation of fungus cells | I23: What is the difference between general fermentation and precision fermentation?
A24: Origin: A = Animal, B = Bacteria, F = Fungi, P = Plant | I24: The main distinction between precision fermentation and general fermentation is that the microorganisms used in precision fermentation are designed to create a particular end product.
I25: Source: Precision Fermentation simply explained
C26: Additional possible references
C27: Cultured fish cells
D28: Ref(s)
D29: Rubio, N., Datar, I., Stachura, D., Kaplan, D., & Krueger, K. (2019). Cell-based fish: a novel approach to seafood production and an opportunity for cellular agriculture. Frontiers in Sustainable Food Systems, 3, 43.
C30: Precision fermentation heme | D30: Reis, G. G., Heidemann, M. S., Goes, H. A. A., & Molento, C. F. M. (2021). Can radical innovation mitigate environmental and animal welfare misconduct in global value chains? The case of cell-based tuna. Technological Forecasting and Social Change, 169, 120845.
D31: Telesetsky, A. (2023). Cellular mariculture: Challenges of delivering sustainable protein security. Marine Policy, 147, 105400.
D32: Ge, J., Wang, X., Bai, Y., Wang, Y., Wang, Y., Tu, T., ... & Zhang, J. (2023). Engineering Escherichia coli for efficient assembly of heme proteins. Microbial Cell Factories, 22(1), 1-14.
G40: Group | H40: High Tech Novel Foods | I40: Low Tech Novel Foods | J40: High Tech (highly processed) meat/diary alternatives | K40: Low Tech (minimally processed) meat/dairy alternatives | L40: Other/Blue Foods
G41: Foods | H41: cultured meat, microbial milk, microbial protein, microbial ovalbumin, microbial fat | I41: mycoprotein (Quorn), insects | J41: soy based meat alternatives (e.g., soy sausages), oat/soy drink | K41: tofu, tempeh, falafel | L41: kelp, microalgae, mussels, oysters
G43: Scenario(s) {to be discussed} | H43: Food as Tech | I43: … | J43: all | K43: Food as Culture | L43: …
A51: ASF Analog | B51: Production Type | C51: Cell origin* | D51: Notes
A52: Cellular/Acellular/Precision Fermentaion
A53: Meat (red) | B53: Cellular | C53: An | D53: Culturing the protein/meat cells
A54: Fish | B54: Cellular | C54: An | D54: Not yet being done/no LCA--> Similar to cultured bovine meat, but with aquaculture component
A55: Milk | B55: Precision Fermentation* | C55: B / F | D55: Microbial production of casein or beta-lactoglobulin
A56: Egg white | B56: Precision Fermentation* | C56: F | D56: Microbial production of ovalbumin
A57: Protein (Solein powder) | B57: Cellular | C57: B | D57: Microbical production of protein cells
A58: Fat | B58: Cellular | C58: An | D58: Not widely being done/studied/no LCA-->cultured insect or psosible other livestock (see Fats, CellAg tab)
A59: Fat | B59: Precision Fermentation* | C59: B / F / Alg | D59: Fungus producing oils with microalgal sugars, cenventional fermentaion
A60: Coffee | B60: Cellular | C60: B / P
A61: Cocoa | B61: Cellular | C61: B / P
A62: Plant-Based/Conventional Agriculture
A63: Insects | B63: Agriculture | C63: An | D63: Similar to livestock rearing, feed and conventional inputs
A64: Mycoprotein (Quorn) | B64: Fermentation | C64: F | D64: Fungi-based protein, Similar to conventional fermentation
A65: Tofu | B65: Fermentation | C65: P | D65: Crop inputs, medium processing
A66: Tempeh | B66: Fermentation | C66: P | D66: Crop inputs, medium processing
A67: Seitan | B67: Agriculture | C67: P | D67: Crop inputs, medium processing
A68: PB-cheese | B68: Agriculture | C68: P | D68: Crop inputs, ingredient isolation or extrusion
A69: PB-milk | B69: Agriculture | C69: P | D69: Crop inputs, ingredient isolation or extrusion
A70: PB-fish | B70: Agriculture | C70: P | D70: Crop inputs, ingredient isolation or extrusion
A71: PB-meat-products | B71: Agriculture | C71: P | D71: Crop inputs, ingredient isolation or extrusion
A72: *Origin: An = Animal, Alg = Algae, B = Bacteria, F = Fungi, P = Plant

Sheet Inputs - Cultured Meat
A2: Cultured Meat
C3: CulturedMeatCombined (CMC) | D3: Tuomisto et al. (2022)
K4: NOT USED (GRAY)
A5: Processes | E5: Raw commodities | K5: Other stuff / ingredients
A6: Name | B6: Amount | C6: Unit (per kg prod) | E6: RAC | F6: Amount | G6: Unit (per kg prod) | K6: Item | L6: Amount | M6: Unit (per kg prod)
A7: Bioreactor | B7: 8.407 | C7: MJ | E7: Glucose | F7: =F21 -> 1.81404 | G7: kg | K7: Oxygen | L7: 0.556 | M7: kg
A8: Cleaning | B8: 0.848 | C8: MJ | K8: Polystyrene | L8: 0.1007 | M8: kg
A9: Water sterilisation | B9: 8.231 | C9: MJ | K9: tapwater | L9: 403.12 | M9: L
A10: Production of medium ingrediets | B10: 4.057 | C10: MJ | K10: sodium hydroxide, without water, in 50% solution state | L10: 0.059 | M10: kg
A11: Total | B11: 21.543
A13: The above data are used in the calculations, received from author correspondence with Hanna Tuomisto
A16: NOTES
A17: See below for the LCI data, we used the cultured meat combined (CMC) scenario from Tuomisto et al. (2022) | K17: Published | M17: % of total GWP
A18: We assume that it is only the DMEM in the ingredient list that comes from agriculture | K18: Minor/Other | L18: Vitamins and minerals | M18: 95
A19: Dulbecco's Modified Eagle's Medium (DMEM) is a 4.5 g/L concentration of glucose, we assume DMEM has a density of 1 kg/L | E19: RAC* | F19: Amount | G19: Unit (per kg prod) | K19: Minor/Other
A20: Source for DMEM data from the producer: https://www.nordicbiolabs.se/nordic-biolabs-ab/cellodling-cellbiologi/cellodlingsmedier/klassiska-medier/dmem/dmem-ha-product | E20: Dulbecco's Modified Eagle's Medium (DMEM) | F20: =C74 -> 403.12 | G20: kg
A21: 95% of GWP is from ingredients (vitamins, oxygen, DMEM, minerals) | E21: Glucose (4.5 g/kg DMEM) | F21: =F20*0.0045 -> 1.81404 | G21: kg glucose
A22: 65% of energy use is from ingredients | K22: Total GWP of Other | L22: =L23*(M18/100) -> 4.636 | M22: kg CO2e/kg
K23: Published total | L23: 4.88 | M23: kg CO2e/kg
A26: highlighted values are used
A41: NOT USED (GRAY)
A42: Tuomisto, H. L., Allan, S. J., & Ellis, M. J. (2022). Prospective life cycle assessment of a bioprocess design for cultured meat production in hollow fiber bioreactors. Science of the Total Environment, 851, 158051.
A43: Supplementary data
A45: Prospective life cycle assessment of a bioprocess design for cultured meat production in hollow fiber bioreactors
A46: Hanna L. Tuomisto, Scott J. Allan, Marianne J. Ellis | M46: Fig. 4. Contribution of different processes on the environmental impacts of cultured meat baseline (CMB) scenario and cultured meat combined (CMC) scenario.
A49: Structure of the data file
A51: The sheet called "LCI data" shows and overview of the data used for the scenarios and refers to the other sheet for additional information regarding specific processes
A52: The basis for those calculations are explained in detail in the Supplementary Information file.
A56: The basis for the parameter values are explained in Process LCI-sheet and the Supplementary Information -file.
A58: The scenarios as explained in Section 2.2.2 in the main manuscript
A60: LCI data
A63: Parameter | B63: Unit | C63: CulturedMeatBaseline (CMB) | D63: 128% mass increase (CMB128) | E63: CulturedMeatCombined (CMC) | F63: adjusted amino acids | G63: Chemical wastewater treatment | H63: CHO cells | J63: Doubling time experimental | K63: seawater cooling | L63: serum-free baseline | M63: Serum free experimental | N63: solar energy | O63: TrypLE | P63: water recycling | Q63: wind energy | R63: Source
A64: INPUTS
A65: Amino0 | B65: Item(s) | C65: 0 | D65: 0 | E65: 0 | F65: 1 | K65: 0 | L65: 0 | N65: 0 | O65: 0 | P65: 0 | Q65: 0 | R65: See Amino-acids-actual-0 - GB in AminoAcids-sheet
A66: Bioreactor energy (Average) | B66: MJ | C66: 19.245 | D66: 8.407 | E66: 0 | F66: 19.245 | G66: 19.245 | H66: 6.323 | J66: 17.845 | K66: 19.12 | L66: 19.245 | M66: 23.816 | N66: 0 | O66: 19.245 | P66: 19.245 | Q66: 0 | R66: Ecoinvent process: market for electricity, medium voltage | electricity, medium voltage | APOS, S - GB
A67: Bioreactor energy (Solar) | B67: MJ | C67: 0 | D67: 0 | E67: 0 | F67: 0 | G67: 0 | K67: 0 | L67: 0 | N67: 19.245 | O67: 0 | P67: 0 | Q67: 0 | R67: Ecoinvent process: electricity production, photovoltaic, 570kWp open ground installation, multi-Si | electricity, low voltage | APOS, S - GB
A68: Bioreactor energy (Wind) | B68: MJ | C68: 0 | D68: 0 | E68: 8.407 | F68: 0 | G68: 0 | K68: 0 | L68: 0 | N68: 0 | O68: 0 | P68: 0 | Q68: 19.245 | R68: Ecoinvent process: electricity production, wind, >3MW turbine, onshore | electricity, high voltage | APOS, S - GB
A69: Clean0 | B69: Item(s) | C69: 1 | D69: 0 | E69: 0 | F69: 1 | G69: 1 | H69: 1 | J69: 1 | K69: 1 | L69: 1 | M69: 1 | N69: 0 | O69: 1 | P69: 1 | Q69: 0 | R69: See Cleaning-sheet
A70: Clean128 | B70: Item(s) | C70: 0 | D70: 1 | E70: 0 | F70: 0 | G70: 0 | K70: 0 | L70: 0 | N70: 0 | O70: 0 | P70: 0 | Q70: 0 | R70: See Cleaning-sheet
A71: CleanSolar | B71: Item(s) | C71: 0 | D71: 0 | E71: 0 | F71: 0 | G71: 0 | K71: 0 | L71: 0 | N71: 1 | O71: 0 | P71: 0 | Q71: 0 | R71: See Cleaning-sheet
A72: CleanWind | B72: Item(s) | C72: 0 | D72: 0 | E72: 0 | F72: 0 | G72: 0 | K72: 0 | L72: 0 | N72: 0 | O72: 0 | P72: 0 | Q72: 1 | R72: See Cleaning-sheet
A73: CleanWind128 | B73: Item(s) | C73: 0 | D73: 0 | E73: 1 | F73: 0 | G73: 0 | K73: 0 | L73: 0 | N73: 0 | O73: 0 | P73: 0 | Q73: 0 | R73: See Cleaning-sheet
A74: DMEM | B74: kg | C74: 403.12 | D74: 176.9 | E74: 0 | F74: 0 | G74: 403.12 | H74: 130.6 | J74: 367.08 | K74: 403.12 | L74: 0 | N74: 0 | O74: 403.12 | P74: 403.12 | Q74: 0 | R74: See DMEM LCI and DMEM -sheets
A75: DMEM (Solar) | B75: kg | C75: 0 | D75: 0 | E75: 0 | F75: 0 | G75: 0 | K75: 0 | L75: 0 | N75: 403.12 | O75: 0 | P75: 0 | Q75: 0 | R75: See DMEM LCI and DMEM -sheets
A76: DMEM (Wind) | B76: kg | C76: 0 | D76: 0 | E76: 0 | F76: 0 | G76: 0 | K76: 0 | L76: 0 | N76: 0 | O76: 0 | P76: 0 | Q76: 403.12 | R76: See DMEM LCI and DMEM -sheets
A77: DMEM without amino acids | B77: kg | C77: 0 | D77: 0 | E77: 0 | F77: 403.12 | G77: 0 | K77: 0 | L77: 0 | N77: 0 | O77: 0 | P77: 0 | Q77: 0 | R77: DMEM without aminoa acids, see DMEM -sheet
A78: Essential | B78: kg | C78: 0 | D78: 0 | E78: 0 | F78: 0 | G78: 0 | K78: 0 | L78: 426.1 | M78: 544.7 | N78: 0 | O78: 0 | P78: 0 | Q78: 0 | R78: See Essential8-sheet
A79: EssentialWind | B79: kg | C79: 0 | D79: 0 | E79: 187 | F79: 0 | G79: 0 | K79: 0 | L79: 0 | N79: 0 | O79: 0 | P79: 0 | Q79: 0 | R79: See Essential8-sheet
A80: FBS | B80: kg | C80: 0.1906 | D80: 0.08377 | E80: 0 | F80: 0.1906 | G80: 0.1906 | H80: 0.061545 | J80: 0.1574 | K80: 0.1906 | L80: 0 | N80: 0.1906 | O80: 0.1906 | P80: 0.1906 | Q80: 0.1906 | R80: Ecoinvent process: urea production, as N | urea, as N | APOS, S - RER; see Supplementary Information Section 2 for details
A81: Glutamine | B81: kg | C81: 0.1008 | D81: 0.0444 | E81: 0 | F81: 0 | G81: 0.1008 | H81: 0.0288 | J81: 0.0848 | K81: 0.1008 | L81: 0 | M81: 0.1468 | N81: 0 | O81: 0.1008 | P81: 0.1008 | Q81: 0 | R81: See Glutamine -sheet
A82: Glutamine (Solar) | B82: kg | C82: 0 | D82: 0 | E82: 0 | F82: 0 | G82: 0 | K82: 0 | L82: 0 | N82: 0.1008 | O82: 0 | P82: 0 | Q82: 0 | R82: See Glutamine -sheet
A83: Glutamine (Wind) | B83: kg | C83: 0 | D83: 0 | E83: 0.0444 | F83: 0 | G83: 0 | K83: 0 | L83: 0 | N83: 0 | O83: 0 | P83: 0 | Q83: 0.1008 | R83: See Glutamine -sheet
A84: Oxygen | B84: kg | C84: 0.556 | D84: 0.244 | E84: 0.244 | F84: 0.556 | G84: 0.556 | H84: 0.55586 | J84: 0.526 | K84: 0.556 | L84: 0.556 | M84: 0.564 | N84: 0.556 | O84: 0.556 | P84: 0.556 | Q84: 0.556 | R84: Ecoinvent process: market for oxygen, liquid | oxygen, liquid | APOS, S - RER
A85: Polystyrene | B85: kg | C85: 0.1007 | D85: 0.0473 | E85: 0.1007 | F85: 0.1007 | G85: 0.1007 | H85: 0.1007 | J85: 0.1007 | K85: 0.1007 | L85: 0.1007 | M85: 0.1007 | N85: 0.1007 | O85: 0.1007 | P85: 0.1007 | Q85: 0.1007 | R85: Ecoinvent process: polystyrene production, general purpose | polystyrene, general purpose | APOS, S - RER
A86: SodiumHypo | B86: kg | C86: 0 | D86: 0 | E86: 0 | F86: 0 | G86: 1.089 | K86: 0 | L86: 0 | N86: 0 | O86: 0 | P86: 0 | Q86: 0 | R86: Ecoinvent process: market for sodium hypochlorite, without water, in 15% solution state | sodium hypochlorite, without water, in 15% solution state | APOS, S - RER
A87: tapwater | B87: L | C87: 403.12 | D87: 176.9 | E87: 43.96 | F87: 403.12 | G87: =403.12+8.7 -> 411.82 | H87: 130.6 | J87: 367.08 | K87: 403.12 | L87: 426.1 | M87: 544.7 | N87: 403.12 | O87: 403.12 | P87: 100.18 | Q87: 403.12 | R87: Ecoinvent process: market for tap water | tap water | APOS, S - Europe without Switzerland
A88: TrypLE | B88: L | O88: 3.087 | R88: See TrypLE-sheet
A89: WaterSterilisation | B89: MJ | C89: 15.456 | D89: 6.78 | E89: 0 | F89: 15.456 | G89: 0 | H89: 5.007 | J89: 15.456 | K89: 15.456 | L89: 15.456 | M89: 15.456 | N89: 0 | O89: 15.456 | P89: 3.841 | Q89: 0 | R89: Ecoinvent process: market for electricity, medium voltage | electricity, medium voltage | APOS, S - GB
A90: WaterSterilisation (Solar) | B90: MJ | C90: 0 | D90: 0 | E90: 0 | F90: 0 | G90: 0 | K90: 0 | L90: 0 | N90: 15.456 | O90: 0 | P90: 0 | Q90: 0 | R90: Ecoinvent process: electricity production, photovoltaic, 570kWp open ground installation, multi-Si | electricity, low voltage | APOS, S - GB
A91: WaterSterilisation (Wind) | B91: MJ | C91: 0 | D91: 0 | E91: 1.6857 | F91: 0 | G91: 0 | K91: 0 | L91: 0 | N91: 0 | O91: 0 | P91: 0 | Q91: 15.456 | R91: Ecoinvent process: electricity production, wind, >3MW turbine, onshore | electricity, high voltage | APOS, S - GB
A92: OUTPUTS
A93: Cultured meat | B93: kg | C93: 1 | D93: 1 | E93: 1 | F93: 1 | G93: 1 | H93: 1 | J93: 1 | K93: 1 | L93: 1 | M93: 1 | N93: 1 | O93: 1 | P93: 1
A94: Lactate | B94: kg | C94: 1.74 | D94: 0.77 | E94: 0.77 | F94: 1.74 | G94: 1.74 | H94: 1.22 | J94: 1.74 | K94: 1.74 | L94: 1.74 | M94: 1.74 | N94: 1.74 | O94: 1.74 | P94: 1.74 | Q94: 1.74
A95: Ammonia | B95: g | C95: 2.2 | D95: 1 | E95: 1 | F95: 1 | G95: 1 | H95: 1 | J95: 1 | K95: 1 | L95: 1 | M95: 1 | N95: 1 | O95: 1 | P95: 1 | Q95: 1
A96: WasteWater | B96: L | C96: 420.803 | D96: 185.131 | E96: 52.191 | F96: 420.803 | G96: =420.803+8.7 -> 429.503 | H96: 148.283 | J96: 384.763 | K96: 420.803 | L96: 420.803 | M96: 562.383 | N96: 420.803 | O96: 420.803 | P96: 117.863 | Q96: 420.803 | R96: Ecoinvent process: market for Was teWater | Was teWater | APOS, S - Europe without Switzerland
A100: DMEM LCA models | N100: Ingredients used in the DMEM | P100: DMEM LCI
A101: The inventory data is provided on DMEM LCI Sheet. If provider is not an LCA database, the specific sheet is indicated. | O101: =4500/O108 -> 2.8019925
Q102: Marinussen & Kool 2010
N103: DMEM D7777 | S103: Requirements in the baseline scenario with different cell mass increase rates
N104: Source for ingredient amounts: Sigma-Aldrich, Product Information, Dulbecco's Modified Eagle's Medium (DME), St. Louis, MO, USA
A105: DMEM (1 L without water) | N105: Classification for average amino acid and hydrolysis product categories based on Mattick et al. 2015. For vitamins produced through fermentation, the same data than for average amino acid production was used. | S105: kg/kg cultured meat
A106: Flow | C106: Amount | D106: Unit | E106: Provider | S106: 0 | U106: 1.28
A107: Average amino acid | C107: 869.8 | D107: mg | E107: Average amino acid | F107: AminoAcids | N107: Components | O107: Concentration (mg/L) | P107: OpenLCA provider | Q107: Database/Data assumptions | R107: Note | T107: SE | V107: SE
A108: calcium chloride | C108: 200 | D108: mg | E108: market for calcium chloride | calcium chloride | APOS, S - RER | F108: Ecoinvent 3.6 | N108: Amino Acids | O108: =SUM(O109:O123) -> 1606 | S108: 0.64741072 | T108: 0.12379048 | U108: 0.2841014 | V108: 0.05434704
A109: glucose | C109: 4500 | D109: mg | E109: market for glucose | glucose | APOS, S - GLO | F109: Ecoinvent 3.6 | N109: Glycine | O109: 30 | P109: Average amino acid | Q109: 50% L-Lysine and 50% L-Threonine | R109: See AminoAcids-sheet for further details | S109: 0.0120936 | T109: 0.0023124 | U109: 0.005307 | V109: 0.0010152
A110: Glutamine | C110: 585 | D110: mg | E110: Glutamine - GB | F110: Glutamine | N110: L-Glutamine | O110: 584 | P110: Glutamine -GB | Q110: Mattick et al. 2015 | R110: See Glutamine-sheet for further details | S110: 0.23542208 | T110: 0.04501472 | U110: 0.1033096 | V110: 0.01976256
A111: Hydrolysis product | C111: 27.2 | D111: mg | E111: Hydrolysis product - GB | F111: AminoAcids | N111: L-Arginine hydrochloride | O111: 84 | P111: Average amino acid | Q111: 50% L-Lysine and 50% L-Threonine | R111: See AminoAcids-sheet for further details | S111: 0.03386208 | T111: 0.00647472 | U111: 0.0148596 | V111: 0.00284256
A112: iron sulfate | C112: 0.1 | D112: mg | E112: market for iron sulfate | iron sulfate | APOS, S - RER | F112: Ecoinvent 3.6 | N112: L-Cystine 2HCl | O112: 63 | P112: Average amino acid | Q112: 50% L-Lysine and 50% L-Threonine | R112: See AminoAcids-sheet for further details | S112: 0.02539656 | T112: 0.00485604 | U112: 0.0111447 | V112: 0.00213192
A113: L-Lysine | C113: 146 | D113: mg | E113: L-Lysine production | F113: AminoAcids | N113: L-Histidine hydrochloride-H2O | O113: 42 | P113: Average amino acid | Q113: 50% L-Lysine and 50% L-Threonine | R113: See AminoAcids-sheet for further details | S113: 0.01693104 | T113: 0.00323736 | U113: 0.0074298 | V113: 0.00142128
A114: L-Threonine - GB | C114: 95 | D114: mg | E114: L-Threonine | F114: AminoAcids | N114: L-Isoleucine | O114: 105 | P114: Average amino acid | Q114: 50% L-Lysine and 50% L-Threonine | R114: See AminoAcids-sheet for further details | S114: 0.0423276 | T114: 0.0080934 | U114: 0.0185745 | V114: 0.0035532
A115: magnesium sulfate | C115: 97.67 | D115: mg | E115: market for magnesium sulfate | magnesium sulfate | APOS, S - GLO | F115: Ecoinvent 3.6 | N115: L-Leucine | O115: 105 | P115: Average amino acid | Q115: 50% L-Lysine and 50% L-Threonine | R115: See AminoAcids-sheet for further details | S115: 0.0423276 | T115: 0.0080934 | U115: 0.0185745 | V115: 0.0035532
A116: Methionine | C116: 30 | D116: mg | E116: Methionine - GB | F116: AminoAcids | N116: L-Lysine hydrochloride | O116: 146 | P116: L-Lysine | Q116: Marinussen & Kool 2010 | R116: See AminoAcids-sheet for further details | S116: 0.05885552 | T116: 0.01125368 | U116: 0.0258274 | V116: 0.00494064
A117: potassium chloride, as K2O | C117: 400 | D117: mg | E117: potassium chloride production | potassium chloride, as K2O | APOS, S - RER | F117: Ecoinvent 3.6 | N117: L-Methionine | O117: 30 | P117: Methionine-GB | Q117: Marinussen & Kool 2010 | R117: See AminoAcids-sheet for further details | S117: 0.0120936 | T117: 0.0023124 | U117: 0.005307 | V117: 0.0010152
A118: sodium bicarbonate | C118: 3700 | D118: mg | E118: market for sodium bicarbonate | sodium bicarbonate | APOS, S - GLO | F118: Ecoinvent 3.6 | N118: L-Phenylalanine | O118: 66 | P118: Average amino acid | Q118: 50% L-Lysine and 50% L-Threonine | R118: See AminoAcids-sheet for further details | S118: 0.02660592 | T118: 0.00508728 | U118: 0.0116754 | V118: 0.00223344
A119: sodium chloride, powder | C119: 6400 | D119: mg | E119: sodium chloride production, powder | sodium chloride, powder | APOS, S - RER | F119: Ecoinvent 3.6 | N119: L-Serine | O119: 42 | P119: Average amino acid | Q119: 50% L-Lysine and 50% L-Threonine | R119: See AminoAcids-sheet for further details | S119: 0.01693104 | T119: 0.00323736 | U119: 0.0074298 | V119: 0.00142128
A120: sodium phosphate | C120: 109 | D120: mg | E120: market for sodium phosphate | sodium phosphate | APOS, S - RER | F120: Ecoinvent 3.6 | N120: L-Threonine | O120: 95 | P120: L-Threonine | Q120: Marinussen & Kool 2010 | R120: See AminoAcids-sheet for further details | S120: 0.0382964 | T120: 0.0073226 | U120: 0.0168055 | V120: 0.0032148
N121: L-Tryptophan | O121: 16 | P121: Average amino acid | Q121: 50% L-Lysine and 50% L-Threonine | R121: See AminoAcids-sheet for further details | S121: 0.00644992 | T121: 0.00123328 | U121: 0.0028304 | V121: 0.00054144
N122: L-Tyrosine * 2Na * 2h2O | O122: 104 | P122: Average amino acid | Q122: 50% L-Lysine and 50% L-Threonine | R122: See AminoAcids-sheet for further details | S122: 0.04192448 | T122: 0.00801632 | U122: 0.0183976 | V122: 0.00351936
A123: DMEM-wind (1 L without water) | N123: L-Valine | O123: 94 | P123: Average amino acid | Q123: 50% L-Lysine and 50% L-Threonine | R123: See AminoAcids-sheet for further details | S123: 0.03789328 | T123: 0.00724552 | U123: 0.0166286 | V123: 0.00318096
A124: Flow | C124: Amount | D124: Unit | E124: Provider | N124: Vitamins | S124: 0 | T124: 0 | U124: 0 | V124: 0
A125: Average amino acid | C125: 869.8 | D125: mg | E125: Average amino acid wind | F125: AminoAcids | N125: Choline chloride | O125: 4 | P125: Hydrolysis product | Q125: Hydrolysis | R125: See AminoAcids-sheet for further details | S125: 0.00161248 | T125: 0.00030832 | U125: 0.0007076 | V125: 0.00013536
A126: calcium chloride | C126: 200 | D126: mg | E126: market for calcium chloride | calcium chloride | APOS, S - RER | F126: Ecoinvent 3.6 | N126: D-Panthothenic Acid * 1/2Ca | O126: 4 | P126: Hydrolysis product | Q126: Hydrolysis | R126: See AminoAcids-sheet for further details | S126: 0.00161248 | T126: 0.00030832 | U126: 0.0007076 | V126: 0.00013536
A127: glucose | C127: 4500 | D127: mg | E127: market for glucose | glucose | APOS, S - GLO | F127: Ecoinvent 3.6 | N127: Folic Acid | O127: 4 | P127: Average amino acid | Q127: 50% L-Lysine and 50% L-Threonine | R127: See AminoAcids-sheet for further details | S127: 0.00161248 | T127: 0.00030832 | U127: 0.0007076 | V127: 0.00013536
A128: Glutamine | C128: 585 | D128: mg | E128: Glutamine -wind | F128: Glutamine | N128: Niacinamide | O128: 4 | P128: Hydrolysis product | Q128: Hydrolysis | R128: See AminoAcids-sheet for further details | S128: 0.00161248 | T128: 0.00030832 | U128: 0.0007076 | V128: 0.00013536
A129: Hydrolysis product | C129: 27.2 | D129: mg | E129: Hydrolysis product -wind | F129: AminoAcids | N129: Pyridoxine * HCL | O129: 4 | P129: =P128 -> Hydrolysis product | Q129: Hydrolysis | R129: See AminoAcids-sheet for further details | S129: 0.00161248 | T129: 0.00030832 | U129: 0.0007076 | V129: 0.00013536
A130: iron sulfate | C130: 0.1 | D130: mg | E130: market for iron sulfate | iron sulfate | APOS, S - RER | F130: Ecoinvent 3.6 | N130: Riboflavin | O130: 0.4 | P130: Average amino acid | Q130: 50% L-Lysine and 50% L-Threonine | R130: See AminoAcids-sheet for further details | S130: 0.000161248 | T130: 3.0832e-05 | U130: 7.076e-05 | V130: 1.3536e-05
A131: L-Lysine | C131: 146 | D131: mg | E131: L-Lysine production wind | F131: AminoAcids | N131: Thiamine hydrochloride | O131: 4 | P131: Hydrolysis product | Q131: Hydrolysis | R131: See AminoAcids-sheet for further details | S131: 0.00161248 | T131: 0.00030832 | U131: 0.0007076 | V131: 0.00013536
A132: L-Threonine - GB | C132: 95 | D132: mg | E132: L-Threonine -wind | F132: AminoAcids | N132: i-Inositol | O132: 7.2 | P132: Hydrolysis product | Q132: Hydrolysis | R132: See AminoAcids-sheet for further details | S132: 0.002902464 | T132: 0.000554976 | U132: 0.00127368 | V132: 0.000243648
A133: magnesium sulfate | C133: 97.67 | D133: mg | E133: market for magnesium sulfate | magnesium sulfate | APOS, S - GLO | F133: Ecoinvent 3.6 | N133: Inorganic Salts | S133: 0 | T133: 0 | U133: 0 | V133: 0
A134: Methionine | C134: 30 | D134: mg | E134: Methionine - GB | F134: AminoAcids | N134: Calcium Chloride (CaCl2-2H2O) | O134: 200 | P134: market for calcium chloride | calcium chloride | APOS, S - RER | Q134: Ecoinvent 3.6 | S134: 0.080624 | T134: 0.015416 | U134: 0.03538 | V134: 0.006768
...

Sheet Inputs - Microbial Milk
A2: Microbial Milk**
A3: Option 1 | E3: Recombinant beta-lactoglobulin (BLG) | F3: Behm et al. (2022) | G3: Scenario 1 (base scenario)—carbon source: sugar beet glucose, fungal biomass applied as feed, 90% product purity, produced in Germany
A4: Converted units--> MJ or kg per kg product (density = 1 kg/L) | E4: T. reesei, Acellular, precision fermentation | G4: functional unit of this study was one tonne of dry rBLG
I5: NOT USED (GRAY)
A6: Processes | E6: Raw commodities | I6: Other stuff / ingredients
A7: Name | B7: Amount | C7: Unit | E7: RAC* | F7: Amount | G7: Unit (per kg prod) | I7: Item | J7: Amount | K7: Unit (per kg prod)
A8: Microfiltration | B8: =((B40*3.6)/1000) -> 0.0072 | C8: MJ | E8: Glucose | F8: =(1/A16+A19)*A21 -> 0.91666667 | G8: kg | I8: Sodium hydroxide, NaOH (dry) | J8: =J40 -> 0.3 | K8: kg
A9: Combined ultra- and diafiltration | B9: =((B41*3.6)/1000) -> 0.07092 | C9: MJ | I9: Sodium chloride, NaCl (dry) | J9: =J41 -> 2.4 | K9: kg
A10: Spray drying | B10: =B42 -> 4.9 | C10: MJ | I10: Sodium phosphate, Na2HPO4 (dry) | J10: =J42 -> 0.05 | K10: kg
A11: SMB system (Chromatographic separation) | B11: =((B43*3.6)/1000) -> 0.00018 | C11: MJ | I11: Trisodium phosphate, NaH2PO4 (dry) | J11: =J43 -> 0.24 | K11: kg
I12: Process water | J12: =J44 -> 145 | K12: L
I13: Antifoam agent | J13: =J45 -> 0 | K13: kg
I14: Ammonium sulphate | J14: =F42/1000 -> 0.0014 | K14: kg
A15: NOTES | I15: Potassium phosphate | J15: =F43/1000 -> 0.002 | K15: kg
A16: 0.24 | B16: kg of enzyme (rBLG)/kg glucose - from Table 18 in Humbird et al. (2011) (see below) | I16: Magnesium sulphate | J16: =F44/1000 -> 0.0003 | K16: kg
A17: 50 | B17: g/L enzyme titer at harvest - from Table 18 in Humbird et al (2011) | I17: Calcium chloride | J17: =F45/1000 -> 0.0004 | K17: kg
A18: 10 | B18: g/L corn steep liquor for 50 g/L of enzyme | I18: Corn steep liquor (nitrogen) | J18: =F40/1000 -> 0.01 | K18: kg
A19: =A17/A18 -> 5 | B19: ratio enzyme to corn steep
B20: Use any "corn steep liquor" to glucose as a proxy
A21: 0.1 | B21: Assume final "microbial milk" is composed of 90% water, and 10% rBLG enzyme | I21: Published | K21: kg CO2e/kg rBLG
I22: Minor/Other | J22: Other materials | K22: 0.25
I23: Minor/Other
A25: highlighted values are used | I25: Total GWP of Other | J25: =K22 -> 0.25 | K25: kg CO2e/kg
I26: Published total | J26: =10.9*A21 -> 1.09 | K26: kg CO2e/kg
A34: NOT USED (GRAY)
A35: Behm, K., Nappa, M., Aro, N., Welman, A., Ledgard, S., Suomalainen, M., & Hill, J. (2022). Comparison of carbon footprint and water scarcity footprint of milk protein produced by cellular agriculture and the dairy industry. The International Journal of Life Cycle Assessment, 27(8), 1017-1034.
A37: Oringinal units (scenario 1) | C37: Scenario 1 (base scenario—carbon source: glucose, fungal biomass applied as feed, 90% product purity
A38: Processes | E38: Raw commodities | I38: Other stuff / ingredients
A39: Name | B39: Amount | C39: Unit | E39: RAC* | F39: Amount | G39: Unit (per kg prod) | I39: Item | J39: Amount | K39: Unit (per kg prod)
A40: Microfiltration | B40: 2 | C40: kwh/m3 | E40: Corn steep liquor | F40: 10 | G40: g/l | I40: Sodium hydroxide, NaOH (dry) | J40: 0.3 | K40: kg/kg target protein
A41: Combined ultra- and diafiltration | B41: 19.7 | C41: kwh/m3 | E41: Antifoam agent | F41: 0.2 | G41: g/l | I41: Sodium chloride, NaCl (dry) | J41: 2.4 | K41: kg/kg target protein
A42: Spray drying | B42: 4.9 | C42: Gj/tonne | E42: Ammonium sulphate | F42: 1.4 | G42: g/l | I42: Sodium phosphate, Na2HPO4 (dry) | J42: 0.05 | K42: kg/kg target protein
A43: SMB system (Chromatographic separation) | B43: 0.05 | C43: kwh/m3 | E43: Potassium phosphate | F43: 2 | G43: g/l | I43: Trisodium phosphate, NaH2PO4 (dry) | J43: 0.24 | K43: kg/kg target protein
E44: Magnesium sulphate | F44: 0.3 | G44: g/l | I44: Process water | J44: 145 | K44: dm3/kg target protein
E45: Calcium chloride | F45: 0.4 | G45: g/l
A46: Additional information in the Supplementary Material
A49: Glucose information
A50: Source: Humbird, D, Davis, R, Tao, L, Kinchin, C, Hsu, D, Aden, A, Schoen, P, Lukas, J, Olthof, B, Worley, M, Sexton, D, and Dudgeon, D. Process Design and Economics for Biochemical Conversion of Lignocellulosic Biomass to Ethanol: Dilute-Acid Pretreatment and Enzymatic Hydrolysis of Corn Stover. United States: N. p., 2011. Web. doi:10.2172/1013269.
A58: Bhandari, P., Mason, S., & Olander, L. (2021). Life cycle assessment and carbon offset potential for cultured milk protein.
A59: Option 2 | E59: Casein in cultured milk - High-end baseline scenario** | F59: Bhandari et al. (2021) [fungal protein+cyanobacteria Smetana et al. (2017)]
A61: Processes | E61: Raw commodities | I61: Other stuff / ingredients
A62: Name | B62: Amount | C62: Unit (per kg prod) | E62: RAC* | F62: Amount | G62: Unit (per kg prod) | I62: Item | J62: Amount | K62: Unit (per kg prod)
A63: Bioreactor energy (Natural gas) | B63: =208.8*0.05 -> 10.44 | C63: MJ | E63: Sugar (beet) | F63: =60*0.05 -> 3 | G63: kg | I63: Water | J63: =2.95*0.05 -> 0.1475 | K63: L
A64: Cleaning of the bioreactor (copied from Tuomisto et al. 2022 - cultured meat process) | B64: 1.709 | C64: MJ | E64: Glucose | F64: =F73*F69 -> 0.06426 | G64: kg | I64: Hydrogen peroxide, 3% solution | J64: =2.4*F69 -> 0.4536 | K64: m^3
A65: WaterSterilisation (copied from Tuomisto et al. 2022 - cultured meat process) | B65: 15.456 | C65: MJ | E65: Fertilizers (Nitrogen) | F65: =F74*F69 -> 0.000378 | G65: kg | I65: Steam | J65: =0.5*F69 -> 0.0945 | K65: kg
A66: Cyanobacteria cultivation (natural gas) | B66: =0.6192*F69 -> 0.1170288 | C66: MJ | E66: Fertilizers (Phosphorus) | F66: =F75*F69 -> 0.000189 | G66: kg | I66: Electrodes (Fe, AL) | J66: =F76*F69 -> 0.000378 | K66: kg
A67: Cyanobacteria processing | B67: =0.0252*F69 -> 0.0047628 | C67: MJ
E69: Cyanobacteria (culture medium)*** | F69: =3.78*0.05 -> 0.189 | G69: kg cy/kg prod
E71: ***Estimates of cultured cyanobacteria information from Smetana et al. (2017)
E72: RAC of 1 kg Cyanobacteria | F72: Amount | G72: Unit (per kg prod)
E73: Glucose | F73: 0.34 | G73: kg
E74: Fertilizers (Nitrogen) | F74: 0.002 | G74: kg | I74: Published total | J74: =64.09*0.05 -> 3.2045 | K74: kg CO2e/kg
E75: Fertilizers (Phosphorus) | F75: 0.001 | G75: kg
E76: Electrodes (Fe, AL) | F76: 0.002 | G76: kg
A78: **It is likely tha 1 kg of cultured milk would be in the range of 3-5% by mass acellularly produced protein and mostly water and vitamins otherwise (low-end would be the estimate of production "at-scale" according to authors)
A83: Cultured milk protein production is a new and proprietary process, and so our analysis is based on data extracted from resources documenting similar production processes. We examined both the production of citric acid and the production of cultured meat or microbe-produced enzymes. The former is likely to underestimate the cultured milk protein production process’s environmental impact, and the latter is likely to overestimate that impact. We assume that emissions from cultured milk protein likely fall somewhere in between the under- and overestimate, and that actual production of cultured protein at-scale would more closely mimic that of our underestimate, based on industry research and emissions calculations for similar products.
A85: Location: | B85: India

Sheet Input - Microbial Ovalbumin
A2: Ovalbumin - Tr-OVA
C3: Ovalbumin (T. reesei)* | D3: Järviö et al. (2021)
C4: *1 kg of produt, with a 8% moisture content and 92% protein content, produced in Finland, average electricity mix | I4: NOT USED (GRAY)
A5: Processes** | E5: Raw commodities | I5: Other stuff / ingredients | N5: **Total Cumulartive Energy Demand
A6: Name | B6: Amount | C6: Unit (per kg prod) | E6: RAC*** | F6: Amount | G6: Unit (per kg prod) | I6: Item | J6: Amount | K6: Unit (per kg prod) | P6: 1 kg of ovalbumin produced by T. reesei (Tr-OVA).
A7: (Bioreactor) Electricity, medium voltage {FI}| market for | Cut-off, U | B7: 20.605572 | C7: MJ | E7: Glucose {WITH LULUC}| market for glucose | Cut-off, U | F7: 2.3368 | G7: kg | I7: Tap water {RER}| market group for | Cut-off, U | J7: 0.7677 | K7: kg | N7: Impact category | O7: Unit | P7: Finland | Q7: Finland - low carbon electricity mix | R7: Germany | S7: Poland
A8: Cleaning of the bioreactor (copied from Tuomisto et al. 2022 - cultured meat process) | B8: 1.709 | C8: MJ | I8: Magnesium sulfate {RER}| production | Cut-off, U | J8: 0.013984 | K8: kg | N8: Non renewable, fossil | O8: MJ | P8: 96.306274 | Q8: 71.345019 | R8: 135.73302 | S8: 180.9377
E9: ***Processes from Simapro | I9: Calcium chloride {RER}| market for calcium chloride | Cut-off, U | J9: 0.018676 | K9: kg | N9: Non-renewable, nuclear | O9: MJ | P9: 54.794086 | Q9: 79.03846 | R9: 25.0618 | S9: 8.161922
I10: Sodium phosphate {RER}| market for sodium phosphate | Cut-off, U | J10: 0.35052 | K10: kg | N10: Non-renewable, biomass | O10: MJ | P10: 0.73268299 | Q10: 0.73210316 | R10: 0.73233877 | S10: 0.732764
A11: **See Total Cumulative Energy Demand for comparisons | I11: Ammonium sulfate, as N {RER}| ammonium sulfate production | Cut-off, U | J11: 0.4702 | K11: kg | N11: Renewable, biomass | O11: MJ | P11: 24.199896 | Q11: 15.50912 | R11: 17.565716 | S11: 21.34572
I12: Zinc oxide {RER}| production | Cut-off, U | J12: 3.28e-05 | K12: kg | N12: Renewable, wind, solar, geothe | O12: MJ | P12: 2.7888769 | Q12: 3.3533537 | R12: 6.1397914 | S12: 4.075354
A13: highlighted values are used | I13: Cobalt {GLO}| production | Cut-off, U | J13: 8.65e-05 | K13: kg | N13: Renewable, water | O13: MJ | P13: 12.889405 | Q13: 15.57226 | R13: 3.6794272 | S13: 3.001821
I14: Iron sulfate {RER}| market for iron sulfate | Cut-off, U | J14: 0.000117 | K14: kg
I15: Manganese sulfate {GLO}| market for | Cut-off, U | J15: 3.74e-05 | K15: kg
I16: Tap water {FI}| market for | Cut-off, U | J16: 44.7 | K16: kg
I17: (Bioreactor) Natural gas, low pressure {FI}| market for | Cut-off, U | J17: 0.051121 | K17: m3
I18: Polydimethylsiloxane {GLO}| market for polydimethylsiloxane | Cut-off, U | J18: 0.039008 | K18: kg
I19: Ammonia, liquid {RER}| market for | Cut-off, U | J19: 0.2559 | K19: kg
I20: Biowaste {EU}| market for | Cut-off, U | J20: 3.65 | K20: kg
I23: Published | K23: % of total GWP
I24: Minor/Other | J24: Ammonia water | K24: 5.3821455
I25: Minor/Other | J25: Ammonium sulfate | K25: 9.1844688
I26: Minor/Other | J26: Salt mix | K26: 10.507066
I27: Minor total | K27: =SUM(K24:K26) -> 25.07368
I28: Total GWP of Other | J28: =J29*(K27/100) -> 2.3997629 | K28: kg CO2e/kg
I29: Published total | J29: 9.5708443 | K29: kg CO2e/kg
A35: NOT USED (GRAY)
A36: Järviö, N., Parviainen, T., Maljanen, N. L., Kobayashi, Y., Kujanpää, L., Ercili-Cura, D., ... & Tuomisto, H. L. (2021). Ovalbumin production using Trichoderma reesei culture and low-carbon energy could mitigate the environmental impacts of chicken-egg-derived ovalbumin. Nature food, 2(12), 1005-1013.
A38: Supportive information 2
A39: Natasha Järviö, Tuure Parviainen, Netta-Leena Maljanen, Yumi Kobayashi, Lauri Kujanpää, Dilek Ercili-Cura, Christopher P. Landowski, Toni Ryynänen, Emilia Nordlund, Hanna L. Tuomisto
A41: Content
A43: Topic | B43: Sheet name | C43: Description
A44: Deterministic results of Tr-OVA production | B44: Deterministic results | C44: Deterministic ReCiPe, CED and water scarcity results of Tr-OVA production for all four scenarios.
A45: Contribution analysis | B45: Contributions | C45: Contribution analysis of inputs per scenario.
B46: Contribution (%) | C46: Contribution analysis of inputs per scenario in %.
A47: Monte Carlo | B47: Monte Carlo results | C47: Results of the Monte Carlo runs for all scenarios and products per kg of product and per kg of protein.
B48: Monte Carlo runs | C48: All Monte Carlo results.
A49: Comparison Tr-OVA with egg white powder from chicken eggs | B49: Tr-OVA-chicken egg comparison | C49: Results of the comparison Tr-OVA with egg white powder from chicken eggs.
B50: Tr-OVA-egg comparison (%) | C50: Results of the comparison Tr-OVA with egg white powder from chicken eggs in percentages.
A51: Sensitivity analysis | B51: Senstivity test | C51: The results of the sensitivity test, taking into account uncertianties per test.
B52: Deterministic results sens.test | C52: Deterministic results of the sensitivity test.
A53: Statistical tests | B53: Descernibility test | C53: Results of the descernibility test.
B54: Dependent modified NHST | C54: Results of the dependent modified null-hypothesis significance testing.
A55: Allocation of by-products | B55: Allocation | C55: Allocation of by-products on a physical and economical basis.
A56: Simapro model | B56: Simapro Tr-OVA | C56: Simapro model of the Tr-OVA model for Finland (for German, Polish and low carbon scenariothe electricity source and natural gas source were changed to its respective country mix).
B57: Simapro chicken | C57: Simapro model of the egg white powder produced using chicken eggs for Germany (for the Polish scenario the electricity source was changed to the Polish electricity mix).
B58: Finnish low carbon mix | C58: Simapro model of the inputs and outputs of the Finnish low carbon electricity mix.
A62: Simapro model for Tr-OVA production | N62: ReCiPe results (per kg product) | U62: Cumulative energy demand (CED) (per kg product) | AB62: Water scarcity (per kg product)
A63: SimaPro 9.1.0.11 | B63: process | C63: Date: | D63: 44343 | E63: Time: | F63: 0.61072694 | N63: Calculation: | O63: Compare | U63: Calculation: | V63: Compare | AB63: Calculation: | AC63: Compare
A64: Project | B64: Tr_OVA | N64: Results: | O64: Impact assessment | U64: Results: | V64: Impact assessment | AB64: Results: | AC64: Impact assessment
N65: Product 1: | O65: 1 kg Tr_OVA (FI) (of project Tr_OVA) | U65: Product 1: | V65: 1 kg Tr_OVA (FI) (of project Tr_OVA) | AB65: Product 1: | AC65: 1 kg Tr_OVA (FI) (of project Tr_OVA)
A66: Outputs | N66: Product 2: | O66: 1 kg Tr_OVA (FI_LOW CARBON) (of project Tr_OVA) | U66: Product 2: | V66: 1 kg Tr_OVA (FI_LOW CARBON) (of project Tr_OVA) | AB66: Product 2: | AC66: 1 kg Tr_OVA (FI_LOW CARBON) (of project Tr_OVA)
A67: Products | B67: Amount | C67: Unit | D67: Allocation (%) | E67: Waste type | F67: Category | G67: Comments | N67: Product 3: | O67: 1 kg Tr_OVA (DE) (of project Tr_OVA) | U67: Product 3: | V67: 1 kg Tr_OVA (DE) (of project Tr_OVA) | AB67: Product 3: | AC67: 1 kg Tr_OVA (DE) (of project Tr_OVA)
A68: Tr_OVA (FI MC) | B68: 1 | C68: kg | D68: 100 | E68: not defined | F68: Agricultural\Food\Market | G68: 1 kg of produt, with a 8% moisture content and 92% protein content | N68: Product 4: | O68: 1 kg Tr_OVA (PL) (of project Tr_OVA) | U68: Product 4: | V68: 1 kg Tr_OVA (PL) (of project Tr_OVA) | AB68: Product 4: | AC68: 1 kg Tr_OVA (PL) (of project Tr_OVA)
N69: Method: | O69: ReCiPe 2016 Midpoint (H) V1.04 / World (2010) H | U69: Method: | V69: Cumulative Energy Demand V1.11 / Cumulative energy demand | AB69: Method: | AC69: AWARE_helsinki_area_TR-OVA V1.01
A70: Avoided products | N70: Indicator: | O70: Characterization | U70: Indicator: | V70: Characterization | AB70: Indicator: | AC70: Characterization
N71: Skip categories: | O71: Never | U71: Skip categories: | V71: Never | AB71: Skip categories: | AC71: Never
A72: Inputs | N72: Exclude infrastructure processes: | O72: No | U72: Exclude infrastructure processes: | V72: No | AB72: Exclude infrastructure processes: | AC72: No
A73: Resources | C73: Amount | D73: Unit | E73: Uncertainty distribution | G73: Min | H73: Max | I73: Comments | N73: Exclude long-term emissions: | O73: No | U73: Exclude long-term emissions: | V73: No | AB73: Exclude long-term emissions: | AC73: No
A74: Occupation, industrial area | C74: 0.01 | D74: m2a | E74: Uniform | G74: 0.008 | H74: 0.012 | I74: Calculated based on 100.000 kg per year, 75 years operational | N74: Sorted on item: | O74: Impact category | U74: Sorted on item: | V74: Impact category | AB74: Sorted on item: | AC74: Impact category
A75: Transformation, to industrial area | C75: 0.000133 | D75: m2 | E75: Uniform | G75: 0.000106667 | H75: 0.00016 | N75: Sort order: | O75: Ascending | U75: Sort order: | V75: Ascending | AB75: Sort order: | AC75: Ascending
A76: Transformation, from agriculture | C76: 0.000133 | D76: m2 | E76: Uniform | G76: 0.000106667 | H76: 0.00016
P77: 1 kg of ovalbumin produced by T. reesei (Tr-OVA). | W77: 1 kg of ovalbumin produced by T. reesei (Tr-OVA). | AD77: 1 kg of ovalbumin produced by T. reesei (Tr-OVA).
A78: Materials/fuels | B78: Amount | C78: Unit | D78: Uncertainty distribution | F78: Min | G78: Max | H78: Comments | N78: Impact category | O78: Unit | P78: Finland | Q78: Finland - low carbon electricity mix | R78: Germany | S78: Poland | U78: Impact category | V78: Unit | W78: Finland | X78: Finland - low carbon electricity mix | Y78: Germany | Z78: Poland | AB78: Impact category | AC78: Unit | AD78: Finland | AE78: Finland - low carbon electricity mix | AF78: Germany | AG78: Poland
A79: Glucose {WITH LULUC}| market for glucose | Cut-off, U | B79: 2.3368 | C79: kg | D79: Uniform | F79: 1.86944 | G79: 2.80416 | H79: Based on World Food LCA Database glucose | N79: Global warming | O79: kg CO2 eq | P79: 9.5708443 | Q79: 7.4002702 | R79: 13.178836 | S79: 16.960183 | U79: Non renewable, fossil | V79: MJ | W79: 96.306274 | X79: 71.345019 | Y79: 135.73302 | Z79: 180.93771 | AB79: Water use | AC79: m3 | AD79: 10.571886 | AE79: 10.559492 | AF79: 9.8931196 | AG79: 10.99907
A80: Polydimethylsiloxane {GLO}| market for polydimethylsiloxane | Cut-off, U | B80: 0.039008 | C80: kg | D80: Uniform | F80: 0.0312064 | G80: 0.0468096 | N80: Stratospheric ozone depletion | O80: kg CFC11 eq | P80: 7.9760849e-05 | Q80: 7.8193364e-05 | R80: 8.1645525e-05 | S80: 7.9613758e-05 | U80: Non-renewable, nuclear | V80: MJ | W80: 54.794086 | X80: 79.03846 | Y80: 25.0618 | Z80: 8.1619217
A81: Ammonia, liquid {RER}| market for | Cut-off, U | B81: 0.2559 | C81: kg | D81: Uniform | F81: 0.20473 | G81: 0.3071 | H81: Process is 100% ammonia, only need 25%, so multiplied by 0.25 and the rest modelled for average european tap water | N81: Ionizing radiation | O81: kBq Co-60 eq | P81: 3.0018586 | Q81: 4.3362163 | R81: 1.3086044 | S81: 0.42735178 | U81: Non-renewable, biomass | V81: MJ | W81: 0.73268299 | X81: 0.73210316 | Y81: 0.73233877 | Z81: 0.73276369
A82: Tap water {RER}| market group for | Cut-off, U | B82: 0.7677 | C82: kg | D82: Uniform | F82: 0.61419 | G82: 0.92129 | H82: Process is 100% ammonia, only need 25%, so multiplied by 0.25 and the rest modelled for average european tap water | N82: Ozone formation, Human health | O82: kg NOx eq | P82: 0.017093226 | Q82: 0.013468716 | R82: 0.019207038 | S82: 0.03251007 | U82: Renewable, biomass | V82: MJ | W82: 24.199896 | X82: 15.50912 | Y82: 17.565716 | Z82: 21.345721
A83: Magnesium sulfate {RER}| production | Cut-off, U | B83: 0.013984 | C83: kg | D83: Uniform | F83: 0.0111872 | G83: 0.0167808 | N83: Fine particulate matter formation | O83: kg PM2.5 eq | P83: 0.013729277 | Q83: 0.011135624 | R83: 0.013895931 | S83: 0.027831295 | U83: Renewable, wind, solar, geothe | V83: MJ | W83: 2.7888769 | X83: 3.3533537 | Y83: 6.1397914 | Z83: 4.075354
A84: Calcium chloride {RER}| market for calcium chloride | Cut-off, U | B84: 0.018676 | C84: kg | D84: Uniform | F84: 0.0149408 | G84: 0.0224112 | N84: Ozone formation, Terrestrial ecosystems | O84: kg NOx eq | P84: 0.017588905 | Q84: 0.013902338 | R84: 0.019693343 | S84: 0.033074545 | U84: Renewable, water | V84: MJ | W84: 12.889405 | X84: 15.57226 | Y84: 3.6794272 | Z84: 3.0018213
A85: Sodium phosphate {RER}| market for sodium phosphate | Cut-off, U | B85: 0.35052 | C85: kg | D85: Uniform | F85: 0.280416 | G85: 0.420624 | N85: Terrestrial acidification | O85: kg SO2 eq | P85: 0.034372275 | Q85: 0.028661756 | R85: 0.038220082 | S85: 0.078006599
A86: Ammonium sulfate, as N {RER}| ammonium sulfate production | Cut-off, U | B86: 0.4702 | C86: kg | D86: Uniform | F86: 0.37616 | G86: 0.56424 | N86: Freshwater eutrophication | O86: kg P eq | P86: 0.0036074272 | Q86: 0.002875369 | R86: 0.011267554 | S86: 0.015211445
A87: Zinc oxide {RER}| production | Cut-off, U | B87: 3.28e-05 | C87: kg | D87: Uniform | F87: 2.62e-05 | G87: 3.93e-05 | N87: Marine eutrophication | O87: kg N eq | P87: 0.005295955 | Q87: 0.0052715477 | R87: 0.0057391277 | S87: 0.0059660756
A88: Cobalt {GLO}| production | Cut-off, U | B88: 8.65e-05 | C88: kg | D88: Uniform | F88: 6.9184e-05 | G88: 0.000103776 | N88: Terrestrial ecotoxicity | O88: kg 1,4-DCB | P88: 35.605216 | Q88: 34.588305 | R88: 35.069207 | S88: 39.888978
A89: Iron sulfate {RER}| market for iron sulfate | Cut-off, U | B89: 0.000117 | C89: kg | D89: Uniform | F89: 9.3472e-05 | G89: 0.000140208 | N89: Freshwater ecotoxicity | O89: kg 1,4-DCB | P89: 0.8227704 | Q89: 0.80852937 | R89: 1.0114691 | S89: 1.1220725
A90: Manganese sulfate {GLO}| market for | Cut-off, U | B90: 3.74e-05 | C90: kg | D90: Uniform | F90: 2.99552e-05 | G90: 4.49328e-05 | N90: Marine ecotoxicity | O90: kg 1,4-DCB | P90: 0.71408069 | Q90: 0.69227156 | R90: 0.97274246 | S90: 1.1285038
A91: Tr_OVA Cleaning of (FI) | B91: 1 | C91: kg | D91: Uniform | F91: 0.8 | G91: 1.2 | N91: Human carcinogenic toxicity | O91: kg 1,4-DCB | P91: 0.6563152 | Q91: 0.60941529 | R91: 1.0131281 | S91: 1.3062583
A92: Tap water {FI}| market for | Cut-off, U | B92: 44.7 | C92: kg | D92: Uniform | F92: 35.76 | G92: 53.64 | N92: Human non-carcinogenic toxicity | O92: kg 1,4-DCB | P92: 12.438798 | Q92: 11.324999 | R92: 19.634037 | S92: 25.808483
N93: Land use | O93: m2a crop eq | P93: 4.5112921 | Q93: 4.1422381 | R93: 4.2450622 | S93: 4.4254283
A94: Electricity/heat | B94: Amount | C94: Unit | D94: Uncertainty distribution | F94: Min | G94: Max | H94: Comments | N94: Mineral resource scarcity | O94: kg Cu eq | P94: 0.087683128 | Q94: 0.088373686 | R94: 0.088110188 | S94: 0.087400401
A95: Electricity, medium voltage {FI}| market for | Cut-off, U | B95: 5.72377 | C95: kWh | D95: Uniform | F95: 4.579 | G95: 6.868524 | N95: Fossil resource scarcity | O95: kg oil eq | P95: 2.0144947 | Q95: 1.4631879 | R95: 2.8765772 | S95: 3.8555362
A96: Natural gas, low pressure {FI}| market for | Cut-off, U | B96: 0.051121 | C96: m3 | D96: Uniform | F96: 0.040896861 | G96: 0.061345291 | H96: Based on a conversion ratio of 11.15 kWh /m3 (used in Ecoinvent). | N96: Water consumption | O96: m3 | P96: 0.43068347 | Q96: 0.40371135 | R96: 0.39285417 | S96: 0.64991633
A98: Emissions to air | C98: Amount | D98: Unit | E98: Uncertainty distribution | G98: Min | H98: Max | I98: Comments
A99: Methane, fossil | C99: 1.021e-05 | D99: kg | E99: Uniform | G99: 8.16696e-06 | H99: 1.22504e-05 | I99: 5 kg CH4 / TJ natural gas
A100: Nitrogen dioxide, FI | C100: 0.0003078 | D100: kg | E100: Uniform | G100: 0.000246 | H100: 0.000369 | I100: 150 kg NO2 / TJ natural gas
A101: Dinitrogen monoxide | C101: 2.042e-07 | D101: kg | E101: Uniform | G101: 1.63339e-07 | H101: 2.45009e-07 | I101: 0.1 kg N2O / TJ natural gas
A102: Carbon dioxide, fossil | C102: 0.1145 | D102: kg | E102: Uniform | G102: 0.091633291 | H102: 0.13744994 | I102: 15.3 tC / TJ natural gas
A103: Water | C103: 43.2 | D103: kg | E103: Uniform | G103: 34.56 | H103: 51.84
A105: Emissions to water
A107: Emissions to soil
A109: Final waste flows
A111: Non material emissions
A113: Social issues
A115: Economic issues
A117: Waste to treatment | B117: Amount | C117: Unit | D117: Uncertainty distribution | F117: Min | G117: Max | H117: Comments
A118: Biowaste {EU}| market for | Cut-off, U | B118: 3.65 | C118: kg | D118: Uniform | F118: 2.92 | G118: 4.38
A120: Input parameters
A122: Calculated parameters

Sheet Input - Mycoprotein
A2: Mycoprotein
C3: Mycoprotein, ready-to-eat product
I4: NOT USED (GRAY)
A5: Processes | E5: Raw commodities | I5: Other stuff / ingredients
A6: Name | B6: Amount | C6: Unit (per kg prod) | E6: RAC | F6: Amount | G6: Unit (per kg prod) | I6: Item | J6: Amount | K6: Unit (per kg prod)
A7: Fermentation/Production | B7: 21.32 | C7: MJ | E7: sugar beet* | F7: =F13/0.3*0.2 -> 2 | G7: kg | I7: tap water | J7: 40 | K7: kg CO2e/kg
E8: egg white | F8: =F21 -> 0.04 | G8: kg | I8: nitrogen fertilizer | J8: 0.069 | K8: kg
A9: highlighted values are used | E9: In email from Quorn they state that they no use hydrolyzed wheat starch instead of sugar beet
E10: Land use should be 4m2 per kg Quorn according to Quorn so we adjust the wheat amount to correspond to that
I11: Sugar beet | J11: =3/0.3 -> 10 | K11: kg of sugar beet
A12: NOTES
A13: 7 | B13: kg sugar beet per kg of sugar | E13: *molasses from sugar beet, original data in LCI | F13: 3 | G13: kg
A14: 6 | B14: kg of molasses/beetfiber per kg of sugar
A15: 0.8 | B15: of impact allocated to sugar
A16: 0.2 | B16: allocation factor for impacts of sugar beet production to molasses | I16: Published | K16: % of total GWP
A17: 0.3 | B17: molasses to sugar beet ratio | I17: Minor/Other | J17: Vitamins and minerals | K17: 2
I18: Minor/Other
E20: albumen accounts for most of an egg’s liquid weight, about 66% | F20: NC Egg Association | I20: Total GWP of Other | J20: =J21*(K17/100) -> 0.12 | K20: kg CO2e/kg
E21: egg white | F21: 0.04 | G21: kg | I21: Published total | J21: 6 | K21: kg CO2e/kg
A28: NOT USED (GRAY)
A29: Smetana, S., Mathys, A., Knoch, A., & Heinz, V. (2015). Meat alternatives: life cycle assessment of most known meat substitutes. The International Journal of Life Cycle Assessment, 20, 1254-1267. | N29: Smetana, S., Profeta, A., Voigt, R., Kircher, C., & Heinz, V. (2021). Meat substitution in burgers: Nutritional scoring, sensorial testing, and life cycle assessment. Future Foods, 4, 100042.
A30: Table 1 Main inputs in the production of meals used in the study (from cradle to plate)
A31: From: Meat alternatives: life cycle assessment of most known meat substitutes
A32: Product | B32: Resources used per FU (1 kg of ready-to-eat product) | N32: Table A1. Main components of studied burger patties, per 113 g.
B33: Main ingredients | C33: Electricity, MJd,g | D33: Tap water, kgd | E33: Transport, kgkmd,h | F33: Otherp | N33: Components | O33: B1 | P33: B2 | Q33: B3 | R33: B4 | S33: B5 | T33: Sources of data | U33: LCI model
A34: (1) Chicken | B34: 1 kg chickena | C34: 49.78* | D34: 16.3* | E34: 850* | F34: – | N34: Beef meat | O34: 102.3 | P34: - | Q34: - | R34: - | S34: - | T34: DPF | U34: Beef meat, fresh, from dairy cattle (AF)
A35: (2) Dairy basedk | B35: 6 kg skimmed milkb | C35: 12.27* | D35: 4.2* | E35: 360* | F35: 0.84 kg oat hull fiberc | N35: Beet juice concentrate | O35: - | P35: - | Q35: - | R35: 3.4 | S35: - | T35: P4 | U35: Own model
A36: (3) Lab grownl | B36: 1 kg uread | C36: 103.5 | D36: 420 | E36: 110 | F36: – | N36: Cellulose and methylcellulose | O36: - | P36: 2.3 | Q36: 2.2 | R36: 1.1 | S36: 1.4 | T36: P2-5 | U36: Carboxymethyl cellulose (EI)
A37: (4) Insect basedm | B37: 0.8 kg carrotsd | C37: 10.762f | D37: 1.34f | E37: 128.5 | F37: 0.57 kg grain mix (rye, wheat, barley)d | N37: Coconut fat and oil | O37: - | P37: 5.7 | Q37: - | R37: 4.5 | S37: - | T37: P2, P4 | U37: Refined coconut oil (AF)
F38: 0.048 kg oat hull fiberc | N38: Egg protein | O38: - | P38: - | Q38: 2.3 | R38: - | S38: - | T38: P3 | U38: Own model
A39: (5) Gluten basede | B39: 1.622 kg wheat graind | C39: 8.94 | D39: 0.954 | E39: 141.1 | F39: 0.15 kg oat hull fiberc | N39: Insects | O39: - | P39: - | Q39: 10.6 | R39: - | S39: - | T39: P3 | U39: Own model
A40: (6) Soy meal basedn | B40: 0.27 kg soy meald | C40: 10.002f | D40: 0.73f | E40: 2791* | F40: 0.15 kg oat hull fiberc | N40: Lemon juice | O40: - | P40: - | Q40: 0.6 | R40: 1.1 | S40: - | T40: P3-4 | U40: Own model
A41: (7) Mycoprotein basedo | B41: 3 kg molasses from sugar beetd | C41: 21.32 | D41: 40 | E41: 215.45 | F41: 0.069 kg nitrogen fertilizerd | N41: Mustard | O41: - | P41: - | Q41: 1.6 | R41: - | S41: - | T41: P3 | U41: Own model
F42: 0.04 kg egg white | N42: Mycoprotein | O42: - | P42: - | Q42: - | R42: 11.3 | S42: - | T42: P4 | U42: (Finnigan, 2010; Jungbluth 2016)
N43: Onion | O43: - | P43: - | Q43: 3.4 | R43: - | S43: 5.7 | T43: P3, P5 | U43: Onion (EI)
A44: aFrom a supermarket (LCA Food DK), based on live chicken for slaughterhouse (Ecoinvent 3 database) | N44: Palm oil | O44: - | P44: - | Q44: - | R44: 3.4 | S44: - | T44: P4 | U44: Palm oil, refined (EI)
A45: bFrom dairy (LCA Food DK), water, electricity, and heat inputs are changed (Ecoinvent 3 database) | N45: Pea protein | O45: - | P45: - | Q45: - | R45: 11.6 | S45: - | T45: P4 | U45: Pea concentrate (AF)
A46: cBy-product of oat cereals production, includes 2.3 m2 of arable land occupation, use of 0.023 kg of nitrogen, 0.0048 kg of phosphate, and 0.0143 kg of potassium fertilizers, and 0.95 MJ of energy for 1 kg production (LCA Food DK, and Ecoinvent 3 database) | N46: Pea protein isolate | O46: - | P46: 20.0 | Q46: - | R46: 3.8 | S46: - | T46: P2, P4 | U46: Pea isolate (AF)
A47: dBased on a product from Ecoinvent 3 database | N47: Potato protein | O47: - | P47: - | Q47: - | R47: 1.1 | S47: - | T47: P4 | U47: Potato protein, wet milling (AF)
A48: evan Zeist et al. (2012) and Deng et al. (2013) | N48: Potato starch | O48: 4.5 | P48: 1.7 | Q48: 1.6 | R48: - | S48: - | T48: DPF, P2, P3 | U48: Potato starch, wet milling (AF)
A49: fData from DIL e.V. are included | N49: Rape oil | O49: - | P49: 15.8 | Q49: 7.1 | R49: - | S49: 11.5 | T49: P2-3, P5 | U49: Crude rape oil (EI)
A50: gFoster et al. (2006) | N50: Salt | O50: 1.1 | P50: 1.1 | Q50: 1.1 | R50: - | S50: 1.7 | T50: DPF, P2-3, P5 | U50: Sodium chloride (EI)
A51: hAssumed resources transported 50 km to assembly and supermarket, 10 km from a supermarket to the consumer (McEachern and Warnaby 2006) | N51: Soy protein | O51: - | P51: - | Q51: 7.1 | R51: - | S51: 18.0 | T51: P3, P5 | U51: Soy concentrate (AF)
A52: iAssumed, 20 g of oil needed to fry 0.5 kg of product | N52: Soy sauce | O52: - | P52: - | Q52: 1.6 | R52: - | S52: - | T52: P3 | U52: Own model
A53: jPYR Ltd (2014) | N53: Spices | O53: 0.6 | P53: - | Q53: 1.4 | R53: - | S53: 3.4 | T53: DPF, P3, P5 | U53: Own model
A54: kBerlin (2002), Blonk et al. (2008), and Head et al. (2011) | N54: Sunflower oil | O54: - | P54: - | Q54: - | R54: 3.4 | S54: - | T54: P4 | U54: Refined sunflower oil (AF)
A55: lTuomisto and De Mattos (2010) and Tuomisto and Roy (2012) | N55: Tap water | O55: 4.5 | P55: 62.2 | Q55: 70.4 | R55: 38.4 | S55: 61.0 | T55: DPF, P2-5 | U55: Tap water (EI)
... A59: pTable 1 does not include the data similar for all scenarios | N59: Wheat starch | O59: - | P59: - | Q59: - | R59: 3.8 | S59: 1.1 | T59: P4, P5 | U59: Wheat starch, wet milling (AF)
N60: Other* | O60: - | P60: 4.3 | Q60: 2.3 | R60: 6.8 | S60: 1.4 | T60: P2-5 | U60: Own model
N61: Direct processing inputs
A62: Smetana, S., Aganovic, K., Irmscher, S., & Heinz, V. (2018). Agri-food waste streams utilization for development of more sustainable food substitutes. Designing sustainable technologies, products and policies: From science to innovation, 145-155. | N62: Electricity, kWh | O62: 0.05 | P62: 0.0114 | Q62: 0.0064 | R62: 0.0156 | S62: 0.0106 | T62: DPF | U62: Medium voltage, consumption mix DE (EI)
N63: Water, kg | O63: - | P63: 1.24 | Q63: 0.24 | R63: 1.24 | S63: 1.24 | U63: Tap water (EI)
N64: Note:
N65: ⁎
N66: additives: spices, additives, extracts, natural colorants, sunflower oil, parsley, ascorbic acid, vinegar, glucose, aromas including smoke aromas, tomato concentrate; B1 – beef patty, B2 – pea patty (Beyond); B3 – insect patty (Bugfoundation); B4 – mycoprotein patty (Quorn); B5 – soy patty (Rügenwalder Mühle); DPF – DIL e.V. pilot facility (German Institute of Food Technologies, Quakenbrück, Germany); P2-P5 – packaging for relevant burgers (B2-B5); AF – Agri-footprint 3.0 database (Blonk Consultants, Netherlands); EI – ecoinvent 3 (Zurich, Switzerland)
A98: Raats, J. (2007). Meat (substitutes) comparing environmental impacts. A Case study comparing Quorn and pork. Training thesis at Centre for Energy and Environmental Studies, University of Groningen. University of Groningen Groningen.
A99: (Studetn thesis) Full text links not working…, but from abstract | C99: https://core.ac.uk/display/12938022
A101: "The system boundaries for this research were set on the production processes taking place only at the different production facilities of both products. Production of raw materials, transportation of raw materials and retail and consumption of the finished products were left out of this analysis, since it is assumed this is the same for both products A first analysis showed that the for the production of Quorn approximately 2,9 kg molasses, 69 grams nitrogen and 13,6 MJ energy was needed."
A103: "The results for this analysis showed that the amounts of required for the production of Quorn varied between: 2,2 to 4,3 kg molasses, 52 to 94 grams nitrogen and 10,4 to 26,1 MJ energy"
A107: Finnigan, T., Lemon, M., Allan, B., & Paton, I. (2010). Mycoprotein, Life cycle Analysis and the food 2030 challenge. Aspects of Applied Biology, (102), 81-90.
A108: Conference proceedings, not openly accessible online
A109: https://www.cabdirect.org/cabdirect/abstract/20103346525

Sheet Input - Yeast Microb. Fat
A2: Fats (Fermentation) yeast Sigtryggsson et al | I2: Allokering | J2: 0.81
C3: Fat, single-cell oil, produced by yeast cells from hydrolysed straw* | D3: Sigtryggsson et al 2023
C4: *Rhodotorula babjevae | I4: NOT USED (GRAY) | M4: Climate imapcts
A5: Processes | E5: Raw commodities | I5: Other stuff / ingredients | M5: Per kg input | Q5: per kg of product
A6: Name | B6: Amount | C6: Unit (per kg prod) | D6: comment | E6: RAC | F6: Amount | G6: Unit (per kg prod) | I6: Item | J6: Amount | K6: Unit (per kg prod) | M6: CO2 | N6: CH4 | O6: N2O | Q6: CO2 | R6: CH4 | S6: N2O
A7: Electricity | B7: 14.77 | C7: MJ | D7: DO NOT ADD AS AN INPUT supplied through burning the lignin fraction of the straw | E7: Wheat straw | F7: 2 | G7: kg | H7: DO NOT ADD AS AN INPUT; FOR FREE IN THE MODEL | I7: Ammonia | J7: 0.13 | K7: kg | M7: 1.987417 | N7: 0.003921 | O7: 3.04e-05 | Q7: =M7*$J7 -> 0.25836421 | R7: =N7*$J7 -> 0.00050973 | S7: =O7*$J7 -> 3.952e-06
A8: Heat (Steam) - Pre-treatment and hydrolysis | B8: 13.3 | C8: MJ | D8: DO NOT ADD AS AN INPUT supplied through burning the lignin fraction of the straw | I8: Sulphuric acid | J8: 0.2 | K8: kg | M8: 0.118355 | N8: 0.00016 | O8: 2.3e-06 | Q8: =M8*$J8 -> 0.023671 | R8: =N8*$J8 -> 3.2e-05 | S8: =O8*$J8 -> 4.6e-07
A9: Diesel for harvesting straw | B9: 0.49 | C9: MJ | I9: Sodium hydroxide | J9: 0.038 | K9: kg | M9: 2.073073 | N9: 0.003656 | O9: 6.44e-05 | Q9: =M9*$J9 -> 0.078776774 | R9: =N9*$J9 -> 0.000138928 | S9: =O9*$J9 -> 2.4472e-06
A10: Diesel | B10: 0.012895 | C10: L/kg | I10: Hexane | J10: 0.06 | K10: kg | M10: 0.82667 | N10: 0.002642 | O10: 1.32e-05 | Q10: =M10*$J10 -> 0.0496002 | R10: =N10*$J10 -> 0.00015852 | S10: =O10*$J10 -> 7.92e-07
I11: Phosphoric acid | J11: 0.05 | K11: kg | M11: 1.591902 | N11: 0.002488 | O11: 2.74e-05 | Q11: =M11*$J11 -> 0.0795951 | R11: =N11*$J11 -> 0.0001244 | S11: =O11*$J11 -> 1.37e-06
A12: Diesel fuel has a specific energy of around 38 mega joules (MJ) per litre | I12: Enzymes | J12: 0.073 | K12: kg | M12: 0.804 | N12: 0.00229 | O12: 0.00044 | Q12: =M12*$J12 -> 0.058692 | R12: =N12*$J12 -> 0.00016717 | S12: =O12*$J12 -> 3.212e-05
P14: Total GHG per kg of product | Q14: =SUM(Q7:Q12) -> 0.54869928 | R14: =SUM(R7:R12) -> 0.001130748 | S14: =SUM(S7:S12) -> 4.11412e-05
A17: highlighted values are used

Sheet Input - Algae Microb. Fat
A2: Fats from heterotropic algae (Fermentation) | C2: USE THIS ONE!
C3: Fat, single-cell oil, produced by algea in fermenation* | D3: Lu et al 2021 | E3: Life cycle assessment of industrial production of microalgal oil from heterotrophic fermentation - ScienceDirect
C4: *Schizochytrium | I4: NOT USED (GRAY)
A5: Processes | E5: Raw commodities | I5: Other stuff / ingredients
A6: Name | B6: Amount | C6: Unit (per kg prod) | E6: RAC | F6: Amount | G6: Unit (per kg prod) | I6: Item | J6: Amount | K6: Unit (per kg prod)
A7: Electricity (Cultivation) | B7: 10 | C7: MJ | E7: Glucose | F7: =3.292206+F10 -> 3.3177406 | G7: kg | I7: Potassium | J7: 0.04013857 | K7: kg
A8: Electricity (disc centrifuge) | B8: 0.209 | C8: MJ | I8: Magnesium | J8: 0.012062642 | K8: kg
A9: Electricity Enzymolys | B9: 0.42666984 | C9: MJ | E9: Corn syrup | F9: 0.018436 | G9: L | I9: Ammonium Sulfate | J9: 0.018436351 | K9: kg
A10: Electricity soilid/luquid seperation | B10: 0.33375063 | C10: MJ | E10: Corn syrup | F10: =F9/F13 -> 0.025534626 | G10: kg | I10: Yeast | J10: 0.36872702 | K10: kg
A11: Electricity oil refining | B11: 0.10683118 | C11: MJ | I11: Sodium Glutamate | J11: 0.36872702 | K11: kg
E12: 1 kilogram of corn syrup is equivalent 722 milliliters | I12: 6-Benzyl Adenine(BA) | J12: 5.53091e-05 | K12: kg
F13: 0.722 | G13: L/kg | I13: Enzymes | J13: 0.065050083 | K13: kg
E14: NOTE: Use any corn syrup as glucose proxy | I14: Manganous Chloride | K14: kg
A15: Residue digestion(biogas production) | I15: Sodium Molybdate | K15: kg
A16: Electricity | B16: -3,296017997 | C16: MJ | I16: Glycerin | K16: kg
A17: Heat | B17: -0,648770732 | C17: MJ | I17: Defoamer | J17: 0.000526753 | K17: L
A18: Emissions from residue recycling | I18: Isoproponol | J18: 0.28369072 | K18: L
A19: VOC | C19: kg | N19: https://www,sciencedirect,com/science/article/pii/S2211926421003131
A20: CO | B20: 0.000258325 | C20: kg
A21: Nox | B21: 0.000258248 | C21: kg
A22: PM10 | C22: kg | I22: Published | K22: % of total GWP
A23: PM2,5 | C23: kg | I23: Minor/Other (proxy from microbial protein) | J23: Nutrient input | K23: 1.7
A24: Sox | C24: kg | I24: Minor/Other (proxy from microbial protein) | J24: Ammonia water | K24: 3.4
A25: CH4 | B25: 0.007069889 | C25: kg | I25: Minor total | K25: 5.1
A26: N2O | B26: 1.61453e-05 | C26: kg
A27: CO2 | B27: 0.93764412 | C27: kg | D27: biogenic-no climate impact | I27: Total GWP of Other | J27: 0.288813 | K27: kg CO2e/kg
I28: Published total | J28: 5.663 | K28: kg CO2e/kg
A31: highlighted values are used
A48: Parsons, S., Allen, M. J., Abeln, F., McManus, M., & Chuck, C. J. (2019). Sustainability and life cycle assessment (LCA) of macroalgae-derived single cell oils. Journal of Cleaner Production, 232, 1272-1281.
A49: LINK to article
A50: Table 1. Life Cycle Inventory (LCI) for the production of microbial derived oil from seaweed. | E50: (NOTE: I am going to guess kg as a unit in these LCI unless otherwise stated) | J50: Conversions
A51: Input | B51: Value | C51: Source | D51: LCI value (units as given) | E51: LCI value (units per kg intermediate) | F51: Amount (unit/kg lipid) | G51: Unit (per kg lipid prod) | J51: 1 kg dry seaweed : 0.6 kg fermentable hydrolysate
A52: Cultivation - Nursery | J52: Total carbohydrates were assumed to be 60% based on Nielsen et al. (2016).
A53: Ammonium nitrate | B53: 0.08 t−1 dry seaweed | C53: (Langlois et al. 2012) | D53: 0.08 | E53: 0.00008 | F53: 0.000952 | G53: kg | J53: biomass yield of 0.35 g g−1 hydrolysate (sugar) and culture density of 120 g L−1, yielding 1.3 g L−1 h−1 yeast biomass which corresponds to 0.52 g L−1 h−1 lipid production
A54: Sodium phosphate | B54: 0.03 t−1 dry seaweed | D54: 0.03 | E54: 0.00003 | F54: 0.000357 | G54: kg | J54: 1 kg fermentable hydrolysate : 0.35 kg yeast biomass
A55: Iron (III) chloride | B55: 0.003 t−1 dry seaweed | D55: 0.003 | E55: 0.000003 | F55: 3.57E-05 | G55: kg | J55: 1.3 kg yeast biomass : 0.52 kg lipid
A56: Anhydrous boric acid | B56: 0.02 t−1 dry seaweed | D56: 0.02 | E56: 0.00002 | F56: 0.000238 | G56: kg
A57: Mineral solution (EDTA) | B57: 0.02 t−1 dry seaweed | D57: 0.02 | E57: 0.00002 | F57: 0.000238 | G57: kg
A58: Electricity (water pumping, lamps, sparger) | B58: 342 kWh t−1 dry seaweed | D58: 342 | E58: 0.342 | F58: 14.65714 | G58: MJ | I58: 1 | J58: kg dry seaweed | K58: 1 | L58: kg fermentable hydrolysate | M58: 1.3 | N58: kg yeast biomass | O58: = | P58: 1.3 | Q58: = | R58: 11.90476 | S58: kg dry seaweed
A59: Water | B59: 4600 L t−1 dry seaweed | D59: 4600 | E59: 4.6 | F59: 54.7619 | G59: L | I59: 0.6 | J59: kg fermentable hydrolysate | K59: 0.35 | L59: kg yeast biomass | M59: 0.52 | N59: kg lipid | P59: 0.1092 | S59: kg lipid
A60: Cultivation – long lines | K60: 1 | L60: kg fermentable hydrolysate | M60: 1.3 | N60: kg yeast biomass | O60: = | P60: 1.3 | Q60: = | R60: 7.142857 | S60: kg fermentable hydrolysate
A61: Diesel | B61: 30 L t−1 dry seaweed | C61: Alvarado-Morales et al. (2013), Edwards and Watson (2011) | D61: 30 | E61: 0.03 | F61: 0.357143 | G61: L | K61: 0.35 | L61: kg yeast biomass | M61: 0.52 | N61: kg lipid | P61: 0.182 | S61: kg lipid
A62: Petrol | B62: 30 L t−1 dry seaweed | D62: 30 | E62: 0.03 | F62: 0.357143 | G62: L | M62: 1.3 | N62: kg yeast biomass | O62: = | P62: 2.5 | Q62: = | R62: 2.5 | S62: kg yeast biomass
A63: Transport | B63: 100 tkm | D63: 100 | M63: 0.52 | N63: kg lipid | S63: kg lipid
A64: Pre-treatment and hydrolysis (incl. enzyme production)
A65: Electricity (milling) | B65: 9.83 kWh t−1 milled dry seaweed | C65: Humbird et al. (2011) | D65: 9.83 | E65: 0.00983 | F65: 0.421286 | G65: MJ
A66: Water | B66: 2.44 m3 t−1 fermentable hydrolysate | D66: 2.44 | E66: 0.00244 | F66: 1.74E-05 | G66: kg
A67: Ammonia | B67: 17 kg t−1 fermentable hydrolysate | D67: 17 | E67: 0.017 | F67: 0.121429 | G67: kg
A68: Sulphuric acid | B68: 33 kg t−1 fermentable hydrolysate | D68: 33 | E68: 0.033 | F68: 0.235714 | G68: kg
A69: Sodium hydroxide | B69: 54 kg t−1 fermentable hydrolysate | D69: 54 | E69: 0.054 | F69: 0.385714 | G69: kg
A70: Quicklime | B70: 21 kg t−1 fermentable hydrolysate | D70: 21 | E70: 0.021 | F70: 0.15 | G70: kg
A71: Sulphur dioxide | B71: 0.3 kg t−1 fermentable hydrolysate | D71: 0.3 | E71: 0.0003 | F71: 0.002143 | G71: kg
A72: Sugar | B72: 40 kg t−1 fermentable hydrolysate | D72: 40 | E72: 0.04 | F72: 0.285714 | G72: kg
A73: Heat (Steam) | B73: 1314 MJ t−1 fermentable hydrolysate | D73: 1314 | E73: 1.314 | F73: 9.385714 | G73: MJ
A74: Electricity | B74: 119 kWh t−1 fermentable hydrolysate | D74: 119 | E74: 0.119 | F74: 3.06 | G74: MJ
A75: Fermentation (CSTR)
A76: Nutrients-->see Section 2.1 and Table 2 in Lardon et al. (2009) | B76: 0.22 kg t−1 yeast biomass | C76: Experimental data for M. pulcherrima, Koutinas (2014), Braunwald (2016) | D76: 0.22 | E76: 0.00022 | F76: 0.00055 | G76: kg | I76: nutrient culture--> | J76: Lardon, L., Hélias, A., Sialve, B., Steyer, J. P., & Bernard, O. (2009). Life-cycle assessment of biodiesel production from microalgae.
A77: Electricity | B77: 3050 kWh t−1 yeast biomass | D77: 3050 | E77: 3.05 | F77: 27.45 | G77: MJ | J77: LINK to article
A78: Biomass productivity | B78: 1.3 g L−1 h−1 | D78: 1.3
A79: Lipid productivity | B79: 0.52 g L−1 h−1 | D79: 0.52 | J79: "Nutrient and CO2 supply to produce 1 kg of algae are determined for both culture methods from the elementary composition proposed in Table 2 for both culture conditions."
A80: Fermentation (raceway pond) | J80: Table 2. Composition and Culture Parameters of C. vulgaris
A81: Nutrients | B81: 0.28 kg t−1 yeast biomass | D81: 0.28 | E81: 0.00028 | F81: 0.0007 | G81: kg | J81: parameter | K81: normal | L81: low N | M81: Value | N81: Amount (kg/kg nutrient culture) | O81: Unit | P81: Amount (kg/kg lipid product) | T81: 0.00055 | U81: kg nutrent culture / kg lipid product
A82: Electricity | B82: 1860 kWh t−1 yeast biomass | D82: 1860 | E82: 1.86 | F82: 16.74 | G82: MJ | I82: protein C4.43H7O1.44N1.16 | J82: protein (g·kg−1) | K82: 282 | L82: 67 | M82: 282 | N82: 0.282 | O82: kg | P82: 0.000155
A83: Biomass productivity | B83: 1.14 g L−1 h−1 | D83: 1.14 | E83: - | I83: lipid C40H7405 | J83: lipid (g·kg−1) | K83: 175 | L83: 385 | M83: 175 | N83: 0.175 | O83: kg | P83: 9.63E-05
A84: Lipid productivity | B84: 0.4 g L−1 h−-1 | D84: 0.4 | E84: - | I84: carbohydrate C6H12O6 | J84: (Glucose) carbohydrates (g·kg−1) | K84: 495 | L84: 529 | M84: 495 | N84: 0.495 | O84: kg | P84: 0.000272
A85: Lipid extraction and refining | J85: lower heating value (MJ·kg−1) | K85: 17.5 | L85: 22.6 | M85: 17.5 | N85: 17.5 | O85: MJ | P85: 0.009625
A86: Hexane | B86: 66 kg t−1 unrefined lipid | C86: Davis et al. (2014) | D86: 66 | E86: 0.066 | F86: 0.066 | G86: kg | J86: C (g·kg−1) | K86: 480 | L86: 538 | M86: 480 | N86: 0.48 | O86: kg | P86: 0.000264
A87: Electricity | B87: 500 kWh t−1 unrefined lipid | D87: 500 | E87: 0.5 | F87: 1.8 | G87: MJ | J87: N (g·kg−1) | K87: 46 | L87: 10.9 | M87: 46 | N87: 0.046 | O87: kg | P87: 2.53E-05 | T87: "Nitrogen is brought by calcium nitrate, phosphorus is brought by single superphosphate, potassium is brought by potassium chloride, and magnesium is brough by magnesium phosphate."
A88: Water | B88: 740 kg t−1 lipid | D88: 740 | E88: 0.74 | F88: 0.74 | G88: kg | J88: P (g·kg−1) | K88: 9.9 | L88: 2.4 | M88: 9.9 | N88: 0.0099 | O88: kg | P88: 5.45E-06
A89: Phosphoric acid | B89: 0.3 kg t−1 lipid | D89: 0.3 | E89: 0.0003 | F89: 0.0003 | G89: kg | J89: K (g·kg−1) | K89: 8.2 | L89: 2 | M89: 8.2 | N89: 0.0082 | O89: kg | P89: 4.51E-06
A90: Sodium hydroxide | B90: 3 kg t−1 lipid | D90: 3 | E90: 0.003 | F90: 0.003 | G90: kg | J90: Mg (g·kg−1) | K90: 3.8 | L90: 0.9 | M90: 3.8 | N90: 0.0038 | O90: kg | P90: 2.09E-06
A91: Clay | B91: 5 kg t−1 lipid | D91: 5 | E91: 0.005 | F91: 0.005 | G91: kg | J91: S (g·kg−1) | K91: 2.2 | L91: 0.5 | M91: 2.2 | N91: 0.0022 | O91: kg | P91: 1.21E-06
A92: Heat (steam) | B92: 350 MJ t−1 lipid | D92: 350 | E92: 0.35 | F92: 0.35 | G92: MJ | J92: CO2 (kg·kg−1) | K92: 1.8 | L92: 2.0 | M92: 1.8 | N92: 1.8 | O92: kg | P92: 0.00099
A93: Electricity (fractionation) | B93: 13 kWh t−1 lipid | D93: 13 | E93: 0.013 | F93: 0.0468 | G93: MJ | J93: growth rate (day−1) | K93: 0.99 | L93: 0.77 | M93: 0.99
A94: Water (fractionation) | B94: 100 kg t−1 lipid | D94: 100 | E94: 0.1 | F94: 0.1 | G94: kg | J94: productivity (g·m−2·day−1) | K94: 24.75 | L94: 19.25 | M94: 24.75
A100: Other possibly useful references
A101: Bajželj, B., Laguzzi, F., & Röös, E. (2021). The role of fats in the transition to sustainable diets. The Lancet Planetary Health, 5(9), e644-e653.
A102: Parsons, S., Chuck, C. J., & McManus, M. C. (2018). Microbial lipids: Progress in life cycle assessment (LCA) and future outlook of heterotrophic algae and yeast-derived oils. Journal of Cleaner Production, 172, 661-672.
A103: Bharathiraja, B., Sridharan, S., Sowmya, V., Yuvaraj, D., & Praveenkumar, R. (2017). Microbial oil–a plausible alternate resource for food and fuel application. Bioresource technology, 233, 423-432.
A104: Cheirsilp, B., & Louhasakul, Y. (2013). Industrial wastes as a promising renewable source for production of microbial lipid and direct transesterification of the lipid into biodiesel. Bioresource technology, 142, 329-337.
A105: Thevenieau, F., & Nicaud, J. M. (2013). Microorganisms as sources of oils. Ocl, 20(6), D603.
A107: LCA (but for biofuel not food)
A108: Davis, R., Aden, A., & Pienkos, P. T. (2011). Techno-economic analysis of autotrophic microalgae for fuel production. Applied Energy, 88(10), 3524-3531.
A109: Benemann, J., Woertz, I., & Lundquist, T. (2012). Life cycle assessment for microalgae oil production. Disruptive Science and Technology, 1(2), 68-78.
A110: Connelly, E. B., Colosi, L. M., Clarens, A. F., & Lambert, J. H. (2015). Life cycle assessment of biofuels from algae hydrothermal liquefaction: the upstream and downstream factors affecting regulatory compliance. Energy & Fuels, 29(3), 1653-1661.
A111: Sitepu, I. R., Garay, L. A., Sestric, R., Levin, D., Block, D. E., German, J. B., & Boundy-Mills, K. L. (2014). Oleaginous yeasts for biodiesel: current and future trends in biology and production. Biotechnology advances, 32(7), 1336-1360.

Sheet Input - Microbial Protein
A2: Microbial Protein
C3: Solein (Solar Foods Oy - Finland) | D3: Järviö et al. (2021) | E3: Finnish average energy mix (FAEM)
I4: NOT USED (GRAY)
A5: Processes | E5: Raw commodities | I5: Other stuff / ingredients
A6: Name | B6: Amount | C6: Unit (per kg prod) | E6: RAC | F6: Amount | G6: Unit (per kg prod) | I6: Item | J6: Amount | K6: Unit (per kg prod)
A7: Fermentation (including transport, sterilization, electrolysis, and pasteurization) | B7: =17.83*3.6 -> 64.188 | C7: MJ | E7: Cupriavidus necator | F7: ?? | I7: Tap water (kg) | J7: 22.57 | K7: kg
A8: Separation | B8: =0.05*3.6 -> 0.18 | C8: MJ | I8: Low Pressure steam (kg)b: | J8: 2.27 | K8: kg
A9: Drying | B9: =0.12*3.6 -> 0.432 | C9: MJ | I9: NH3 | J9: 0.00093908125 | K9: kg | L9: 0,11 kg of Nutrient solution per kg MP --> ingredients list in Table S1 below
A10: Cleaning in place | B10: =0.0795*3.6 -> 0.2862 | C10: MJ | I10: KH2PO4 | J10: 0.00018390625 | K10: kg
I11: Na2HPO4 * 2H2 O | J11: 0.000232025 | K11: kg
I12: MgSO4 * 7 H2O | J12: 0.0002426125 | K12: kg
I13: CaSO4 | J13: 4.409375e-05 | K13: kg
E14: "Methanotrophic bacteria obtain energy and carbon from methane, whereas hydrogen-oxidizing bacteria (HOB) utilize hydrogen and carbon dioxide; therefore, crops are not needed as a source of carbon." | I14: MnSO4 | J14: 2.28125e-06 | K14: kg
I15: NaVO3 * H2O | J15: 5.09375e-08 | K15: kg
I16: FeSO4 | J16: 3.940625e-05 | K16: kg
I17: ZnSO4 * 7 H2O | J17: 9.25e-07 | K17: kg
I18: H3BO3 | J18: 1.31875e-07 | K18: kg
I19: CoSO4 | J19: 3.61875e-07 | K19: kg
I20: CuSO4 | J20: 7.125e-08 | K20: kg
I21: NiSO2 | J21: 1.26875e-07 | K21: kg
I22: Na2MoO2 * 2 H2O | J22: 2.4375e-08 | K22: kg
I23: CO2 (kg)b | J23: 1.76 | K23: kg
I24: Ammonia water 25 wt-% (NH3) (kg) | J24: 0.57 | K24: kg
I25: LP steam (kg) | J25: 4.93 | K25: kg
I26: Sodium hydroxide (NaOH) (kg) | J26: 0.00185 | K26: kg
... I28: Water (kg) | J28: 0.723 | K28: kg
I31: Published | K31: % of total GWP
I32: Minor/Other | J32: Nutrient input | K32: 1.7
I33: Minor/Other | J33: Ammonia water | K33: 3.4
I34: Minor total | K34: =SUM(K32:K33) -> 5.1
I36: Total GWP of Other | J36: =J37*(K34/100) -> 0.42808047 | K36: kg CO2e/kg
I37: Published total | J37: 8.3937348 | K37: kg CO2e/kg
A38: NOT USED (GRAY)
A39: Järviö, N., Maljanen, N. L., Kobayashi, Y., Ryynänen, T., & Tuomisto, H. L. (2021). An attributional life cycle assessment of microbial protein production: a case study on using hydrogen-oxidizing bacteria. Science of the Total Environment, 776, 145764.
A40: https://www.sciencedirect.com/science/article/pii/S0048969721008317#s0010
A42: RAC (see bwlow)
A43: The production occurs in a continuous stirred-tank bioreactor where the bacteria grow continuously in steady-state conditions. Hydrogen, oxygen, and CO2 gases are the main inputs into the fermentation.
A44: Water-based liquid mineral medium is supplied continuously to the cultivation through filter sterilization. The medium contains ammonium as a nitrogen source and inorganic salts containing sulfur, phosphorus, magnesium, sodium, potassium, iron, and calcium. Manganese, zinc, vanadium, boron, molybdenum, cobalt, nickel, and copper are present in minor amounts. Phosphoric acid (H3PO4) and sodium hydroxide (NaOH) are used to control pH.
A45: (See inventory data in SI below)
A48: Energy Requirements
B50: Renewable, wind, solar, geothe | C50: Renewable, water | D50: Renewable, biomass | E50: Non renewable, fossil | F50: Non-renewable, nuclear | G50: Non-renewable, biomass | H50: Renewable - total | I50: Non-renewable - total | J50: CED - total | K50: scenario
A51: count | B51: 1000 | C51: 1000 | D51: 1000 | E51: 1000 | F51: 1000 | G51: 1000 | H51: 1000 | I51: 1000 | K51: FAEM | L51: Finnish Average Electricty Mix
A52: mean | B52: 4.8065484 | C52: 21.505317 | D52: 17.391698 | E52: 98.729765 | F52: 97.501753 | G52: 0.0018980137 | H52: 43.703564 | I52: 196.23342 | J52: =H52+I52 -> 239.93698 | K52: FAEM
A53: std | B53: 0.43651714 | C53: 2.0482359 | D53: 1.6342399 | E53: 11.268248 | F53: 26.767045 | G53: 0.00036561733 | H53: 4.1100376 | I53: 30.339507 | J53: 32.826385 | K53: FAEM
A54: min | B54: 3.7237239 | C54: 16.333315 | D54: 13.201201 | E54: 67.8208 | F54: 41.27322 | G54: 0.0010762425 | H54: 33.25824 | I54: 117.99835 | J54: =H54+I54 -> 151.25658 | K54: FAEM
A55: 25% | B55: 4.5009998 | C55: 20.069966 | D55: 16.248106 | E55: 91.214475 | F55: 77.151687 | G55: 0.0016440976 | H55: 40.853295 | I55: 174.50805 | J55: =H55+I55 -> 215.36135 | K55: FAEM
A56: 50% | B56: 4.7900924 | C56: 21.41104 | D56: 17.35033 | E56: 97.440692 | F56: 95.095008 | G56: 0.0018426905 | H56: 43.556774 | I56: 193.8025 | J56: =H56+I56 -> 237.35927 | K56: FAEM
A57: 75% | B57: 5.0937178 | C57: 22.848428 | D57: 18.484627 | E57: 105.82189 | F57: 111.79212 | G57: 0.0021100609 | H57: 46.401816 | I57: 213.63839 | J57: =H57+I57 -> 260.04021 | K57: FAEM
A58: max | B58: 6.4462846 | C58: 29.145159 | D58: 23.448008 | E58: 145.0854 | F58: 221.1176 | G58: 0.0035191237 | H58: 58.952687 | I58: 326.07947 | J58: =H58+I58 -> 385.03216 | K58: FAEM
A59: count | B59: 1000 | C59: 1000 | D59: 1000 | E59: 1000 | F59: 1000 | G59: 1000 | H59: 1000 | I59: 1000 | K59: FHE | L59: Finnish Hydropower Energy
A60: mean | B60: 0.045568543 | C60: 91.155692 | D60: 0.13043684 | E60: 9.4155659 | F60: 0.45718754 | G60: 0.00056816716 | H60: 91.331698 | I60: 9.8733216 | J60: =$H$46+$I$46 -> 0 | K60: FHE
A61: std | B61: 0.0052288358 | C61: 0.031539161 | D61: 0.031196265 | E61: 0.70653788 | F61: 0.13822383 | G61: 0.00018111736 | H61: 0.054070263 | I61: 0.73910694 | J61: =((H61^2)+(I61^2))^0.5 -> 0.74108208 | K61: FHE
A62: min | B62: 0.033609868 | C62: 91.067133 | D62: 0.072177628 | E62: 7.3229654 | F62: 0.17255618 | G62: 0.00023168203 | H62: 91.187614 | I62: 7.5925007 | J62: =H62+I62 -> 98.780115 | K62: FHE
A63: 25% | B63: 0.042002558 | C63: 91.133006 | D63: 0.11069405 | E63: 8.8963661 | F63: 0.36185437 | G63: 0.00044232948 | H63: 91.295269 | I63: 9.3261857 | J63: =H63+I63 -> 100.62145 | K63: FHE
A64: 50% | B64: 0.045031891 | C64: 91.153193 | D64: 0.12402212 | E64: 9.3983161 | F64: 0.43654819 | G64: 0.00053734286 | H64: 91.326285 | I64: 9.841817 | J64: =H64+I64 -> 101.1681 | K64: FHE
A65: 75% | B65: 0.048239867 | C65: 91.176876 | D65: 0.14366327 | E65: 9.8550516 | F65: 0.52780622 | G65: 0.00066973998 | H65: 91.361501 | I65: 10.350545 | J65: =H65+I65 -> 101.71205 | K65: FHE
A66: max | B66: 0.070177085 | C66: 91.286917 | D66: 0.38500812 | E66: 12.009032 | F66: 1.1917944 | G66: 0.0018183155 | H66: 91.646354 | I66: 12.532001 | J66: =H66+I66 -> 104.17835 | K66: FHE
A69: Supplementary Information Table of Contents
A71: Topic | B71: Sheet name | C71: Description
A72: ReCiPe results FAEM & FHE | B72: ReCiPe | C72: Results of all scenarios
B73: Results various energy options | C73: The results for the different eletricity mixes used for Finland
A74: Monte Carlo | B74: FAEM_MC_95 | C74: Monte carlo results for the BAU scenario with 95% confidence
B75: FAEM_MC_90 | C75: Monte carlo results for the BAU scenario with 90% confidence
B76: FHE_MC_95 | C76: Monte carlo results for the RE scenario with 95% confidence
B77: FHE_MC_90 | C77: Monte carlo results for the RE scenario with 90% confidence
A78: Protein comparison results | B78: Comparison | C78: Calculations of the LCA comparison of MP with other protein sources
A79: Wastewater treatment | B79: Data | C79: Data required to calculate the environmental impact of wastewater treatment option
B80: LCI UF + RO recycling system | C80: Life cycle inventory of wastewater treatment options
B81: LCI WWTP | C81: Calculation for the wastewater treatment options for the supernatant
B82: LCI WWTP for CIP | C82: Calculation for the wastewater treatment options for cleaning in place (CIP)
A83: Sensitivity analysis | B83: Sensitivity_analysis | C83: Results of the different sensitivity test
A84: Cumulative energy demand results | B84: CED | C84: Results of the CED analysis
A85: Contribution analysis | B85: Contribution analysis % | C85: Numbers of the contribution analysis in percentages
B86: Contribution_totals | C86: Total numbers of the contribution analysis
A87: Simapro model | B87: Uncert. rang. & Simapro model | C87: The model for the hourly outputs of 160 * FU in Simapro plus all uncertainty ranges calculated with the Pedigree method.
A90: Processes
A92: Inputs for the production of microbial protein based on a hourly output of 160 kg of MP product at factory gate with 5% moisture content
A94: Products
A95: Microbial protein - HELSINKI | B95: =160/0.95 -> 168.42105 | C95: kg | F95: Food\Other | I95: including 5% moisture (160 kg dry weight)
A97: Avoided products
A99: Resources | C99: Amount | D99: Unit | I99: Comments
A100: Occupation, industrial area | B100: land | C100: 0.198 | D100: m2a | E100: Undefined | I100: Based on 1580 m2
A101: Transformation, from grassland, natural, for livestock grazing | B101: land | C101: 0.00396 | D101: m2 | E101: Undefined
A102: Transformation, to industrial area | B102: land | C102: 0.00396 | D102: m2 | E102: Undefined
A104: Materials/fuels | B104: Amount | C104: Unit | D104: Uncertainty type | E104: Uncertainty range | H104: Comments
A105: Carbon dioxide, liquid {RER}| market for | Cut-off, U | B105: 296,3*CO2_suppl | C105: kg | D105: Undefined | H105: (4,4,1,1,1,na)
A106: Tap water {HELSINKI}| market for | Cut-off, U | B106: (3792*Sc1+1228,8*Sc3)+(383*Steam_elec) | C106: kg | D106: Undefined | H106: (1,1,1,1,1,na)2 parts:
H107: part 1: Choose scenario water (Sc1 = no recycling, Sc3 = 80% recycling).
H108: Second one is only for if steam is produced onsite (See Neste report for details, both bioreactor block (173 kg/h) and media preparation and chemical block (210)
A109: Ammonia, liquid {RER}| market for | Cut-off, U | B109: 24.04 | C109: kg | D109: Undefined | H109: (1,4,1,1,4,na)24.04 kg pure ammonia per 160 kg of DW biomass
A110: Tap water {Europe without Switzerland}| market for | Cut-off, U | B110: 72.12 | C110: kg | D110: Undefined | H110: (1,4,1,1,4,na)24.04 kg pure ammonia per 160 kg of DW biomass. Ammonia water needed with 24.04 kg being 25% and 75% water. Tap water from EU source.
A111: Transport, freight, lorry 16-32 metric ton, euro4 {RER}| market for transport, freight, lorry 16-32 metric ton, EURO4 | Cut-off, U | B111: 72,12/1000*400 | C111: tkm | D111: Undefined | H111: (3,4,1,2,1,na)For the transportation of the water part of ammonia water for production of ammonia water, 400 km (one way)
A112: Magnesium sulfate {GLO}| market for | Cut-off, U | B112: 6.21 | C112: kg | D112: Lognormal | E112: 1.11 | H112: (1,4,1,1,1,na)
A113: Iron sulfate {RER}| production | Cut-off, U | B113: 1.009 | C113: kg | D113: Lognormal | E113: 1.11
A114: Transport, freight, lorry 16-32 metric ton, euro4 {RER}| market for transport, freight, lorry 16-32 metric ton, EURO4 | Cut-off, U | B114: 1,009/1000*100 | C114: tkm | D114: Undefined | H114: (3,1,1,2,1,na)Transport for iron sulfate (100 km)
A115: Transport, freight, aircraft, unspecified {GLO}| market for transport, freight, aircraft, unspecified | Cut-off, U | B115: 1,009/1000*2250 | C115: tkm | D115: Undefined | H115: Transport of iron sulfate (1500 km)
A116: Sodium phosphate {RER}| production | Cut-off, U | B116: 5.94 | C116: kg | D116: Lognormal | E116: 1.52 | H116: (1,4,1,1,4,na)
A117: Transport, freight, lorry 16-32 metric ton, euro4 {RER}| market for transport, freight, lorry 16-32 metric ton, EURO4 | Cut-off, U | B117: 5,94/1000*400 | C117: tkm | D117: Undefined | H117: Transport for Sodium phosphate (400 km)
A118: Transport, freight, aircraft, unspecified {GLO}| market for transport, freight, aircraft, unspecified | Cut-off, U | B118: 5,94/1000*1500 | C118: tkm | D118: Undefined | H118: Transport for Sodium phosphate (1500km)
A119: Potassium replacement | market for | Cut-off, U | B119: 4.71 | C119: kg | D119: Lognormal | E119: 1.11
...

Sheet Input - Insect
A2: Insect (H. illucens)
C3: Hermetia illucens* | D3: Smetana et al. (2016)
C4: *H. illucens, high moisture intermediate, meat substitute**
A5: Processes | E5: Raw commodities | I5: Other stuff / ingredients
A6: Name | B6: Amount | C6: Unit (per kg prod) | E6: RAC | F6: Amount | G6: Unit (per kg prod) | I6: Item | J6: Amount | K6: Unit (per kg prod)
A7: Electricity - Feeding/harvesting/processing | B7: =C28*D19 -> 3.426 | C7: MJ | E7: Rye meal | F7: =20.66*D19 -> 4.132 | G7: kg | I7: Tap Water - Feeding/Harvesting/Processing | J7: =E28*D19 -> 3.752 | K7: kg
A8: Heat - Feeding/harvesting/processing | B8: =D28*D19 -> 1.02 | C8: MJ | E8: Wheat bran | F8: =0.76*D19 -> 0.152 | G8: kg | I8: Tap Water - High moisture intermediate production | J8: =E39 -> 0.6 | K8: kg
A9: Electricity - High moisture intermediate production | B9: =C39 -> 0.243 | C9: MJ | E9: Soybean meal | F9: 0.2 | G9: kg
I12: Published | K12: % of total GWP
I13: Minor/Other | J13: All inputs accounted for in total (no minor inputs)
I14: Minor/Other
I16: Total GWP of Other | K16: kg CO2e/kg
J17: =AVERAGEA(1.36,15.1) -> 8.23
I18: Published total | J18: 1.36–15.1 | K18: kg CO2e/kg
D19: 0.2 | E19: **kg insect meal baseline (1)/kg insect meat substitute
A23: Smetana, S., Palanisamy, M., Mathys, A., & Heinz, V. (2016). Sustainability of insect use for feed and food: Life Cycle Assessment perspective. Journal of cleaner production, 137, 741-751.
A25: Table 1. Life cycle inventory of main insect production and processing stages used in the study. | I25: Table 2. Comparison of impact results for midpoint categories with literature sources (recalculated for FU 1 kg of insect protein meal).
A26: Scenario/product | B26: Resources used per FU (1 kg of a product) + 0.9 kg fat | I26: LCA studies | J26: Midpoint impact categories
B27: Main raw material inputs | C27: Electricity, MJ | D27: Heat, MJ | E27: Tap water, kg | F27: Other | J27: GWP, kg CO2 eq. | K27: Energy use, MJ | L27: Land use, m2 arable
A28: (1) Baseline/PP | B28: 20.66 kg ryemeal | C28: 17.13 | D28: 5.1 | E28: 18.76 | F28: 0.76 kg wheat bran | I28: HLA (van Zanten et al., 2015) | J28: 0.77 | K28: 9.3 | L28: 0.032
A29: (2) Chicken manure/PP | B29: 79.8 kg chicken manure | C29: 20.88 | D29: 5.1 | E29: 18.76 | F29: 39.9 kg for biowaste treatment | I29: HLB (Roffeis et al., 2015) | J29: – | K29: 159.85–288.15 | L29: 2.79–5.32
A30: (3) Cattle manure/PP | B30: 79.8 kg cattle manure | C30: 20.88 | D30: 5.1 | E30: 18.76 | F30: 39.9 kg for biowaste treatment | I30: BSFC (Komakech et al., 2015) | J30: 1.24 | K30: 1.512 | L30: –
A31: (4) Beet pulp/PP | B31: 109.9 kg beet pulp* | C31: 71.6 | D31: 12.86 | E31: 80.43 | F31: – | I31: BSFD (Muys et al., 2014) | J31: – | K31: 13.4–64.06 | L31: 0.01–0.04
A32: (5) DDGS/PP | B32: 25.46 kg DDGS | C32: 17.13 | D32: 5.1 | E32: 66.93 | F32: – | I32: MWE (Oonincx and de Boer, 2012) | J32: 3.5 | K32: 44.32 | L32: 4.68
A33: (6) Municipal waste/PP | B33: 40.28 kg municipal organic waste * | C33: 9.35 | D33: 3.9 | E33: – | F33: 18.05 kg for biowaste treatment | I33: MWF (Smetana et al., 2015) | J33: 7.1–7.55 | K33: 80.0–101.0 | L33: 3.75–3.8
A34: (7) Generic feed/PP | B34: 0.35 kg soybean meal; 0.31 kg maize; 0.17 kg sweet sorghum seeds | C34: – | D34: – | E34: – | F34: 0.17 kg barley grain, DDGS, rape meal, molasses, etc. | I34: BSFG (Salomone et al., 2016) | J34: 2.1 | K34: 15.1 | L34: 0.05
A35: (8) Fishmeal/PP | B35: 4,66 kg fish byproducts mix to produce | C35: 6.2 | D35: 0.68 | E35: – | F35: – | I35: BSF modelG this study | J35: 1.36–15.1 | K35: 21.2–99.6 | L35: 0.032–7.03
A36: (9) Chicken feed/PP | B36: 0.58 kg maize meal, 0.34 kg soybean meal | C36: 0.252 | D36: 0.438 | E36: 0.142 | F36: 0.05 kg soybean oil, 0.03 kg minerals and vitamins | I36: Note: HL – larvae of Musca domestica; BSF – larvae of Hermetia illucens; MW – larvae of Tenebrio molitor; GWP – global warming potential; Diets: A – poultry manure and house waste; B – pig manure; C – waste; D – brewery wastes; E – mixed diet; F – mixed diet; G – food wastes; H – variety of diets; Impact assessment methods: A – separate indicators; B – ReCiPe; C – CML (Guinée et al., 2002) and Solomon (Solomon, 2007); D – ReCiPe; E – separate indicators; F – ReCiPe and IMPACT 2002+; G – CML; H – ReCiPe and IMPACT 2002+.
A37: (10) Whey protein/PP | B37: 70 kg whey | C37: 0.18 | D37: 1.28 | E37: 0.79 | F37: –
A38: (11) HMI soya/MS | B38: 0.4 kg soybean meal | C38: 0.243 | D38: – | E38: 0.6 | F38: –
A39: (12) HMI insect/MS | B39: 0.2 kg insect meal (1), 0.2 kg soybean meal | C39: 0.243 | D39: – | E39: 0.6 | F39: –
A40: (13) Chicken meat/M | B40: 1 kg of chicken meat from a slaughterhouse | C40: 1.032 | D40: 0.5 | E40: 12.38 | F40: –
A41: Note: PP – protein powder; MS – meat substitutes; M – meat; DDGS - distiller's dried grains with solubles; HMI – high moisture intermediate; * – moisture content 60%.
A45: Smetana, S., Schmitt, E., & Mathys, A. (2019). Sustainable use of Hermetia illucens insect biomass for feed and food: Attributional and consequential life cycle assessment. Resources, Conservation and Recycling, 144, 285-296.
A47: Table 1A. Impact results for midpoint categories (A-LCA, IMPACT 2002+, FU 1 kg of product)
A49: Impact category | B49: Unit | C49: IF | D49: HF | E49: HP | F49: HP_ST | G49: HP_MT | H49: HP_LT | I49: HM | J49: HM_ST | K49: HM_MT | L49: HM_LT
A50: Carcinogens | B50: kg C2H3Cl eq. | C50: 0.014 | D50: 0.068 | E50: 0.034 | F50: 0.027 | G50: 0.025 | H50: 0.006 | I50: 0.099 | J50: 0.081 | K50: 0.073 | L50: 0.025
A51: Non-carcinogens | B51: kg C2H3Cl eq. | C51: 0.029 | D51: 0.093 | E51: 0.032 | F51: 0.026 | G51: 0.013 | H51: 0.011 | I51: 0.128 | J51: 0.103 | K51: 0.053 | L51: 0.043
A52: Respiratory inorganics | B52: g PM2.5 eq. | C52: 0.567 | D52: 2.08 | E52: 0.658 | F52: 0.52 | G52: 0.308 | H52: 0.381 | I52: 2.852 | J52: 2.224 | K52: 1.406 | L52: 1.512
A53: Ionizing radiation | B53: Bq C-14 eq. | C53: 7.944 | D53: 39.173 | E53: 9.311 | F53: 7.759 | G53: 6.89 | H53: 2.621 | I53: 53.146 | J53: 41.749 | K53: 38.4 | L53: 10.375
A54: Ozone layer depletion | B54: mg CFC-11 eq. | C54: 0.068 | D54: 0.313 | E54: 0.091 | F54: 0.074 | G54: 0.066 | H54: 0.042 | I54: 0.43 | J54: 0.339 | K54: 0.309 | L54: 0.169
A55: Respiratory organics | B55: g C2H4 eq. | C55: 0.143 | D55: 0.581 | E55: 0.21 | F55: 0.165 | G55: 0.137 | H55: 0.14 | I55: 0.811 | J55: 0.641 | K55: 0.531 | L55: 0.554
A56: Aquatic ecotoxicity | B56: ton TEG water | C56: 163.292 | D56: 535.702 | E56: 0.176 | F56: 0.157 | G56: 0.125 | H56: 0.11 | I56: 0.733 | J56: 0.643 | K56: 0.522 | L56: 0.43
A57: Terrestrial ecotoxicity | B57: ton TEG soil | C57: 79.043 | D57: 247.422 | E57: 0.081 | F57: 0.068 | G57: 0.036 | H57: 0.032 | I57: 0.337 | J57: 0.278 | K57: 0.157 | L57: 0.122
A58: Terrestrial acid./nitri. | B58: kg SO2 eq. | C58: 0.029 | D58: 0.092 | E58: 0.03 | F58: 0.023 | G58: 0.007 | H58: 0.005 | I58: 0.125 | J58: 0.096 | K58: 0.031 | L58: 0.02
A59: Land occupation | B59: m2org.arable | C59: 0.473 | D59: 1.383 | E59: 0.477 | F59: 0.36 | G59: 0.028 | H59: 0.056 | I59: 1.888 | J59: 1.423 | K59: 0.143 | L59: 0.224
A60: Aquatic acidification | B60: kg SO2 eq. | C60: 0.005 | D60: 0.015 | E60: 0.005 | F60: 0.004 | G60: 0.002 | H60: 0.001 | I60: 0.021 | J60: 0.016 | K60: 0.007 | L60: 0.005
